Workbook
Name loss_rate_xfpd: 'Loss Rate'!$H$14

Sheet Yield Summary
A1: Zed — Portfolio yield on receivables
A2: Gross and net yield by book month, annualized: the June, July and August 2026 books — whose interest was earned in July–September — and the three together. PHP; before operating, servicing and funding costs.
B4: Jun 2026 book | C4: Annualized | D4: Jul 2026 book | E4: Annualized | F4: Aug 2026 book | G4: Annualized | H4: Jun–Aug 2026 | I4: Annualized | J4: Notes
A5: Months in period | B5: 1 | D5: 1 | F5: 1 | H5: 3
A6: Average receivables of the book month (denominator for all yields) | B6: ='Monthly Detail'!G16 | D6: ='Monthly Detail'!H16 | F6: ='Monthly Detail'!I16 | H6: =AVERAGE('Monthly Detail'!G16:I16) | J6: The capital employed in the month. Everything below is what that capital earned and lost: interchange and upfront fees when it was created, interest and late fees the following month, losses on the principal it lent.
A7: Earned when the balance is created — the book month's purchases and conversions
A8: Purchase volume settled | B8: ='Monthly Detail'!G20 | D8: ='Monthly Detail'!H20 | F8: ='Monthly Detail'!I20 | H8: ='Monthly Detail'!G20+'Monthly Detail'!H20+'Monthly Detail'!I20 | J8: Cardholder purchases settled through Mastercard in the book month, net of returns.
A9: Purchase turnover (annualized purchase volume ÷ average receivables) | C9: =B8*12/B$5/B$6 | E9: =D8*12/D$5/D$6 | G9: =F8*12/F$5/F$6 | I9: =H8*12/H$5/H$6 | J9: How many times a year the book is re-spent. Falls as more of the book revolves.
A10: Interchange rate on purchase volume | C10: =B11/B8 | E10: =D11/D8 | G10: =F11/F8 | I10: =H11/H8 | J10: Set by Mastercard by merchant category and domestic/foreign; gross of network and processing costs.
A11: Interchange income | B11: ='Monthly Detail'!G9 | C11: =C10*C9 | D11: ='Monthly Detail'!H9 | E11: =E10*E9 | F11: ='Monthly Detail'!I9 | G11: =G10*G9 | H11: ='Monthly Detail'!G9+'Monthly Detail'!H9+'Monthly Detail'!I9 | I11: =I10*I9 | J11: Yield = interchange rate × purchase turnover. Mastercard settles each purchase to the merchant net of interchange and the cardholder is billed the full amount, so interchange is collected through cardholder payments. Earned once, when the receivable is created.
A12: Installment upfront fees | B12: ='Monthly Detail'!G7 | C12: =B12*12/B$5/B$6 | D12: ='Monthly Detail'!H7 | E12: =D12*12/D$5/D$6 | F12: ='Monthly Detail'!I7 | G12: =F12*12/F$5/F$6 | H12: ='Monthly Detail'!G7+'Monthly Detail'!H7+'Monthly Detail'!I7 | I12: =H12*12/H$5/H$6 | J12: 0.5% × term in months, billed when a purchase is converted to installments (within the purchase's statement cycle).
A13: Installment interest | B13: ='Monthly Detail'!G12 | C13: =B13*12/B$5/B$6 | D13: ='Monthly Detail'!H12 | E13: =D13*12/D$5/D$6 | F13: ='Monthly Detail'!I12 | G13: =F13*12/F$5/F$6 | H13: ='Monthly Detail'!G12+'Monthly Detail'!H12+'Monthly Detail'!I12 | I13: =H13*12/H$5/H$6 | J13: 1% of the original plan amount per installment (add-on; about 1.5% per month on the declining balance), billed with each installment on every statement closing while the plan is outstanding — the first on the first statement after conversion. Earned by the plans on the book month's statements; 14th-close statements allocated across their cycle days.
A14: Earned the following month — charged on the balance billed at the end of the book month
A15: Revolving interest (accrued) | B15: ='Monthly Detail'!H11 | C15: =B15*12/B$5/B$6 | D15: ='Monthly Detail'!I11 | E15: =D15*12/D$5/D$6 | F15: ='Monthly Detail'!J11 | G15: =F15*12/F$5/F$6 | H15: ='Monthly Detail'!H11+'Monthly Detail'!I11+'Monthly Detail'!J11 | I15: =H15*12/H$5/H$6 | J15: 3% per month (BSP cap) on billed balances not paid in full by the due date; a purchase earns no interest until it has been statemented. Accrual basis: each statement cycle's interest allocated across the calendar days it covers. For the June book this is July's interest, and so on.
A16: Late payment fees | B16: ='Monthly Detail'!H8 | C16: =B16*12/B$5/B$6 | D16: ='Monthly Detail'!I8 | E16: =D16*12/D$5/D$6 | F16: ='Monthly Detail'!J8 | G16: =F16*12/F$5/F$6 | H16: ='Monthly Detail'!H8+'Monthly Detail'!I8+'Monthly Detail'!J8 | I16: =H16*12/H$5/H$6 | J16: Billed when the book month's statement is not paid by its due date; following month.
A17: Interest and fees (rows 12, 13, 15, 16) | B17: =B12+B13+B15+B16 | C17: =B17*12/B$5/B$6 | D17: =D12+D13+D15+D16 | E17: =D17*12/D$5/D$6 | F17: =F12+F13+F15+F16 | G17: =F17*12/F$5/F$6 | H17: =H12+H13+H15+H16 | I17: =H17*12/H$5/H$6
A19: Gross yield (annualized, on the book month's average receivables)
A20: Gross yield — interest and fees | C20: =C17 | E20: =E17 | G20: =G17 | I20: =I17
A21: Gross yield — all revenue, including interchange | B21: =B11+B17 | C21: =C11+C17 | D21: =D11+D17 | E21: =E11+E17 | F21: =F11+F17 | G21: =G11+G17 | H21: =H11+H17 | I21: =I11+I17 | J21: Amount column: the revenue attributable to the book month.
A23: Loss on the principal the book month lent — a function of turnover
A24: Principal flow in the book month (purchase volume + pay-a-friend transfers) | B24: ='Monthly Detail'!G22 | D24: ='Monthly Detail'!H22 | F24: ='Monthly Detail'!I22 | H24: ='Monthly Detail'!G22+'Monthly Detail'!H22+'Monthly Detail'!I22 | J24: Everything that became a receivable in the month: Mastercard purchases net of returns plus pay-a-friend transfers (which earn no interchange).
A25: Principal turnover (annualized principal flow ÷ average receivables) | C25: =B24*12/B$5/B$6 | E25: =D24*12/D$5/D$6 | G25: =F24*12/F$5/F$6 | I25: =H24*12/H$5/H$6 | J25: Each peso of receivables is re-lent several times a year, so a loss rate on originations must be multiplied by turnover to compare it with a yield on balances. Differs from purchase turnover only by pay-a-friend.
A26: Loss rate on originated principal — ≥90 DPD, excluding first-payment defaults | C26: =loss_rate_xfpd | E26: =loss_rate_xfpd | G26: =loss_rate_xfpd | I26: =loss_rate_xfpd | J26: See the Loss Rate tab. Principal 90+ days past due ÷ originated principal on statements whose due date is ≥90 days old, vintages since January 2026, gross of recoveries; first-payment-default accounts (never made a payment; fraud/identity rather than credit) excluded from numerator and denominator. The same rate is applied to every period.
A27: Loss on receivables (loss rate × principal turnover) | C27: =C26*C25 | E27: =E26*E25 | G27: =G26*G25 | I27: =I26*I25
A29: Net yield
A30: Net yield — all revenue less loss on receivables | C30: =C21-C27 | E30: =E21-E27 | G30: =G21-G27 | I30: =I21-I27 | J30: Before operating, servicing and funding costs.
A32: Reference — conventional basis (all of a month's revenue over that month's own average receivables)
A33: Period on the conventional basis | B33: Jul 2026 | D33: Aug 2026 | F33: Sep 2026 | H33: Jul–Sep 2026
A34: Gross yield — all revenue | C34: ='Monthly Detail'!H37 | E34: ='Monthly Detail'!I37 | G34: ='Monthly Detail'!J37 | I34: ='Monthly Detail'!K37 | J34: What a reader computing yield on the tape in the usual way will get: July–September revenue over July–September average receivables, which include each month's own purchases that have not yet been billed. Lower than the book-month basis while the book is growing; identical when it is flat.
A35: Net yield — all revenue less loss on receivables | C35: ='Monthly Detail'!H37-loss_rate_xfpd*'Monthly Detail'!H22*12/'Monthly Detail'!H25/'Monthly Detail'!H16 | E35: ='Monthly Detail'!I37-loss_rate_xfpd*'Monthly Detail'!I22*12/'Monthly Detail'!I25/'Monthly Detail'!I16 | G35: ='Monthly Detail'!J37-loss_rate_xfpd*'Monthly Detail'!J22*12/'Monthly Detail'!J25/'Monthly Detail'!J16 | I35: ='Monthly Detail'!K37-loss_rate_xfpd*'Monthly Detail'!K22*12/'Monthly Detail'!K25/'Monthly Detail'!K16
A37: Memo — USD equivalents
A38: PHP per USD | B38: 55.8 | D38: 55.8 | F38: 55.8 | H38: 55.8
A39: Average receivables of the book month (USD) | B39: =B6/B38 | D39: =D6/D38 | F39: =F6/F38 | H39: =H6/H38
A40: Revenue attributable to the book month (USD) | B40: =B21/B38 | D40: =D21/D38 | F40: =F21/F38 | H40: =H21/H38
A41: Principal flow (USD) | B41: =B24/B38 | D41: =D24/D38 | F41: =F24/F38 | H41: =H24/H38

Sheet Monthly Detail
A1: Monthly revenue, receivables and originations — January to September 2026
A2: PHP. Revenue is recognised in the month billed (interest and fees) or settled (interchange). Yields are annualized simply: month ÷ average receivables × 12.
A4: Line | B4: Jan 2026 | C4: Feb 2026 | D4: Mar 2026 | E4: Apr 2026 | F4: May 2026 | G4: Jun 2026 | H4: Jul 2026 | I4: Aug 2026 | J4: Sep 2026 | K4: Jul–Sep 2026
A5: Revolving interest | B5: 0 | C5: 0 | D5: 0 | E5: 0 | F5: 0 | G5: 685463.41 | H5: 1501634.9 | I5: 1951592 | J5: 2229680 | K5: =SUM(H5:J5)
A6: Installment interest | B6: 1316.21 | C6: 47765.48 | D6: 134016.53 | E6: 220070.96 | F6: 257582.01 | G6: 340853.06 | H6: 403236.04 | I6: 445213.13 | J6: 486325.05 | K6: =SUM(H6:J6)
A7: Installment upfront fees | B7: 2185.69 | C7: 146390.53 | D7: 291311.38 | E7: 307856.48 | F7: 320397.94 | G7: 337749.34 | H7: 290513.47 | I7: 341458.41 | J7: 439733.93 | K7: =SUM(H7:J7)
A8: Late payment fees | B8: 64707.62 | C8: 71011.07 | D8: 104805.31 | E8: 138112.4 | F8: 139049.93 | G8: 84871.59 | H8: 89421.49 | I8: 108174.67 | J8: 126426.4 | K8: =SUM(H8:J8)
A9: Interchange | B9: 800466.96 | C9: 864632.93 | D9: 1364620.7 | E9: 1521533.3 | F9: 1545608.6 | G9: 1963194.1 | H9: 1811444.7 | I9: 1892210.1 | J9: 2630889.8 | K9: =SUM(H9:J9)
A10: Total revenue — billed basis (ties to management reporting) | B10: =SUM(B5:B9) | C10: =SUM(C5:C9) | D10: =SUM(D5:D9) | E10: =SUM(E5:E9) | F10: =SUM(F5:F9) | G10: =SUM(G5:G9) | H10: =SUM(H5:H9) | I10: =SUM(I5:I9) | ... K10: =SUM(K5:K9)
A11: Revolving interest — accrued (calendar month) | H11: 1658171.4 | I11: 2023314.9 | J11: 2282599.6 | K11: =SUM(H11:J11)
A12: Installment interest — allocated across cycle days (calendar month) | G12: 380786.2 | H12: 430644.66 | I12: 467199.88 | J12: 517295.33 | K12: =SUM(H12:J12)
A13: Total revenue — accrual basis (used in Yield Summary) | H13: =H11+H12+H7+H8+H9 | I13: =I11+I12+I7+I8+I9 | J13: =J11+J12+J7+J8+J9 | K13: =K11+K12+K7+K8+K9
A15: Balances and volumes
A16: Average receivables outstanding | B16: 60876935 | C16: 61287126 | D16: 78004358 | E16: 1.0522668e+08 | F16: 1.2617837e+08 | G16: 1.4394623e+08 | H16: 1.5860461e+08 | I16: 1.766253e+08 | J16: 2.1115916e+08 | K16: =AVERAGE(H16:J16)
A17: Average receivables outstanding, prior month (reference) | C17: =B16 | D17: =C16 | E17: =D16 | F17: =E16 | G17: =F16 | H17: =G16 | I17: =H16 | J17: =I16 | K17: =AVERAGE(G16:I16)
A18: Receivables outstanding, end of month | B18: 59172827 | C18: 63401424 | D18: 92607291 | E18: 1.1784608e+08 | F18: 1.3451065e+08 | G18: 1.5338181e+08 | H18: 1.6382741e+08 | I18: 1.8942319e+08 | J18: 2.3289513e+08 | K18: =J18
A19: Principal originated, statement-month basis (base on which the loss rate is measured) | B19: 69900974 | C19: 60820771 | D19: 89743206 | E19: 1.0711537e+08 | F19: 1.1818498e+08 | G19: 1.3641748e+08 | H19: 1.4062427e+08 | I19: 1.4188834e+08 | J19: 1.6022121e+08 | K19: =SUM(H19:J19)
A20: Purchase volume settled (Mastercard, net of returns) | B20: 59671645 | C20: 60642781 | D20: 95344566 | E20: 1.0594721e+08 | F20: 1.1040024e+08 | G20: 1.3714599e+08 | H20: 1.2724966e+08 | I20: 1.303889e+08 | J20: 1.9086099e+08 | K20: =SUM(H20:J20)
A21: Pay-a-friend transfers (cardholder-to-cardholder, charged to the card; no interchange) | B21: 1060000 | C21: 980000 | D21: 1900000 | E21: 1190000 | F21: 2250000 | G21: 2040000 | H21: 2730000 | I21: 2970000 | J21: 2650000 | K21: =SUM(H21:J21)
A22: Principal flow (purchase volume + pay-a-friend) — calendar-month loss base | B22: =B20+B21 | C22: =C20+C21 | D22: =D20+D21 | E22: =E20+E21 | F22: =F20+F21 | G22: =G20+G21 | H22: =H20+H21 | I22: =I20+I21 | ... K22: =K20+K21
A24: Annualized yields by book month — interchange and upfront fees earned when the month's balance was created, installment charges billed on the month's statements, and the revolving interest and late fees charged on it the following month, ÷ that month's average receivables
A25: Months in period | B25: 1 | C25: 1 | D25: 1 | E25: 1 | F25: 1 | G25: 1 | H25: 1 | I25: 1 | J25: 1 | K25: 3
A26: Revolving interest and late fees charged the following month | B26: =(C5+C8)*12/B25/B16 | C26: =(D5+D8)*12/C25/C16 | D26: =(E5+E8)*12/D25/D16 | E26: =(F5+F8)*12/E25/E16 | F26: =(G5+G8)*12/F25/F16 | G26: =(H11+H8)*12/G25/G16 | H26: =(I11+I8)*12/H25/H16 | I26: =(J11+J8)*12/I25/I16
A27: Installment interest (billed with each installment on the book month's statements) | B27: =B6*12/B25/B16 | C27: =C6*12/C25/C16 | D27: =D6*12/D25/D16 | E27: =E6*12/E25/E16 | F27: =F6*12/F25/F16 | G27: =G12*12/G25/G16 | H27: =H12*12/H25/H16 | I27: =I12*12/I25/I16
A28: Installment upfront fees (at conversion, same month) | B28: =B7*12/B25/B16 | C28: =C7*12/C25/C16 | D28: =D7*12/D25/D16 | E28: =E7*12/E25/E16 | F28: =F7*12/F25/F16 | G28: =G7*12/G25/G16 | H28: =H7*12/H25/H16 | I28: =I7*12/I25/I16
A29: Purchase turnover (annualized purchase volume ÷ average receivables) | B29: =B20*12/B25/B16 | C29: =C20*12/C25/C16 | D29: =D20*12/D25/D16 | E29: =E20*12/E25/E16 | F29: =F20*12/F25/F16 | G29: =G20*12/G25/G16 | H29: =H20*12/H25/H16 | I29: =I20*12/I25/I16
A30: Interchange rate on purchase volume | B30: =B9/B20 | C30: =C9/C20 | D30: =D9/D20 | E30: =E9/E20 | F30: =F9/F20 | G30: =G9/G20 | H30: =H9/H20 | I30: =I9/I20
A31: Interchange (rate × purchase turnover, same month) | B31: =B9*12/B25/B16 | C31: =C9*12/C25/C16 | D31: =D9*12/D25/D16 | E31: =E9*12/E25/E16 | F31: =F9*12/F25/F16 | G31: =G9*12/G25/G16 | H31: =H9*12/H25/H16 | I31: =I9*12/I25/I16
A32: Gross yield — all revenue | B32: =((C5+C8)+B6+B7+B9)*12/B25/B16 | C32: =((D5+D8)+C6+C7+C9)*12/C25/C16 | D32: =((E5+E8)+D6+D7+D9)*12/D25/D16 | E32: =((F5+F8)+E6+E7+E9)*12/E25/E16 | F32: =((G5+G8)+F6+F7+F9)*12/F25/F16 | G32: =((H11+H8)+G12+G7+G9)*12/G25/G16 | H32: =((I11+I8)+H12+H7+H9)*12/H25/H16 | I32: =((J11+J8)+I12+I7+I9)*12/I25/I16
A33: Principal turnover (annualized principal flow ÷ average receivables) | B33: =B22*12/B25/B16 | C33: =C22*12/C25/C16 | D33: =D22*12/D25/D16 | E33: =E22*12/E25/E16 | F33: =F22*12/F25/F16 | G33: =G22*12/G25/G16 | H33: =H22*12/H25/H16 | I33: =I22*12/I25/I16
A35: Reference — conventional basis: all of a month's revenue over that month's own average receivables
A36: Interest and fees | B36: =SUM(B5:B8)*12/B25/B16 | C36: =SUM(C5:C8)*12/C25/C16 | D36: =SUM(D5:D8)*12/D25/D16 | E36: =SUM(E5:E8)*12/E25/E16 | F36: =SUM(F5:F8)*12/F25/F16 | G36: =SUM(G5:G8)*12/G25/G16 | H36: =(H11+H12+H7+H8)*12/H25/H16 | I36: =(I11+I12+I7+I8)*12/I25/I16 | J36: =(J11+J12+J7+J8)*12/J25/J16 | K36: =(K11+K12+K7+K8)*12/K25/K16
A37: Gross yield — all revenue | B37: =SUM(B5:B8)*12/B25/B16+B9*12/B25/B16 | C37: =SUM(C5:C8)*12/C25/C16+C9*12/C25/C16 | D37: =SUM(D5:D8)*12/D25/D16+D9*12/D25/D16 | E37: =SUM(E5:E8)*12/E25/E16+E9*12/E25/E16 | F37: =SUM(F5:F8)*12/F25/F16+F9*12/F25/F16 | G37: =SUM(G5:G8)*12/G25/G16+G9*12/G25/G16 | H37: =(H11+H12+H7+H8)*12/H25/H16+H9*12/H25/H16 | I37: =(I11+I12+I7+I8)*12/I25/I16+I9*12/I25/I16 | J37: =(J11+J12+J7+J8)*12/J25/J16+J9*12/J25/J16 | K37: =(K11+K12+K7+K8)*12/K25/K16+K9*12/K25/K16
A39: Installment plans scaled from March 2026 and revolving interest was introduced with the June 2026 statement cycle, so July–September 2026 is the first quarter with every revenue line in place. Earlier months are shown for completeness on the billed basis. Accrued interest allocates each statement cycle's interest across the calendar days it covers (half the book statements on the 14th, so those cycles straddle two months); it is shown for July–September, where the October 14 cycle is available to complete September. Yields are by book month: a month's balance earns interchange and upfront fees when it is created (that month's purchases and conversions), installment charges on the statements closing in the month (1% of the original plan amount per installment, for every plan outstanding at the close), and revolving interest and late fees the following month (charged on the balance billed at month end, net of payments). The conventional basis is shown for reference; the two coincide when the book is not growing.

Sheet Loss Rate
A1: Loss rate on originated principal — 90+ days past due, vintages since January 2026
A2: PHP. Each row is the principal originated in that month and how much of it sits on an account 90 or more days past due today (data as of 27 October 2026). Vintages begin January 2026, the first full month after the current underwriting model was introduced (December 2025).
A4: Origination month | B4: Accounts | C4: Principal originated | D4: Seasoned principal (due ≥90 days ago) | E4: Excluded: FPD principal 90+ DPD | F4: Denominator: seasoned, ex-FPD | G4: Numerator: 90+ DPD, ex-FPD | H4: Loss rate
A5: Jan 2026 | B5: 3828 | C5: 69900974 | D5: 69900974 | E5: 195035.55 | F5: 69690793 | G5: 1577286.9 | H5: =IF(F5=0,"not yet seasoned",G5/F5)
A6: Feb 2026 | B6: 4029 | C6: 60820771 | D6: 60820771 | E6: 31366.54 | F6: 60789405 | G6: 685527.14 | H6: =IF(F6=0,"not yet seasoned",G6/F6)
A7: Mar 2026 | B7: 5113 | C7: 89743206 | D7: 89743206 | E7: 562712.45 | F7: 89089555 | G7: 1404938.6 | H7: =IF(F7=0,"not yet seasoned",G7/F7)
A8: Apr 2026 | B8: 6505 | C8: 1.0711537e+08 | D8: 1.0711537e+08 | E8: 911016.11 | F8: 1.0612324e+08 | G8: 1471002.6 | H8: =IF(F8=0,"not yet seasoned",G8/F8)
A9: May 2026 | B9: 7564 | C9: 1.1818498e+08 | D9: 1.1818498e+08 | E9: 889165.96 | F9: 1.1722674e+08 | G9: 1061583 | H9: =IF(F9=0,"not yet seasoned",G9/F9)
A10: Jun 2026 | B10: 9024 | C10: 1.3641748e+08 | D10: 1.3641748e+08 | E10: 499873.5 | F10: 1.3591761e+08 | G10: 459463.31 | H10: =IF(F10=0,"not yet seasoned",G10/F10)
A11: Jul 2026 | B11: 11366 | C11: 1.4062427e+08 | D11: 0 | E11: 29390.51 | F11: 0 | G11: 8828.19 | H11: =IF(F11=0,"not yet seasoned",G11/F11)
A12: Aug 2026 | B12: 12347 | C12: 1.4188834e+08 | D12: 0 | E12: 0 | F12: 0 | G12: 0 | H12: =IF(F12=0,"not yet seasoned",G12/F12)
A13: Sep 2026 | B13: 13196 | C13: 1.6022121e+08 | D13: 0 | E13: 0 | F13: 0 | G13: 0 | H13: =IF(F13=0,"not yet seasoned",G13/F13)
A14: Since January 2026 (all vintages above) | B14: =SUM(B5:B13) | C14: =SUM(C5:C13) | D14: =SUM(D5:D13) | E14: =SUM(E5:E13) | F14: =SUM(F5:F13) | G14: =SUM(G5:G13) | H14: =G14/F14
A16: How to read this table
A17: • Loss measure. Principal on accounts 90 or more days past due is used as the proxy for loss. Zed fully provisions at 180 days past due and has not yet written off any balances, so no recoveries are assumed and nothing has been reduced for cash collected after an account went delinquent. Interest and fees are excluded from both numerator and denominator.
A18: • Seasoning. The denominator counts only principal whose statement due date is at least 90 days in the past, so the rate is measured on principal that has had the chance to reach 90 days past due. On this basis the July–September 2026 vintages are not yet measurable and are shown for completeness.
A19: • First-payment defaults (FPD). An account whose first-ever statement was the one missed, i.e. a cardholder who never made a payment. These are fraud or identity cases rather than credit losses and are excluded from the loss rate; the principal excluded is shown in column E so the adjustment is visible. Receivables of this kind would ordinarily fall outside facility eligibility criteria. First-payment default is managed separately from credit underwriting: duplicate-applicant checks (exact name and date of birth, ID number) have been in place since 1 October 2026, and from the 24 October 2026 decisioning run every application is screened for bank account numbers shared with another applicant, repeated selfie or ID images, invite-name mismatches and past-due bureau tradelines, with business-owner limits set on half of declared income pending documents.
A20: • Why January 2026. The current underwriting model (V2) was deployed in December 2025 and is the model that originates the portfolio today; earlier vintages were originated under the prior model.
A22: Loss emergence — when a vintage's loss arrives (ex-FPD, same measure as the table above)
A23: Origination month | B23: By month 3 on book | C23: By month 4 | D23: By month 5 | E23: By month 6 | F23: By month 8 | G23: Today | H23: Months on book today
A24: Jan 2026 | B24: 0.00675 | C24: 0.02263 | D24: 0.02263 | E24: 0.02263 | F24: 0.02263 | G24: 0.02263 | H24: 9
A25: Feb 2026 | B25: 0.00851 | C25: 0.01028 | D25: 0.01118 | E25: 0.01128 | F25: — | G25: 0.01128 | H25: 8
A26: Mar 2026 | B26: 0.00455 | C26: 0.01469 | D26: 0.01577 | E26: 0.01577 | F26: — | G26: 0.01577 | H26: 7
A27: Apr 2026 | B27: 0.00773 | C27: 0.01313 | D27: 0.01366 | E27: — | F27: — | G27: 0.01386 | H27: 6
A28: May 2026 | B28: 0.00494 | C28: 0.00758 | D28: — | E28: — | F28: — | G28: 0.00906 | H28: 5
A29: Jun 2026 | B29: 0.00215 | C29: — | D29: — | E29: — | F29: — | G29: 0.00338 | H29: 4
A30: How to read this table
A31: • Each cell is the part of the vintage's loss rate (principal ≥90 DPD today ÷ seasoned principal, ex-FPD — the same measure as the table above) that comes from accounts which had reached 90 days past due by the end of month n after the origination month. 'Today' is the full current loss rate. Cells are blank where month n has not yet ended.
A32: • The loss on a vintage is essentially complete by month 4 on book: January–March 2026 show no further movement from month 4 to month 6–8. Because cash is applied to the oldest balances first, an account that defaults later has already repaid its earlier months' purchases, so late defaults fall on later vintages rather than reopening old ones.
A33: • Read across the 'Today' column for the trend in fully emerged vintages: 2.26% (Jan), 1.13% (Feb), 1.58% (Mar), 1.39% (Apr), 0.91% (May, at month 5 — effectively final). June is at month 4 with one month of emergence still to come.

Sheet Notes
A1: Definitions and sources
A3: Item | B3: Definition
A4: Scope | B4: Zed's Philippine credit card receivables, all cardholders. Yield Summary covers the June, July and August 2026 books and the three together — the books whose interest was earned in July–September 2026, the first quarter with every revenue line in place (installment plans scaled from March 2026; revolving interest introduced with the June 2026 cycle). Monthly Detail shows January–September 2026. All figures in PHP unless marked USD (converted at 55.8 for reference only).
A5: Book month (yield basis) | B5: Yields are measured by book month: the month's average receivables outstanding (principal, interest and fees billed to cardholders, plus installment principal not yet billed) are the capital employed, and the revenue attributed to them is what that capital earned — interchange and upfront fees when the balance was created (that month's purchases and conversions), installment charges on the month's statements (a fixed charge per installment for every plan outstanding at the close), and revolving interest and late fees the following month, because revolving interest is charged on the balance billed at month end, net of payments (adjusted daily balance), and a purchase earns no interest until it has been statemented. Losses are the loss rate on the principal the month lent. The June, July and August 2026 books are shown — the books whose interest arrived in July–September, the first quarter with every revenue line in place — and the three together, where the denominator is the average of the three months. The conventional basis (a month's revenue over that month's own average receivables) is shown for reference; the two coincide when the book is not growing and differ by roughly the monthly growth rate while it is.
A6: Annualization | B6: Simple: monthly amount ÷ the book month's average receivables × 12. No compounding.
A7: Revolving interest | B7: Finance charge on billed balances not paid in full by the due date; 3% per month, the BSP ceiling. Under the BSP's credit card rules interest is charged only on billed balances, so purchases earn no interest until they are statemented, and balances paid within the grace period never do. Launched with the statement cycle closing 30 June 2026. Yield Summary uses an accrual basis: each statement cycle's interest is allocated evenly across the calendar days the cycle covers (cycles close on the 14th and on the last day of the month); Monthly Detail carries the billed basis, which ties to management reporting.
A8: Installment interest and upfront fees | B8: Installment interest is 1% of the original plan amount per installment (add-on), billed together with the principal installment on every statement closing while the plan is outstanding, starting with the first statement after conversion; on the declining balance it is about 1.5% per month. The upfront conversion fee is 0.5% per month of term, billed when a purchase is converted. Both are attributed to the book month: the fee to the month of conversion, the interest to the month whose statements carried the installment (14th-close statements allocated across their cycle days).
A9: Late payment fees | B9: Fee billed when the minimum payment is not received by the due date.
A10: Interchange | B10: Interchange received from Mastercard on cardholder purchases, gross (network and processing costs are not netted). Interchange is earned when a purchase settles, not on balances, so its yield on receivables is shown as interchange rate on purchase volume × purchase turnover (annualized purchase volume ÷ the book month's average receivables) — the same construction as the loss line. Mastercard settles the merchant net of interchange and the cardholder is billed the full purchase amount, so the interchange margin is collected as part of the cardholder's payment.
A11: Turnover | B11: Annualized flow in the book month ÷ its average receivables. Purchase turnover uses Mastercard purchase volume (the interchange base); principal turnover uses principal flow (the loss base). They differ only by pay-a-friend transfers.
A12: Principal flow | B12: Calendar-month flow of new receivables: Mastercard purchase volume net of returns plus pay-a-friend transfers (cardholder-to-cardholder transfers charged to the card, which earn no interchange). This is the loss base in the Yield Summary.
A13: Principal originated (Loss Rate tab) | B13: The same quantity measured by statement month: charges on statements closing in the month (cycles close on the 14th and the last day), net of refunds, chargebacks and cancelled installment-plan re-bookings. The loss rate is measured on this basis because delinquency is tracked by statement; a statement month covers roughly the second half of the prior calendar month and the first half of the current one, so individual months differ from the calendar flow by timing while the two agree over longer windows (Jan–Sep 2026: ₱1,025M vs ₱1,035M).
A14: Loss rate | B14: Principal on accounts 90 or more days past due today, divided by originated principal on statements whose due date is at least 90 days old, for origination months January–September 2026 (in practice January–June, the vintages old enough to be measured), excluding first-payment-default accounts from both numerator and denominator. The window, the seasoning rule and the FPD definition are set out on the Loss Rate tab, which also shows the FPD principal excluded. Gross of recoveries; no balances have been written off to date (full provision at 180 DPD).
... A18: Prepared | B18: Zed Financial, October 2026. Prepared for Accial Capital in connection with its evaluation of a receivables facility.
