Workbook
Name loss_rate_xfpd: 'Loss Rate'!$H$14

Sheet Yield Summary
A1: Zed — Portfolio yield on receivables
A2: Each column is a book: a month's average receivables and what that capital earned and lost. The product works in two steps — a purchase earns interchange the day it settles and, if converted to an installment, its upfront fee and installment is charged on the statements that follow; it earns revolving interest only after it has been billed and left unpaid past the due date, i.e. in the following month, which is also when a missed payment draws a late fee. So each book carries its own month's interchange, upfront fees and installment charges, the following month's revolving interest and late fees, and the loss rate on the principal it lent. Annualized, PHP, before operating, servicing and funding costs.
B3: Book — the month's receivables and what they earned (interest and late fees arrive the following month)
B4: Jun 2026 | C4: Annualized | D4: Jul 2026 | E4: Annualized | F4: Aug 2026 | G4: Annualized | H4: Jun–Aug 2026 | I4: Annualized | J4: Notes
A5: Average receivables of the book month (denominator) | B5: ='Monthly Detail'!G16 -> 1.4394623e+08 | D5: ='Monthly Detail'!H16 -> 1.5860461e+08 | F5: ='Monthly Detail'!I16 -> 1.766253e+08 | H5: =AVERAGE('Monthly Detail'!G16:I16) -> 1.5972538e+08 | J5: The capital employed; the quarter averages the three months.
A6: Earned as the balance is created — the book month's purchases, conversions and statements
A7: Purchase volume settled | B7: ='Monthly Detail'!G20 -> 1.3714599e+08 | D7: ='Monthly Detail'!H20 -> 1.2724966e+08 | F7: ='Monthly Detail'!I20 -> 1.303889e+08 | H7: ='Monthly Detail'!G20+'Monthly Detail'!H20+'Monthly Detail'!I20 -> 3.9478454e+08 | J7: Mastercard purchases in the month, net of returns.
A8: Purchase turnover | C8: =B7*12/B$5 -> 11.433101 | E8: =D7*12/D$5 -> 9.6276891 | G8: =F7*12/F$5 -> 8.8586786 | I8: =H7*4/H$5 -> 9.8865826 | J8: Annualized purchases ÷ receivables: how often the book is re-spent
A9: Interchange rate on purchase volume | C9: =B10/B7 -> 0.01431463 | E9: =D10/D7 -> 0.014235361 | G9: =F10/F7 -> 0.01451205 | I9: =H10/H7 -> 0.014354283 | J9: Set by Mastercard by merchant category and domestic/foreign
A10: Interchange income | B10: ='Monthly Detail'!G9 -> 1963194.1 | C10: =C9*C8 -> 0.16366062 | D10: ='Monthly Detail'!H9 -> 1811444.7 | E10: =E9*E8 -> 0.13705363 | F10: ='Monthly Detail'!I9 -> 1892210.1 | G10: =G9*G8 -> 0.12855758 | H10: ='Monthly Detail'!G9+'Monthly Detail'!H9+'Monthly Detail'!I9 -> 5666849 | I10: =I9*I8 -> 0.1419148 | J10: Rate × turnover
A11: Installments | B11: =B12+B13 -> 718535.54 | C11: =B11*12/B$5 -> 0.059900328 | D11: =D12+D13 -> 721158.13 | E11: =D11*12/D$5 -> 0.054562711 | F11: =F12+F13 -> 808658.29 | G11: =F11*12/F$5 -> 0.054940597 | H11: =H12+H13 -> 2248352 | I11: =H11*4/H$5 -> 0.05630544 | J11: Upfront fees + installment interest
A12: Installment upfront fees | B12: ='Monthly Detail'!G7 -> 337749.34 | C12: =B12*12/B$5 -> 0.028156292 | D12: ='Monthly Detail'!H7 -> 290513.47 | E12: =D12*12/D$5 -> 0.021980204 | F12: ='Monthly Detail'!I7 -> 341458.41 | G12: =F12*12/F$5 -> 0.023198833 | H12: ='Monthly Detail'!G7+'Monthly Detail'!H7+'Monthly Detail'!I7 -> 969721.22 | I12: =H12*4/H$5 -> 0.024284712 | J12: 0.5% × term in months, billed at conversion.
A13: Installment interest | B13: ='Monthly Detail'!G12 -> 380786.2 | C13: =B13*12/B$5 -> 0.031744036 | D13: ='Monthly Detail'!H12 -> 430644.66 | E13: =D13*12/D$5 -> 0.032582507 | F13: ='Monthly Detail'!I12 -> 467199.88 | G13: =F13*12/F$5 -> 0.031741764 | H13: ='Monthly Detail'!G12+'Monthly Detail'!H12+'Monthly Detail'!I12 -> 1278630.7 | I13: =H13*4/H$5 -> 0.032020728 | J13: 1% of plan per month of term (3% on 3 months); one charge per statement, from the first after conversion
A14: Earned the following month — charged on the balance billed at the end of the book month
A15: Revolving interest (accrued) | B15: ='Monthly Detail'!H11 -> 1658171.4 | C15: =B15*12/B$5 -> 0.13823257 | D15: ='Monthly Detail'!I11 -> 2023314.9 | E15: =D15*12/D$5 -> 0.15308369 | F15: ='Monthly Detail'!J11 -> 2282599.6 | G15: =F15*12/F$5 -> 0.15508081 | H15: ='Monthly Detail'!H11+'Monthly Detail'!I11+'Monthly Detail'!J11 -> 5964085.9 | I15: =H15*4/H$5 -> 0.1493585 | J15: 3%/month (BSP cap) on billed balances unpaid past due date; no interest until a purchase is statemented
A16: Late payment fees | B16: ='Monthly Detail'!H8 -> 89421.49 | C16: =B16*12/B$5 -> 0.0074545743 | D16: ='Monthly Detail'!I8 -> 108174.67 | E16: =D16*12/D$5 -> 0.0081844786 | F16: ='Monthly Detail'!J8 -> 126426.4 | G16: =F16*12/F$5 -> 0.0085894648 | H16: ='Monthly Detail'!H8+'Monthly Detail'!I8+'Monthly Detail'!J8 -> 324022.56 | I16: =H16*4/H$5 -> 0.0081144915 | J16: Charged when the book month's statement is not paid by its due date.
A17: Gross yield
A18: Interchange | B18: =B10 -> 1963194.1 | C18: =C10 -> 0.16366062 | D18: =D10 -> 1811444.7 | E18: =E10 -> 0.13705363 | F18: =F10 -> 1892210.1 | G18: =G10 -> 0.12855758 | H18: =H10 -> 5666849 | I18: =I10 -> 0.1419148
A19: Interest and fees | B19: =B11+B15+B16 -> 2466128.4 | C19: =B19*12/B$5 -> 0.20558747 | D19: =D11+D15+D16 -> 2852647.7 | E19: =D19*12/D$5 -> 0.21583088 | F19: =F11+F15+F16 -> 3217684.3 | G19: =F19*12/F$5 -> 0.21861088 | H19: =H11+H15+H16 -> 8536460.4 | I19: =H19*4/H$5 -> 0.21377843 | J19: Installments + revolving interest + late fees
A20: Gross yield — all revenue | B20: =B18+B19 -> 4429322.5 | C20: =C18+C19 -> 0.36924809 | D20: =D18+D19 -> 4664092.4 | E20: =E18+E19 -> 0.3528845 | F20: =F18+F19 -> 5109894.4 | G20: =G18+G19 -> 0.34716846 | H20: =H18+H19 -> 14203309 | I20: =I18+I19 -> 0.35569324 | J20: Amount: revenue attributable to the book.
A21: Loss on the principal the book lent
A22: Principal flow (purchase volume + pay-a-friend transfers) | B22: ='Monthly Detail'!G22 -> 1.3918599e+08 | D22: ='Monthly Detail'!H22 -> 1.2997966e+08 | F22: ='Monthly Detail'!I22 -> 1.333589e+08 | H22: ='Monthly Detail'!G22+'Monthly Detail'!H22+'Monthly Detail'!I22 -> 4.0252454e+08 | J22: Everything that became a receivable in the month; pay-a-friend transfers earn no interchange.
A23: Principal turnover | C23: =B22*12/B$5 -> 11.603165 | E23: =D22*12/D$5 -> 9.8342405 | G23: =F22*12/F$5 -> 9.0604617 | I23: =H22*4/H$5 -> 10.080415 | J23: Annualized principal flow ÷ receivables
A24: Loss rate on originated principal — ≥90 DPD, excluding first-payment defaults | C24: =loss_rate_xfpd -> 0.011520732 | E24: =loss_rate_xfpd -> 0.011520732 | G24: =loss_rate_xfpd -> 0.011520732 | I24: =loss_rate_xfpd -> 0.011520732 | J24: Loss Rate tab: 90+ DPD ÷ principal seasoned 90 days, vintages since Jan 2026, ex-FPD, before recoveries
A25: Loss on receivables | C25: =C24*C23 -> 0.13367695 | E25: =E24*E23 -> 0.11329765 | G25: =G24*G23 -> 0.10438315 | I25: =I24*I23 -> 0.11613376 | J25: Loss rate × principal turnover
A26: Net yield
A27: Net yield — all revenue less loss on receivables | C27: =C20-C25 -> 0.23557114 | E27: =E20-E25 -> 0.23958686 | G27: =G20-G25 -> 0.24278531 | I27: =I20-I25 -> 0.23955948 | J27: Before operating, servicing and funding costs.

Sheet Monthly Detail
A1: Monthly revenue, receivables and originations — January to September 2026
A2: PHP. Revenue is recognised in the month billed (interest and fees) or settled (interchange). Yields are annualized simply: month ÷ average receivables × 12.
A4: Line | B4: Jan 2026 | C4: Feb 2026 | D4: Mar 2026 | E4: Apr 2026 | F4: May 2026 | G4: Jun 2026 | H4: Jul 2026 | I4: Aug 2026 | J4: Sep 2026 | K4: Jul–Sep 2026
A5: Revolving interest | B5: 0 | C5: 0 | D5: 0 | E5: 0 | F5: 0 | G5: 685463.41 | H5: 1501634.9 | I5: 1951592 | J5: 2229680 | K5: =SUM(H5:J5) -> 5682907
A6: Installment interest | B6: 1316.21 | C6: 47765.48 | D6: 134016.53 | E6: 220070.96 | F6: 257582.01 | G6: 340853.06 | H6: 403236.04 | I6: 445213.13 | J6: 486325.05 | K6: =SUM(H6:J6) -> 1334774.2
A7: Installment upfront fees | B7: 2185.69 | C7: 146390.53 | D7: 291311.38 | E7: 307856.48 | F7: 320397.94 | G7: 337749.34 | H7: 290513.47 | I7: 341458.41 | J7: 439733.93 | K7: =SUM(H7:J7) -> 1071705.8
A8: Late payment fees | B8: 64707.62 | C8: 71011.07 | D8: 104805.31 | E8: 138112.4 | F8: 139049.93 | G8: 84871.59 | H8: 89421.49 | I8: 108174.67 | J8: 126426.4 | K8: =SUM(H8:J8) -> 324022.56
A9: Interchange | B9: 800466.96 | C9: 864632.93 | D9: 1364620.7 | E9: 1521533.3 | F9: 1545608.6 | G9: 1963194.1 | H9: 1811444.7 | I9: 1892210.1 | J9: 2630889.8 | K9: =SUM(H9:J9) -> 6334544.7
A10: Total revenue — billed basis (ties to management reporting) | B10: =SUM(B5:B9) -> 868676.48 | C10: =SUM(C5:C9) -> 1129800 | D10: =SUM(D5:D9) -> 1894753.9 | E10: =SUM(E5:E9) -> 2187573.1 | F10: =SUM(F5:F9) -> 2262638.5 | G10: =SUM(G5:G9) -> 3412131.5 | H10: =SUM(H5:H9) -> 4096250.6 | I10: =SUM(I5:I9) -> 4738648.4 | ... K10: =SUM(K5:K9) -> 14747954
A11: Revolving interest — accrued (calendar month) | H11: 1658171.4 | I11: 2023314.9 | J11: 2282599.6 | K11: =SUM(H11:J11) -> 5964085.9
A12: Installment interest — allocated across cycle days (calendar month) | G12: 380786.2 | H12: 430644.66 | I12: 467199.88 | J12: 517295.33 | K12: =SUM(H12:J12) -> 1415139.9
A13: Total revenue — accrual basis (used in Yield Summary) | H13: =H11+H12+H7+H8+H9 -> 4280195.8 | I13: =I11+I12+I7+I8+I9 -> 4832358 | J13: =J11+J12+J7+J8+J9 -> 5996945.1 | K13: =K11+K12+K7+K8+K9 -> 15109499
A15: Balances and volumes
A16: Average receivables outstanding | B16: 60876935 | C16: 61287126 | D16: 78004358 | E16: 1.0522668e+08 | F16: 1.2617837e+08 | G16: 1.4394623e+08 | H16: 1.5860461e+08 | I16: 1.766253e+08 | J16: 2.1115916e+08 | K16: =AVERAGE(H16:J16) -> 1.8212969e+08
A17: Average receivables outstanding, prior month (reference) | C17: =B16 -> 60876935 | D17: =C16 -> 61287126 | E17: =D16 -> 78004358 | F17: =E16 -> 1.0522668e+08 | G17: =F16 -> 1.2617837e+08 | H17: =G16 -> 1.4394623e+08 | I17: =H16 -> 1.5860461e+08 | J17: =I16 -> 1.766253e+08 | K17: =AVERAGE(G16:I16) -> 1.5972538e+08
A18: Receivables outstanding, end of month | B18: 59172827 | C18: 63401424 | D18: 92607291 | E18: 1.1784608e+08 | F18: 1.3451065e+08 | G18: 1.5338181e+08 | H18: 1.6382741e+08 | I18: 1.8942319e+08 | J18: 2.3289513e+08 | K18: =J18 -> 2.3289513e+08
A19: Principal originated, statement-month basis (base on which the loss rate is measured) | B19: 69900974 | C19: 60820771 | D19: 89743206 | E19: 1.0711537e+08 | F19: 1.1818498e+08 | G19: 1.3641748e+08 | H19: 1.4062427e+08 | I19: 1.4188834e+08 | J19: 1.6022121e+08 | K19: =SUM(H19:J19) -> 4.4273382e+08
A20: Purchase volume settled (Mastercard, net of returns) | B20: 59671645 | C20: 60642781 | D20: 95344566 | E20: 1.0594721e+08 | F20: 1.1040024e+08 | G20: 1.3714599e+08 | H20: 1.2724966e+08 | I20: 1.303889e+08 | J20: 1.9086099e+08 | K20: =SUM(H20:J20) -> 4.4849955e+08
A21: Pay-a-friend transfers (cardholder-to-cardholder, charged to the card; no interchange) | B21: 1060000 | C21: 980000 | D21: 1900000 | E21: 1190000 | F21: 2250000 | G21: 2040000 | H21: 2730000 | I21: 2970000 | J21: 2650000 | K21: =SUM(H21:J21) -> 8350000
A22: Principal flow (purchase volume + pay-a-friend) — calendar-month loss base | B22: =B20+B21 -> 60731645 | C22: =C20+C21 -> 61622781 | D22: =D20+D21 -> 97244566 | E22: =E20+E21 -> 1.0713721e+08 | F22: =F20+F21 -> 1.1265024e+08 | G22: =G20+G21 -> 1.3918599e+08 | H22: =H20+H21 -> 1.2997966e+08 | I22: =I20+I21 -> 1.333589e+08 | ... K22: =K20+K21 -> 4.5684955e+08
A24: Annualized yields by book month — interchange and upfront fees earned when the month's balance was created, installment charges billed on the month's statements, and the revolving interest and late fees charged on it the following month, ÷ that month's average receivables
A25: Months in period | B25: 1 | C25: 1 | D25: 1 | E25: 1 | F25: 1 | G25: 1 | H25: 1 | I25: 1 | J25: 1 | K25: 3
A26: Revolving interest and late fees charged the following month | B26: =(C5+C8)*12/B25/B16 -> 0.01399763 | C26: =(D5+D8)*12/C25/C16 -> 0.020520847 | D26: =(E5+E8)*12/D25/D16 -> 0.021246875 | E26: =(F5+F8)*12/E25/E16 -> 0.015857187 | F26: =(G5+G8)*12/F25/F16 -> 0.073261529 | G26: =(H11+H8)*12/G25/G16 -> 0.14568714 | H26: =(I11+I8)*12/H25/H16 -> 0.16126817 | I26: =(J11+J8)*12/I25/I16 -> 0.16367028
A27: Installment interest (billed with each installment on the book month's statements) | B27: =B6*12/B25/B16 -> 0.00025944999 | C27: =C6*12/C25/C16 -> 0.009352466 | D27: =D6*12/D25/D16 -> 0.020616776 | E27: =E6*12/E25/E16 -> 0.025096786 | F27: =F6*12/F25/F16 -> 0.024496942 | G27: =G12*12/G25/G16 -> 0.031744036 | H27: =H12*12/H25/H16 -> 0.032582507 | I27: =I12*12/I25/I16 -> 0.031741764
A28: Installment upfront fees (at conversion, same month) | B28: =B7*12/B25/B16 -> 0.00043084101 | C28: =C7*12/C25/C16 -> 0.02866322 | D28: =D7*12/D25/D16 -> 0.044814632 | E28: =E7*12/E25/E16 -> 0.035107804 | F28: =F7*12/F25/F16 -> 0.030470955 | G28: =G7*12/G25/G16 -> 0.028156292 | H28: =H7*12/H25/H16 -> 0.021980204 | I28: =I7*12/I25/I16 -> 0.023198833
A29: Purchase turnover (annualized purchase volume ÷ average receivables) | B29: =B20*12/B25/B16 -> 11.762414 | C29: =C20*12/C25/C16 -> 11.873837 | D29: =D20*12/D25/D16 -> 14.667575 | E29: =E20*12/E25/E16 -> 12.082169 | F29: =F20*12/F25/F16 -> 10.499446 | G29: =G20*12/G25/G16 -> 11.433101 | H29: =H20*12/H25/H16 -> 9.6276891 | I29: =I20*12/I25/I16 -> 8.8586786
A30: Interchange rate on purchase volume | B30: =B9/B20 -> 0.013414528 | C30: =C9/C20 -> 0.014257805 | D30: =D9/D20 -> 0.014312517 | E30: =E9/E20 -> 0.014361239 | F30: =F9/F20 -> 0.014000047 | G30: =G9/G20 -> 0.01431463 | H30: =H9/H20 -> 0.014235361 | I30: =I9/I20 -> 0.01451205
A31: Interchange (rate × purchase turnover, same month) | B31: =B9*12/B25/B16 -> 0.15778724 | C31: =C9*12/C25/C16 -> 0.16929486 | D31: =D9*12/D25/D16 -> 0.20992992 | E31: =E9*12/E25/E16 -> 0.17351492 | F31: =F9*12/F25/F16 -> 0.14699274 | G31: =G9*12/G25/G16 -> 0.16366062 | H31: =H9*12/H25/H16 -> 0.13705363 | I31: =I9*12/I25/I16 -> 0.12855758
A32: Gross yield — all revenue | B32: =((C5+C8)+B6+B7+B9)*12/B25/B16 -> 0.17247516 | C32: =((D5+D8)+C6+C7+C9)*12/C25/C16 -> 0.22783139 | D32: =((E5+E8)+D6+D7+D9)*12/D25/D16 -> 0.2966082 | E32: =((F5+F8)+E6+E7+E9)*12/E25/E16 -> 0.24957669 | F32: =((G5+G8)+F6+F7+F9)*12/F25/F16 -> 0.27522216 | G32: =((H11+H8)+G12+G7+G9)*12/G25/G16 -> 0.36924809 | H32: =((I11+I8)+H12+H7+H9)*12/H25/H16 -> 0.3528845 | I32: =((J11+J8)+I12+I7+I9)*12/I25/I16 -> 0.34716846
A33: Principal turnover (annualized principal flow ÷ average receivables) | B33: =B22*12/B25/B16 -> 11.971361 | C33: =C22*12/C25/C16 -> 12.065721 | D33: =D22*12/D25/D16 -> 14.959867 | E33: =E22*12/E25/E16 -> 12.217876 | F33: =F22*12/F25/F16 -> 10.713429 | G33: =G22*12/G25/G16 -> 11.603165 | H33: =H22*12/H25/H16 -> 9.8342405 | I33: =I22*12/I25/I16 -> 9.0604617
A35: Reference — conventional basis: all of a month's revenue over that month's own average receivables
A36: Interest and fees | B36: =SUM(B5:B8)*12/B25/B16 -> 0.013445392 | C36: =SUM(C5:C8)*12/C25/C16 -> 0.051919631 | D36: =SUM(D5:D8)*12/D25/D16 -> 0.081554401 | E36: =SUM(E5:E8)*12/E25/E16 -> 0.07595486 | F36: =SUM(F5:F8)*12/F25/F16 -> 0.068192027 | G36: =SUM(G5:G8)*12/G25/G16 -> 0.12078989 | H36: =(H11+H12+H7+H8)*12/H25/H16 -> 0.18678532 | I36: =(I11+I12+I7+I8)*12/I25/I16 -> 0.19975493 | J36: =(J11+J12+J7+J8)*12/J25/J16 -> 0.19129013 | K36: =(K11+K12+K7+K8)*12/K25/K16 -> 0.19271881
A37: Gross yield — all revenue | B37: =SUM(B5:B8)*12/B25/B16+B9*12/B25/B16 -> 0.17123263 | C37: =SUM(C5:C8)*12/C25/C16+C9*12/C25/C16 -> 0.22121449 | D37: =SUM(D5:D8)*12/D25/D16+D9*12/D25/D16 -> 0.29148432 | E37: =SUM(E5:E8)*12/E25/E16+E9*12/E25/E16 -> 0.24946978 | F37: =SUM(F5:F8)*12/F25/F16+F9*12/F25/F16 -> 0.21518477 | G37: =SUM(G5:G8)*12/G25/G16+G9*12/G25/G16 -> 0.2844505 | H37: =(H11+H12+H7+H8)*12/H25/H16+H9*12/H25/H16 -> 0.32383894 | I37: =(I11+I12+I7+I8)*12/I25/I16+I9*12/I25/I16 -> 0.32831251 | J37: =(J11+J12+J7+J8)*12/J25/J16+J9*12/J25/J16 -> 0.34080142 | K37: =(K11+K12+K7+K8)*12/K25/K16+K9*12/K25/K16 -> 0.33184043
A39: Installment plans scaled from March 2026 and revolving interest was introduced with the June 2026 statement cycle, so July–September 2026 is the first quarter with every revenue line in place. Earlier months are shown for completeness on the billed basis. Accrued interest allocates each statement cycle's interest across the calendar days it covers (half the book statements on the 14th, so those cycles straddle two months); it is shown for July–September, where the October 14 cycle is available to complete September. Yields are by book month: a month's balance earns interchange and upfront fees when it is created (that month's purchases and conversions), installment charges on the statements closing in the month (1% of the original plan amount per installment, for every plan outstanding at the close), and revolving interest and late fees the following month (charged on the balance billed at month end, net of payments). The conventional basis is shown for reference; the two coincide when the book is not growing.

Sheet Loss Rate
A1: Loss rate on originated principal — 90+ days past due, vintages since January 2026
A2: PHP. Each row is the principal originated in that month and how much of it sits on an account 90 or more days past due today (data as of 27 October 2026). Vintages begin January 2026, the first full month after the current underwriting model was introduced (December 2025).
A4: Origination month | B4: Accounts | C4: Principal originated | D4: Seasoned principal (due ≥90 days ago) | E4: Excluded: FPD principal 90+ DPD | F4: Denominator: seasoned, ex-FPD | G4: Numerator: 90+ DPD, ex-FPD | H4: Loss rate
A5: Jan 2026 | B5: 3828 | C5: 69900974 | D5: 69900974 | E5: 195035.55 | F5: 69690793 | G5: 1577286.9 | H5: =IF(F5=0,"not yet seasoned",G5/F5) -> 0.022632643
A6: Feb 2026 | B6: 4029 | C6: 60820771 | D6: 60820771 | E6: 31366.54 | F6: 60789405 | G6: 685527.14 | H6: =IF(F6=0,"not yet seasoned",G6/F6) -> 0.011277083
A7: Mar 2026 | B7: 5113 | C7: 89743206 | D7: 89743206 | E7: 562712.45 | F7: 89089555 | G7: 1404938.6 | H7: =IF(F7=0,"not yet seasoned",G7/F7) -> 0.015769959
A8: Apr 2026 | B8: 6505 | C8: 1.0711537e+08 | D8: 1.0711537e+08 | E8: 911016.11 | F8: 1.0612324e+08 | G8: 1471002.6 | H8: =IF(F8=0,"not yet seasoned",G8/F8) -> 0.013861267
A9: May 2026 | B9: 7564 | C9: 1.1818498e+08 | D9: 1.1818498e+08 | E9: 889165.96 | F9: 1.1722674e+08 | G9: 1061583 | H9: =IF(F9=0,"not yet seasoned",G9/F9) -> 0.0090558091
A10: Jun 2026 | B10: 9024 | C10: 1.3641748e+08 | D10: 1.3641748e+08 | E10: 499873.5 | F10: 1.3591761e+08 | G10: 459463.31 | H10: =IF(F10=0,"not yet seasoned",G10/F10) -> 0.0033804547
A11: Jul 2026 | B11: 11366 | C11: 1.4062427e+08 | D11: 0 | E11: 29390.51 | F11: 0 | G11: 8828.19 | H11: =IF(F11=0,"not yet seasoned",G11/F11) -> not yet seasoned
A12: Aug 2026 | B12: 12347 | C12: 1.4188834e+08 | D12: 0 | E12: 0 | F12: 0 | G12: 0 | H12: =IF(F12=0,"not yet seasoned",G12/F12) -> not yet seasoned
A13: Sep 2026 | B13: 13196 | C13: 1.6022121e+08 | D13: 0 | E13: 0 | F13: 0 | G13: 0 | H13: =IF(F13=0,"not yet seasoned",G13/F13) -> not yet seasoned
A14: Since January 2026 (all vintages above) | B14: =SUM(B5:B13) -> 72972 | C14: =SUM(C5:C13) -> 1.0249166e+09 | D14: =SUM(D5:D13) -> 5.8218278e+08 | E14: =SUM(E5:E13) -> 3118560.6 | F14: =SUM(F5:F13) -> 5.7883734e+08 | G14: =SUM(G5:G13) -> 6668629.7 | H14: =G14/F14 -> 0.011520732
A16: How to read this table
A17: • Loss measure. Principal on accounts 90 or more days past due is used as the proxy for loss. Zed fully provisions at 180 days past due and has not yet written off any balances, so no recoveries are assumed and nothing has been reduced for cash collected after an account went delinquent. Interest and fees are excluded from both numerator and denominator.
A18: • Seasoning. The denominator counts only principal whose statement due date is at least 90 days in the past, so the rate is measured on principal that has had the chance to reach 90 days past due. On this basis the July–September 2026 vintages are not yet measurable and are shown for completeness.
A19: • First-payment defaults (FPD). An account whose first statement was never paid: billed once, no payment at all. Zed treats these as fraud and identity losses for its own account rather than credit losses, and excludes them here on that basis. The principal excluded is shown in column E.
A20: • Fraud controls and their timing. Basic duplicate-applicant checks have been part of decisioning since May 2026 and the first set of major improvements to our second generation credit model were released on 5 May 2026 (v2.1). Version 2.1 sharply reduced uncoordinated first-payment default on new accounts: first-payment defaults fell from 1.2–1.5% of cards issued in February–April 2026 to 0.4% of cards issued in May–August. On 24 October 2026 Zed deployed a full suite of fraud-signal policies, informed by its review of first-payment defaults: bank account numbers shared across applicants, repeated selfie or ID images, invite-name mismatches, business-owner income verification and past-due bureau tradelines.
A21: • Why January 2026. The current underwriting model (V2) was deployed in December 2025 and is the model that originates the portfolio today; earlier vintages were originated under the prior model.

Sheet Notes
A1: Definitions and sources
A3: Item | B3: Definition
A4: Scope | B4: Zed's Philippine credit card receivables, all cardholders. Yield Summary covers the June, July and August 2026 books and the three together — the books whose interest was earned in July–September 2026, the first quarter with every revenue line in place (installment plans scaled from March 2026; revolving interest introduced with the June 2026 cycle). Monthly Detail shows January–September 2026. All figures in PHP unless marked USD (converted at 55.8 for reference only).
A5: Book month (yield basis) | B5: Yields are measured by book month: the month's average receivables outstanding (principal, interest and fees billed to cardholders, plus installment principal not yet billed) are the capital employed, and the revenue attributed to them is what that capital earned — interchange and upfront fees when the balance was created (that month's purchases and conversions), installment charges on the month's statements (a fixed charge per installment for every plan outstanding at the close), and revolving interest and late fees the following month, because revolving interest is charged on the balance billed at month end, net of payments (adjusted daily balance), and a purchase earns no interest until it has been statemented. Losses are the loss rate on the principal the month lent. The June, July and August 2026 books are shown — the books whose interest arrived in July–September, the first quarter with every revenue line in place — and the three together, where the denominator is the average of the three months. The conventional basis (a month's revenue over that month's own average receivables) is shown for reference; the two coincide when the book is not growing and differ by roughly the monthly growth rate while it is.
A6: Annualization | B6: Simple: monthly amount ÷ the book month's average receivables × 12. No compounding.
A7: Revolving interest | B7: Finance charge on billed balances not paid in full by the due date; 3% per month, the BSP ceiling. Under the BSP's credit card rules interest is charged only on billed balances, so purchases earn no interest until they are statemented, and balances paid within the grace period never do. Launched with the statement cycle closing 30 June 2026. Yield Summary uses an accrual basis: each statement cycle's interest is allocated evenly across the calendar days the cycle covers (cycles close on the 14th and on the last day of the month); Monthly Detail carries the billed basis, which ties to management reporting.
A8: Installment interest and upfront fees | B8: Installment interest is 1% of the original plan amount per installment (add-on), billed together with the principal installment on every statement closing while the plan is outstanding, starting with the first statement after conversion; on the declining balance it is about 1.5% per month. The upfront conversion fee is 0.5% per month of term, billed when a purchase is converted. Both are attributed to the book month: the fee to the month of conversion, the interest to the month whose statements carried the installment (14th-close statements allocated across their cycle days).
A9: Late payment fees | B9: Fee billed when the minimum payment is not received by the due date.
A10: Interchange | B10: Interchange received from Mastercard on cardholder purchases, gross (network and processing costs are not netted). Interchange is earned when a purchase settles, not on balances, so its yield on receivables is shown as interchange rate on purchase volume × purchase turnover (annualized purchase volume ÷ the book month's average receivables) — the same construction as the loss line. Mastercard settles the merchant net of interchange and the cardholder is billed the full purchase amount, so the interchange margin is collected as part of the cardholder's payment.
A11: Turnover | B11: Annualized flow in the book month ÷ its average receivables. Purchase turnover uses Mastercard purchase volume (the interchange base); principal turnover uses principal flow (the loss base). They differ only by pay-a-friend transfers.
A12: Principal flow | B12: Calendar-month flow of new receivables: Mastercard purchase volume net of returns plus pay-a-friend transfers (cardholder-to-cardholder transfers charged to the card, which earn no interchange). This is the loss base in the Yield Summary.
A13: Principal originated (Loss Rate tab) | B13: The same quantity measured by statement month: charges on statements closing in the month (cycles close on the 14th and the last day), net of refunds, chargebacks and cancelled installment-plan re-bookings. The loss rate is measured on this basis because delinquency is tracked by statement; a statement month covers roughly the second half of the prior calendar month and the first half of the current one, so individual months differ from the calendar flow by timing while the two agree over longer windows (Jan–Sep 2026: ₱1,025M vs ₱1,035M).
A14: Loss rate | B14: Principal on accounts 90 or more days past due today, divided by originated principal on statements whose due date is at least 90 days old, for origination months January–September 2026 (in practice January–June, the vintages old enough to be measured), excluding first-payment-default accounts from both numerator and denominator. The window, the seasoning rule and the FPD definition are set out on the Loss Rate tab, which also shows the FPD principal excluded. Gross of recoveries; no balances have been written off to date (full provision at 180 DPD).
... A18: Prepared | B18: Zed Financial, October 2026, in connection with the evaluation of a receivables facility.
