Workbook
Name loss_rate_xfpd: 'Loss Rate'!$H$14

Sheet Yield Summary
A1: Zed — Portfolio yield on receivables
A2: Gross and net yield on average receivables outstanding, annualized. July, August and September 2026 and the quarter together. PHP; before operating, servicing and funding costs.
B4: Jul 2026 | C4: Annualized | D4: Aug 2026 | E4: Annualized | F4: Sep 2026 | G4: Annualized | H4: Jul–Sep 2026 | I4: Annualized | J4: Notes
A5: Months in period | B5: 1 | D5: 1 | F5: 1 | H5: 3
A6: Average receivables outstanding | B6: ='Monthly Detail'!H16 | D6: ='Monthly Detail'!I16 | F6: ='Monthly Detail'!J16 | H6: ='Monthly Detail'!K16 | J6: Monthly average of daily receivables; the quarter is the average of the three monthly averages.
A7: Interest and fees — earned on balances
A8: Revolving interest (accrued) | B8: ='Monthly Detail'!H11 | C8: =B8*12/B$5/B$6 | D8: ='Monthly Detail'!I11 | E8: =D8*12/D$5/D$6 | F8: ='Monthly Detail'!J11 | G8: =F8*12/F$5/F$6 | H8: ='Monthly Detail'!K11 | I8: =H8*12/H$5/H$6 | J8: Charged at 3% per month (BSP cap) on billed balances not paid in full by the due date; interest is only charged after a balance is statemented, so unbilled purchases and balances paid within the grace period earn no interest. Accrual basis: statement interest allocated across the calendar days of each cycle (billed basis shown as memo below).
A9: Installment interest (accrued) | B9: ='Monthly Detail'!H12 | C9: =B9*12/B$5/B$6 | D9: ='Monthly Detail'!I12 | E9: =D9*12/D$5/D$6 | F9: ='Monthly Detail'!J12 | G9: =F9*12/F$5/F$6 | H9: ='Monthly Detail'!K12 | I9: =H9*12/H$5/H$6 | J9: 1% per month on installment balances; accrual basis.
A10: Installment upfront fees | B10: ='Monthly Detail'!H7 | C10: =B10*12/B$5/B$6 | D10: ='Monthly Detail'!I7 | E10: =D10*12/D$5/D$6 | F10: ='Monthly Detail'!J7 | G10: =F10*12/F$5/F$6 | H10: ='Monthly Detail'!K7 | I10: =H10*12/H$5/H$6 | J10: 0.5% × term in months, billed at conversion.
A11: Late payment fees | B11: ='Monthly Detail'!H8 | C11: =B11*12/B$5/B$6 | D11: ='Monthly Detail'!I8 | E11: =D11*12/D$5/D$6 | F11: ='Monthly Detail'!J8 | G11: =F11*12/F$5/F$6 | H11: ='Monthly Detail'!K8 | I11: =H11*12/H$5/H$6
A12: Interest and fees | B12: =SUM(B8:B11) | C12: =B12*12/B$5/B$6 | D12: =SUM(D8:D11) | E12: =D12*12/D$5/D$6 | F12: =SUM(F8:F11) | G12: =F12*12/F$5/F$6 | H12: =SUM(H8:H11) | I12: =H12*12/H$5/H$6
A14: Interchange — earned on purchases, so a function of turnover
A15: Purchase volume settled | B15: ='Monthly Detail'!H19 | D15: ='Monthly Detail'!I19 | F15: ='Monthly Detail'!J19 | H15: ='Monthly Detail'!K19 | J15: Cardholder purchases settled through Mastercard, net of returns.
A16: Purchase turnover (annualized purchase volume ÷ average receivables) | C16: =B15*12/B$5/B$6 | E16: =D15*12/D$5/D$6 | G16: =F15*12/F$5/F$6 | I16: =H15*12/H$5/H$6 | J16: How many times a year the book is re-spent. Falls as more of the book revolves.
A17: Interchange rate on purchase volume | C17: =B18/B15 | E17: =D18/D15 | G17: =F18/F15 | I17: =H18/H15 | J17: Set by Mastercard by merchant category and domestic/foreign; gross of network and processing costs.
A18: Interchange income | B18: ='Monthly Detail'!H9 | C18: =C17*C16 | D18: ='Monthly Detail'!I9 | E18: =E17*E16 | F18: ='Monthly Detail'!J9 | G18: =G17*G16 | H18: ='Monthly Detail'!K9 | I18: =I17*I16 | J18: Yield on receivables = interchange rate × purchase turnover. Mastercard settles each purchase to the merchant net of interchange and the cardholder is billed the full amount, so interchange is collected through cardholder payments. It is earned once, when the receivable is created; a balance that then revolves earns interest, not further interchange.
A20: Gross yield (annualized, on average receivables)
A21: Gross yield — interest and fees | C21: =C12 | E21: =E12 | G21: =G12 | I21: =I12
A22: Gross yield — all revenue, including interchange | B22: =B12+B18 | C22: =C12+C18 | D22: =D12+D18 | E22: =E12+E18 | F22: =F12+F18 | G22: =G12+G18 | H22: =H12+H18 | I22: =I12+I18 | J22: Amount column: total revenue for the period on the accrual basis (Monthly Detail).
A23: Memo: revolving + installment interest, billed basis (statements closing in the month) | B23: ='Monthly Detail'!H5+'Monthly Detail'!H6 | C23: =B23*12/B$5/B$6 | D23: ='Monthly Detail'!I5+'Monthly Detail'!I6 | E23: =D23*12/D$5/D$6 | F23: ='Monthly Detail'!J5+'Monthly Detail'!J6 | G23: =F23*12/F$5/F$6 | H23: ='Monthly Detail'!K5+'Monthly Detail'!K6 | I23: =H23*12/H$5/H$6 | J23: Management reporting basis; lower than accrued in a growing book because the 14th-close cycles lag the calendar month by about two weeks.
A25: Loss on receivables — also a function of turnover
A26: Principal flow in period (purchase volume + pay-a-friend transfers) | B26: ='Monthly Detail'!H21 | D26: ='Monthly Detail'!I21 | F26: ='Monthly Detail'!J21 | H26: ='Monthly Detail'!K21 | J26: Everything that became a receivable in the month: Mastercard purchases net of returns plus pay-a-friend transfers (which earn no interchange). Calendar-month, same basis as average receivables.
A27: Principal turnover (annualized principal flow ÷ average receivables) | C27: =B26*12/B$5/B$6 | E27: =D26*12/D$5/D$6 | G27: =F26*12/F$5/F$6 | I27: =H26*12/H$5/H$6 | J27: Each peso of receivables is re-lent several times a year, so a loss rate on originations must be multiplied by turnover to compare it with a yield on balances. Differs from purchase turnover only by pay-a-friend.
A28: Loss rate on originated principal — ≥90 DPD, excluding first-payment defaults | C28: =loss_rate_xfpd | E28: =loss_rate_xfpd | G28: =loss_rate_xfpd | I28: =loss_rate_xfpd | J28: See the Loss Rate tab. Principal 90+ days past due ÷ originated principal on statements whose due date is ≥90 days old, vintages since January 2026, gross of recoveries; first-payment-default accounts (never made a payment; fraud/identity rather than credit) excluded from numerator and denominator. The same rate is applied to every period.
A29: Loss on receivables (loss rate × principal turnover) | C29: =C28*C27 | E29: =E28*E27 | G29: =G28*G27 | I29: =I28*I27
A31: Net yield
A32: Net yield — all revenue less loss on receivables | C32: =C22-C29 | E32: =E22-E29 | G32: =G22-G29 | I32: =I22-I29 | J32: Before operating, servicing and funding costs.
A34: Memo — USD equivalents
A35: PHP per USD | B35: 55.8 | D35: 55.8 | F35: 55.8 | H35: 55.8
A36: Average receivables outstanding (USD) | B36: =B6/B35 | D36: =D6/D35 | F36: =F6/F35 | H36: =H6/H35
A37: Total revenue (USD) | B37: =B22/B35 | D37: =D22/D35 | F37: =F22/F35 | H37: =H22/H35
A38: Principal flow (USD) | B38: =B26/B35 | D38: =D26/D35 | F38: =F26/F35 | H38: =H26/H35

Sheet Monthly Detail
A1: Monthly revenue, receivables and originations — January to September 2026
A2: PHP. Revenue is recognised in the month billed (interest and fees) or settled (interchange). Yields are annualized simply: month ÷ average receivables × 12.
A4: Line | B4: Jan 2026 | C4: Feb 2026 | D4: Mar 2026 | E4: Apr 2026 | F4: May 2026 | G4: Jun 2026 | H4: Jul 2026 | I4: Aug 2026 | J4: Sep 2026 | K4: Jul–Sep 2026
A5: Revolving interest | B5: 0 | C5: 0 | D5: 0 | E5: 0 | F5: 0 | G5: 685463.41 | H5: 1501634.9 | I5: 1951592 | J5: 2229680 | K5: =SUM(H5:J5)
A6: Installment interest | B6: 1316.21 | C6: 47765.48 | D6: 134016.53 | E6: 220070.96 | F6: 257582.01 | G6: 340853.06 | H6: 403236.04 | I6: 445213.13 | J6: 486325.05 | K6: =SUM(H6:J6)
A7: Installment upfront fees | B7: 2185.69 | C7: 146390.53 | D7: 291311.38 | E7: 307856.48 | F7: 320397.94 | G7: 337749.34 | H7: 290513.47 | I7: 341458.41 | J7: 439733.93 | K7: =SUM(H7:J7)
A8: Late payment fees | B8: 64707.62 | C8: 71011.07 | D8: 104805.31 | E8: 138112.4 | F8: 139049.93 | G8: 84871.59 | H8: 89421.49 | I8: 108174.67 | J8: 126426.4 | K8: =SUM(H8:J8)
A9: Interchange | B9: 800466.96 | C9: 864632.93 | D9: 1364620.7 | E9: 1521533.3 | F9: 1545608.6 | G9: 1963194.1 | H9: 1811444.7 | I9: 1892210.1 | J9: 2630889.8 | K9: =SUM(H9:J9)
A10: Total revenue — billed basis (ties to management reporting) | B10: =SUM(B5:B9) | C10: =SUM(C5:C9) | D10: =SUM(D5:D9) | E10: =SUM(E5:E9) | F10: =SUM(F5:F9) | G10: =SUM(G5:G9) | H10: =SUM(H5:H9) | I10: =SUM(I5:I9) | ... K10: =SUM(K5:K9)
A11: Revolving interest — accrued (calendar month) | H11: 1658171.4 | I11: 2023314.9 | J11: 2282599.6 | K11: =SUM(H11:J11)
A12: Installment interest — accrued (calendar month) | H12: 430644.66 | I12: 467199.88 | J12: 517295.33 | K12: =SUM(H12:J12)
A13: Total revenue — accrual basis (used in Yield Summary) | H13: =H11+H12+H7+H8+H9 | I13: =I11+I12+I7+I8+I9 | J13: =J11+J12+J7+J8+J9 | K13: =K11+K12+K7+K8+K9
A15: Balances and volumes
A16: Average receivables outstanding | B16: 60876935 | C16: 61287126 | D16: 78004358 | E16: 1.0522668e+08 | F16: 1.2617837e+08 | G16: 1.4394623e+08 | H16: 1.5860461e+08 | I16: 1.766253e+08 | J16: 2.1115916e+08 | K16: =AVERAGE(H16:J16)
A17: Receivables outstanding, end of month | B17: 59172827 | C17: 63401424 | D17: 92607291 | E17: 1.1784608e+08 | F17: 1.3451065e+08 | G17: 1.5338181e+08 | H17: 1.6382741e+08 | I17: 1.8942319e+08 | J17: 2.3289513e+08 | K17: =J17
A18: Principal originated, statement-month basis (base on which the loss rate is measured) | B18: 69900974 | C18: 60820771 | D18: 89743206 | E18: 1.0711537e+08 | F18: 1.1818498e+08 | G18: 1.3641748e+08 | H18: 1.4062427e+08 | I18: 1.4188834e+08 | J18: 1.6022121e+08 | K18: =SUM(H18:J18)
A19: Purchase volume settled (Mastercard, net of returns) | B19: 59671645 | C19: 60642781 | D19: 95344566 | E19: 1.0594721e+08 | F19: 1.1040024e+08 | G19: 1.3714599e+08 | H19: 1.2724966e+08 | I19: 1.303889e+08 | J19: 1.9086099e+08 | K19: =SUM(H19:J19)
A20: Pay-a-friend transfers (cardholder-to-cardholder, charged to the card; no interchange) | B20: 1060000 | C20: 980000 | D20: 1900000 | E20: 1190000 | F20: 2250000 | G20: 2040000 | H20: 2730000 | I20: 2970000 | J20: 2650000 | K20: =SUM(H20:J20)
A21: Principal flow (purchase volume + pay-a-friend) — calendar-month loss base | B21: =B19+B20 | C21: =C19+C20 | D21: =D19+D20 | E21: =E19+E20 | F21: =F19+F20 | G21: =G19+G20 | H21: =H19+H20 | I21: =I19+I20 | ... K21: =K19+K20
A23: Annualized yields on average receivables
A24: Months in period | B24: 1 | C24: 1 | D24: 1 | E24: 1 | F24: 1 | G24: 1 | H24: 1 | I24: 1 | J24: 1 | K24: 3
A25: Interest and fees (revolving + installment + late) — accrual basis Jul–Sep, billed before | B25: =SUM(B5:B8)*12/B24/B16 | C25: =SUM(C5:C8)*12/C24/C16 | D25: =SUM(D5:D8)*12/D24/D16 | E25: =SUM(E5:E8)*12/E24/E16 | F25: =SUM(F5:F8)*12/F24/F16 | G25: =SUM(G5:G8)*12/G24/G16 | H25: =(H11+H12+H7+H8)*12/H24/H16 | I25: =(I11+I12+I7+I8)*12/I24/I16 | J25: =(J11+J12+J7+J8)*12/J24/J16 | K25: =(K11+K12+K7+K8)*12/K24/K16
A26: Interchange | B26: =B9*12/B24/B16 | C26: =C9*12/C24/C16 | D26: =D9*12/D24/D16 | E26: =E9*12/E24/E16 | F26: =F9*12/F24/F16 | G26: =G9*12/G24/G16 | H26: =H9*12/H24/H16 | I26: =I9*12/I24/I16 | ... K26: =K9*12/K24/K16
A27: Gross yield — all revenue | B27: =B10*12/B24/B16 | C27: =C10*12/C24/C16 | D27: =D10*12/D24/D16 | E27: =E10*12/E24/E16 | F27: =F10*12/F24/F16 | G27: =G10*12/G24/G16 | H27: =H13*12/H24/H16 | I27: =I13*12/I24/I16 | J27: =J13*12/J24/J16 | K27: =K13*12/K24/K16
A28: Principal turnover (annualized principal flow ÷ average receivables) | B28: =B21*12/B24/B16 | C28: =C21*12/C24/C16 | D28: =D21*12/D24/D16 | E28: =E21*12/E24/E16 | F28: =F21*12/F24/F16 | G28: =G21*12/G24/G16 | H28: =H21*12/H24/H16 | I28: =I21*12/I24/I16 | ... K28: =K21*12/K24/K16
A29: Purchase turnover (annualized purchase volume ÷ average receivables) | B29: =B19*12/B24/B16 | C29: =C19*12/C24/C16 | D29: =D19*12/D24/D16 | E29: =E19*12/E24/E16 | F29: =F19*12/F24/F16 | G29: =G19*12/G24/G16 | H29: =H19*12/H24/H16 | I29: =I19*12/I24/I16 | ... K29: =K19*12/K24/K16
A30: Interchange rate on purchase volume | B30: =B9/B19 | C30: =C9/C19 | D30: =D9/D19 | E30: =E9/E19 | F30: =F9/F19 | G30: =G9/G19 | H30: =H9/H19 | I30: =I9/I19 | ... K30: =K9/K19
A32: Installment plans scaled from March 2026 and revolving interest was introduced with the June 2026 statement cycle, so July–September 2026 is the first quarter with every revenue line in place. Earlier months are shown for completeness on the billed basis. Accrued interest allocates each statement cycle's interest across the calendar days it covers (half the book statements on the 14th, so those cycles straddle two months); it is shown for July–September, where the October 14 cycle is available to complete September.

Sheet Loss Rate
A1: Loss rate on originated principal — 90+ days past due, vintages since January 2026
A2: PHP. Each row is the principal originated in that month and how much of it sits on an account 90 or more days past due today (data as of 27 October 2026). Vintages begin January 2026, the first full month after the current underwriting model was introduced (December 2025).
A4: Origination month | B4: Accounts | C4: Principal originated | D4: Seasoned principal (due ≥90 days ago) | E4: Excluded: FPD principal 90+ DPD | F4: Denominator: seasoned, ex-FPD | G4: Numerator: 90+ DPD, ex-FPD | H4: Loss rate
A5: Jan 2026 | B5: 3828 | C5: 69900974 | D5: 69900974 | E5: 195035.55 | F5: 69690793 | G5: 1577286.9 | H5: =IF(F5=0,"not yet seasoned",G5/F5)
A6: Feb 2026 | B6: 4029 | C6: 60820771 | D6: 60820771 | E6: 31366.54 | F6: 60789405 | G6: 685527.14 | H6: =IF(F6=0,"not yet seasoned",G6/F6)
A7: Mar 2026 | B7: 5113 | C7: 89743206 | D7: 89743206 | E7: 562712.45 | F7: 89089555 | G7: 1404938.6 | H7: =IF(F7=0,"not yet seasoned",G7/F7)
A8: Apr 2026 | B8: 6505 | C8: 1.0711537e+08 | D8: 1.0711537e+08 | E8: 911016.11 | F8: 1.0612324e+08 | G8: 1471002.6 | H8: =IF(F8=0,"not yet seasoned",G8/F8)
A9: May 2026 | B9: 7564 | C9: 1.1818498e+08 | D9: 1.1818498e+08 | E9: 889165.96 | F9: 1.1722674e+08 | G9: 1061583 | H9: =IF(F9=0,"not yet seasoned",G9/F9)
A10: Jun 2026 | B10: 9024 | C10: 1.3641748e+08 | D10: 1.3641748e+08 | E10: 499873.5 | F10: 1.3591761e+08 | G10: 459463.31 | H10: =IF(F10=0,"not yet seasoned",G10/F10)
A11: Jul 2026 | B11: 11366 | C11: 1.4062427e+08 | D11: 0 | E11: 29390.51 | F11: 0 | G11: 8828.19 | H11: =IF(F11=0,"not yet seasoned",G11/F11)
A12: Aug 2026 | B12: 12347 | C12: 1.4188834e+08 | D12: 0 | E12: 0 | F12: 0 | G12: 0 | H12: =IF(F12=0,"not yet seasoned",G12/F12)
A13: Sep 2026 | B13: 13196 | C13: 1.6022121e+08 | D13: 0 | E13: 0 | F13: 0 | G13: 0 | H13: =IF(F13=0,"not yet seasoned",G13/F13)
A14: Since January 2026 (all vintages above) | B14: =SUM(B5:B13) | C14: =SUM(C5:C13) | D14: =SUM(D5:D13) | E14: =SUM(E5:E13) | F14: =SUM(F5:F13) | G14: =SUM(G5:G13) | H14: =G14/F14
A16: How to read this table
A17: • Loss measure. Principal on accounts 90 or more days past due is used as the proxy for loss. Zed fully provisions at 180 days past due and has not yet written off any balances, so no recoveries are assumed and nothing has been reduced for cash collected after an account went delinquent. Interest and fees are excluded from both numerator and denominator.
A18: • Seasoning. The denominator counts only principal whose statement due date is at least 90 days in the past, so the rate is measured on principal that has had the chance to reach 90 days past due. On this basis the July–September 2026 vintages are not yet measurable and are shown for completeness.
A19: • First-payment defaults (FPD). An account whose first-ever statement was the one missed, i.e. a cardholder who never made a payment. These are fraud or identity cases rather than credit losses and are excluded from the loss rate; the principal excluded is shown in column E so the adjustment is visible. Receivables of this kind would ordinarily fall outside facility eligibility criteria. First-payment default is managed separately from credit underwriting: duplicate-applicant checks (exact name and date of birth, ID number) have been in place since 1 October 2026, and from the 24 October 2026 decisioning run every application is screened for bank account numbers shared with another applicant, repeated selfie or ID images, invite-name mismatches and past-due bureau tradelines, with business-owner limits set on half of declared income pending documents.
A20: • Why January 2026. The current underwriting model (V2) was deployed in December 2025 and is the model that originates the portfolio today; earlier vintages were originated under the prior model.
A22: Loss emergence — when a vintage's loss arrives (ex-FPD, same measure as the table above)
A23: Origination month | B23: By month 3 on book | C23: By month 4 | D23: By month 5 | E23: By month 6 | F23: By month 8 | G23: Today | H23: Months on book today
A24: Jan 2026 | B24: 0.00675 | C24: 0.02263 | D24: 0.02263 | E24: 0.02263 | F24: 0.02263 | G24: 0.02263 | H24: 9
A25: Feb 2026 | B25: 0.00851 | C25: 0.01028 | D25: 0.01118 | E25: 0.01128 | F25: — | G25: 0.01128 | H25: 8
A26: Mar 2026 | B26: 0.00455 | C26: 0.01469 | D26: 0.01577 | E26: 0.01577 | F26: — | G26: 0.01577 | H26: 7
A27: Apr 2026 | B27: 0.00773 | C27: 0.01313 | D27: 0.01366 | E27: — | F27: — | G27: 0.01386 | H27: 6
A28: May 2026 | B28: 0.00494 | C28: 0.00758 | D28: — | E28: — | F28: — | G28: 0.00906 | H28: 5
A29: Jun 2026 | B29: 0.00215 | C29: — | D29: — | E29: — | F29: — | G29: 0.00338 | H29: 4
A30: How to read this table
A31: • Each cell is the part of the vintage's loss rate (principal ≥90 DPD today ÷ seasoned principal, ex-FPD — the same measure as the table above) that comes from accounts which had reached 90 days past due by the end of month n after the origination month. 'Today' is the full current loss rate. Cells are blank where month n has not yet ended.
A32: • The loss on a vintage is essentially complete by month 4 on book: January–March 2026 show no further movement from month 4 to month 6–8. Because cash is applied to the oldest balances first, an account that defaults later has already repaid its earlier months' purchases, so late defaults fall on later vintages rather than reopening old ones.
A33: • Read across the 'Today' column for the trend in fully emerged vintages: 2.26% (Jan), 1.13% (Feb), 1.58% (Mar), 1.39% (Apr), 0.91% (May, at month 5 — effectively final). June is at month 4 with one month of emergence still to come.

Sheet Notes
A1: Definitions and sources
A3: Item | B3: Definition
A4: Scope | B4: Zed's Philippine credit card receivables, all cardholders. Yield Summary covers July, August and September 2026 and the quarter together — the first quarter with every revenue line in place (installment plans scaled from March 2026; revolving interest introduced with the June 2026 cycle). Monthly Detail shows January–September 2026. All figures in PHP unless marked USD (converted at 55.8 for reference only).
A5: Average receivables | B5: Monthly average of receivables outstanding (principal, interest and fees billed to cardholders, plus installment principal not yet billed). The July–September figure is the simple average of the three monthly averages, and yields for the quarter are revenue for the three months × 12 ÷ 3 ÷ that average.
A6: Annualization | B6: Simple: monthly amount ÷ average receivables × 12. No compounding.
A7: Revolving interest | B7: Finance charge on billed balances not paid in full by the due date; 3% per month, the BSP ceiling. Under the BSP's credit card rules interest is charged only on billed balances, so purchases earn no interest until they are statemented, and balances paid within the grace period never do. Launched with the statement cycle closing 30 June 2026. Yield Summary uses an accrual basis: each statement cycle's interest is allocated evenly across the calendar days the cycle covers (cycles close on the 14th and on the last day of the month), so the numerator and the calendar-average denominator cover the same days; the billed basis is shown as a memo and ties to management reporting.
A8: Installment interest and upfront fees | B8: Interest of 1% per month billed on installment plan balances (accrual basis in the Yield Summary, as for revolving interest), and an upfront conversion fee of 0.5% per month of term billed when a purchase is converted to installments.
A9: Late payment fees | B9: Fee billed when the minimum payment is not received by the due date.
A10: Interchange | B10: Interchange received from Mastercard on cardholder purchases, gross (network and processing costs are not netted). Interchange is earned when a purchase settles, not on balances, so its yield on receivables is shown as interchange rate on purchase volume × purchase turnover (annualized purchase volume ÷ average receivables) — the same construction as the loss line. Mastercard settles the merchant net of interchange and the cardholder is billed the full purchase amount, so the interchange margin is collected as part of the cardholder's payment.
A11: Turnover | B11: Annualized flow ÷ average receivables. Purchase turnover uses Mastercard purchase volume (the interchange base); principal turnover uses principal flow (the loss base). They differ only by pay-a-friend transfers.
A12: Principal flow | B12: Calendar-month flow of new receivables: Mastercard purchase volume net of returns plus pay-a-friend transfers (cardholder-to-cardholder transfers charged to the card, which earn no interchange). This is the loss base in the Yield Summary and is on the same calendar basis as average receivables.
A13: Principal originated (Loss Rate tab) | B13: The same quantity measured by statement month: charges on statements closing in the month (cycles close on the 14th and the last day), net of refunds, chargebacks and cancelled installment-plan re-bookings. The loss rate is measured on this basis because delinquency is tracked by statement; a statement month covers roughly the second half of the prior calendar month and the first half of the current one, so individual months differ from the calendar flow by timing while the two agree over longer windows (Jan–Sep 2026: ₱1,025M vs ₱1,035M).
A14: Loss rate | B14: Principal on accounts 90 or more days past due today, divided by originated principal on statements whose due date is at least 90 days old, for origination months January–September 2026 (in practice January–June, the vintages old enough to be measured), excluding first-payment-default accounts from both numerator and denominator. The window, the seasoning rule and the FPD definition are set out on the Loss Rate tab, which also shows the FPD principal excluded. Gross of recoveries; no balances have been written off to date (full provision at 180 DPD).
... A18: Prepared | B18: Zed Financial, October 2026. Prepared for Accial Capital in connection with its evaluation of a receivables facility.
