Workbook
Name ForEx: Monthly!$C$2
Name IQ_CH: 110000
Name IQ_CQ: 5000
Name IQ_CY: 10000
Name IQ_DAILY: 500000
Name IQ_FH: 100000
Name IQ_FQ: 500
Name IQ_FWD_CY: 10001
Name IQ_FWD_CY1: 10002
Name IQ_FWD_CY2: 10003
Name IQ_FWD_FY: 1001
Name IQ_FWD_FY1: 1002
Name IQ_FWD_FY2: 1003
Name IQ_FWD_Q: 501
Name IQ_FWD_Q1: 502
Name IQ_FWD_Q2: 503
Name IQ_FY: 1000
Name IQ_LATESTK: 1000
Name IQ_LATESTQ: 500
Name IQ_LTM: 2000
Name IQ_LTMMONTH: 120000
Name IQ_MONTH: 15000
Name IQ_NTM: 6000
Name IQ_TODAY: 0
Name IQ_WEEK: 50000
Name IQ_YTD: 3000
Name IQ_YTDMONTH: 130000

Sheet KPIs Definition
B2: KPI | C2: Definition | D2: Data Source
B3: Monthly Active Users (MAU) | C3: Customers that have generated revenue in the last 30 calendar days | D3: 1. i2cTransaction History Settlement Extract 2. Late Payment Fee Allocation 3. Wye Customer List (for user ID) 4. DFC file - date 01
B4: Monthly/Daily Transacting Users | C4: Customers that have at least 1 transaction in the last 30 calendar days/24 hours | D4: BQ
B5: Settlement Volume + Returns | C5: Gross Settlements - Returns Settlements in USD are translated to PHP using the actual average forex rate from Mastercard | D5: i2C, Network Settlement Summary
B6: Users | C6: Total number of cardholders in Open/Active status as of the end of the month. Does not include Closed accounts | D6: Wye Customer List
B7: Revolvers | C7: Number of accounts that have revolved the balance in the past 30 days | D7: i2C, SSRP_DFC File
B8: Interest-Earning Portfolio | C8: Total outstanding balance earning interest (including accounts that are past due) | D8: i2C, SSRP_DFC File
B9: Interchange Fee Income | C9: Interchange fee revenue earned from the merchant's side of each card transaction. Interchange fee revenue in USD is translated to PHP using the actual average forex rate from Mastercard | D9: i2C, Network Settlement Summary
B10: Late Payment Fee | C10: Late payment fees collected | D10: Late Payment Fee Allocation using Late Payment Fee and Payment Transactions from i2C
B11: Installments Revenue (Interest on Installments) | C11: Interests billed on outstanding installment principal including final interest charges upon termination | D11: i2C, Transaction History Settlement Extract
B12: Installments Revenue (Upfront Fee) | C12: One-time set-up fee billed on conversion of purchases into installment | D12: i2C, Transaction History Settlement Extract
B13: Finance Charge (Revolving) | C13: Accrued interests on revolving principal balance | D13: i2C, SSRP_DFC File
... B22: Balance Paymens Volume | C22: Total customer payments received in the last 30 days | D22: i2C, Transaction History Settlement Extract

Sheet Monthly
A1: Monthly KPIs
B2: Forex | C2: 55.8
C4: Ready to ship | D4: Ready to ship | E4: Ready to ship | F4: Ready to ship | G4: Ready to ship | H4: Ready to ship | I4: Ready to ship | J4: Ready to ship | K4: Ready to ship | L4: Ready to ship | M4: Ready to ship | N4: Ready to ship | O4: Ready to ship | P4: Ready to ship | Q4: Ready to ship | R4: Ready to ship | S4: Ready to ship | T4: Ready to ship | U4: Ready to ship | V4: Ready to ship | W4: Ready to ship
C5: 45688 | D5: 45716 | E5: 45747 | F5: 45777 | G5: 45808 | H5: 45838 | I5: 45869 | J5: 45900 | K5: 45930 | L5: 45961 | M5: 45991 | N5: 46022 | O5: 46053 | P5: 46081 | Q5: 46112 | R5: 46142 | S5: 46173 | T5: 46203 | U5: 46234 | V5: 46265 | W5: 46295
B6: CORE METRICS
B7: Monthly Active Users (Revenue) | C7: 400 | D7: 477 | E7: 554 | F7: 705 | G7: 912 | H7: 1354 | I7: 1596 | J7: 1892 | K7: 2391 | L7: 2431 | M7: 2429 | N7: 2672 | O7: 2767 | P7: 3406 | Q7: 4243 | R7: 5339 | S7: 6252 | T7: 7638 | U7: 8555 | V7: 9269 | W7: 11608
B8: Monthly Active Rate | C8: =C7/C23 -> 0.91012514 | D8: =D7/D23 -> 0.82525952 | E8: =E7/E23 -> 0.79597701 | F8: =F7/F23 -> 0.82843713 | G8: =G7/G23 -> 0.80886918 | H8: =H7/H23 -> 0.86324514 | I8: =I7/I23 -> 0.77306854 | J8: =J7/J23 -> 0.70994371 | ... W8: =W7/W23 -> 0.78700973
B10: Monthly Average Revenue Per Active Cardholder / Active User | C10: =C40/C7 -> 577.5386 | D10: =D40/D7 -> 483.81593 | E10: =E40/E7 -> 475.31238 | F10: =F40/F7 -> 442.19067 | G10: =G40/G7 -> 384.11937 | H10: =H40/H7 -> 346.40899 | I10: =I40/I7 -> 361.28972 | J10: =J40/J7 -> 332.19091 | ... W10: =W40/W7 -> 509.39483
B11: Monthly Average Revenue Per Active Cardholder $ / Active User | C11: =C10/$C$2 -> 10.350154 | D11: =D10/$C$2 -> 8.6705364 | E11: =E10/$C$2 -> 8.5181431 | F11: =F10/$C$2 -> 7.9245639 | G11: =G10/$C$2 -> 6.8838598 | H11: =H10/$C$2 -> 6.2080464 | I11: =I10/$C$2 -> 6.4747261 | J11: =J10/$C$2 -> 5.9532421 | ... W11: =W10/$C$2 -> 9.1289396 | X11: =15/X68 -> 0.046012194
B12: MoM Growth | C12: =C10/581.56-1 -> -0.0069148497 | D12: =D10/C10-1 -> -0.16227949 | E12: =E10/D10-1 -> -0.017576003 | F12: =F10/E10-1 -> -0.069684101 | G12: =G10/F10-1 -> -0.13132636 | H12: =H10/G10-1 -> -0.098173613 | I12: =I10/H10-1 -> 0.042957112 | J12: =J10/I10-1 -> -0.080541481 | K12: =K10/J10-1 -> 0.17627139 | ... W12: =W10/V10-1 -> -0.0036018034
B14: Monthly Transacting Users | C14: 398 | D14: 483 | E14: 567 | F14: 715 | G14: 951 | H14: 1369 | I14: 1628 | J14: 1985 | K14: 2380 | L14: 2459 | M14: 2490 | N14: 2699 | O14: 2695 | P14: 3350 | Q14: 4178 | R14: 5252 | S14: 6143 | T14: 7479 | U14: 8387 | V14: 9089 | W14: 11374
B15: MoM Growth | C15: =C14/296-1 -> 0.34459459 | D15: =D14/C14-1 -> 0.21356784 | E15: =E14/D14-1 -> 0.17391304 | F15: =F14/E14-1 -> 0.26102293 | G15: =G14/F14-1 -> 0.33006993 | H15: =H14/G14-1 -> 0.43953733 | I15: =I14/H14-1 -> 0.18918919 | J15: =J14/I14-1 -> 0.21928747 | K15: =K14/J14-1 -> 0.19899244 | ... W15: =W14/V14-1 -> 0.25140279
B16: Monthly Transact Rate | C16: =C14/C23 -> 0.90557452 | D16: =D14/D23 -> 0.83564014 | E16: =E14/E23 -> 0.81465517 | F16: =F14/F23 -> 0.84018801 | G16: =G14/G23 -> 0.84345898 | H16: =H14/H23 -> 0.87280842 | I16: =I14/I23 -> 0.78856866 | J16: =J14/J23 -> 0.74484053 | ... W16: =W14/W23 -> 0.77114478
B17: MoM Growth | C17: =C16/296-1 -> -0.99694063 | D17: =D16/C16-1 -> -0.077226531 | E17: =E16/D16-1 -> -0.025112444 | F17: =F16/E16-1 -> 0.031341901 | G17: =G16/F16-1 -> 0.0038931357 | H17: =H16/G16-1 -> 0.034796518 | I17: =I16/H16-1 -> -0.096515746 | J17: =J16/I16-1 -> -0.05545254 | K17: =K16/J16-1 -> 0.0011953193 | ... W17: =W16/V16-1 -> 0.083836401
B19: SUPPORTING METRICS (Financial/Revenue)
B20: CARDHOLDER ACCOUNTS
B21: Users (end of the month) | C21: 512 | D21: 644 | E21: 748 | F21: 954 | G21: 1301 | H21: 1836 | I21: 2293 | J21: 3037 | K21: 3346 | L21: 3412 | M21: =Daily!LX8 -> 3467 | N21: =Daily!NC8 -> 3831 | O21: =Daily!OH8 -> 4040 | P21: =Daily!PJ8 -> 5113 | Q21: =Daily!QO8 -> 6502 | R21: =Daily!RS8 -> 7561 | S21: =Daily!SX8 -> 9025 | T21: 11366 | U21: =Daily!VH8 -> 12352 | V21: =Daily!WM8 -> 13197 | W21: =Daily!XQ8 -> 16302
B22: MoM Growth | C22: =C21/296-1 -> 0.72972973 | D22: =D21/C21-1 -> 0.2578125 | E22: =E21/D21-1 -> 0.16149068 | F22: =F21/E21-1 -> 0.27540107 | G22: =G21/F21-1 -> 0.36373166 | H22: =H21/G21-1 -> 0.41122214 | I22: =I21/H21-1 -> 0.24891068 | J22: =J21/I21-1 -> 0.32446577 | K22: =K21/J21-1 -> 0.10174514 | ... W22: =W21/V21-1 -> 0.23528075
B23: Users (average) | C23: =AVERAGE(367,C21) -> 439.5 | D23: =AVERAGE(C21,D21) -> 578 | E23: =AVERAGE(D21,E21) -> 696 | F23: =AVERAGE(E21,F21) -> 851 | G23: =AVERAGE(F21,G21) -> 1127.5 | H23: =AVERAGE(G21,H21) -> 1568.5 | I23: =AVERAGE(H21,I21) -> 2064.5 | J23: =AVERAGE(I21,J21) -> 2665 | K23: =AVERAGE(J21,K21) -> 3191.5 | ... W23: =AVERAGE(V21,W21) -> 14749.5
B24: New Users | D24: =D21-C21 -> 132 | E24: =E21-D21 -> 104 | F24: =F21-E21 -> 206 | G24: =G21-F21 -> 347 | H24: =H21-G21 -> 535 | I24: =I21-H21 -> 457 | J24: =J21-I21 -> 744 | K24: =K21-J21 -> 309 | ... W24: =W21-V21 -> 3105
B26: REVENUES | O26: =O27*12 -> 186812.15 | W26: =W27*12 -> 1271624.8
B27: Total Revenue (in USD) | C27: =SUM(C28,C32) -> 4140.0616 | D27: =SUM(D28,D32) -> 4135.8459 | E27: =SUM(E28,E32) -> 4719.0513 | F27: =SUM(F28,F32) -> 5586.8176 | G27: =SUM(G28,G32) -> 6278.0801 | H27: =SUM(H28,H32) -> 8405.6948 | I27: =SUM(I28,I32) -> 10333.663 | J27: =SUM(J28,J32) -> 11263.534 | K27: =SUM(K28,K32) -> 16743.284 | L27: =SUM(L28,L32,L34) -> 17223.997 | M27: =SUM(M28,M32,M34) -> 16778.068 | N27: =SUM(N28,N32,N34) -> 19485.28 | O27: =SUM(O28,O32,O34) -> 15567.679 | P27: =SUM(P28,P32,P34) -> 20247.312 | Q27: =SUM(Q28,Q32,Q34) -> 33956.163 | R27: =SUM(R28,R32,R34) -> 39203.819 | S27: =SUM(S28,S32,S34) -> 40549.077 | T27: =SUM(T28,T32,T34,T38) -> 61149.31 | U27: =SUM(U28,U32,U34,U38) -> 73409.51 | V27: =SUM(V28,V32,V34,V38) -> 84922.014 | W27: =SUM(W28,W32,W34,W38) -> 105968.73 | X27: =W27/O27 -> 6.8069705
B28: Interchange Fee Income | C28: =SUM(C29:C30) -> 4140.0616 | D28: =SUM(D29:D30) -> 4135.8459 | E28: =SUM(E29:E30) -> 4719.0513 | F28: =SUM(F29:F30) -> 5586.8176 | G28: =SUM(G29:G30) -> 6278.0801 | H28: =SUM(H29:H30) -> 8405.6948 | I28: =SUM(I29:I30) -> 10333.663 | J28: =SUM(J29:J30) -> 10940.774 | ... W28: =SUM(W29:W30) -> 47148.563
B29: from PHP settlements | C29: =C43/ForEx -> 2380.5781 | D29: =D43/ForEx -> 2588.7737 | E29: =E43/ForEx -> 2744.3315 | F29: =F43/ForEx -> 3411.8667 | G29: =G43/ForEx -> 3983.1867 | H29: =H43/ForEx -> 5110.1625 | I29: =I43/ForEx -> 6305.7428 | J29: =J43/ForEx -> 6711.6912 | ... W29: =W43/ForEx -> 24756.701
B30: from USD settlements | C30: =C44/ForEx -> 1759.4835 | D30: =D44/ForEx -> 1547.0722 | E30: =E44/ForEx -> 1974.7197 | F30: =F44/ForEx -> 2174.9509 | G30: =G44/ForEx -> 2294.8934 | H30: =H44/ForEx -> 3295.5323 | I30: =I44/ForEx -> 4027.9201 | J30: =J44/ForEx -> 4229.083 | ... W30: =W44/ForEx -> 22391.862
B32: Late Payment Fee | C32: =C49/ForEx -> 0 | D32: =D49/ForEx -> 0 | E32: =E49/ForEx -> 0 | F32: =F49/ForEx -> 0 | G32: =G49/ForEx -> 0 | H32: =H49/ForEx -> 0 | I32: =I49/ForEx -> 0 | J32: =J49/ForEx -> 322.75986 | ... W32: =W49/ForEx -> 2265.7061
X33: =X34/W7 -> 5.686622
B34: Installments Revenue | C34: =SUM(C35:C36) -> 0 | D34: =SUM(D35:D36) -> 0 | E34: =SUM(E35:E36) -> 0 | F34: =SUM(F35:F36) -> 0 | G34: =SUM(G35:G36) -> 0 | H34: =SUM(H35:H36) -> 0 | I34: =SUM(I35:I36) -> 0 | J34: =SUM(J35:J36) -> 0 | ... W34: =SUM(W35:W36) -> 16596.039 | X34: =W34+W32+W28 -> 66010.308
B35: Interest on Installments | O35: =O52/ForEx -> 23.587993 | P35: =P52/ForEx -> 856.01219 | Q35: =Q52/ForEx -> 2401.7299 | R35: =R52/ForEx -> 3943.924 | S35: =S52/ForEx -> 4616.1651 | T35: =T52/ForEx -> 6108.4778 | U35: =U52/ForEx -> 7226.4523 | V35: =V52/ForEx -> 7978.7299 | W35: =W52/ForEx -> 8715.5027
B36: Upfront-fee | O36: =O53/ForEx -> 39.170072 | P36: =P53/ForEx -> 2623.4862 | Q36: =Q53/ForEx -> 5220.6341 | R36: =R53/ForEx -> 5517.1412 | S36: =S53/ForEx -> 5741.8986 | T36: =T53/ForEx -> 6052.8556 | U36: =U53/ForEx -> 5206.3346 | V36: =V53/ForEx -> 6119.3263 | W36: =W53/ForEx -> 7880.5364
X37: =W38/W7 -> 3.4423177
B38: Finance Charge - Revolving | T38: =T55/ForEx -> 12284.291 | U38: =U55/ForEx -> 26911.02 | V38: =V55/ForEx -> 34974.768 | W38: =W55/ForEx -> 39958.423
B40: Total Revenue (in PHP) | C40: =SUM(C42,C49,C51) -> 231015.44 | D40: =SUM(D42,D49,D51) -> 230780.2 | E40: =SUM(E42,E49,E51) -> 263323.06 | F40: =SUM(F42,F49,F51) -> 311744.42 | G40: =SUM(G42,G49,G51) -> 350316.87 | H40: =SUM(H42,H49,H51) -> 469037.77 | I40: =SUM(I42,I49,I51) -> 576618.39 | J40: =SUM(J42,J49,J51) -> 628505.2 | ... S40: =SUM(S42,S49,S51) -> 2262638.5 | T40: =SUM(T42,T49,T51,T55) -> 3412131.5 | U40: =SUM(U42,U49,U51,U55) -> 4096250.6 | V40: =SUM(V42,V49,V51,V55) -> 4738648.4 | W40: =SUM(W42,W49,W51,W55) -> 5913055.2 | X40: =W40/W67 -> 0.028002836 | Y40: =W40/O40 -> 6.8069705
B41: MoM Growth | C41: =C40/296-1 -> 779.45757 | D41: =D40/C40-1 -> -0.0010182869 | E41: =E40/D40-1 -> 0.14101236 | F41: =F40/E40-1 -> 0.18388576 | G41: =G40/F40-1 -> 0.123731 | H41: =H40/G40-1 -> 0.33889575 | I41: =I40/H40-1 -> 0.22936451 | J41: =J40/I40-1 -> 0.08998466 | K41: =K40/J40-1 -> 0.48650364 | ... W41: =W40/V40-1 -> 0.24783583
B42: Interchange Fee Revenue | C42: =SUM(C43:C44) -> 231015.44 | D42: =SUM(D43:D44) -> 230780.2 | E42: =SUM(E43:E44) -> 263323.06 | F42: =SUM(F43:F44) -> 311744.42 | G42: =SUM(G43:G44) -> 350316.87 | H42: =SUM(H43:H44) -> 469037.77 | I42: =SUM(I43:I44) -> 576618.39 | J42: =SUM(J43:J44) -> 610495.2 | ... W42: =SUM(W43:W44) -> 2630889.8 | X42: =W42/$W$40 -> 0.44492901 | Y42: =W42/W67 -> 0.012459274
B43: from PHP settlements | C43: 132836.26 | D43: 144453.57 | E43: 153133.7 | F43: 190382.16 | G43: 222261.82 | H43: 285147.07 | I43: 351860.45 | J43: 374512.37 | K43: 524935.95 | L43: 511370.68 | M43: 524190.36 | N43: =570005.93+45165.27 -> 615171.2 | O43: =473195.71-45165.27 -> 428030.44 | P43: 470518.06 | Q43: 713547.5 | R43: 745657.84 | S43: 861989.74 | T43: 1005284.9 | U43: 850608.48 | V43: 860091.33 | W43: 1381423.9
B44: from USD settlements | C44: 98179.18 | D44: 86326.63 | E44: 110189.36 | F44: 121362.26 | G44: 128055.05 | H44: 183890.7 | I44: 224757.94 | J44: 235982.83 | K44: 353418.65 | L44: 395728.36 | M44: 367025.81 | N44: 440107.44 | O44: 372436.52 | P44: 394114.87 | Q44: 651073.19 | R44: 775875.43 | S44: 683618.88 | T44: 957909.19 | U44: 960836.27 | V44: 1032118.8 | W44: 1249465.9
B46: from USD settlements | C46: 1671.15 | D46: 1483.93 | E46: 1917.09 | F46: 2126.46 | G46: 2297.8 | H46: 3261.93 | I46: 3954.72 | J46: 4120.67 | K46: 6171.23 | L46: 6784.49 | M46: 6224.82 | N46: 7472.84 | O46: 6294.13 | P46: 6657.78 | Q46: 10960.97 | R46: 12872.83 | S46: 11128.97 | T46: 15636.11 | U46: 15596.98 | V46: 16792.13 | W46: 19940.25
B47: Forex (Revenue) | C47: =C44/C46 -> 58.749472 | D47: =D44/D46 -> 58.174328 | E47: =E44/E46 -> 57.477406 | F47: =F44/F46 -> 57.07244 | G47: =G44/G46 -> 55.729415 | H47: =H44/H46 -> 56.374815 | I47: =I44/I46 -> 56.832833 | J47: =J44/J46 -> 57.268073 | ... T47: =T44/T46 -> 61.262628 | V47: =V44/V46 -> 61.464436 | W47: =W44/W46 -> 62.660493
B49: Late Payment Fee Revenue | C49: 0 | D49: 0 | E49: 0 | F49: 0 | G49: 0 | H49: 0 | I49: 0 | J49: 18010 | K49: 55920.67 | L49: 54000 | M49: 45000 | N49: 32000 | O49: 64707.62 | P49: 71011.07 | Q49: 104805.31 | R49: 138112.4 | S49: 139049.93 | T49: 84871.59 | U49: 89421.49 | V49: 108174.67 | W49: 126426.4
B51: Installments Revenue | C51: =SUM(C52:C53) -> 0 | D51: =SUM(D52:D53) -> 0 | E51: =SUM(E52:E53) -> 0 | F51: =SUM(F52:F53) -> 0 | G51: =SUM(G52:G53) -> 0 | H51: =SUM(H52:H53) -> 0 | I51: =SUM(I52:I53) -> 0 | J51: =SUM(J52:J53) -> 0 | ... W51: =SUM(W52:W53) -> 926058.98
B52: Interest on Installments | O52: 1316.21 | P52: 47765.48 | Q52: 134016.53 | R52: 220070.96 | S52: 257582.01 | T52: 340853.06 | U52: 403236.04 | V52: 445213.13 | W52: =473476.04+ 12849.01 -> 486325.05
B53: Upfront-fee | O53: 2185.69 | P53: 146390.53 | Q53: 291311.38 | R53: 307856.48 | S53: 320397.94 | T53: 337749.34 | U53: 290513.47 | V53: 341458.41 | W53: 439733.93
B55: Finance Charge - Revolving | T55: 685463.41 | U55: =514130.54+1011603.98-24099.62 -> 1501634.9 | V55: =741444.8-7240.66+1217387.89 -> 1951592 | W55: =859028.91+ 1376926.69 -4827.53-1448.04 -> 2229680
B57: Interchange Fee Rate (Average) | C57: =C42/C127 -> 0.016235018 | D57: =D42/D127 -> 0.016760831 | E57: =E42/E127 -> 0.015149529 | F57: =F42/F127 -> 0.014876151 | G57: =G42/G127 -> 0.01507451 | H57: =H42/H127 -> 0.01494122 | I57: =I42/I127 -> 0.014932899 | J57: =J42/J127 -> 0.015095442 | ... W57: =W42/W127 -> 0.013784324
B58: Interchange Fee Rate (USD Settlements) | C58: =C30/C123 -> 0.019047422 | D58: =D30/D123 -> 0.018116003 | E58: =E30/E123 -> 0.015243769 | F58: =F30/F123 -> 0.014858216 | G58: =G30/G123 -> 0.015281227 | H58: =H30/H123 -> 0.016966987 | I58: =I30/I123 -> 0.017948979 | J58: =J30/J123 -> 0.017969201 | ... W58: =W30/W123 -> 0.018726427
B59: Interchange Fee Rate (PHP Settlements) | C59: =C43/C128 -> 0.014637615 | D59: =D43/D128 -> 0.016043614 | E59: =E43/E128 -> 0.015082435 | F59: =F43/F128 -> 0.014887607 | G59: =G43/G128 -> 0.014957931 | H59: =H43/H128 -> 0.013873034 | I59: =I43/I128 -> 0.013485421 | J59: =J43/J128 -> 0.013713516 | ... W59: =W43/W128 -> 0.011916164
B61: LOANS OUTSTANDING
Q62: =Q65/55.8 -> 1659628.9
B63: Credit Card Receivables (end of month) | C63: 7536921.6 | D63: 8266373.5 | E63: 12309943 | F63: 14273935 | G63: 16971800 | H63: 24868851 | I63: 27338345 | J63: 32652519 | K63: 45714494 | L63: 48254789 | M63: =Daily!LX27 -> 53453371 | N63: =Daily!NC27 -> 62581043 | O63: =Daily!OH27 -> 59169325 | P63: =Daily!OI27 -> 57194020 | Q63: =Daily!QO27 -> 76890495 | R63: =Daily!RS27 -> 92395050 | S63: =Daily!SX27 -> 98705222 | T63: =Daily!UB27 -> 1.2690536e+08 | U63: =Daily!VH27 -> 135674397 | V63: =Daily!WM27 -> 1.5948172e+08 | W63: =Daily!XQ27 -> 1.9912358e+08
B64: Installment Receivables (end of month) | C64: 0 | D64: 0 | E64: 0 | F64: 0 | G64: 0 | H64: 0 | I64: 0 | J64: 0 | K64: 0 | L64: 0 | M64: 0 | N64: 0 | O64: 3501.9 | P64: 6207404.1 | Q64: 15716796 | R64: 25451026 | S64: 35805433 | T64: =Daily!UB28 -> 26476445 | U64: =Daily!VH28 -> 28153017 | V64: =Daily!WM28 -> 29941463 | W64: =Daily!XQ28 -> 33771552
B65: Total Receivables Outstanding (end of the month) | C65: =SUM(C63:C64) -> 7536921.6 | D65: =SUM(D63:D64) -> 8266373.5 | E65: =SUM(E63:E64) -> 12309943 | F65: =SUM(F63:F64) -> 14273935 | G65: =SUM(G63:G64) -> 16971800 | H65: =SUM(H63:H64) -> 24868851 | I65: =SUM(I63:I64) -> 27338345 | J65: =SUM(J63:J64) -> 32652519 | ... W65: =SUM(W63:W64) -> 2.3289513e+08 | X65: =W65-W84 -> 2.1672086e+08 | Y65: 2.5235963e+08
P66: =P65/O65-1 -> 0.071461808 | Q66: =Q65/P65-1 -> 0.46065001 | R66: =R65/Q65-1 -> 0.27253562 | S66: =S65/R65-1 -> 0.1414097 | T66: =T65/S65-1 -> 0.14029486 | U66: =U65/T65-1 -> 0.068101983 | V66: =V65/U65-1 -> 0.1562362 | W66: =W65/V65-1 -> 0.22949641 | Y66: =Y65/O65-1 -> 3.2647891
B67: Total Loans Outstanding (average) | D67: =AVERAGE(C65:D65) -> 7901647.5 | E67: =AVERAGE(D65:E65) -> 10288158 | F67: =AVERAGE(E65:F65) -> 13291939 | G67: =AVERAGE(F65:G65) -> 15622867 | H67: =AVERAGE(G65:H65) -> 20920326 | I67: =AVERAGE(H65:I65) -> 26103598 | J67: =AVERAGE(I65:J65) -> 29995432 | K67: =AVERAGE(J65:K65) -> 39183506 | ... W67: =AVERAGE(V65:W65) -> 2.1115916e+08 | X67: =W67/55.8 -> 3784214.3
X68: =X67/W7 -> 326.00054
B69: Installment Conversions (Principal) | O69: 131622.28 | P69: =SUM(Daily!OT34:PJ34) -> 6088323.3 | Q69: 9405672.9 | R69: 9842937.3 | S69: 9776427 | T69: 10075552 | U69: 8525587.5 | V69: 9858769.1 | W69: 12255674
B70: % of Loans Outstanding | O70: =O69/O63 -> 0.002224502 | P70: =P69/P63 -> 0.10645035 | Q70: =Q69/Q63 -> 0.12232556 | R70: =R69/R63 -> 0.106531 | S70: =S69/S63 -> 0.099046706 | T70: =T69/T63 -> 0.07939422 | U70: =U69/U63 -> 0.062838587 | V70: =V69/V63 -> 0.061817548 | W70: =W69/W63 -> 0.061548082 | AA70: 75387049
B71: Installment Conversion (Transaction Count) | P71: =SUM(Daily!OT35:PJ35) -> 536 | Q71: 806 | R71: =SUM(Daily!QP35:RS35) -> 853 | S71: =871-82 -> 789 | T71: =884-105 -> 779 | U71: 651 | V71: 738 | W71: 955 | AA71: =AA70/V65 -> 0.39798216
B73: DELINQUENCIES (END OF MONTH)
B74: Total Delinquent (DPD30>) | C74: =SUM(C79:C84) -> 316838.88 | D74: =SUM(D79:D84) -> 492021 | E74: =SUM(E79:E84) -> 552335.64 | F74: =SUM(F79:F84) -> 451396.54 | G74: =SUM(G79:G84) -> 730025.04 | H74: =SUM(H79:H84) -> 1051369.9 | I74: =SUM(I79:I84) -> 1504737.7 | J74: =SUM(J79:J84) -> 2300905.5 | ... W74: =SUM(W79:W84) -> 21176742
B75: Delinquency (% of Outstanding Balance) | C75: =C74/C63 -> 0.042038235 | D75: =D74/D63 -> 0.05952078 | E75: =E74/E63 -> 0.044869067 | F75: =F74/F63 -> 0.031623834 | G75: =G74/G63 -> 0.043014003 | H75: =H74/H63 -> 0.042276576 | I75: =I74/I63 -> 0.055041287 | J75: =J74/J63 -> 0.0704664 | ... W75: =W74/W63 -> 0.10634975
B77: Aging
B78: 1-30 days | C78: 329309.04 | D78: 392998.85 | E78: 25920.18 | F78: 283227.06 | G78: 425034.18 | H78: 1469964.6 | I78: 894713.62 | J78: 606355.27 | K78: =Daily!JO49 -> 1103872.5 | L78: =Daily!KT49 -> 1767002.5 | M78: =Daily!LX49 -> 2349152.4 | N78: =Daily!NC49 -> 3615006.5 | O78: =Daily!OH49 -> 2148853.1 | P78: =Daily!PJ49 -> 2666196.1 | Q78: =Daily!QO49 -> 731936.44 | R78: =Daily!RS49 -> 2919677.1 | S78: =Daily!SX49 -> 2280707.9 | T78: =Daily!UB49 -> 1227233.9 | U78: =Daily!VH49 -> 529446.71 | V78: =Daily!WM49 -> 343952.44 | W78: =Daily!XQ49 -> 467395.94
B79: 31-60 days | C79: 109767.06 | D79: 203375.7 | E79: 138781.44 | F79: 14625.23 | G79: 289863.5 | H79: 373574.03 | I79: 508270.59 | J79: 849122.97 | K79: =Daily!JO50 -> 592244.36 | L79: =Daily!KT50 -> 1282996.4 | M79: =Daily!LX50 -> 1879959.8 | N79: =Daily!NC50 -> 2815060.7 | O79: =Daily!OH50 -> 3407674.3 | P79: =Daily!PJ50 -> 2215107.6 | Q79: =Daily!QO50 -> 2478456.9 | R79: =Daily!RS50 -> 709621.31 | S79: =Daily!SX50 -> 1772861.5 | T79: =Daily!UB50 -> 1996865.4 | U79: =Daily!VH50 -> 876699.89 | V79: =Daily!WM50 -> 333636.5 | W79: =Daily!XQ50 -> 334949.09
B80: 61-89 days | C80: 24966.24 | D80: 96353.48 | E80: 176860.04 | F80: 134291.44 | G80: 14625.23 | H80: 258969.32 | I80: 198079.38 | J80: 270266.16 | K80: =Daily!JO51 -> 658035.01 | L80: =Daily!KT51 -> 489301.38 | M80: =Daily!LX51 -> 1184214.9 | N80: =Daily!NC51 -> 1500280.1 | O80: =Daily!OH51 -> 2824665 | P80: =Daily!PJ51 -> 3401447.3 | Q80: =Daily!QO51 -> 2012679.6 | R80: =Daily!RS51 -> 2085741.7 | S80: =Daily!SX51 -> 662531.82 | T80: =Daily!UB51 -> 1707617.1 | U80: =Daily!VH51 -> 1914170.7 | V80: =Daily!WM51 -> 436983.4 | W80: =Daily!XQ51 -> 219942.45
B81: 90-120 days | C81: 75384.44 | D81: 24966.24 | E81: 96353.48 | F81: 154622.13 | G81: 134291.44 | H81: 14625.23 | I81: 390796.15 | J81: 412491.96 | K81: =Daily!JO52 -> 595623.85 | L81: =Daily!KT52 -> 687235.16 | M81: =Daily!LX52 -> 545741.89 | N81: =Daily!NC52 -> 1348928.2 | O81: =Daily!OH52 -> 1283885.1 | P81: =Daily!PJ52 -> 2732397.2 | Q81: =Daily!QO52 -> 3281034.8 | R81: =Daily!RS52 -> 1885064.3 | S81: =Daily!SX52 -> 1907725.2 | T81: =Daily!UB52 -> 589635.04 | U81: =Daily!VH52 -> 1656871.7 | V81: =Daily!WM52 -> 1611561.4 | W81: =Daily!XQ52 -> 1280199.7
B82: 121-150 days | C82: 0 | D82: 60604.44 | E82: 24966.24 | F82: 24990 | G82: 154622.13 | H82: 124191.44 | I82: 14625.23 | J82: 322762.84 | K82: =Daily!JO53 -> 196375.63 | L82: =Daily!KT53 -> 391795.06 | M82: =Daily!LX53 -> 600056.3 | N82: =Daily!NC53 -> 460493.44 | O82: =Daily!OH53 -> 950879.85 | P82: =Daily!PJ53 -> 1389219.1 | Q82: =Daily!QO53 -> 2623254 | R82: =Daily!RS53 -> 3244057.8 | S82: =Daily!SX53 -> 1809377 | T82: =Daily!UB53 -> 1913116.8 | U82: =Daily!VH53 -> 590233.66 | V82: =Daily!WM53 -> 2016513.9 | W82: =Daily!XQ53 -> 1092036.7
B83: 151-180 days | C83: 74910 | D83: 0 | E83: 47964.44 | F83: 24966.24 | G83: 24990 | H83: 154622.13 | I83: 124191.44 | J83: 64530.23 | K83: =Daily!JO54 -> 231773.37 | L83: =Daily!KT54 -> 397955.61 | M83: =Daily!LX54 -> 375687.37 | N83: =Daily!NC54 -> 690654.93 | O83: =Daily!OH54 -> 854944.54 | P83: =Daily!PJ54 -> 1177306.8 | Q83: =Daily!QO54 -> 1348876.3 | R83: =Daily!RS54 -> 2592092 | S83: =Daily!SX54 -> 3156884.1 | T83: =Daily!UB54 -> 1771417.2 | U83: =Daily!VH54 -> 1843618.2 | V83: =Daily!WM54 -> 798151.02 | W83: =Daily!XQ54 -> 2075346 | X83: =SUM(W78:W83) -> 5469869.9 | Z83: =X83/W65 -> 0.023486408
B84: 181 days and over | C84: 31811.14 | D84: 106721.14 | E84: 67410 | F84: 97901.5 | G84: 111632.74 | H84: 125387.74 | I84: 268774.87 | J84: 381731.31 | K84: =Daily!JO55 -> 435026.54 | L84: =Daily!KT55 -> 652109.6 | M84: =Daily!LX55 -> 973071 | N84: =Daily!NC55 -> 1354039.1 | O84: =Daily!OH55 -> 2050539.1 | P84: =Daily!PJ55 -> 2529235.1 | Q84: =Daily!QO55 -> 3675280.9 | R84: =Daily!RS55 -> 5013821.6 | S84: =Daily!SX55 -> 7734015.5 | T84: =Daily!UB55 -> 10636807 | U84: =Daily!VH55 -> 12548665 | V84: =Daily!WM55 -> 15020072 | W84: =Daily!XQ55 -> 16174268 | X84: =X83/X65 -> 0.025239241 | Y84: =W84/W65 -> 0.069448719 | Z84: 8000000 | AA84: =Z84/SUM(W78:W84) -> 0.36961509
B85: Charge off amount | C85: =Daily!JG56 -> 0 | D85: =Daily!JH56 -> 0 | E85: =Daily!JI56 -> 0 | F85: =Daily!JJ56 -> 0 | G85: =Daily!JK56 -> 0 | H85: =Daily!JL56 -> 0 | I85: =Daily!JM56 -> 0 | J85: =Daily!JN56 -> 0 | K85: =Daily!JO56 -> 0 | L85: =Daily!KT56 -> 0 | M85: =Daily!LX56 -> 0 | N85: =Daily!NC56 -> 0 | O85: =Daily!OH56 -> 0 | P85: =Daily!PJ56 -> 0 | Q85: =Daily!QO56 -> 0 | R85: =Daily!RS56 -> 0 | S85: =Daily!SX56 -> 0 | T85: =Daily!UB56 -> 0 | U85: =Daily!VH56 -> 0 | V85: =Daily!WM56 -> 0 | W85: =Daily!XQ56 -> 0
B87: Total Delinquent (DPD30>, excluding payment plans) | C87: =SUM(C92:C97) -> 149761.74 | D87: =SUM(D92:D97) -> 224273.81 | E87: =SUM(E92:E97) -> 153677.94 | F87: =SUM(F92:F97) -> 269919.89 | G87: =SUM(G92:G97) -> 685085.04 | H87: =SUM(H92:H97) -> 922945.82 | I87: =SUM(I92:I97) -> 1378730.6 | J87: =SUM(J92:J97) -> 2226056.9 | ... W87: =SUM(W92:W97) -> 20719606
B88: Delinquency (% of Outstanding Balance) | C88: =C87/C63 -> 0.019870412 | D88: =D87/D63 -> 0.027130859 | E88: =E87/E63 -> 0.01248405 | F88: =F87/F63 -> 0.018909985 | G88: =G87/G63 -> 0.040366081 | H88: =H87/H63 -> 0.037112523 | I88: =I87/I63 -> 0.050432117 | J88: =J87/J63 -> 0.068174125 | ... W88: =W87/W63 -> 0.10405401
B90: Aging
B91: 1-30 days | C91: 281189.74 | D91: 238534.15 | E91: 25920.18 | F91: 263992.05 | G91: 129776.9 | H91: 1454964.6 | I91: 795404.4 | J91: 471863.52 | K91: 677296.38 | L91: 1236436.6 | M91: 2347970.4 | N91: 2692938.2 | O91: 1716256.8 | P91: 2301892.9 | Q91: 510580.58 | R91: 2907228.7 | S91: 2261469.9 | T91: 811019.17 | U91: 298941.99 | V91: 139925.66 | W91: 365247.77
B92: 31-60 days | C92: 24990 | D92: 79076.57 | E92: 8479.79 | F92: 14625.23 | G92: 289863.5 | H92: 292053.03 | I92: 472439.11 | J92: 832596.08 | K92: 344359.25 | L92: 892037.55 | M92: 1418108.8 | N92: 2051688.5 | O92: 2365197.4 | P92: 1021060.4 | Q92: 1901079.2 | R92: 369783.1 | S92: 1637972.1 | T92: 1825638.3 | U92: 798072.4 | V92: 269230.8 | W92: 227826.38
B93: 61-89 days | C93: 24966.24 | D93: 24990 | E93: 74910.91 | F93: 8989.79 | G93: 14625.23 | H93: 245771.25 | I93: 183089.91 | J93: 270266.16 | K93: 325661.99 | L93: 320667.85 | M93: 971604.75 | N93: 1212081.3 | O93: 1950086.2 | P93: 2702714.8 | Q93: 1275138.1 | R93: 1793330.2 | S93: 522585.51 | T93: 1615317.2 | U93: 1847250.2 | V93: 383263.71 | W93: 205714.33
B94: 90-120 days | C94: 24895.5 | D94: 24966.24 | E94: 24990 | F94: 154622.13 | G94: 134291.44 | H94: 14625.23 | I94: 338080.04 | J94: 399993.08 | K94: 353159.29 | L94: 413033.38 | M94: 493585.57 | N94: 1150913.5 | O94: 967672.18 | P94: 2339485.7 | Q94: 2791106.7 | R94: 1570412.5 | S94: 1746327.1 | T94: 530309.57 | U94: 1646255.8 | V94: 1611561.4 | W94: 1280199.7
B95: 121-150 days | C95: 0 | D95: 20331 | E95: 24966.24 | F95: 24990 | G95: 154622.13 | H95: 124191.44 | I95: 14625.23 | J95: 288175.04 | K95: 196375.63 | L95: 174240.59 | M95: 600056.3 | N95: 433899.12 | O95: 815446.79 | P95: 1171725.6 | Q95: 2434438.1 | R95: 2844212.4 | S95: 1627874.4 | T95: 1857297.9 | U95: 548339.07 | V95: 1988543.5 | W95: 1059751.7
B96: 151-180 days | C96: 74910 | D96: 0 | E96: 20331 | F96: 24966.24 | G96: 24990 | H96: 154622.13 | I96: 124191.44 | J96: 64530.23 | K96: 114741.19 | L96: 351294.95 | M96: 342857.35 | N96: 673817.93 | O96: 815089.24 | P96: 1043327.2 | Q96: 1145402 | R96: 2486221 | S96: 2906423.1 | T96: 1650209.8 | U96: 1772818.6 | V96: 743571 | W96: 2075346 | X96: 8700000
B97: 181 days and over | C97: 0 | D97: 74910 | E97: 0 | F97: 41726.5 | G97: 66692.74 | H97: 91682.74 | I97: 246304.87 | J97: 370496.31 | K97: 280444.08 | L97: 406714.53 | M97: 796049.22 | N97: 1145906.6 | O97: 1928516.1 | P97: 2450445.2 | Q97: 3544210.2 | R97: 4788306.8 | S97: 7415566.5 | T97: 10319224 | U97: 12463291 | V97: 14935463 | W97: 15870768 | X97: =SUM(W91:W97) -> 21084854
B98: Charge off amount | C98: 0 | D98: 0 | E98: 0 | F98: 0 | G98: 0 | H98: 0 | I98: 0 | J98: 0 | K98: 0 | L98: 0 | M98: 0 | N98: 0 | O98: 0 | P98: 0 | Q98: 0 | R98: 0 | X98: =X96/X97 -> 0.41261846
B100: Payment Plan
B101: Accounts in payment plan | C101: 7 | D101: 9 | E101: 7 | F101: 4 | G101: 5 | H101: 5 | I101: 10 | J101: 10 | K101: 46 | L101: 53 | M101: 35 | N101: 54 | O101: 74 | P101: 87 | Q101: 74 | R101: 61 | S101: 46 | T101: 39 | U101: 25 | V101: 24 | W101: 22
B102: Total outstanding balance | C102: 215196.44 | D102: 422211.89 | E102: 398657.7 | F102: 200711.66 | G102: 340197.28 | H102: 143424.07 | I102: 225316.28 | J102: 209340.32 | K102: 1520913.5 | L102: 1873970.3 | M102: 937651.2 | N102: 2423217.8 | O102: 2963176.4 | P102: 3080257.5 | Q102: 2549563.9 | R102: 1690581.2 | S102: 1205884.4 | T102: 1233677 | U102: 584736.2 | V102: 489311.08 | W102: 559284.15
B104: OTHER METRICS
B105: GROSS TRANSACTION VOLUME (GTV) | E105: =SUM(C106:E106) -> 48066351 | H105: =SUM(F106:H106) -> 81149768 | K105: =SUM(I106:K106) -> 1.4508091e+08 | N105: =SUM(L106:N106) -> 2.062352e+08
B106: Total GTV | C106: =SUM(Daily!C19:AG19) -> 14265387 | D106: =SUM(Daily!AH19:BI19) -> 15389668 | E106: =SUM(Daily!BJ19:CN19) -> 18411295 | F106: =SUM(Daily!CO19:DR19) -> 22066769 | G106: =SUM(Daily!DS19:EW19) -> 25830587 | H106: =SUM(Daily!EX19:GA19) -> 33252411 | I106: =SUM(Daily!GB19:HF19) -> 40571217 | J106: =SUM(Daily!HG19:IK19) -> 46731157 | K106: =SUM(Daily!IL19:JO19) -> 57778536 | L106: =SUM(Daily!JP19:KT19) -> 65017653 | M106: =SUM(Daily!KU19:LX19) -> 68758349 | N106: =SUM(Daily!LY19:NC19) -> 72459195 | O106: =SUM(Daily!ND19:OH19) -> 62289569 | P106: 66496760 | Q106: =SUM(Daily!PK19:QO19) -> 1.0427639e+08 | R106: =SUM(Daily!QP19:RS19) -> 1.1515947e+08 | S106: 1.2975117e+08 | T106: =SUM(Daily!SY19:UB19) -> 1.4086402e+08 | U106: 1.4131782e+08 | V106: 1.6747218e+08 | W106: 1.9193702e+08
O107: =O106/ForEx -> 1116300.5 | P107: =P106/ForEx -> 1191698.2 | Q107: =Q106/ForEx -> 1868752.5 | R107: =R106/ForEx -> 2063789.9 | S107: =S106/ForEx -> 2325289.8 | T107: =T106/ForEx -> 2524444.8 | U107: =U106/ForEx -> 2532577.4 | V107: =V106/ForEx -> 3001293.5 | W107: =W106/ForEx -> 3439731.5
B109: Monthly GTV per User | C109: =C106/C23 -> 32458.219 | D109: =D106/D23 -> 26625.723 | E109: =E106/E23 -> 26453.01 | F109: =F106/F23 -> 25930.398 | G109: =G106/G23 -> 22909.612 | H109: =H106/H23 -> 21200.135 | I109: =I106/I23 -> 19651.837 | J109: =J106/J23 -> 17535.144 | ... W109: =W106/W23 -> 13013.12
B110: Monthly GTV per Active User | C110: =C106/C14 -> 35842.682 | D110: =D106/D14 -> 31862.667 | E110: =E106/E14 -> 32471.42 | F110: =F106/F14 -> 30862.614 | G110: =G106/G14 -> 27161.501 | H110: =H106/H14 -> 24289.563 | I110: =I106/I14 -> 24920.895 | J110: =J106/J14 -> 23542.145 | ... T110: =T106/T14 -> 18834.606 | U110: =U106/U7 -> 16518.739 | V110: =V106/V7 -> 18067.988 | W110: =W106/W7 -> 16534.891
B111: Monthly GTV per Active User (USD) | C111: =C110/ForEx -> 642.34197 | D111: =D110/ForEx -> 571.01554 | E111: =E110/ForEx -> 581.92509 | F111: =F110/ForEx -> 553.09344 | G111: =G110/ForEx -> 486.76525 | H111: =H110/ForEx -> 435.29682 | I111: =I110/ForEx -> 446.61102 | J111: =J110/ForEx -> 421.90224 | ... W111: =W110/ForEx -> 296.32422
B113: Transaction Count - GTV | C113: =SUM(Daily!C22:AG22) -> 7108 | D113: =SUM(Daily!AH22:BI22) -> 7902 | E113: =SUM(Daily!BJ22:CN22) -> 10498 | F113: =SUM(Daily!CO22:DR22) -> 12775 | G113: =SUM(Daily!DS22:EW22) -> 16241 | H113: =SUM(Daily!EX22:GA22) -> 22200 | I113: =SUM(Daily!GB22:HF22) -> 26185 | J113: =SUM(Daily!HG22:IK22) -> 31820 | K113: =SUM(Daily!IL22:JO22) -> 39812 | L113: =SUM(Daily!JP22:KT22) -> 43647 | M113: =SUM(Daily!KU22:LX22) -> 51269 | N113: =SUM(Daily!LY22:NC22) -> 54130 | O113: =SUM(Daily!ND22:OH22) -> 45388 | P113: 52090 | Q113: =SUM(Daily!PK22:QO22) -> 74398 | R113: =SUM(Daily!QP22:RS22) -> 89784 | S113: =SUM(Daily!RT22:SX22) -> 101042 | T113: =SUM(Daily!SY22:UB22) -> 109237 | U113: 116098 | V113: 124285 | W113: 136648
B115: Average Ticket Size | C115: =C106/C113 -> 2006.9481 | D115: =D106/D113 -> 1947.5662 | E115: =E106/E113 -> 1753.7907 | F115: =F106/F113 -> 1727.34 | G115: =G106/G113 -> 1590.4555 | H115: =H106/H113 -> 1497.8564 | I115: =I106/I113 -> 1549.4068 | J115: =J106/J113 -> 1468.6096 | ... W115: =W106/W113 -> 1404.6091
B116: Average Ticket Size (USD) | C116: =C115/ForEx -> 35.966813 | D116: =D115/ForEx -> 34.90262 | E116: =E115/ForEx -> 31.429942 | F116: =F115/ForEx -> 30.955915 | G116: =G115/ForEx -> 28.502786 | H116: =H115/ForEx -> 26.843304 | I116: =I115/ForEx -> 27.767147 | J116: =J115/ForEx -> 26.319168 | ... W116: =W115/ForEx -> 25.172205
B118: SETTLEMENT VOLUME
B119: Total Settlement Volume (inc. interchange fee) - in USD | C119: =SUM(C120:C123) -> 255008.13 | D119: =SUM(D120:D123) -> 246756.61 | E119: =SUM(E120:E123) -> 311498.22 | F119: =SUM(F120:F123) -> 375555.3 | G119: =SUM(G120:G123) -> 416469.92 | H119: =SUM(H120:H123) -> 562584.22 | I119: =SUM(I120:I123) -> 692006.46 | J119: =SUM(J120:J123) -> 724773.35 | ... V119: =SUM(V120:V123) -> 2336718.6 | W119: =SUM(W120,W123) -> 3273308.9 | X119: =W119*0.01 -> 32733.089 | Y119: =X119/W7 -> 2.8198733
B120: PHP settlements | C120: =C128/ForEx -> 162634.29 | D120: =D128/ForEx -> 161358.51 | E120: =E128/ForEx -> 181955.47 | F120: =F128/ForEx -> 229174.95 | G120: =G128/ForEx -> 266292.62 | H120: =H128/ForEx -> 368352.19 | I120: =I128/ForEx -> 467597.03 | J120: =J128/ForEx -> 489421.6 | ... V120: =V128/ForEx -> 1349569.2 | W120: =SUM(W121:W122) -> 2077572.9
B121: Gross Settlement Volume | W121: =W129/ForEx -> 2102570.9
B122: Returns | W122: =W130/ForEx -> -24997.94
B123: USD settlements | C123: 92373.84 | D123: 85398.1 | E123: 129542.75 | F123: 146380.35 | G123: 150177.3 | H123: 194232.03 | I123: 224409.43 | J123: 235351.75 | K123: 365219.73 | L123: 391308.39 | M123: 365378.24 | N123: 432172.6 | O123: 363421.62 | P123: 386187.22 | Q123: 640993.1 | R123: 750551.92 | S123: 666394.16 | T123: 937457.43 | U123: 937498.35 | V123: 987149.38 | W123: =SUM(W124:W125) -> 1195735.9
...

Sheet Daily
A1: Daily KPIs | WE1: =WE8-VY8 -> 107 | WF1: 380 | WG1: 720 | WH1: =WI2-WH2 -> -1001.7 | WI1: =WI2-WF8 -> 286 | WT1: =WT8*1.1 -> 16677.1
UV2: =UV8-UC8 -> 214 | WG2: =WH2-WF8 -> 1287.7 | WH2: =1.1*WF8 -> 14164.7 | WI2: 13163 | WT2: =WT1-WT8 -> 1516.1
B3: Forex | C3: 55.8 | SJ3: 60 | SK3: 60 | SL3: 60 | SM3: 60 | SN3: 60 | SO3: 60 | SP3: 60 | SQ3: 60 | SR3: 60 | SS3: 60 | ST3: 60 | SU3: 60 | SV3: 60 | SW3: 60 | SX3: 60 | SY3: 55.8 | SZ3: 55.8 | TA3: 55.8 | TB3: 55.8 | TC3: 55.8 | TD3: 55.8 | TE3: 55.8 | TF3: 55.8 | TG3: 55.8 | TH3: 55.8 | TI3: 55.8 | TJ3: 55.8 | TK3: 55.8 | TL3: 55.8 | TM3: 55.8 | TN3: 55.8 | TO3: 55.8 | TP3: 55.8 | TQ3: 55.8 | TR3: 55.8 | TS3: 55.8 | TT3: 55.8 | TU3: 55.8 | TV3: 55.8 | TW3: 55.8 | TX3: 55.8 | TY3: 55.8 | TZ3: 55.8 | UA3: 55.8 | UB3: 55.8 | UC3: 55.8 | UD3: 55.8 | UE3: 55.8 | UF3: 55.8 | UG3: 55.8 | UH3: 55.8 | UI3: 55.8 | UJ3: 55.8 | UK3: 55.8 | UL3: 55.8 | UM3: 55.8 | UN3: 55.8 | UO3: 55.8 | UP3: 55.8 | UQ3: 55.8 | UR3: 55.8 | US3: 55.8 | UT3: 55.8 | UU3: 55.8 | UV3: 55.8 | UW3: 55.8 | UX3: 55.8 | UY3: 55.8 | UZ3: 55.8 | VA3: 55.8 | VB3: 55.8 | VC3: 55.8 | VD3: 55.8 | VE3: 55.8 | VF3: 55.8 | VG3: 55.8 | VH3: 55.8 | VI3: 55.8 | VJ3: 55.8 | VK3: 55.8 | VL3: 55.8 | VM3: 55.8 | VN3: 55.8 | VO3: 55.8 | VP3: 55.8 | VQ3: 55.8 | VR3: 55.8 | VS3: 55.8 | VT3: 55.8 | VU3: 55.8 | VV3: 55.8 | VW3: 55.8 | VX3: 55.8 | VY3: 55.8 | VZ3: 55.8 | WA3: 55.8 | WB3: 55.8 | WC3: 55.8 | WD3: 55.8 | WE3: 55.8 | WF3: 55.8 | WG3: 55.8 | WH3: 55.8 | WI3: 55.8 | WJ3: 55.8 | WK3: 55.8 | WL3: 55.8 | WM3: 55.8 | WN3: 55.8 | WO3: 55.8 | WP3: 55.8 | WQ3: 55.8 | WR3: 55.8 | WS3: 55.8 | WT3: 55.8 | WU3: 55.8 | WV3: 55.8 | WW3: 55.8 | WX3: 55.8 | WY3: 55.8 | WZ3: 55.8 | XA3: 55.8 | XB3: 55.8 | XC3: 55.8 | XD3: 55.8 | XE3: 55.8 | XF3: 55.8 | XG3: 55.8 | XH3: 55.8 | XI3: 55.8 | XJ3: 55.8 | XK3: 55.8 | XL3: 55.8 | XM3: 55.8 | XN3: 55.8 | XO3: 55.8 | XP3: 55.8 | XQ3: 55.8 | XR3: 55.8 | XS3: 55.8 | XT3: 55.8 | XU3: 55.8 | XV3: 55.8 | XW3: 55.8 | XX3: 55.8 | XY3: 55.8 | XZ3: 55.8 | YA3: 55.8 | YB3: 55.8 | YC3: 55.8 | YD3: 55.8 | YE3: 55.8 | YF3: 55.8 | YG3: 55.8 | YH3: 55.8 | YI3: 55.8 | YJ3: 55.8 | YK3: 55.8 | YL3: 55.8 | YM3: 55.8
WI4: =WI8-NC8 -> 9249
C5: 45658 | D5: 45659 | E5: 45660 | F5: 45661 | G5: 45662 | H5: 45663 | I5: 45664 | J5: 45665 | K5: 45666 | L5: 45667 | M5: 45668 | N5: 45669 | O5: 45670 | P5: 45671 | Q5: 45672 | R5: 45673 | S5: 45674 | T5: 45675 | U5: 45676 | V5: 45677 | W5: 45678 | X5: 45679 | Y5: 45680 | Z5: 45681 | AA5: 45682 | AB5: 45683 | AC5: 45684 | AD5: 45685 | AE5: 45686 | AF5: 45687 | AG5: 45688 | AH5: 45689 | AI5: 45690 | AJ5: 45691 | AK5: 45692 | AL5: 45693 | AM5: 45694 | AN5: 45695 | AO5: 45696 | AP5: 45697 | AQ5: 45698 | AR5: 45699 | AS5: 45700 | AT5: 45701 | AU5: 45702 | AV5: 45703 | AW5: 45704 | AX5: 45705 | AY5: 45706 | AZ5: 45707 | BA5: 45708 | BB5: 45709 | BC5: 45710 | BD5: 45711 | BE5: 45712 | BF5: 45713 | BG5: 45714 | BH5: 45715 | BI5: 45716 | BJ5: 45717 | BK5: 45718 | BL5: 45719 | BM5: 45720 | BN5: 45721 | BO5: 45722 | BP5: 45723 | BQ5: 45724 | BR5: 45725 | BS5: 45726 | BT5: 45727 | BU5: 45728 | BV5: 45729 | BW5: 45730 | BX5: 45731 | BY5: 45732 | BZ5: 45733 | CA5: 45734 | CB5: 45735 | CC5: 45736 | CD5: 45737 | CE5: 45738 | CF5: 45739 | CG5: 45740 | CH5: 45741 | CI5: 45742 | CJ5: 45743 | CK5: 45744 | CL5: 45745 | CM5: 45746 | CN5: 45747 | CO5: 45748 | CP5: 45749 | CQ5: 45750 | CR5: 45751 | CS5: 45752 | CT5: 45753 | CU5: 45754 | CV5: 45755 | CW5: 45756 | CX5: 45757 | CY5: 45758 | CZ5: 45759 | DA5: 45760 | DB5: 45761 | DC5: 45762 | DD5: 45763 | DE5: 45764 | DF5: 45765 | DG5: 45766 | DH5: 45767 | DI5: 45768 | DJ5: 45769 | DK5: 45770 | DL5: 45771 | DM5: 45772 | DN5: 45773 | DO5: 45774 | DP5: 45775 | DQ5: 45776 | DR5: 45777 | DS5: 45778 | DT5: 45779 | DU5: 45780 | DV5: 45781 | DW5: 45782 | DX5: 45783 | DY5: 45784 | DZ5: 45785 | EA5: 45786 | EB5: 45787 | EC5: 45788 | ED5: 45789 | EE5: 45790 | EF5: 45791 | EG5: 45792 | EH5: 45793 | EI5: 45794 | EJ5: 45795 | EK5: 45796 | EL5: 45797 | EM5: 45798 | EN5: 45799 | EO5: 45800 | EP5: 45801 | EQ5: 45802 | ER5: 45803 | ES5: 45804 | ET5: 45805 | EU5: 45806 | EV5: 45807 | EW5: 45808 | EX5: 45809 | EY5: 45810 | EZ5: 45811 | FA5: 45812 | FB5: 45813 | FC5: 45814 | FD5: 45815 | FE5: 45816 | FF5: 45817 | FG5: 45818 | FH5: 45819 | FI5: 45820 | FJ5: 45821 | FK5: 45822 | FL5: 45823 | FM5: 45824 | FN5: 45825 | FO5: 45826 | FP5: 45827 | FQ5: 45828 | FR5: 45829 | FS5: 45830 | FT5: 45831 | FU5: 45832 | FV5: 45833 | FW5: 45834 | FX5: 45835 | FY5: 45836 | FZ5: 45837 | GA5: 45838 | GB5: 45839 | GC5: 45840 | GD5: 45841 | GE5: 45842 | GF5: 45843 | GG5: 45844 | GH5: 45845 | GI5: 45846 | GJ5: 45847 | GK5: 45848 | GL5: 45849 | GM5: 45850 | GN5: 45851 | GO5: 45852 | GP5: 45853 | GQ5: 45854 | GR5: 45855 | GS5: 45856 | GT5: 45857 | GU5: 45858 | GV5: 45859 | GW5: 45860 | GX5: 45861 | GY5: 45862 | GZ5: 45863 | HA5: 45864 | HB5: 45865 | HC5: 45866 | HD5: 45867 | HE5: 45868 | HF5: 45869 | HG5: 45870 | HH5: 45871 | HI5: 45872 | HJ5: 45873 | HK5: 45874 | HL5: 45875 | HM5: 45876 | HN5: 45877 | HO5: 45878 | HP5: 45879 | HQ5: 45880 | HR5: 45881 | HS5: 45882 | HT5: 45883 | HU5: 45884 | HV5: 45885 | HW5: 45886 | HX5: 45887 | HY5: 45888 | HZ5: 45889 | IA5: 45890 | IB5: 45891 | IC5: 45892 | ID5: 45893 | IE5: 45894 | IF5: 45895 | IG5: 45896 | IH5: 45897 | II5: 45898 | IJ5: 45899 | IK5: 45900 | IL5: 45901 | IM5: 45902 | IN5: 45903 | IO5: 45904 | IP5: 45905 | IQ5: 45906 | IR5: 45907 | IS5: 45908 | IT5: 45909 | IU5: 45910 | IV5: 45911 | IW5: 45912 | IX5: 45913 | IY5: 45914 | IZ5: 45915 | JA5: 45916 | JB5: 45917 | JC5: 45918 | JD5: 45919 | JE5: 45920 | JF5: 45921 | JG5: 45922 | JH5: 45923 | JI5: 45924 | JJ5: 45925 | JK5: 45926 | JL5: 45927 | JM5: 45928 | JN5: 45929 | JO5: 45930 | JP5: 45931 | JQ5: 45932 | JR5: 45933 | JS5: 45934 | JT5: 45935 | JU5: 45936 | JV5: 45937 | JW5: 45938 | JX5: 45939 | JY5: 45940 | JZ5: 45941 | KA5: 45942 | KB5: 45943 | KC5: 45944 | KD5: 45945 | KE5: 45946 | KF5: 45947 | KG5: 45948 | KH5: 45949 | KI5: 45950 | KJ5: 45951 | KK5: 45952 | KL5: 45953 | KM5: 45954 | KN5: 45955 | KO5: 45956 | KP5: 45957 | KQ5: 45958 | KR5: 45959 | KS5: 45960 | KT5: 45961 | KU5: 45962 | KV5: 45963 | KW5: 45964 | KX5: 45965 | KY5: 45966 | KZ5: 45967 | LA5: 45968 | LB5: 45969 | LC5: 45970 | LD5: 45971 | LE5: 45972 | LF5: 45973 | LG5: 45974 | LH5: 45975 | LI5: 45976 | LJ5: 45977 | LK5: 45978 | LL5: 45979 | LM5: 45980 | LN5: 45981 | LO5: 45982 | LP5: 45983 | LQ5: 45984 | LR5: 45985 | LS5: 45986 | LT5: 45987 | LU5: 45988 | LV5: 45989 | LW5: 45990 | LX5: 45991 | LY5: 45992 | LZ5: 45993 | MA5: 45994 | MB5: 45995 | MC5: 45996 | MD5: 45997 | ME5: 45998 | MF5: 45999 | MG5: 46000 | MH5: 46001 | MI5: 46002 | MJ5: 46003 | MK5: 46004 | ML5: 46005 | MM5: 46006 | MN5: 46007 | MO5: 46008 | MP5: 46009 | MQ5: 46010 | MR5: 46011 | MS5: 46012 | MT5: 46013 | MU5: 46014 | MV5: 46015 | MW5: 46016 | MX5: 46017 | MY5: 46018 | MZ5: 46019 | NA5: 46020 | NB5: 46021 | NC5: 46022 | ND5: 46023 | NE5: 46024 | NF5: 46025 | NG5: 46026 | NH5: 46027 | NI5: 46028 | NJ5: 46029 | NK5: 46030 | NL5: 46031 | NM5: 46032 | NN5: 46033 | NO5: 46034 | NP5: 46035 | NQ5: 46036 | NR5: 46037 | NS5: 46038 | NT5: 46039 | NU5: 46040 | NV5: 46041 | NW5: 46042 | NX5: 46043 | NY5: 46044 | NZ5: 46045 | OA5: 46046 | OB5: 46047 | OC5: 46048 | OD5: 46049 | OE5: 46050 | OF5: 46051 | OG5: 46052 | OH5: 46053 | OI5: 46054 | OJ5: 46055 | OK5: 46056 | OL5: 46057 | OM5: 46058 | ON5: 46059 | OO5: 46060 | OP5: 46061 | OQ5: 46062 | OR5: 46063 | OS5: 46064 | OT5: 46065 | OU5: 46066 | OV5: 46067 | OW5: 46068 | OX5: 46069 | OY5: 46070 | OZ5: 46071 | PA5: 46072 | PB5: 46073 | PC5: 46074 | PD5: 46075 | PE5: 46076 | PF5: 46077 | PG5: 46078 | PH5: 46079 | PI5: 46080 | PJ5: 46081 | PK5: 46082 | PL5: 46083 | PM5: 46084 | PN5: 46085 | PO5: 46086 | PP5: 46087 | PQ5: 46088 | PR5: 46089 | PS5: 46090 | PT5: 46091 | PU5: 46092 | PV5: 46093 | PW5: 46094 | PX5: 46095 | PY5: 46096 | PZ5: 46097 | QA5: 46098 | QB5: 46099 | QC5: 46100 | QD5: 46101 | QE5: 46102 | QF5: 46103 | QG5: 46104 | QH5: 46105 | QI5: 46106 | QJ5: 46107 | QK5: 46108 | QL5: 46109 | QM5: 46110 | QN5: 46111 | QO5: 46112 | QP5: 46113 | QQ5: 46114 | QR5: 46115 | QS5: 46116 | QT5: 46117 | QU5: 46118 | QV5: 46119 | QW5: 46120 | QX5: 46121 | QY5: 46122 | QZ5: 46123 | RA5: 46124 | RB5: 46125 | RC5: 46126 | RD5: 46127 | RE5: 46128 | RF5: 46129 | RG5: 46130 | RH5: 46131 | RI5: 46132 | RJ5: 46133 | RK5: 46134 | RL5: 46135 | RM5: 46136 | RN5: 46137 | RO5: 46138 | RP5: 46139 | RQ5: 46140 | RR5: 46141 | RS5: 46142 | RT5: 46143 | RU5: 46144 | RV5: 46145 | RW5: 46146 | RX5: 46147 | RY5: 46148 | RZ5: 46149 | SA5: 46150 | SB5: 46151 | SC5: 46152 | SD5: 46153 | SE5: 46154 | SF5: 46155 | SG5: 46156 | SH5: 46157 | SI5: 46158 | SJ5: 46159 | SK5: 46160 | SL5: 46161 | SM5: 46162 | SN5: 46163 | SO5: 46164 | SP5: 46165 | SQ5: 46166 | SR5: 46167 | SS5: 46168 | ST5: 46169 | SU5: 46170 | SV5: 46171 | SW5: 46172 | SX5: 46173 | SY5: 46174 | SZ5: 46175 | TA5: 46176 | TB5: 46177 | TC5: 46178 | TD5: 46179 | TE5: 46180 | TF5: 46181 | TG5: 46182 | TH5: 46183 | TI5: 46184 | TJ5: 46185 | TK5: 46186 | TL5: 46187 | TM5: 46188 | TN5: 46189 | TO5: 46190 | TP5: 46191 | TQ5: 46192 | TR5: 46193 | TS5: 46194 | TT5: 46195 | TU5: 46196 | TV5: 46197 | TW5: 46198 | TX5: 46199 | TY5: 46200 | TZ5: 46201 | UA5: 46202 | UB5: 46203 | UC5: 46204 | UD5: 46205 | UE5: 46206 | UF5: 46207 | UG5: 46208 | UH5: 46209 | UI5: 46210 | UJ5: 46211 | UK5: 46212 | UL5: 46213 | UM5: 46214 | UN5: 46215 | UO5: 46216 | UP5: 46217 | UQ5: 46218 | UR5: 46219 | US5: 46220 | UT5: 46221 | UU5: 46222 | UV5: 46223 | UW5: 46224 | UX5: 46225 | UY5: 46226 | UZ5: 46227 | VA5: 46228 | VB5: 46229 | VC5: 46230 | VD5: 46231 | VE5: 46232 | VF5: 46232 | VG5: 46233 | VH5: 46234 | VI5: 46235 | VJ5: 46236 | VK5: 46237 | VL5: 46238 | VM5: 46239 | VN5: 46240 | VO5: 46241 | VP5: 46242 | VQ5: 46243 | VR5: 46244 | VS5: 46245 | VT5: 46246 | VU5: 46247 | VV5: 46248 | VW5: 46249 | VX5: 46250 | VY5: 46251 | VZ5: 46252 | WA5: 46253 | WB5: 46254 | WC5: 46255 | WD5: 46256 | WE5: 46257 | WF5: 46258 | WG5: 46259 | WH5: 46260 | WI5: 46261 | WJ5: 46262 | WK5: 46263 | WL5: 46264 | WM5: 46265 | WN5: 46266 | WO5: 46267 | WP5: 46268 | WQ5: 46269 | WR5: 46270 | WS5: 46271 | WT5: 46272 | WU5: 46273 | WV5: 46274 | WW5: 46275 | WX5: 46276 | WY5: 46277 | WZ5: 46278 | XA5: 46279 | XB5: 46280 | XC5: 46281 | XD5: 46282 | XE5: 46283 | XF5: 46284 | XG5: 46285 | XH5: 46286 | XI5: 46287 | XJ5: 46288 | XK5: 46289 | XL5: 46290 | XM5: 46291 | XN5: 46292 | XO5: 46293 | XP5: 46294 | XQ5: 46295 | XR5: 46296 | XS5: 46297 | XT5: 46298 | XU5: 46299 | XV5: 46300 | XW5: 46301 | XX5: 46302 | XY5: 46303 | XZ5: 46304 | YA5: 46305 | YB5: 46306 | YC5: 46307 | YD5: 46308 | YE5: 46309 | YF5: 46310 | YG5: 46311 | YH5: 46312 | YI5: 46313 | YJ5: 46314 | YK5: 46315 | YL5: 46316 | YM5: 46317
B6: CORE METRICS
B7: Cardholder Accounts | VC7: =VC8-UC8 -> 643
B8: Users | C8: 367 | D8: 367 | E8: 373 | F8: 376 | G8: 376 | H8: 376 | I8: 386 | J8: 396 | K8: 405 | L8: 416 | M8: 415 | N8: 415 | O8: 415 | P8: 421 | Q8: 432 | R8: 440 | S8: 448 | T8: 450 | U8: 450 | V8: 451 | W8: 462 | X8: 475 | Y8: 487 | Z8: 503 | AA8: 503 | AB8: 503 | AC8: 503 | AD8: 503 | AE8: 504 | AF8: 505 | AG8: 512 | AH8: 512 | AI8: 512 | AJ8: 512 | AK8: 523 | AL8: 533 | AM8: 536 | AN8: 542 | AO8: 544 | AP8: 544 | AQ8: 544 | AR8: 554 | AS8: 569 | AT8: 571 | AU8: 577 | AV8: 577 | AW8: 577 | AX8: 581 | AY8: 582 | AZ8: 599 | BA8: 602 | BB8: 609 | BC8: 609 | BD8: 609 | BE8: 611 | BF8: 624 | BG8: 632 | BH8: 643 | BI8: 644 | BJ8: 644 | BK8: 644 | BL8: 644 | BM8: 644 | BN8: 644 | BO8: 644 | BP8: 645 | BQ8: 645 | BR8: 655 | BS8: 655 | BT8: 661 | BU8: 661 | BV8: 663 | BW8: 669 | BX8: 669 | BY8: 669 | BZ8: 669 | CA8: 682 | CB8: 692 | CC8: 698 | CD8: 703 | CE8: 703 | CF8: 703 | CG8: 708 | CH8: 709 | CI8: 719 | CJ8: 737 | CK8: 737 | CL8: 737 | CM8: 737 | CN8: 748 | CO8: 748 | CP8: 765 | CQ8: 775 | CR8: 778 | CS8: 778 | CT8: 778 | CU8: 799 | CV8: 792 | CW8: 801 | CX8: 804 | CY8: 804 | CZ8: 804 | DA8: 804 | DB8: 808 | DC8: 809 | DD8: 842 | DE8: 861 | DF8: 878 | DG8: 878 | DH8: 878 | DI8: 886 | DJ8: 886 | DK8: 905 | DL8: 913 | DM8: 913 | DN8: 913 | DO8: 913 | DP8: 931 | DQ8: 943 | DR8: 954 | DS8: 954 | DT8: 955 | DU8: 955 | DV8: 955 | DW8: 955 | DX8: 969 | DY8: 982 | DZ8: 1000 | EA8: 1000 | EB8: 1000 | EC8: 1000 | ED8: 1000 | EE8: 1000 | EF8: 1000 | EG8: 1026 | EH8: 1041 | EI8: 1041 | EJ8: 1056 | EK8: 1100 | EL8: 1170 | EM8: 1185 | EN8: 1200 | EO8: 1208 | EP8: 1208 | EQ8: 1208 | ER8: 1208 | ES8: 1252 | ET8: 1274 | EU8: 1289 | EV8: 1301 | EW8: 1301 | EX8: 1301 | EY8: 1321 | EZ8: 1352 | FA8: 1406 | FB8: 1425 | FC8: 1432 | FD8: 1432 | FE8: 1432 | FF8: 1432 | FG8: 1502 | FH8: 1517 | FI8: 1517 | FJ8: 1602 | FK8: 1602 | FL8: 1602 | FM8: 1646 | FN8: 1669 | FO8: 1738 | FP8: 1759 | FQ8: 1759 | FR8: 1760 | FS8: 1760 | FT8: 1804 | FU8: 1836 | FV8: 1836 | FW8: 1836 | FX8: 1836 | FY8: 1836 | FZ8: 1836 | GA8: 1836 | GB8: 1836 | GC8: 1836 | GD8: 1836 | GE8: 1836 | GF8: 1836 | GG8: 1836 | GH8: 1858 | GI8: 1858 | GJ8: 1877 | GK8: 1917 | GL8: 2003 | GM8: 2003 | GN8: 2003 | GO8: 2052 | GP8: 2052 | GQ8: 2052 | GR8: 2052 | GS8: 2068 | GT8: 2068 | GU8: 2135 | GV8: 2165 | GW8: 2165 | GX8: 2165 | GY8: 2165 | GZ8: 2219 | HA8: 2219 | HB8: 2219 | HC8: 2261 | HD8: 2261 | HE8: 2276 | HF8: 2293 | HG8: 2304 | HH8: 2304 | HI8: 2304 | HJ8: 2304 | HK8: 2324 | HL8: 2327 | HM8: 2342 | HN8: 2350 | HO8: 2350 | HP8: 2350 | HQ8: 2371 | HR8: 2372 | HS8: 2377 | HT8: 2382 | HU8: 2425 | HV8: 2425 | HW8: 2425 | HX8: 2651 | HY8: 2651 | HZ8: 2651 | IA8: 2651 | IB8: 2651 | IC8: 2651 | ID8: 2651 | IE8: 2651 | IF8: 2651 | IG8: 2857 | IH8: 2858 | II8: 2858 | IJ8: 2858 | IK8: 3037 | IL8: 3037 | IM8: 3039 | IN8: 3041 | IO8: 3041 | IP8: 3175 | IQ8: 3182 | IR8: 3182 | IS8: 3215 | IT8: 3215 | IU8: 3217 | IV8: 3262 | IW8: 3266 | IX8: 3266 | IY8: 3266 | IZ8: 3268 | JA8: 3275 | JB8: 3279 | JC8: 3279 | JD8: 3279 | JE8: 3279 | JF8: 3279 | JG8: 3279 | JH8: 3279 | JI8: 3281 | JJ8: 3313 | JK8: 3313 | JL8: 3313 | JM8: 3313 | JN8: 3335 | JO8: 3336 | JP8: 3346 | JQ8: 3346 | JR8: 3345 | JS8: 3345 | JT8: 3345 | JU8: 3345 | JV8: 3350 | JW8: 3350 | JX8: 3350 | JY8: 3365 | JZ8: 3365 | KA8: 3365 | KB8: 3365 | KC8: 3365 | KD8: 3365 | KE8: 3370 | KF8: 3370 | KG8: 3370 | KH8: 3370 | KI8: 3381 | KJ8: 3381 | KK8: 3403 | KL8: 3413 | KM8: 3413 | KN8: 3413 | KO8: 3413 | KP8: 3413 | KQ8: 3413 | KR8: 3412 | KS8: 3412 | KT8: 3412 | KU8: 3412 | KV8: 3412 | KW8: 3423 | KX8: 3423 | KY8: 3423 | KZ8: 3423 | LA8: 3423 | LB8: 3423 | LC8: 3423 | LD8: 3423 | LE8: 3472 | LF8: 3471 | LG8: 3474 | LH8: 3474 | LI8: 3474 | LJ8: 3474 | LK8: 3474 | LL8: 3474 | LM8: 3465 | LN8: 3465 | LO8: 3465 | LP8: 3465 | LQ8: 3465 | LR8: 3465 | LS8: 3467 | LT8: 3467 | LU8: 3467 | LV8: 3467 | LW8: 3467 | LX8: 3467 | LY8: 3467 | LZ8: 3467 | MA8: 3452 | MB8: 3452 | MC8: 3707 | MD8: 3707 | ME8: 3707 | MF8: 3707 | MG8: 3707 | MH8: 3707 | MI8: 3766 | MJ8: 3757 | MK8: 3757 | ML8: 3757 | MM8: 3792 | MN8: 3792 | MO8: 3829 | MP8: 3831 | MQ8: 3831 | MR8: 3831 | MS8: 3831 | MT8: 3831 | MU8: 3831 | MV8: 3831 | MW8: 3831 | MX8: 3831 | MY8: 3831 | MZ8: 3831 | NA8: 3831 | NB8: 3831 | NC8: 3831 | ND8: 3831 | NE8: 3831 | NF8: 3831 | NG8: 3831 | NH8: 3828 | NI8: 3823 | NJ8: 3839 | NK8: 3839 | NL8: 3839 | NM8: 3839 | NN8: 3839 | NO8: 3861 | NP8: 3862 | NQ8: 3862 | NR8: 3862 | NS8: 3861 | NT8: 3861 | NU8: 3861 | NV8: 3875 | NW8: 3875 | NX8: 3875 | NY8: 3875 | NZ8: 3875 | OA8: 3875 | OB8: 3875 | OC8: 3875 | OD8: 3913 | OE8: 3965 | OF8: 4000 | OG8: 4040 | OH8: 4040 | OI8: 4040 | OJ8: 4061 | OK8: 4083 | OL8: 4083 | OM8: 4091 | ON8: 4103 | OO8: 4103 | OP8: 4103 | OQ8: 4103 | OR8: 4153 | OS8: 4232 | OT8: 4272 | OU8: 4306 | OV8: 4306 | OW8: 4385 | OX8: 4434 | OY8: 4477 | OZ8: 4593 | PA8: 4708 | PB8: 4720 | PC8: 4796 | PD8: 4796 | PE8: 4810 | PF8: 4852 | PG8: 4986 | PH8: 5082 | PI8: 5113 | PJ8: 5113 | PK8: 5113 | PL8: 5145 | PM8: 5177 | PN8: 5180 | PO8: 5180 | PP8: 5202 | PQ8: 5202 | PR8: 5202 | PS8: 5200 | PT8: 5257 | PU8: 5268 | PV8: 5292 | PW8: 5392 | PX8: 5392 | PY8: 5392 | PZ8: 5438 | QA8: 5437 | QB8: 5569 | QC8: 5569 | QD8: 5649 | QE8: 5649 | QF8: 5694 | QG8: 5694 | QH8: 5694 | QI8: 5694 | QJ8: 5876 | QK8: 5965 | QL8: 5965 | QM8: 5965 | QN8: 6005 | QO8: 6502 | QP8: 6498 | QQ8: 6498 | QR8: 6849 | QS8: 6849 | QT8: 6849 | QU8: 6847 | QV8: 7045 | QW8: 7084 | QX8: 7084 | QY8: 7084 | QZ8: 7084 | RA8: 7084 | RB8: 7081 | RC8: 7174 | RD8: 7174 | RE8: 7231 | RF8: 7231 | RG8: 7231 | RH8: 7231 | RI8: 7300 | RJ8: 7356 | RK8: 7356 | RL8: 7357 | RM8: 7506 | RN8: 7506 | RO8: 7506 | RP8: 7566 | RQ8: 7566 | RR8: 7562 | RS8: 7561 | RT8: 7561 | RU8: 7561 | RV8: 7561 | RW8: 7561 | RX8: 7728 | RY8: 7870 | RZ8: 7920 | SA8: 7920 | SB8: 7920 | SC8: 7920 | SD8: 8126 | SE8: 8126 | SF8: 8153 | SG8: 8232 | SH8: 8232 | SI8: 8233 | SJ8: 8233 | SK8: 8366 | SL8: 8538 | SM8: 8571 | SN8: 8571 | SO8: 8638 | SP8: 8638 | SQ8: 8638 | SR8: 8638 | SS8: 8772 | ST8: 8908 | SU8: 8981 | SV8: 9025 | SW8: 9025 | SX8: 9025 | SY8: 9024 | SZ8: 9024 | TA8: 9092 | TB8: 9091 | TC8: 9253 | TD8: 9253 | TE8: 9253 | TF8: 9292 | TG8: 9656 | TH8: 9786 | TI8: 9784 | TJ8: 9784 | TK8: 9784 | TL8: 9784 | TM8: 9984 | TN8: 10265 | TO8: 10421 | TP8: 10449 | TQ8: 10449 | TR8: 10449 | TS8: 10449 | TT8: 10449 | TU8: 10879 | TV8: 10926 | TW8: 10942 | TX8: 11075 | TY8: 11075 | TZ8: 11075 | UA8: 11086 | UB8: 11382 | UC8: 11394 | UD8: 11394 | UE8: 11388 | UF8: 11388 | UG8: 11388 | UH8: 11388 | UI8: 11385 | UJ8: 11503 | UK8: 11517 | UL8: 11517 | UM8: 11517 | UN8: 11517 | UO8: 11540 | UP8: 11540 | UQ8: 11584 | UR8: 11596 | US8: 11608 | UT8: 11608 | UU8: 11608 | UV8: 11608 | UW8: 11911 | UX8: 11941 | UY8: 12025 | UZ8: 12025 | VA8: 12025 | VB8: 12025 | VC8: 12037 | VD8: 12041 | VE8: 12155 | VF8: 12155 | VG8: 12295 | VH8: 12352 | VI8: 12353 | VJ8: 12353 | VK8: 12352 | VL8: 12352 | VM8: 12448 | VN8: 12448 | VO8: 12565 | VP8: 12565 | VQ8: 12565 | VR8: 12598 | VS8: 12733 | VT8: 12733 | VU8: 12733 | VV8: 12770 | VW8: 12770 | VX8: 12770 | VY8: 12770 | VZ8: 12770 | WA8: 12877 | WB8: 12877 | WC8: 12877 | WD8: 12877 | WE8: 12877 | WF8: 12877 | WG8: 13069 | WH8: 13069 | WI8: 13080 | WJ8: 13197 | WK8: 13197 | WL8: 13197 | WM8: 13197 | WN8: 14031 | WO8: 14268 | WP8: 14308 | WQ8: 14308 | WR8: 14892 | WS8: 14962 | WT8: 15161 | WU8: 15160 | WV8: 15160 | WW8: 15348 | WX8: 15392 | WY8: 15392 | WZ8: 15392 | XA8: 15392 | XB8: 15563 | XC8: 15661 | XD8: 15675 | XE8: 15731 | XF8: 15731 | XG8: 15731 | XH8: 15777 | XI8: 15811 | XJ8: 15877 | XK8: 15959 | XL8: 16034 | XM8: 16034 | XN8: 16034 | XO8: 16034 | XP8: 16303 | XQ8: 16302 | XR8: 16302 | XS8: 16302 | XT8: 16302 | XU8: 16302 | XV8: 16302 | XW8: 16303 | XX8: 16303 | XY8: 16303 | XZ8: 16302 | YA8: 16302 | YB8: 16302 | YC8: 16302 | YD8: 16302 | YE8: 16302 | YF8: 16302 | YG8: 16302 | YH8: 16302 | YI8: 16302 | YJ8: 16301 | YK8: 16301 | YL8: 16301 | YM8: 16301
B9: New Users (Closures) | AG9: =AG8-AF8 -> 7 | AH9: =AH8-AG8 -> 0 | AI9: =AI8-AH8 -> 0 | AJ9: =AJ8-AI8 -> 0 | AK9: =AK8-AJ8 -> 11 | AL9: =AL8-AK8 -> 10 | AM9: =AM8-AL8 -> 3 | AN9: =AN8-AM8 -> 6 | ... VR9: =VR8-VQ8 -> 33 | VS9: 135 | VT9: =VT8-VS8 -> 0 | VU9: =VU8-VT8 -> 0 | VV9: =VV8-VU8 -> 37 | VW9: =VW8-VV8 -> 0 | VX9: =VX8-VW8 -> 0 | VY9: =VY8-VX8 -> 0 | VZ9: =VZ8-VY8 -> 0 | WA9: =WA8-VZ8 -> 107 | ... WH9: =WH8-WG8 -> 0 | WI9: 11 | WJ9: =WJ8-WI8 -> 117 | WK9: =WK8-WJ8 -> 0 | WL9: =WL8-WK8 -> 0 | WM9: =WM8-WL8 -> 0 | WN9: =WN8-WM8 -> 834 | WO9: =WO8-WN8 -> 237 | WP9: 40 | WQ9: =WQ8-WP8 -> 0 | WR9: =WR8-WQ8 -> 584 | WS9: =WS8-WR8 -> 70 | WT9: =WT8-WS8 -> 199 | WU9: =WU8-WT8 -> -1 | WV9: =WV8-WU8 -> 0 | WW9: =WW8-WV8 -> 188 | WX9: =WX8-WW8 -> 44 | ... YB9: =YB8-YA8 -> 0 | YC9: 0 | YD9: =YD8-YC8 -> 0 | YE9: =YE8-YD8 -> 0 | YF9: =YF8-YE8 -> 0 | YG9: =YG8-YF8 -> 0 | YH9: =YH8-YG8 -> 0 | YI9: =YI8-YH8 -> 0 | YJ9: =YJ8-YI8 -> -1 | YK9: =YK8-YJ8 -> 0 | ... YM9: =YM8-YL8 -> 0
B10: Growth | C10: =C8/296-1 -> 0.23986486 | D10: =D8/C8-1 -> 0 | E10: =E8/D8-1 -> 0.016348774 | F10: =F8/E8-1 -> 0.0080428954 | G10: =G8/F8-1 -> 0 | H10: =H8/G8-1 -> 0 | I10: =I8/H8-1 -> 0.026595745 | J10: =J8/I8-1 -> 0.025906736 | K10: =K8/J8-1 -> 0.022727273 | ... AF10: =AF8/AE8-1 -> 0.001984127 | AG10: =IFERROR(AG8/AF8-1,"") -> 0.013861386 | AH10: =IFERROR(AH8/AG8-1,"") -> 0 | AI10: =IFERROR(AI8/AH8-1,"") -> 0 | AJ10: =IFERROR(AJ8/AI8-1,"") -> 0 | AK10: =IFERROR(AK8/AJ8-1,"") -> 0.021484375 | AL10: =IFERROR(AL8/AK8-1,"") -> 0.019120459 | AM10: =IFERROR(AM8/AL8-1,"") -> 0.0056285178 | AN10: =IFERROR(AN8/AM8-1,"") -> 0.01119403 | ... VR10: =IFERROR(VR8/VQ8-1,"") -> 0.002626343 | VS10: 0.010715987 | VT10: =IFERROR(VT8/VS8-1,"") -> 0 | VU10: =IFERROR(VU8/VT8-1,"") -> 0 | VV10: =IFERROR(VV8/VU8-1,"") -> 0.0029058352 | VW10: =IFERROR(VW8/VV8-1,"") -> 0 | VX10: =IFERROR(VX8/VW8-1,"") -> 0 | VY10: =IFERROR(VY8/VX8-1,"") -> 0 | VZ10: =IFERROR(VZ8/VY8-1,"") -> 0 | WA10: =IFERROR(WA8/VZ8-1,"") -> 0.0083790133 | ... WH10: =IFERROR(WH8/WG8-1,"") -> 0 | WI10: 0.00084168643 | WJ10: =IFERROR(WJ8/WI8-1,"") -> 0.0089449541 | WK10: =IFERROR(WK8/WJ8-1,"") -> 0 | WL10: =IFERROR(WL8/WK8-1,"") -> 0 | WM10: =IFERROR(WM8/WL8-1,"") -> 0 | WN10: =IFERROR(WN8/WM8-1,"") -> 0.063196181 | WO10: =IFERROR(WO8/WN8-1,"") -> 0.01689117 | WP10: 0.0028034763 | WQ10: =IFERROR(WQ8/WP8-1,"") -> 0 | WR10: =IFERROR(WR8/WQ8-1,"") -> 0.040816327 | WS10: =IFERROR(WS8/WR8-1,"") -> 0.0047005103 | WT10: =IFERROR(WT8/WS8-1,"") -> 0.013300361 | WU10: =IFERROR(WU8/WT8-1,"") -> -6.595871e-05 | WV10: =IFERROR(WV8/WU8-1,"") -> 0 | WW10: =IFERROR(WW8/WV8-1,"") -> 0.012401055 | WX10: =IFERROR(WX8/WW8-1,"") -> 0.002866823 | ... YB10: =IFERROR(YB8/YA8-1,"") -> 0 | YC10: 0 | YD10: =IFERROR(YD8/YC8-1,"") -> 0 | YE10: =IFERROR(YE8/YD8-1,"") -> 0 | YF10: =IFERROR(YF8/YE8-1,"") -> 0 | YG10: =IFERROR(YG8/YF8-1,"") -> 0 | YH10: =IFERROR(YH8/YG8-1,"") -> 0 | YI10: =IFERROR(YI8/YH8-1,"") -> 0 | YJ10: =IFERROR(YJ8/YI8-1,"") -> -6.1342167e-05 | YK10: =IFERROR(YK8/YJ8-1,"") -> 0 | ... YM10: =IFERROR(YM8/YL8-1,"") -> 0
B12: Daily Transacting Users | C12: 85 | D12: 72 | E12: 92 | F12: 95 | G12: 85 | H12: 79 | I12: 98 | J12: 91 | K12: 91 | L12: 95 | M12: 99 | N12: 85 | O12: 80 | P12: 107 | Q12: 114 | R12: 122 | S12: 113 | T12: 114 | U12: 97 | V12: 105 | W12: 107 | X12: 109 | Y12: 128 | Z12: 121 | AA12: 118 | AB12: 125 | AC12: 107 | AD12: 109 | AE12: 128 | AF12: 107 | AG12: 108 | AH12: 135 | AI12: 124 | AJ12: 96 | AK12: 110 | AL12: 139 | AM12: 129 | AN12: 116 | AO12: 131 | AP12: 118 | AQ12: 114 | AR12: 122 | AS12: 122 | AT12: 129 | AU12: 143 | AV12: 163 | AW12: 130 | AX12: 142 | AY12: 132 | AZ12: 144 | BA12: 145 | BB12: 140 | BC12: 148 | BD12: 142 | BE12: 148 | BF12: 126 | BG12: 118 | BH12: 145 | BI12: 140 | BJ12: 195 | BK12: 166 | BL12: 156 | BM12: 147 | BN12: 141 | BO12: 149 | BP12: 149 | BQ12: 149 | BR12: 140 | BS12: 137 | BT12: 132 | BU12: 130 | BV12: 127 | BW12: 166 | BX12: 173 | BY12: 149 | BZ12: 138 | CA12: 159 | CB12: 154 | CC12: 165 | CD12: 160 | CE12: 182 | CF12: 163 | CG12: 144 | CH12: 162 | CI12: 162 | CK12: 171 | CL12: 188 | CM12: 160 | CN12: 170 | CO12: 168 | CP12: 183 | CQ12: 169 | CR12: 193 | CS12: 192 | CT12: 187 | CU12: 178 | CV12: 165 | CW12: 178 | CX12: 193 | CY12: 174 | CZ12: 198 | DA12: 184 | DB12: 176 | DC12: 193 | DD12: 208 | DE12: 173 | DF12: 160 | DG12: 199 | DH12: 200 | DI12: 192 | DJ12: 196 | DK12: 210 | DL12: 202 | DM12: 194 | DN12: 216 | DO12: 232 | DP12: 192 | DQ12: 172 | DR12: 207 | DS12: 230 | DT12: 222 | DU12: 209 | DV12: 192 | DW12: 201 | DX12: 189 | DY12: 214 | DZ12: 224 | EA12: 215 | EB12: 228 | EC12: 214 | ED12: 180 | EE12: 180 | EF12: 208 | EG12: 237 | EH12: 236 | EI12: 249 | EJ12: 249 | EK12: 213 | EL12: 249 | EM12: 267 | EN12: 278 | EO12: 303 | EP12: 273 | EQ12: 256 | ER12: 228 | ES12: 265 | ET12: 253 | EU12: 270 | EV12: 279 | EW12: 274 | EX12: 309 | EY12: 270 | EZ12: 284 | FA12: 302 | FB12: 321 | FC12: 337 | FD12: 316 | FE12: 308 | FF12: 281 | FG12: 289 | FH12: 299 | FI12: 310 | FJ12: 315 | FK12: 355 | FL12: 343 | FM12: 312 | FN12: 322 | FO12: 310 | FP12: 369 | FQ12: 360 | FR12: 357 | FS12: 376 | FT12: 352 | FU12: 352 | FV12: 359 | FW12: 351 | FX12: 361 | FY12: 396 | FZ12: 363 | GA12: 350 | GB12: 366 | GC12: 368 | GD12: 376 | GE12: 382 | GF12: 415 | GG12: 388 | GH12: 390 | GI12: 323 | GJ12: 345 | GK12: 358 | GL12: 389 | GM12: 389 | GN12: 414 | GO12: 398 | GP12: 386 | GQ12: 417 | GR12: 412 | GS12: 422 | GT12: 442 | GU12: 438 | GV12: 361 | GW12: 363 | GX12: 360 | GY12: 364 | GZ12: 409 | HA12: 447 | HB12: 412 | HC12: 396 | HD12: 361 | HE12: 416 | HF12: 424 | HG12: 493 | HH12: 492 | HI12: 486 | HJ12: 409 | HK12: 392 | HL12: 430 | HM12: 442 | HN12: 445 | HO12: 469 | HP12: 455 | HQ12: 396 | HR12: 382 | HS12: 400 | HT12: 429 | HU12: 493 | HV12: 512 | HW12: 491 | HX12: 468 | HY12: 484 | HZ12: 517 | IA12: 538 | IB12: 502 | IC12: 502 | ID12: 486 | IE12: 474 | IF12: 413 | IG12: 467 | IH12: 486 | II12: 500 | IJ12: 516 | IK12: 532 | IL12: 605 | IM12: 568 | IN12: 555 | IO12: 568 | IP12: 591 | IQ12: 658 | IR12: 619 | IS12: 562 | IT12: 633 | IU12: 552 | IV12: 523 | IW12: 599 | IX12: 648 | IY12: 608 | IZ12: 651 | JA12: 596 | JB12: 608 | JC12: 616 | JD12: 600 | JE12: 632 | JF12: 599 | JG12: 531 | JH12: 566 | JI12: 538 | JJ12: 588 | JK12: 578 | JL12: 616 | JM12: 607 | JN12: 527 | JO12: 585 | JP12: 637 | JQ12: 655 | JR12: 641 | JS12: 682 | JT12: 670 | JU12: 626 | JV12: 627 | JW12: 613 | JX12: 609 | JY12: 643 | JZ12: 689 | KA12: 637 | KB12: 528 | KC12: 576 | KD12: 639 | KE12: 611 | KF12: 691 | KG12: 686 | KH12: 674 | KI12: 606 | KJ12: 646 | KK12: 611 | KL12: 610 | KM12: 594 | KN12: 653 | KO12: 633 | KP12: 587 | KQ12: 567 | KR12: 591 | KS12: 576 | KT12: 650 | KU12: 652 | KV12: 693 | KW12: 629 | KX12: 585 | KY12: 640 | KZ12: 590 | LA12: 735 | LB12: 775 | LC12: 640 | LD12: 660 | LE12: 752 | LF12: 654 | LG12: 679 | LH12: 674 | LI12: 758 | LJ12: 756 | LK12: 645 | LL12: 800 | LM12: 724 | LN12: 720 | LO12: 744 | LP12: 778 | LQ12: 733 | LR12: 711 | LS12: 638 | LT12: 727 | LU12: 781 | LV12: 788 | LW12: 812 | LX12: 779 | LY12: 841 | LZ12: 786 | MA12: 761 | MB12: 748 | MC12: 779 | MD12: 797 | ME12: 802 | MF12: 759 | MG12: 674 | MH12: 708 | MI12: 718 | MJ12: 730 | MK12: 760 | ML12: 739 | MM12: 747 | MN12: 710 | MO12: 737 | MP12: 759 | MQ12: 731 | MR12: 815 | MS12: 779 | MT12: 764 | MU12: 778 | MV12: 714 | MW12: 572 | MX12: 669 | MY12: 710 | MZ12: 695 | NA12: 668 | NB12: 684 | NC12: 684 | ND12: 626 | NE12: 737 | NF12: 747 | NG12: 735 | NH12: 721 | NI12: 641 | NJ12: 648 | NK12: 643 | NL12: 661 | NM12: 713 | NN12: 662 | NO12: 655 | NP12: 628 | NQ12: 622 | NR12: 686 | NS12: 694 | NT12: 755 | NU12: 776 | NV12: 673 | NW12: 667 | NX12: 716 | NY12: 657 | NZ12: 683 | OA12: 697 | OB12: 673 | OC12: 646 | OD12: 645 | OE12: 641 | OF12: 609 | OG12: 701 | OH12: 729 | OI12: 873 | OJ12: 809 | OK12: 735 | OL12: 701 | OM12: 732 | ON12: 729 | OO12: 783 | OP12: 746 | OQ12: 674 | OR12: 704 | OS12: 716 | OT12: 698 | OU12: 865 | OV12: 883 | OW12: 880 | OX12: 853 | OY12: 864 | OZ12: 841 | PA12: 860 | PB12: 875 | PC12: 971 | PD12: 910 | PE12: 901 | PF12: 831 | PG12: 833 | PH12: 914 | PI12: 1012 | PJ12: 1085 | PK12: 1181 | PL12: 1065 | PM12: 1095 | PN12: 999 | PO12: 1044 | PP12: 1025 | PQ12: 1058 | PR12: 990 | PS12: 892 | PT12: 867 | PU12: 899 | PV12: 909 | PW12: 974 | PX12: 1047 | PY12: 1091 | PZ12: 1027 | QA12: 1055 | QB12: 1100 | QC12: 1056 | QD12: 1116 | QE12: 1127 | QF12: 1100 | QG12: 1009 | QH12: 1041 | QI12: 991 | QJ12: 1003 | QK12: 1097 | QL12: 1166 | QM12: 1090 | QN12: 1049 | QO12: 1068 | QP12: 1382 | QQ12: 1172 | QR12: 1075 | QS12: 1311 | QT12: 1344 | QU12: 1262 | QV12: 1259 | QW12: 1281 | QX12: 1313 | QY12: 1258 | QZ12: 1300 | RA12: 1289 | RB12: 1217 | RC12: 1229 | RD12: 1271 | RE12: 1390 | RF12: 1430 | RG12: 1473 | RH12: 1443 | RI12: 1321 | RJ12: 1289 | RK12: 1283 | RL12: 1248 | RM12: 1327 | RN12: 1404 | RO12: 1385 | RP12: 1260 | RQ12: 1219 | RR12: 1199 | RS12: 1321 | RT12: 1529 | RU12: 1490 | RV12: 1459 | RW12: 1387 | RX12: 1389 | RY12: 1350 | RZ12: 1363 | SA12: 1356 | SB12: 1429 | SC12: 1510 | SD12: 1350 | SE12: 1259 | SF12: 1309 | SG12: 1349 | SH12: 1555 | SI12: 1541 | SJ12: 1605 | SK12: 1592 | SL12: 1457 | SM12: 1505 | SN12: 1467 | SO12: 1552 | SP12: 1612 | SQ12: 1594 | SR12: 1475 | SS12: 1431 | ST12: 1492 | SU12: 1468 | SV12: 1504 | SW12: 1502 | SX12: 1486 | SY12: 1781 | SZ12: 1694 | TA12: 1625 | TB12: 1597 | TC12: 1693 | TD12: 1859 | TE12: 1684 | TF12: 1534 | TG12: 1562 | TH12: 1531 | TI12: 1536 | TJ12: 1663 | TK12: 1645 | TL12: 1678 | TM12: 1636 | TN12: 1620 | TO12: 1724 | TP12: 1733 | TQ12: 1805 | TR12: 1823 | TS12: 1787 | TT12: 1555 | TU12: 1642 | TV12: 1570 | TW12: 1659 | TX12: 1704 | TY12: 1748 | TZ12: 1745 | UA12: 1551 | UB12: 1683 | UC12: 1963 | UD12: 1871 | UE12: 1962 | UF12: 1963 | UG12: 1931 | UH12: 1777 | UI12: 1820 | UJ12: 1719 | UK12: 1701 | UL12: 1708 | UM12: 1843 | UN12: 1787 | UO12: 1644 | UP12: 1654 | UQ12: 1838 | UR12: 1790 | US12: 1873 | UT12: 1961 | UU12: 1933 | UV12: 1733 | UW12: 1701 | UX12: 1715 | UY12: 1718 | UZ12: 1769 | VA12: 1862 | VB12: 1758 | VC12: 1648 | VD12: 1617 | VE12: 1610 | VF12: 1610 | VG12: 1714 | VH12: 1800 | VI12: 2294 | VJ12: 2136 | VK12: 1886 | VL12: 1828 | VM12: 1779 | VN12: 1832 | VO12: 1925 | VP12: 1998 | VQ12: 1795 | VR12: 1639 | VS12: 1675 | VT12: 1626 | VU12: 1703 | VV12: 1800 | VW12: 2146 | VX12: 2015 | VY12: 1750 | VZ12: 1691 | WA12: 1773 | WB12: 2052 | WC12: 2191 | WD12: 2254 | WE12: 2197 | WF12: 2003 | WG12: 1957 | WH12: 1885 | WI12: 1940 | WJ12: 1907 | WK12: 1974 | WL12: 2067 | WM12: 1996 | WN12: 2414 | WO12: 2302 | WP12: 2224 | WQ12: 2280 | WR12: 2434 | WS12: 2455 | WT12: 2291 | WU12: 2379 | WV12: 2480 | WW12: 2335 | WX12: 2500 | WY12: 2437 | WZ12: 2451 | XA12: 2288 | XB12: 2314 | XC12: 2450 | XD12: 2425 | XE12: 2543 | XF12: 2573 | XG12: 2644 | XH12: 2382 | XI12: 2315 | XJ12: 2448 | XK12: 2448 | XL12: 2553 | XM12: 2634 | XN12: 2553 | XO12: 2311 | XP12: 2342 | XQ12: 2504 | XR12: 2754 | XS12: 2708 | XT12: 2858 | XU12: 2710 | XV12: 2494 | XW12: 2483 | XX12: 2471 | XY12: 2460 | XZ12: 2631 | YA12: 2757 | YB12: 2607 | YC12: 2300 | YD12: 2250 | YE12: 2296 | YF12: 2495 | YG12: 2700 | YH12: 2817 | YI12: 2864 | YJ12: 2509 | YK12: 2470 | YL12: 2483 | YM12: 2452
B13: Growth | C13: =C12/296-1 -> -0.71283784 | D13: =D12/C12-1 -> -0.15294118 | E13: =E12/D12-1 -> 0.27777778 | F13: =F12/E12-1 -> 0.032608696 | G13: =G12/F12-1 -> -0.10526316 | H13: =H12/G12-1 -> -0.070588235 | I13: =I12/H12-1 -> 0.24050633 | J13: =J12/I12-1 -> -0.071428571 | K13: =K12/J12-1 -> 0 | ... AF13: =AF12/AE12-1 -> -0.1640625 | AG13: =IFERROR(AG12/AF12-1,"") -> 0.0093457944 | AH13: =IFERROR(AH12/AG12-1,"") -> 0.25 | AI13: =IFERROR(AI12/AH12-1,"") -> -0.081481481 | AJ13: =IFERROR(AJ12/AI12-1,"") -> -0.22580645 | AK13: =IFERROR(AK12/AJ12-1,"") -> 0.14583333 | AL13: =IFERROR(AL12/AK12-1,"") -> 0.26363636 | AM13: =IFERROR(AM12/AL12-1,"") -> -0.071942446 | AN13: =IFERROR(AN12/AM12-1,"") -> -0.10077519 | ... VR13: =IFERROR(VR12/VQ12-1,"") -> -0.086908078 | VS13: 0.021964613 | VT13: =IFERROR(VT12/VS12-1,"") -> -0.029253731 | VU13: =IFERROR(VU12/VT12-1,"") -> 0.047355474 | VV13: =IFERROR(VV12/VU12-1,"") -> 0.056958309 | VW13: =IFERROR(VW12/VV12-1,"") -> 0.19222222 | VX13: =IFERROR(VX12/VW12-1,"") -> -0.061043802 | VY13: =IFERROR(VY12/VX12-1,"") -> -0.13151365 | VZ13: =IFERROR(VZ12/VY12-1,"") -> -0.033714286 | WA13: =IFERROR(WA12/VZ12-1,"") -> 0.048492017 | ... WH13: =IFERROR(WH12/WG12-1,"") -> -0.036791007 | WI13: 0.029177719 | WJ13: =IFERROR(WJ12/WI12-1,"") -> -0.017010309 | WK13: =IFERROR(WK12/WJ12-1,"") -> 0.035133718 | WL13: =IFERROR(WL12/WK12-1,"") -> 0.047112462 | WM13: =IFERROR(WM12/WL12-1,"") -> -0.034349299 | WN13: =IFERROR(WN12/WM12-1,"") -> 0.20941884 | WO13: =IFERROR(WO12/WN12-1,"") -> -0.046396023 | WP13: -0.033883579 | WQ13: =IFERROR(WQ12/WP12-1,"") -> 0.025179856 | WR13: =IFERROR(WR12/WQ12-1,"") -> 0.06754386 | WS13: =IFERROR(WS12/WR12-1,"") -> 0.0086277732 | WT13: =IFERROR(WT12/WS12-1,"") -> -0.066802444 | WU13: =IFERROR(WU12/WT12-1,"") -> 0.038411174 | WV13: =IFERROR(WV12/WU12-1,"") -> 0.042454813 | WW13: =IFERROR(WW12/WV12-1,"") -> -0.058467742 | WX13: =IFERROR(WX12/WW12-1,"") -> 0.070663812 | ... YB13: =IFERROR(YB12/YA12-1,"") -> -0.054406964 | YC13: -0.12 | YD13: =IFERROR(YD12/YC12-1,"") -> -0.02173913 | YE13: =IFERROR(YE12/YD12-1,"") -> 0.020444444 | YF13: =IFERROR(YF12/YE12-1,"") -> 0.086672474 | YG13: =IFERROR(YG12/YF12-1,"") -> 0.082164329 | YH13: =IFERROR(YH12/YG12-1,"") -> 0.043333333 | YI13: =IFERROR(YI12/YH12-1,"") -> 0.016684416 | YJ13: =IFERROR(YJ12/YI12-1,"") -> -0.12395251 | YK13: =IFERROR(YK12/YJ12-1,"") -> -0.015544041 | ... YM13: =IFERROR(YM12/YL12-1,"") -> -0.012484897
B15: Transact Rate | C15: =C12/C8 -> 0.23160763 | D15: =D12/D8 -> 0.19618529 | E15: =E12/E8 -> 0.24664879 | F15: =F12/F8 -> 0.25265957 | G15: =G12/G8 -> 0.22606383 | H15: =H12/H8 -> 0.21010638 | I15: =I12/I8 -> 0.25388601 | J15: =J12/J8 -> 0.22979798 | ... WH15: =WH12/WH8 -> 0.14423445 | WI15: 0.14831804 | WJ15: =WJ12/WJ8 -> 0.14450254 | WK15: =WK12/WK8 -> 0.14957945 | WL15: =WL12/WL8 -> 0.15662651 | WM15: =WM12/WM8 -> 0.1512465 | WN15: =WN12/WN8 -> 0.17204761 | WO15: =WO12/WO8 -> 0.16134006 | WP15: 0.15543752 | WQ15: =WQ12/WQ8 -> 0.15935141 | WR15: =WR12/WR8 -> 0.16344346 | WS15: =WS12/WS8 -> 0.16408234 | WT15: =WT12/WT8 -> 0.1511114 | WU15: =WU12/WU8 -> 0.15692612 | WV15: =WV12/WV8 -> 0.16358839 | WW15: =WW12/WW8 -> 0.15213709 | WX15: =WX12/WX8 -> 0.16242204 | ... YB15: =YB12/YB8 -> 0.15991903 | YC15: 0.141 | YD15: =YD12/YD8 -> 0.13801987 | YE15: =YE12/YE8 -> 0.14084161 | YF15: =YF12/YF8 -> 0.15304871 | YG15: =YG12/YG8 -> 0.16562385 | YH15: =YH12/YH8 -> 0.17280088 | YI15: =YI12/YI8 -> 0.17568397 | YJ15: =YJ12/YJ8 -> 0.15391694 | YK15: =YK12/YK8 -> 0.15152445 | ... YM15: =YM12/YM8 -> 0.15042022
B18: Gross Transaction Volume (GTV)
B19: Transaction Value | C19: 486965.33 | D19: 738869.58 | E19: 373364.62 | F19: 443005.49 | G19: 220729.95 | H19: 367007.18 | I19: 689649.58 | J19: 302217.47 | K19: 366689.26 | L19: 346122.45 | M19: 460807.93 | N19: 326748.02 | O19: 315842.28 | P19: 236066.14 | Q19: 954450.41 | R19: 820996.79 | S19: 795837.43 | T19: 700276.06 | U19: 340449.98 | V19: 472914.8 | W19: 455883.24 | X19: 331977.14 | Y19: 454052.38 | Z19: 445666.32 | AA19: 453871.03 | AB19: 377065.95 | AC19: 289043.17 | AD19: 350666.06 | AE19: 409193.83 | AF19: 392536.51 | AG19: 546421.06 | AH19: 546601.2 | AI19: 883585.55 | AJ19: 404135.64 | AK19: 398796.36 | AL19: 580799.63 | AM19: 439350.91 | AN19: 374546.47 | AO19: 348506.46 | AP19: 500609.78 | AQ19: 379108.34 | AR19: 400463.92 | AS19: 476621.53 | AT19: 1005233.8 | AU19: 1010463.2 | AV19: 757517.89 | AW19: 401468.48 | AX19: 699155.92 | AY19: 501073.22 | AZ19: 441040.35 | BA19: 591282.11 | BB19: 323227.22 | BC19: 832247.37 | BD19: 434876.56 | BE19: 391249.15 | BF19: 349493.61 | BG19: 331500.29 | BH19: 648781.05 | BI19: 937932.06 | BJ19: 902173.95 | BK19: 794930.13 | BL19: 636792.89 | BM19: 494048.23 | BN19: 306826.31 | BO19: 714120.01 | BP19: 551460.07 | BQ19: 577631.04 | BR19: 584819.18 | BS19: 548078.59 | BT19: 405741.14 | BU19: 375212.17 | BV19: 542091.54 | BW19: 694490.25 | BX19: 942228.8 | BY19: 441709.26 | BZ19: 498801.51 | CA19: 403821.7 | CB19: 523255.6 | CC19: 965037.02 | CD19: 530923.31 | CE19: 730623.09 | CF19: 621300.57 | CG19: 426415.31 | CH19: 698645.92 | CI19: 656329.8 | CJ19: 387304.82 | CK19: 580402.73 | CL19: 681585.98 | CM19: 491101.49 | CN19: 703392.77 | CO19: 615387.05 | CP19: 1039585.1 | CQ19: 677731.06 | CR19: 519403.33 | CS19: 730015.3 | CT19: 844208.41 | CU19: 720005.68 | CV19: 671677.47 | CW19: 859573.42 | CX19: 713368.24 | CY19: 1074529.6 | CZ19: 889184.67 | DA19: 555501.26 | DB19: 635067.78 | DC19: 966554.16 | DD19: 663627.56 | DE19: 653116.03 | DF19: 733655.3 | DG19: 696131.67 | DH19: 771901.34 | DI19: 678340.34 | DJ19: 691962.22 | DK19: 1045628.1 | DL19: 682075.43 | DM19: 600434.79 | DN19: 732022.43 | DO19: 739517.38 | DP19: 482804.8 | DQ19: 595112.65 | DR19: 788646.53 | DS19: 999406.21 | DT19: 1560862.4 | DU19: 731949.6 | DV19: 673987.43 | DW19: 580686.05 | DX19: 643608.8 | DY19: 684490.65 | DZ19: 643145.28 | EA19: 972975.55 | EB19: 785943.15 | EC19: 920839.43 | ED19: 571283.49 | EE19: 387231.98 | EF19: 710564.8 | EG19: 964571.95 | EH19: 935924.24 | EI19: 1157775.5 | EJ19: 693597.93 | EK19: 793081.16 | EL19: 688057.77 | EM19: 920395.38 | EN19: 871818.32 | EO19: 1222228.9 | EP19: 857527.47 | EQ19: 880900.49 | ER19: 643933.7 | ES19: 1040412.3 | ET19: 554857.92 | EU19: 749159.19 | EV19: 1051763.4 | EW19: 937606.86 | EX19: 1488863.2 | EY19: 1250456.4 | EZ19: 882241.18 | FA19: 1117198.7 | FB19: 1169676.4 | FC19: 1045536 | FD19: 1237422.8 | FE19: 983814.96 | FF19: 895694.52 | FG19: 882684.63 | FH19: 802234.51 | FI19: 820559.93 | FJ19: 1054346 | FK19: 1441216.1 | FL19: 1142915.2 | FM19: 973092.18 | FN19: 964616.47 | FO19: 786624.71 | FP19: 1222767.1 | FQ19: 1187846.7 | FR19: 794152.17 | FS19: 981306.9 | FT19: 1165643.3 | FU19: 1274836.8 | FV19: 1606343 | FW19: 1431790.6 | FX19: 938809.81 | FY19: 1224095.3 | FZ19: 1144190.7 | GA19: 1341434.8 | GB19: 1632277 | GC19: 1723121.3 | GD19: 1133542 | GE19: 1101832.3 | GF19: 1401841.5 | GG19: 1103935.8 | GH19: 1439733.6 | GI19: 760733.32 | GJ19: 1241937.9 | GK19: 951413.91 | GL19: 1116166.1 | GM19: 993967.8 | GN19: 1176532.8 | GO19: 1157589.8 | GP19: 1285617.8 | GQ19: 1344951.8 | GR19: 1232907.1 | GS19: 1531590.5 | GT19: 1686738.2 | GU19: 1492859.6 | GV19: 1480551.9 | GW19: 1999085.2 | GX19: 1632685.2 | GY19: 1118538 | GZ19: 1529433.1 | HA19: 1426697.7 | HB19: 1089392.3 | HC19: 1080402.1 | HD19: 1048937.4 | HE19: 1188979 | HF19: 1467224.6 | HG19: 1733015.5 | HH19: 2062945.6 | HI19: 1352606.7 | HJ19: 1201048.6 | HK19: 1352498.2 | HL19: 1265272.1 | HM19: 1960688.8 | HN19: 1715612.2 | HO19: 1253644.3 | HP19: 1131606.4 | HQ19: 1299273.6 | HR19: 1187087.2 | HS19: 1163033.6 | HT19: 1312912.2 | HU19: 2072277.4 | HV19: 1623393 | HW19: 1349656.5 | HX19: 1566720.1 | HY19: 1845014.7 | HZ19: 1258505.6 | IA19: 1477296.5 | IB19: 1705202.8 | IC19: 1387264 | ID19: 1148453.4 | IE19: 1261402.6 | IF19: 1730745.9 | IG19: 1490020.6 | IH19: 1568398.3 | II19: 1615169.4 | IJ19: 1695200 | IK19: 1945191.9 | IL19: 2917753.1 | IM19: 2483959.8 | IN19: 1853784.6 | IO19: 1572693.9 | IP19: 1734692.8 | IQ19: 1995113.9 | IR19: 1892993.9 | IS19: 1353565.6 | IT19: 1824923.8 | IU19: 1478167.7 | IV19: 1364312.6 | IW19: 2134268.7 | IX19: 2471938.4 | IY19: 2346566 | IZ19: 2329959.5 | JA19: 1728006.2 | JB19: 1597154.6 | JC19: 2729112.6 | JD19: 1695374.6 | JE19: 2001244.4 | JF19: 1824981.8 | JG19: 1595446.2 | JH19: 1662668.4 | JI19: 1651203.6 | JJ19: 2042606.5 | JK19: 1959518.8 | JL19: 1978334.8 | JM19: 1875258.4 | JN19: 1598060.3 | JO19: 2084870.7 | JP19: 2824176.7 | JQ19: 2738023.2 | JR19: 2312554.7 | JS19: 2725405.3 | JT19: 2294740.3 | JU19: 1973825.5 | JV19: 2113553.8 | JW19: 1690822.5 | JX19: 2313588.9 | JY19: 2304185.4 | JZ19: 2150146.7 | KA19: 1837257.1 | KB19: 1529567.8 | KC19: 2136338.9 | KD19: 2843226.6 | KE19: 2102590.2 | KF19: 2447742.3 | KG19: 2447700.1 | KH19: 1756277.1 | KI19: 2010379.2 | KJ19: 1925266.7 | KK19: 1849821.9 | KL19: 1440221.8 | KM19: 1686376.6 | KN19: 1996732.4 | KO19: 1816037.8 | KP19: 1471707.1 | KQ19: 1914670.1 | KR19: 1953329.1 | KS19: 1918566.6 | KT19: 2492820.2 | KU19: 2142954.5 | KV19: 3022015 | KW19: 3175373.6 | KX19: 1927245.6 | KY19: 2113800 | KZ19: 1938402.1 | LA19: 2754021.1 | LB19: 2619611.5 | LC19: 2063729.9 | LD19: 2078589.1 | LE19: 2264095.2 | LF19: 2108360.7 | LG19: 1645485.1 | LH19: 2140303.6 | LI19: 2505513.4 | LJ19: 3125347.3 | LK19: 1821576 | LL19: 2189308.1 | LM19: 1997825.1 | LN19: 2134807.6 | LO19: 2231888.2 | LP19: 2526357.1 | LQ19: 2283908.1 | LR19: 2133846.4 | LS19: 1604626.2 | LT19: 2255672.3 | LU19: 2410482.9 | LV19: 2574686 | LW19: 2675531.8 | LX19: 2292985.8 | LY19: 3120013.4 | LZ19: 3009562.9 | MA19: 1946899.8 | MB19: 2185330.5 | MC19: 2920019.5 | MD19: 2824735.3 | ME19: 2457400.6 | MF19: 2770922.3 | MG19: 1747307.1 | MH19: 1911890.2 | MI19: 1774786.8 | MJ19: 2647221.9 | MK19: 2276988.7 | ML19: 2252713.7 | MM19: 2598717.9 | MN19: 1899759.7 | MO19: 2002427.8 | MP19: 2970569.2 | MQ19: 2011528 | MR19: 2452514.4 | MS19: 2431497.5 | MT19: 2266997.6 | MU19: 2923173.3 | MV19: 2079236.6 | MW19: 1513098.2 | MX19: 2272224.4 | MY19: 2151079 | MZ19: 1834047.1 | NA19: 2456075.8 | NB19: 2339871.9 | NC19: 2410583.4 | ND19: 1954157.3 | NE19: 2665578.4 | NF19: 2516920.5 | NG19: 2258359.5 | NH19: 1751160.9 | NI19: 1916842.3 | NJ19: 1566346 | NK19: 1665154.9 | NL19: 2122402.2 | NM19: 1957906 | NN19: 1708319.6 | NO19: 1572339.1 | NP19: 2024261.7 | NQ19: 1952894.9 | NR19: 2134012.4 | NS19: 1942789.6 | NT19: 2020200.2 | NU19: 2304114.1 | NV19: 2383414.8 | NW19: 1895364.8 | NX19: 2081594 | NY19: 1790375 | NZ19: 2610723.8 | OA19: 2089192.4 | OB19: 1981472.6 | OC19: 1565992.8 | OD19: 1942576.5 | OE19: 1686172.9 | OF19: 1495248.6 | OG19: 2233972.6 | OH19: =2495799.69+3908.59 -> 2499708.3 | OI19: 3109991.9 | OJ19: 3180800.7 | OK19: 1972039.6 | OL19: 2524502.2 | OM19: 2103249.4 | ON19: 2019153.2 | OO19: 2059476.1 | OP19: 1755323.8 | OQ19: 1611170 | OR19: 1840735 | OS19: 1510110.6 | OT19: 1773107.9 | OU19: 2354001.1 | OV19: 3353547.7 | OW19: 2869968.6 | OX19: 2687367.9 | OY19: 2711081.7 | OZ19: 2509137 | PA19: 2160720.3 | PB19: 2179221.5 | PC19: 2179221.5 | PD19: 2469121 | PE19: 2514430.2 | PF19: 2275260.7 | PG19: 2127917.4 | PH19: 2128903.6 | PI19: 2940353 | PJ19: 2995858.1 | PK19: 4237504.9 | PL19: 4362645.9 | PM19: 3727954.5 | PN19: 2350612.7 | PO19: 3253176 | PP19: 3025832.1 | PQ19: 2981744.1 | PR19: 2709087.4 | PS19: 2075891.1 | PT19: 2698725 | PU19: 2028983.3 | PV19: 2248955.1 | PW19: 2960128.1 | PX19: 3368052.1 | PY19: 3575052.8 | PZ19: 7309518.5 | QA19: 3510551.5 | QB19: 3629961.2 | QC19: 3678928.2 | QD19: 3648604.8 | QE19: 3568144.5 | QF19: 3418952.5 | QG19: 2527710.6 | QH19: 3123644.3 | QI19: 3066609.9 | QJ19: 3091554 | QK19: 3373651.6 | QL19: 3692421.5 | QM19: 3835660.4 | QN19: 3437370.5 | QO19: 3758759.5 | QP19: 4714997.1 | QQ19: 4660289.9 | QR19: 3467455.5 | QS19: 4964454.8 | QT19: 4525886.9 | QU19: 3985719.1 | QV19: 3893229.7 | QW19: 3765745.9 | QX19: 3627239.9 | QY19: 4136936.3 | QZ19: 3395542.4 | RA19: 3189777.8 | RB19: 3361512.2 | RC19: 4146259.7 | RD19: 3855631.3 | RE19: 4650720.7 | RF19: 4926484.1 | RG19: 4550421.7 | RH19: 3923048.1 | RI19: 3621596.7 | RJ19: 3433692 | RK19: 3244171.8 | RL19: 3115660.1 | RM19: 3411695.2 | RN19: 4087389.2 | RO19: 3778955.6 | RP19: 2672720.6 | RQ19: 3166996.9 | RR19: 3545424.9 | RS19: 3339818.4 | RT19: 5358819.7 | RU19: 5991618.5 | RV19: 4249590.1 | RW19: 3796239.6 | RX19: 4125727.6 | RY19: 3677925.9 | RZ19: 3555790.4 | SA19: 4306045.4 | SB19: 3876158.3 | SC19: 3909798 | SD19: 3400020.4 | SE19: 2950045.5 | SF19: 3400559.9 | SG19: 3687767.3 | SH19: 4912717.3 | SI19: 4506329.7 | SJ19: 4932004.4 | SK19: 4788303 | SL19: 3849321.6 | SM19: 4482896.4 | SN19: 3736580.6 | SO19: 3761675.6 | SP19: 5037785.2 | SQ19: 4516926.4 | SR19: 4516926.4 | SS19: 3599580.3 | ST19: 4063939.7 | SU19: 3811666.8 | SV19: 4398957.3 | SW19: 4703359.3 | SX19: 4244742 | SY19: 5963055.4 | SZ19: 6460125.2 | TA19: 4681671.9 | TB19: 4406227.5 | TC19: 6175099.3 | TD19: 6231211.8 | TE19: 5356027.2 | TF19: 4561817.4 | TG19: 4594434.7 | TH19: 4003443.1 | TI19: 3974171.5 | TJ19: 4674624.3 | TK19: 4060299.7 | TL19: 4655263.4 | TM19: 4591014.7 | TN19: 4921025.2 | TO19: 4920065.2 | TP19: 4410735.2 | TQ19: 4763511.5 | TR19: 5283480.9 | TS19: 4515851.5 | TT19: 4357709.6 | TU19: 4235436.3 | TV19: 3961838.9 | TW19: 4238301.5 | TX19: 4385970.3 | TY19: 4682057 | TZ19: 3897476.5 | UA19: 3753498.5 | UB19: 4148573.1 | UC19: 5653317.7 | UD19: 5240166.2 | UE19: 5355702 | UF19: 5522573.8 | UG19: 5019114.6 | UH19: 5705157 | UI19: 5042324.7 | UJ19: 4133008.5 | UK19: 3992743.3 | UL19: 4841635.8 | UM19: 4833177 | UN19: 4405963.9 | UO19: 3438279.6 | UP19: 4011951.7 | UQ19: 5264691.7 | UR19: 5631755.8 | US19: 5050902.3 | UT19: 5171299.4 | UU19: 4952825.7 | UV19: 3933857.1 | UW19: 4318635.3 | UX19: 3932175.8 | UY19: 3552169.2 | UZ19: 3985107.4 | VA19: 5022294.4 | VB19: 4056665 | VC19: 3900577.4 | VD19: 3786236 | VE19: 3454550.7 | VF19: 3454550.7 | VG19: 4079155.6 | VH19: 4029801.4 | VI19: 7573095.7 | VJ19: 6167538.4 | VK19: 5236170.1 | VL19: 4496363.5 | VM19: 4471961.8 | VN19: 4611360.5 | VO19: 4830436.6 | VP19: 5772307 | VQ19: 4181665.5 | VR19: 3879750.6 | VS19: 4054676.7 | VT19: 3499167.2 | VU19: 3829243.2 | VV19: 4348430 | VW19: 5941730.2 | VX19: 5346318.8 | VY19: 3890967.2 | VZ19: 4512766.9 | WA19: 5114057.2 | WB19: 5196847.9 | WC19: 5571510.5 | WD19: 5673369.8 | WE19: 5682309.1 | WF19: 4951735.7 | WG19: 5031483.4 | WH19: 4487256.7 | WI19: 5070233.7 | WJ19: 4568358 | WK19: 5968469 | WL19: 6257099.7 | WM19: 5441316.6 | WN19: 7022681.7 | WO19: 5718049 | WP19: 6115728.3 | WQ19: 6119048.2 | WR19: 6630173.4 | WS19: 6757620.7 | WT19: 5956084 | WU19: 6889025.9 | WV19: 6528092.5 | WW19: 5358250.5 | WX19: 6994256 | WY19: 6462652.4 | WZ19: 6461225.8 | XA19: 6130756.4 | XB19: 5572566.7 | XC19: 6803575.4 | XD19: 6467348.6 | XE19: 7351547 | XF19: 6655994.4 | XG19: 7098318.1 | XH19: 6430080.5 | XI19: 5985488.8 | XJ19: 6159124.2 | XK19: 6865943.8 | XL19: 7059418.3 | XM19: 6960912.2 | XN19: 6725805 | XO19: 5803765.5 | XP19: 6264378.3 | XQ19: 6432724 | XR19: 8402753.6 | XS19: 7694928.6 | XT19: 8087580.6 | XU19: 7740220.4 | XV19: 7065263.3 | XW19: 6623169.8 | XX19: 6490840.6 | XY19: 7532992.9 | XZ19: 7832729.2 | YA19: 7863513.4 | YB19: 7491364.2 | YC19: 6076238 | YD19: 6561041.9 | YE19: 5713854.2 | YF19: 7328780.3 | YG19: 8213389.2 | YH19: 7950245.9 | YI19: 7625321.8 | YJ19: 7280168.5 | YK19: 6830951.3 | YL19: 6296790.7 | YM19: 5765360.3
B20: Growth | C20: =C19/296-1 -> 1644.1531 | D20: =D19/C19-1 -> 0.51729401 | E20: =E19/D19-1 -> -0.49468129 | F20: =F19/E19-1 -> 0.18652241 | G20: =G19/F19-1 -> -0.50174444 | H20: =H19/G19-1 -> 0.6626977 | I20: =I19/H19-1 -> 0.87911741 | J20: =J19/I19-1 -> -0.56178111 | K20: =K19/J19-1 -> 0.21332913 | ... VR20: =VR19/VQ19-1 -> -0.072199691 | VS20: 0.045086953 | VT20: =VT19/VS19-1 -> -0.13700464 | VU20: =VU19/VT19-1 -> 0.094329889 | VV20: =VV19/VU19-1 -> 0.1355847 | VW20: =VW19/VV19-1 -> 0.36640814 | VX20: =VX19/VW19-1 -> -0.10020841 | VY20: =VY19/VX19-1 -> -0.27221565 | VZ20: =VZ19/VY19-1 -> 0.15980596 | WA20: =WA19/VZ19-1 -> 0.13324204 | ... WH20: =WH19/WG19-1 -> -0.10816426 | WI20: 0.12991834 | WJ20: =WJ19/WI19-1 -> -0.098984718 | WK20: =WK19/WJ19-1 -> 0.30648013 | WL20: =WL19/WK19-1 -> 0.048359249 | WM20: =WM19/WL19-1 -> -0.13037718 | WN20: =WN19/WM19-1 -> 0.29062176 | WO20: =WO19/WN19-1 -> -0.18577413 | WP20: 0.069548066 | WQ20: =WQ19/WP19-1 -> 0.00054283968 | WR20: =WR19/WQ19-1 -> 0.083530184 | WS20: =WS19/WR19-1 -> 0.019222319 | WT20: =WT19/WS19-1 -> -0.11861226 | WU20: =WU19/WT19-1 -> 0.15663679 | WV20: =WV19/WU19-1 -> -0.052392509 | WW20: =WW19/WV19-1 -> -0.1792012 | WX20: =WX19/WW19-1 -> 0.30532455 | ... YB20: =YB19/YA19-1 -> -0.047326072 | YC20: -0.19 | YD20: =YD19/YC19-1 -> 0.079786845 | YE20: =YE19/YD19-1 -> -0.12912395 | YF20: =YF19/YE19-1 -> 0.28263342 | YG20: =YG19/YF19-1 -> 0.12070342 | YH20: =YH19/YG19-1 -> -0.03203833 | YI20: =YI19/YH19-1 -> -0.040869692 | YJ20: =YJ19/YI19-1 -> -0.045264102 | YK20: =YK19/YJ19-1 -> -0.061704231 | ... YM20: =YM19/YL19-1 -> -0.084397028
B22: Transaction Count | C22: 204 | D22: 165 | E22: 206 | F22: 233 | G22: 171 | H22: 167 | I22: 196 | J22: 198 | K22: 195 | L22: 206 | M22: 254 | N22: 189 | O22: 166 | P22: 215 | Q22: 322 | R22: 285 | S22: 247 | T22: 240 | U22: 219 | V22: 225 | W22: 223 | X22: 241 | Y22: 283 | Z22: 265 | AA22: 267 | AB22: 257 | AC22: 231 | AD22: 264 | AE22: 288 | AF22: 241 | AG22: 245 | AH22: 327 | AI22: 275 | AJ22: 185 | AK22: 249 | AL22: 265 | AM22: 264 | AN22: 260 | AO22: 278 | AP22: 242 | AQ22: 220 | AR22: 284 | AS22: 272 | AT22: 280 | AU22: 291 | AV22: 347 | AW22: 267 | AX22: 310 | AY22: 259 | AZ22: 287 | BA22: 309 | BB22: 298 | BC22: 317 | BD22: 336 | BE22: 297 | BF22: 281 | BG22: 255 | BH22: 332 | BI22: 315 | BJ22: 464 | BK22: 376 | BL22: 328 | BM22: 316 | BN22: 269 | BO22: 313 | BP22: 324 | BQ22: 329 | BR22: 303 | BS22: 277 | BT22: 264 | BU22: 273 | BV22: 269 | BW22: 399 | BX22: 399 | BY22: 329 | BZ22: 279 | CA22: 316 | CB22: 358 | CC22: 351 | CD22: 351 | CE22: 413 | CF22: 340 | CG22: 287 | CH22: 319 | CI22: 363 | CJ22: 342 | CK22: 403 | CL22: 427 | CM22: 346 | CN22: 371 | CO22: 358 | CP22: 412 | CQ22: 390 | CR22: 430 | CS22: 455 | CT22: 437 | CU22: 364 | CV22: 350 | CW22: 382 | CX22: 466 | CY22: 406 | CZ22: 466 | DA22: 411 | DB22: 363 | DC22: 466 | DD22: 459 | DE22: 407 | DF22: 324 | DG22: 461 | DH22: 431 | DI22: 428 | DJ22: 450 | DK22: 534 | DL22: 465 | DM22: 440 | DN22: 515 | DO22: 497 | DP22: 389 | DQ22: 364 | DR22: 455 | DS22: 488 | DT22: 444 | DU22: 428 | DV22: 397 | DW22: 411 | DX22: 409 | DY22: 480 | DZ22: 499 | EA22: 470 | EB22: 490 | EC22: 459 | ED22: 409 | EE22: 381 | EF22: 440 | EG22: 536 | EH22: 546 | EI22: 600 | EJ22: 512 | EK22: 531 | EL22: 579 | EM22: 583 | EN22: 607 | EO22: 724 | EP22: 649 | EQ22: 618 | ER22: 477 | ES22: 631 | ET22: 520 | EU22: 555 | EV22: 667 | EW22: 701 | EX22: 697 | EY22: 590 | EZ22: 623 | FA22: 688 | FB22: 759 | FC22: 761 | FD22: 724 | FE22: 761 | FF22: 601 | FG22: 600 | FH22: 677 | FI22: 661 | FJ22: 699 | FK22: 767 | FL22: 748 | FM22: 695 | FN22: 762 | FO22: 681 | FP22: 802 | FQ22: 798 | FR22: 745 | FS22: 833 | FT22: 822 | FU22: 736 | FV22: 847 | FW22: 759 | FX22: 767 | FY22: 902 | FZ22: 866 | GA22: 829 | GB22: 770 | GC22: 815 | GD22: 836 | GE22: 846 | GF22: 879 | GG22: 816 | GH22: 823 | GI22: 683 | GJ22: 733 | GK22: 750 | GL22: 908 | GM22: 839 | GN22: 910 | GO22: 814 | GP22: 852 | GQ22: 889 | GR22: 873 | GS22: 927 | GT22: 920 | GU22: 972 | GV22: 744 | GW22: 787 | GX22: 751 | GY22: 788 | GZ22: 904 | HA22: 991 | HB22: 905 | HC22: 836 | HD22: 820 | HE22: 908 | HF22: 896 | HG22: 1072 | HH22: 1128 | HI22: 1079 | HJ22: 852 | HK22: 872 | HL22: 914 | HM22: 938 | HN22: 970 | HO22: 1015 | HP22: 922 | HQ22: 781 | HR22: 779 | HS22: 784 | HT22: 899 | HU22: 1104 | HV22: 1111 | HW22: 1129 | HX22: 1035 | HY22: 1083 | HZ22: 1086 | IA22: 1172 | IB22: 1140 | IC22: 1076 | ID22: 1120 | IE22: 1039 | IF22: 932 | IG22: 1100 | IH22: 1029 | II22: 1166 | IJ22: 1206 | IK22: 1287 | IL22: 1349 | IM22: 1262 | IN22: 1214 | IO22: 1306 | IP22: 1357 | IQ22: 1532 | IR22: 1382 | IS22: 1232 | IT22: 1430 | IU22: 1221 | IV22: 1151 | IW22: 1394 | IX22: 1419 | IY22: 1438 | IZ22: 1485 | JA22: 1322 | JB22: 1318 | JC22: 1390 | JD22: 1313 | JE22: 1449 | JF22: 1440 | JG22: 1111 | JH22: 1233 | JI22: 1176 | JJ22: 1310 | JK22: 1305 | JL22: 1451 | JM22: 1361 | JN22: 1151 | JO22: 1310 | JP22: 1602 | JQ22: 1506 | JR22: 1457 | JS22: 1633 | JT22: 1580 | JU22: 1376 | JV22: 1351 | JW22: 1405 | JX22: 1323 | JY22: 1494 | JZ22: 1566 | KA22: 1401 | KB22: 1070 | KC22: 1259 | KD22: 1403 | KE22: 1365 | KF22: 1552 | KG22: 1601 | KH22: 1520 | KI22: 1294 | KJ22: 1396 | KK22: 1318 | KL22: 1283 | KM22: 1364 | KN22: 1463 | KO22: 1387 | KP22: 1248 | KQ22: 1324 | KR22: 1318 | KS22: 1288 | KT22: 1500 | KU22: 1385 | KV22: 1579 | KW22: 1420 | KX22: 1352 | KY22: 1469 | KZ22: 1296 | LA22: 1727 | LB22: 1819 | LC22: 1402 | LD22: 1459 | LE22: 1769 | LF22: 1515 | LG22: 1562 | LH22: 1703 | LI22: 1902 | LJ22: 1805 | LK22: 1447 | LL22: 2258 | LM22: 1756 | LN22: 1679 | LO22: 1757 | LP22: 1847 | LQ22: 1724 | LR22: 1602 | LS22: 1838 | LT22: 1943 | LU22: 2178 | LV22: 2119 | LW22: 2063 | LX22: 1894 | LY22: 1994 | LZ22: 2036 | MA22: 1732 | MB22: 1806 | MC22: 1979 | MD22: 2067 | ME22: 2004 | MF22: 1766 | MG22: 1573 | MH22: 1700 | MI22: 1698 | MJ22: 1818 | MK22: 1789 | ML22: 1861 | MM22: 1817 | MN22: 1655 | MO22: 1742 | MP22: 1823 | MQ22: 1777 | MR22: 1959 | MS22: 1901 | MT22: 1730 | MU22: 1858 | MV22: 1678 | MW22: 1286 | MX22: 1549 | MY22: 1593 | MZ22: 1535 | NA22: 1394 | NB22: 1504 | NC22: 1506 | ND22: 1393 | NE22: 1634 | NF22: 1663 | NG22: 1633 | NH22: 1488 | NI22: 1408 | NJ22: 1398 | NK22: 1316 | NL22: 1390 | NM22: 1528 | NN22: 1370 | NO22: 1336 | NP22: 1286 | NQ22: 1275 | NR22: 1497 | NS22: 1578 | NT22: 1725 | NU22: 1676 | NV22: 1437 | NW22: 1439 | NX22: 1515 | NY22: 1342 | NZ22: 1482 | OA22: 1534 | OB22: 1552 | OC22: 1423 | OD22: 1345 | OE22: 1343 | OF22: 1302 | OG22: 1501 | OH22: 1579 | OI22: 1993 | OJ22: 1742 | OK22: 1648 | OL22: 1554 | OM22: 1549 | ON22: 1599 | OO22: 1805 | OP22: 1615 | OQ22: 1453 | OR22: 1533 | OS22: 1547 | OT22: 1561 | OU22: 1941 | OV22: 2065 | OW22: 2030 | OX22: 1941 | OY22: 1880 | OZ22: 1974 | PA22: 1923 | PB22: 1946 | PC22: 2211 | PD22: 1995 | PE22: 1990 | PF22: 1761 | PG22: 1841 | PH22: 2075 | PI22: 2371 | PJ22: 2550 | PK22: 2826 | PL22: 2371 | PM22: 2560 | PN22: 2195 | PO22: 2269 | PP22: 2277 | PQ22: 2318 | PR22: 2253 | PS22: 1840 | PT22: 1815 | PU22: 1806 | PV22: 1911 | PW22: 2192 | PX22: 2575 | PY22: 2554 | PZ22: 2403 | QA22: 2384 | QB22: 2511 | QC22: 2478 | QD22: 2768 | QE22: 2863 | QF22: 2567 | QG22: 2397 | QH22: 2387 | QI22: 2347 | QJ22: 2307 | QK22: 2630 | QL22: 3017 | QM22: 2571 | QN22: 2423 | QO22: 2583 | QP22: 3293 | QQ22: 2775 | QR22: 2433 | QS22: 3572 | QT22: 3713 | QU22: 2883 | QV22: 2965 | QW22: 3083 | QX22: 3144 | QY22: 2842 | QZ22: 2911 | RA22: 2860 | RB22: 2788 | RC22: 2770 | RD22: 2936 | RE22: 3277 | RF22: 3237 | RG22: 3542 | RH22: 3289 | RI22: 2921 | RJ22: 2802 | RK22: 2824 | RL22: 2766 | RM22: 3043 | RN22: 3202 | RO22: 3069 | RP22: 2608 | RQ22: 2646 | RR22: 2674 | RS22: 2916 | RT22: 3458 | RU22: 3341 | RV22: 3246 | RW22: 2977 | RX22: 3193 | RY22: 3016 | RZ22: 3015 | SA22: 3023 | SB22: 3186 | SC22: 3374 | SD22: 2971 | SE22: 2622 | SF22: 2834 | SG22: 2969 | SH22: 3410 | SI22: 3640 | SJ22: 3643 | SK22: 3525 | SL22: 3185 | SM22: 3239 | SN22: 3231 | SO22: 3437 | SP22: 3775 | SQ22: 3501 | SR22: 3013 | SS22: 3093 | ST22: 3417 | SU22: 3447 | SV22: 3370 | SW22: 3516 | SX22: 3375 | SY22: 4178 | SZ22: 3713 | TA22: 3542 | TB22: 3364 | TC22: 3705 | TD22: 4306 | TE22: 3842 | TF22: 3238 | TG22: 3372 | TH22: 3347 | TI22: 3421 | TJ22: 3700 | TK22: 3683 | TL22: 3693 | TM22: 3543 | TN22: 3590 | TO22: 3801 | TP22: 3720 | TQ22: 3928 | TR22: 4121 | TS22: 3837 | TT22: 3127 | TU22: 3590 | TV22: 3386 | TW22: 3534 | TX22: 3600 | TY22: 3843 | TZ22: 3685 | UA22: 3267 | UB22: 3561 | UC22: 4230 | UD22: 3834 | UE22: 4332 | UF22: 4228 | UG22: 4147 | UH22: 3697 | UI22: 3881 | UJ22: 3635 | UK22: 3519 | UL22: 3564 | UM22: 4024 | UN22: 3819 | UO22: 3475 | UP22: 3320 | UQ22: 3888 | UR22: 3872 | US22: 3990 | UT22: 4131 | UU22: 4052 | UV22: 3551 | UW22: 3408 | UX22: 3499 | UY22: 3607 | UZ22: 3553 | VA22: 3954 | VB22: 3685 | VC22: 3372 | VD22: 3226 | VE22: 3385 | VF22: 3385 | VG22: 3556 | VH22: 3664 | VI22: 4958 | VJ22: 4347 | VK22: 3889 | VL22: 3807 | VM22: 3565 | VN22: 3551 | VO22: 4013 | VP22: 4187 | VQ22: 3663 | VR22: 3259 | VS22: 3345 | VT22: 3377 | VU22: 3504 | VV22: 3738 | VW22: 4551 | VX22: 4248 | VY22: 3636 | VZ22: 3330 | WA22: 3476 | WB22: 4225 | WC22: 4692 | WD22: 4991 | WE22: 4753 | WF22: 4110 | WG22: 4220 | WH22: 3965 | WI22: 4072 | WJ22: 4044 | WK22: 4142 | WL22: 4440 | WM22: 4187 | WN22: 5249 | WO22: 4998 | WP22: 5037 | WQ22: 4907 | WR22: 5620 | WS22: 5482 | WT22: 4977 | WU22: 5091 | WV22: 5661 | WW22: 5042 | WX22: 5384 | WY22: 5402 | WZ22: 5301 | XA22: 4817 | XB22: 4970 | XC22: 5265 | XD22: 5218 | XE22: 5583 | XF22: 5823 | XG22: 5835 | XH22: 5237 | XI22: 5103 | XJ22: 5319 | XK22: 5453 | XL22: 5679 | XM22: 6079 | XN22: 5848 | XO22: 5226 | XP22: 5447 | XQ22: 5586 | XR22: 6371 | XS22: 6204 | XT22: 6834 | XU22: 6464 | XV22: 5612 | XW22: 5703 | XX22: 5706 | XY22: 5536 | XZ22: 5888 | YA22: 6446 | YB22: 5952 | YC22: 5133 | YD22: 4952 | YE22: 5399 | YF22: 5777 | YG22: 6311 | YH22: 6778 | YI22: 6599 | YJ22: 5842 | YK22: 5801 | YL22: 5642 | YM22: 5626
B23: Growth | C23: =C22/296-1 -> -0.31081081 | D23: =D22/C22-1 -> -0.19117647 | E23: =E22/D22-1 -> 0.24848485 | F23: =F22/E22-1 -> 0.13106796 | G23: =G22/F22-1 -> -0.26609442 | H23: =H22/G22-1 -> -0.023391813 | I23: =I22/H22-1 -> 0.17365269 | J23: =J22/I22-1 -> 0.010204082 | K23: =K22/J22-1 -> -0.015151515 | ... VR23: =VR22/VQ22-1 -> -0.11029211 | VS23: 0.026388463 | VT23: =VT22/VS22-1 -> 0.0095665172 | VU23: =VU22/VT22-1 -> 0.037607344 | VV23: =VV22/VU22-1 -> 0.066780822 | VW23: =VW22/VV22-1 -> 0.21749599 | VX23: =VX22/VW22-1 -> -0.066578774 | VY23: =VY22/VX22-1 -> -0.1440678 | VZ23: =VZ22/VY22-1 -> -0.084158416 | WA23: =WA22/VZ22-1 -> 0.043843844 | ... WH23: =WH22/WG22-1 -> -0.06042654 | WI23: 0.026986129 | WJ23: =WJ22/WI22-1 -> -0.0068762279 | WK23: =WK22/WJ22-1 -> 0.024233432 | WL23: =WL22/WK22-1 -> 0.07194592 | WM23: =WM22/WL22-1 -> -0.056981982 | WN23: =WN22/WM22-1 -> 0.25364223 | WO23: =WO22/WN22-1 -> -0.047818632 | WP23: 0.0078031212 | WQ23: =WQ22/WP22-1 -> -0.025809013 | WR23: =WR22/WQ22-1 -> 0.14530263 | WS23: =WS22/WR22-1 -> -0.02455516 | WT23: =WT22/WS22-1 -> -0.092119664 | WU23: =WU22/WT22-1 -> 0.022905365 | WV23: =WV22/WU22-1 -> 0.11196229 | WW23: =WW22/WV22-1 -> -0.10934464 | WX23: =WX22/WW22-1 -> 0.067830226 | ... YB23: =YB22/YA22-1 -> -0.076636674 | YC23: -0.14 | YD23: =YD22/YC22-1 -> -0.03526203 | YE23: =YE22/YD22-1 -> 0.090266559 | YF23: =YF22/YE22-1 -> 0.070012965 | YG23: =YG22/YF22-1 -> 0.09243552 | YH23: =YH22/YG22-1 -> 0.073997782 | YI23: =YI22/YH22-1 -> -0.02640897 | YJ23: =YJ22/YI22-1 -> -0.11471435 | YK23: =YK22/YJ22-1 -> -0.0070181445 | ... YM23: =YM22/YL22-1 -> -0.0028358738
B25: Average Ticket Size | C25: =C19/C22 -> 2387.085 | D25: =D19/D22 -> 4477.9975 | E25: =E19/E22 -> 1812.4496 | F25: =F19/F22 -> 1901.3111 | G25: =G19/G22 -> 1290.8184 | H25: =H19/H22 -> 2197.6478 | I25: =I19/I22 -> 3518.6203 | J25: =J19/J22 -> 1526.3509 | ... WH25: =WH19/WH22 -> 1131.7167 | WI25: 1245.1458 | WJ25: =WJ19/WJ22 -> 1129.6632 | WK25: =WK19/WK22 -> 1440.9631 | WL25: =WL19/WL22 -> 1409.2567 | WM25: =WM19/WM22 -> 1299.5741 | WN25: =WN19/WN22 -> 1337.9085 | WO25: =WO19/WO22 -> 1144.0674 | WP25: 1214.1609 | WQ25: =WQ19/WQ22 -> 1247.0039 | WR25: =WR19/WR22 -> 1179.7462 | WS25: =WS19/WS22 -> 1232.6926 | WT25: =WT19/WT22 -> 1196.7217 | WU25: =WU19/WU22 -> 1353.1774 | WV25: =WV19/WV22 -> 1153.1695 | WW25: =WW19/WW22 -> 1062.7232 | WX25: =WX19/WX22 -> 1299.0817 | ... YB25: =YB19/YB22 -> 1258.6297 | YC25: 1184 | YD25: =YD19/YD22 -> 1324.9277 | YE25: =YE19/YE22 -> 1058.3171 | YF25: =YF19/YF22 -> 1268.6135 | YG25: =YG19/YG22 -> 1301.4402 | YH25: =YH19/YH22 -> 1172.9486 | YI25: =YI19/YI22 -> 1155.5269 | YJ25: =YJ19/YJ22 -> 1246.1774 | YK25: =YK19/YK22 -> 1177.5472 | ... YM25: =YM19/YM22 -> 1024.7708
B27: Total Outstanding Balance - Purchase Balance | C27: 6856615.4 | D27: 6968637.5 | E27: 7054135.2 | F27: 6942359.8 | G27: 6756230.7 | H27: 6597207.4 | I27: 6470978.4 | J27: 6076780.9 | K27: 6109304.6 | L27: 6228747.3 | M27: 6556329.1 | N27: 6709521.7 | O27: 6938883.1 | P27: 6843594.9 | Q27: 6411031.8 | R27: 6279936.6 | S27: 6518327.3 | T27: 6577508.2 | U27: 7334156.4 | V27: 7404342.2 | W27: 7461960.4 | X27: 7297561.1 | Y27: 7423216.5 | Z27: 7318683.8 | AA27: 7692878.4 | AB27: 7923143.9 | AC27: 8136723.2 | AD27: 8068252.6 | AE27: 7785460.1 | AF27: 7821038 | AG27: 7536921.6 | AH27: 6950112.8 | AI27: 7382156.8 | AJ27: 7448045.2 | AK27: 7371787.7 | AL27: 6963550 | AM27: 7436007.7 | AN27: 7279338.4 | AO27: 7048624.2 | AP27: 7321935.5 | AQ27: 7818395.8 | AR27: 6870651.4 | AS27: 7107971.8 | AT27: 7300803 | AU27: 7319771.5 | AV27: 6693149.6 | AW27: 7199022.4 | AX27: 7458406.4 | AY27: 7800279.3 | AZ27: 7478023.8 | BA27: 7476973.7 | BB27: 7534941.5 | BC27: 7371769.2 | BD27: 7693994.9 | BE27: 8003536.5 | BF27: 7968789.1 | BG27: 8032198.6 | BH27: 8027869 | BI27: 8266373.5 | BJ27: 8447650.3 | BK27: 8657534.1 | BL27: 9271381.9 | BM27: 9435802.8 | BN27: 9545371.7 | BO27: 9758150.9 | BP27: 10002942 | BQ27: 10509055 | BR27: 10765730 | BS27: 11052998 | BT27: 11429829 | BU27: 11452305 | BV27: 10996279 | BW27: 10655486 | BX27: 10697931 | BY27: 11204387 | BZ27: 10998873 | CA27: 11397619 | CB27: 11217580 | CC27: 11328568 | CD27: 11239782 | CE27: 11435863 | CF27: 11729446 | CG27: 11630147 | CH27: 11769281 | CI27: 11848432 | CJ27: 12106020 | CK27: 12238616 | CL27: 11902461 | CM27: 12309787 | CN27: 12309943 | CO27: 12307397 | CP27: 11971449 | CQ27: 12371021 | CR27: 12192255 | CS27: 12276705 | CT27: 12506451 | CU27: 13181929 | CV27: 13448986 | CW27: 13818666 | CX27: 13840130 | CY27: 13129361 | CZ27: 13512335 | DA27: 14001432 | DB27: 14430348 | DC27: 13924754 | DD27: 14277629 | DE27: 13683897 | DF27: 13324116 | DG27: 14388576 | DH27: 14652216 | DI27: 14363032 | DJ27: 14637799 | DK27: 14986496 | DL27: 14455900 | DM27: 14648234 | DN27: 14891032 | DO27: 15042810 | DP27: 14687864 | DQ27: 14498586 | DR27: 14273935 | DS27: 13893825 | DT27: 13860637 | DU27: 14212030 | DV27: 14545941 | DW27: 14840150 | DX27: 14902732 | DY27: 15117758 | DZ27: 15351292 | EA27: 15442646 | EB27: 15415418 | EC27: 16344417 | ED27: 16646472 | EE27: 16928407 | EF27: 16557587 | EG27: 15789512 | EH27: 15265544 | EI27: 15542774 | EJ27: 15831307 | EK27: 16178054 | EL27: 16342527 | EM27: 16454991 | EN27: 16281006 | EO27: 16405963 | EP27: 16260311 | EQ27: 16987513 | ER27: 17635545 | ES27: 17740934 | ET27: 17219229 | EU27: 16865672 | EV27: 16613989 | EW27: 16971800 | EX27: 16888509 | EY27: 16699574 | EZ27: 16867620 | FA27: 17145313 | FB27: 17544463 | FC27: 17456716 | FD27: 18326332 | FE27: 18993812 | FF27: 19692310 | FG27: 19906214 | FH27: 20104090 | FI27: 20158861 | FJ27: 19920299 | FK27: 20273962 | FL27: 20667504 | FM27: 21123112 | FN27: 21335483 | FO27: 20996196 | FP27: 21358896 | FQ27: 21136279 | FR27: 21860210 | FS27: 21634779 | FT27: 22745652 | FU27: 22727507 | FV27: 23439410 | FW27: 23931782 | FX27: 24139538 | FY27: 24159332 | FZ27: 24358939 | GA27: 24868851 | GB27: 23948320 | GC27: 22089799 | GD27: 22434176 | GE27: 21970604 | GF27: 22970575 | GG27: 23414768 | GH27: 23922238 | GI27: 24213480 | GJ27: 24931422 | GK27: 25099256 | GL27: 24834154 | GM27: 25106338 | GN27: 25492935 | GO27: 24712935 | GP27: 24581279 | GQ27: 25195498 | GR27: 24851685 | GS27: 21929901 | GT27: 23480239 | GU27: 23952982 | GV27: 24953078 | GW27: 24955539 | GX27: 25564312 | GY27: 24953078 | GZ27: 26350121 | HA27: 27257529 | HB27: 27772355 | HC27: 28567855 | HD27: 28051826 | HE27: 27627661 | HF27: 27338345 | HG27: 26759739 | HH27: 26741657 | HI27: 27469355 | HJ27: 27728654 | HK27: 28551393 | HL27: 28925529 | HM27: 28680655 | HN27: 27890594 | HO27: 29228260 | HP27: 29556189 | HQ27: 30410863 | HR27: 31087789 | HS27: 31459694 | HT27: 31647001 | HU27: 30764145 | HV27: 31141086 | HW27: 31414317 | HX27: 31143156 | HY27: 29415784 | HZ27: 30479186 | IA27: 30672707 | IB27: 30009238 | IC27: 29439586 | ID27: 31419446 | IE27: 32332175 | IF27: 32638889 | IG27: 32776144 | IH27: 33125153 | II27: 33131499 | IJ27: 32652519 | IK27: 33412005 | IL27: 33453625 | IM27: 34339670 | IN27: 35082617 | IO27: 35811844 | IP27: 35812986 | IQ27: 36477705 | IR27: 36189456 | IS27: 37868575 | IT27: 38774576 | IU27: 39151982 | IV27: 39632456 | IW27: 38904662 | IX27: 39311332 | IY27: 39783798 | IZ27: 40429573 | JA27: 41204802 | JB27: 39328220 | JC27: 39650485 | JD27: 40896906 | JE27: 41613371 | JF27: 42205332 | JG27: 43460992 | JH27: 43490153 | JI27: 43659113 | JJ27: 43914465 | JK27: 44077082 | JL27: 45198290 | JM27: 45504795 | JN27: 46542116 | JO27: 45715372 | JP27: 44135180 | JQ27: 43136002 | JR27: 43587134 | JS27: 44045667 | JT27: 44299464 | JU27: 45725265 | JV27: 45512574 | JW27: 45970832 | JX27: 46830164 | JY27: 46800026 | JZ27: 47224330 | KA27: 48428438 | KB27: 49634892 | KC27: 48966579 | KD27: 47469753 | KE27: 47573205 | KF27: 46885846 | KG27: 45396717 | KH27: 46314720 | KI27: 47043197 | KJ27: 47889234 | KK27: 47666971 | KL27: 48221962 | KM27: 47762532 | KN27: 48505055 | KO27: 48872578 | KP27: 49990857 | KQ27: 50299314 | KR27: 50518499 | KS27: 49508274 | KT27: 48254789 | KU27: 49283876 | KV27: 48161337 | KW27: 49163221 | KX27: 50567165 | KY27: 50695718 | KZ27: 50967984 | LA27: 49752093 | LB27: 50979486 | LC27: 51962061 | LD27: 53164833 | LE27: 52433377 | LF27: 52787355 | LG27: 53037707 | LH27: 52271569 | LI27: 51984713 | LJ27: 51485284 | LK27: 51655992 | LL27: 50102201 | LM27: 49885730 | LN27: 50517856 | LO27: 50572571 | LP27: 50869274 | LQ27: 51424326 | LR27: 53169861 | LS27: 53394425 | LT27: 53771362 | LU27: 54013803 | LV27: 52802550 | LW27: 53117269 | LX27: 53453371 | LY27: 52825558 | LZ27: 51524872 | MA27: 53344936 | MB27: 53798668 | MC27: 53574998 | MD27: 53192982 | ME27: 54785383 | MF27: 57095253 | MG27: 58070299 | MH27: 58352314 | MI27: 58554327 | MJ27: 57495261 | MK27: 57906815 | ML27: 58351759 | MM27: 58887891 | MN27: 58926962 | MO27: 58340094 | MP27: 55763513 | MQ27: 55553391 | MR27: 55771202 | MS27: 55761043 | MT27: 57339215 | MU27: 56914288 | MV27: 58300153 | MW27: 59489634 | MX27: 58919338 | MY27: 59528628 | MZ27: 59932896 | NA27: 59407889 | NB27: 58906374 | NC27: 62581043 | ND27: 62479413 | NE27: 59516738 | NF27: 59730559 | NG27: 59986490 | NH27: 61216347 | NI27: 61074628 | NJ27: 60394292 | NK27: 60747148 | NL27: 60621194 | NM27: 61361057 | NN27: 61675370 | NO27: 61899193 | NP27: 61728847 | NQ27: 60566351 | NR27: 58655480 | NS27: 57715663 | NT27: 56768452 | NU27: 55087166 | NV27: 56448711 | NW27: 57520344 | NX27: 58184632 | NY27: 59359428 | NZ27: 58737591 | OA27: 60060981 | OB27: 60515622 | OC27: 60701893 | OD27: 61031268 | OE27: 61460878 | OF27: 60759238 | OG27: 59375627 | OH27: 59169325 | OI27: 57194020 | OJ27: 55257970 | OK27: 57935865 | OL27: 59026176 | OM27: 60154909 | ON27: 60262282 | OO27: 61478675 | OP27: 62100327 | OQ27: 63372712 | OR27: 63346010 | OS27: 62764859 | OT27: 59588494 | OU27: 57869478 | OV27: 56078893 | OW27: 56949457 | OX27: 57488669 | OY27: 57845021 | OZ27: 54841408 | PA27: 56275988 | PB27: 56462093 | PC27: 57300604 | PD27: 57847790 | PE27: 60092666 | PF27: 60446692 | PG27: 61019699 | PH27: 60727999 | PI27: 59877042 | PJ27: 59980559 | PK27: 58535493 | PL27: 58562166 | PM27: 60364646 | PN27: 62096704 | PO27: 61783462 | PP27: 62569496 | PQ27: 63759103 | PR27: 64710931 | PS27: 67496777 | PT27: 66747120 | PU27: 67821889 | PV27: 66299573 | PW27: 64390735 | PX27: 65461537 | PY27: 66289763 | PZ27: 67041810 | QA27: 66693344 | QB27: 64701980 | QC27: 65836294 | QD27: 65067821 | QE27: 68951009 | QF27: 70399626 | QG27: 73233048 | QH27: 74317201 | QI27: 75208444 | QJ27: 75915518 | QK27: 75644610 | QL27: 76114358 | QM27: 76762185 | QN27: 77363036 | QO27: 76890495 | QP27: 75603037 | QQ27: 72467155 | QR27: 71939975 | QS27: 77266389 | QT27: 78774405 | QU27: 81418236 | QV27: 83378384 | QW27: 84021556 | QX27: 85828101 | QY27: 85584081 | QZ27: 87747707 | RA27: 88237149 | RB27: 89026036 | RC27: 88168259 | RD27: 88446330 | RE27: 85957782 | RF27: 84417248 | RG27: 81313104 | RH27: 82231429 | RI27: 85453171 | RJ27: 87001421 | RK27: 88644972 | RL27: 89722855 | RM27: 90006512 | RN27: 91362861 | RO27: 92095286 | RP27: 95038391 | RQ27: 94790469 | RR27: 94126192 | RS27: 92395050 | RT27: 89038197 | RU27: 86916358 | RV27: 87679774 | RW27: 90016400 | RX27: 91231700 | RY27: 91981781 | RZ27: 93496471 | SA27: 92361498 | SB27: 93856409 | SC27: 94488646 | SD27: 95070754 | SE27: 97584110 | SF27: 97635811 | SG27: 96896531 | SH27: 94981615 | SI27: 93146703 | SJ27: 91671646 | SK27: 88689290 | SL27: 89838789 | SM27: 91440810 | SN27: 92704210 | SO27: 93172969 | SP27: 93163827 | SQ27: 95182765 | SR27: 98558523 | SS27: 99742067 | ST27: 1.0119728e+08 | SU27: 1.0100086e+08 | SV27: 98276652 | SW27: 99176196 | SX27: 98705222 | SY27: 99356621 | SZ27: 96450486 | TA27: 97676505 | TB27: 1.0021074e+08 | TC27: 1.0089783e+08 | TD27: 1.0397363e+08 | TE27: 1.0636094e+08 | TF27: 1.1097477e+08 | TG27: 1.1297206e+08 | TH27: 1.1359553e+08 | TI27: 1.1283832e+08 | TJ27: 1.116971e+08 | TK27: 1.1466235e+08 | TL27: 1.1536783e+08 | TM27: 1.1812113e+08 | TN27: 1.1656612e+08 | TO27: 1.1648686e+08 | TP27: 1.1214168e+08 | TQ27: 1.1013269e+08 | TR27: 1.156129e+08 | TS27: 1.1706165e+08 | TT27: 121409387 | TU27: 1.2204784e+08 | TV27: 1.2368382e+08 | TW27: 1.2454708e+08 | TX27: 1.2523292e+08 | TY27: 1.265611e+08 | TZ27: 1.2715222e+08 | UA27: 1.2924286e+08 | UB27: 1.2690536e+08 | UC27: 1.2487808e+08 | UD27: 1.2061442e+08 | UE27: 1.2012504e+08 | UF27: 1.2303067e+08 | UG27: 1.2480984e+08 | UH27: 1.2878763e+08 | UI27: 1.3164182e+08 | UJ27: 1.3361174e+08 | UK27: 1.3552193e+08 | UL27: 1.3595463e+08 | UM27: 1.36893e+08 | UN27: 1.3753038e+08 | UO27: 1.3738126e+08 | UP27: 1.3889437e+08 | UQ27: 1.3560115e+08 | UR27: 1.3299604e+08 | US27: 1.2978163e+08 | UT27: 1.2637185e+08 | UU27: 1.2800597e+08 | UV27: 1.3149836e+08 | UW27: 1.3359747e+08 | UX27: 1.3533057e+08 | UY27: 1.3685572e+08 | UZ27: 1.3666847e+08 | VA27: 1.3820082e+08 | VB27: 1.3880699e+08 | VC27: 1.4175e+08 | VD27: 1.4245883e+08 | VE27: 1.4151596e+08 | VF27: 1.4151596e+08 | VG27: 1.3801409e+08 | VH27: 135674397 | VI27: 1.3605562e+08 | VJ27: 1.3293676e+08 | VK27: 1.362126e+08 | VL27: 1.3716361e+08 | VM27: 1.3863428e+08 | VN27: 1.3997402e+08 | VO27: 1.4043143e+08 | VP27: 1.4248011e+08 | VQ27: 1.4400797e+08 | VR27: 1.4393106e+08 | VS27: 1.4747012e+08 | VT27: 1.4797621e+08 | VU27: 1.4743178e+08 | VV27: 1.4546848e+08 | VW27: 1.463208e+08 | VX27: 1.458907e+08 | VY27: 1.4685387e+08 | VZ27: 1.3942447e+08 | WA27: 1.3993623e+08 | WB27: 1.4107313e+08 | WC27: 1.4145112e+08 | WD27: 1.4661447e+08 | WE27: 1.4939345e+08 | WF27: 1.5279453e+08 | WG27: 1.548068e+08 | WH27: 1.5652115e+08 | WI27: 1.5655878e+08 | WJ27: 1.5691328e+08 | WK27: 1.5421943e+08 | WL27: 1.561403e+08 | WM27: 1.5948172e+08 | WN27: 1.6060467e+08 | WO27: 1.5648903e+08 | WP27: 1.5770164e+08 | WQ27: 1.5727002e+08 | WR27: 1.57931e+08 | WS27: 1.6333466e+08 | WT27: 1.6824741e+08 | WU27: 1.7120457e+08 | WV27: 1.7488926e+08 | WW27: 1.7606179e+08 | WX27: 1.7564333e+08 | WY27: 1.7855682e+08 | WZ27: 1.7973101e+08 | XA27: 1.7914601e+08 | XB27: 1.8547767e+08 | XC27: 1.803733e+08 | XD27: 1.7838842e+08 | XE27: 1.7062929e+08 | XF27: 1.7411094e+08 | XG27: 1.7629303e+08 | XH27: 1.789455e+08 | XI27: 1.8410745e+08 | XJ27: 1.8666816e+08 | XK27: 1.876497e+08 | XL27: 1.8961964e+08 | XM27: 1.9324835e+08 | XN27: 1.9473708e+08 | XO27: 1.9936454e+08 | XP27: 2.0080173e+08 | XQ27: 1.9912358e+08 | XR27: 2.0237892e+08 | XS27: 1.9450174e+08 | XT27: 1.9714747e+08 | XU27: 1.9851318e+08 | XV27: 2.0428483e+08 | XW27: 2.0532124e+08 | XX27: 2.0676238e+08 | XY27: 2.0961807e+08 | XZ27: 2.1011485e+08 | YA27: 2.0950884e+08 | YB27: 2.1408997e+08 | YC27: 217772616 | YD27: 2.1844163e+08 | YE27: 2.1698529e+08 | YF27: 2.1941572e+08 | YG27: 2.1239307e+08 | YH27: 2.1176856e+08 | YI27: 2.0323545e+08 | YJ27: 2.0460993e+08 | YK27: 2.1053021e+08 | YL27: 2.1142074e+08 | YM27: 2.1347301e+08
B28: Total Remaining Principal Balance - Installments | RZ28: 17776592 | SA28: 17776592 | SB28: 18198183 | SC28: 18330601 | SD28: 18575262 | SE28: 18745085 | SF28: 19144498 | SG28: 19477654 | SH28: 19805179 | SI28: 17878447 | SJ28: 18092790 | SK28: 18344847 | SL28: 18762402 | SM28: 19082690 | SN28: 19326333 | SO28: 19633171 | SP28: 19850570 | SQ28: 20112676 | SR28: 20389558 | SS28: 20735479 | ST28: 21231300 | SU28: 21634501 | SV28: 22216650 | SW28: 23078719 | SX28: 23331301 | SY28: 23789930 | SZ28: 20095078 | TA28: 20349494 | TB28: 20762618 | TC28: 21017077 | TD28: 21292747 | TE28: 21509274 | TF28: 21669165 | TG28: 22248608 | TH28: 22388162 | TI28: 23039402 | TJ28: 23447494 | TK28: 23878002 | TL28: 24176128 | TM28: 24579265 | TN28: 22012351 | TO28: 22195128 | TP28: 22576662 | TQ28: 22903382 | TR28: 23105045 | TS28: 23351273 | TT28: 23654174 | TU28: 23971933 | TV28: 24315429 | TW28: 24560584 | TX28: 25033088 | TY28: 25394511 | TZ28: 25620018 | UA28: 26227716 | UB28: 26476445 | UC28: 27231643 | UD28: 22926297 | UE28: 23348197 | UF28: 23543094 | UG28: 23713696 | UH28: 23883704 | UI28: 24159879 | UJ28: 24470424 | UK28: 24748762 | UL28: 25242016 | UM28: 25556399 | UN28: 25986278 | UO28: 26317076 | UP28: 26628402 | UQ28: 23602335 | UR28: 23751743 | US28: 23825985 | UT28: 24010868 | UU28: 24263546 | UV28: 24415415 | UW28: 24637196 | UX28: 24943186 | UY28: 25189599 | UZ28: 25451741 | VA28: 25611748 | VB28: 25965608 | VC28: 26211574 | VD28: 26573055 | VE28: 27178537 | VF28: 27178537 | VG28: 27717531 | VH28: 28153017 | VI28: 23540960 | VJ28: 23925146 | VK28: 24114071 | VL28: 24252784 | VM28: 24518715 | VN28: 24679745 | VO28: 24936198 | VP28: 25049762 | VQ28: 25240943 | VR28: 25529964 | VS28: 25812152 | VT28: 26399337 | VU28: 26643060 | VV28: 27089269 | VW28: 23939770 | VX28: 24206361 | VZ28: 24719888 | WA28: 24897869 | WB28: 25331338 | WC28: 25426819 | WD28: 25624126 | WE28: 25859127 | WF28: 26292716 | WG28: 26537362 | WH28: 27048380 | WI28: 27394058 | WJ28: 28011099 | WK28: 28611945 | WL28: 29054739 | WM28: 29941463 | WN28: 25226763 | WO28: 25455583 | WP28: 25789407 | WQ28: 26052825 | WR28: 26483258 | WS28: 26723966 | WT28: 27147065 | WU28: 27599391 | WV28: 27693045 | WW28: 28139245 | WX28: 28675959 | WY28: 29038001 | WZ28: 29524210 | XA28: 30001456 | XB28: 26948729 | XC28: 27258793 | XD28: 27809210 | XE28: 28102972 | XF28: 28247504 | XG28: 28441023 | XH28: 28733715 | XI28: 29180532 | XJ28: 29655901 | XK28: 30180255 | XL28: 30395378 | XM28: 30725866 | XN28: 31049144 | XO28: 31859570 | XP28: 32676160 | XQ28: 33771552 | XR28: 28664907 | XS28: 28949848 | XT28: 29218051 | XU28: 29548139 | XV28: 30015641 | XW28: 30674697 | XX28: 31055653 | XY28: 31428808 | XZ28: 31688720 | YA28: 31978479 | YB28: 32495226 | YC28: 33475750 | YD28: 34087350 | YE28: 34917770 | YF28: 30945131 | YG28: 31233897 | YH28: 31452110 | YI28: 32000028 | YJ28: 32479516 | YK28: 33005372 | YL28: 33358392 | YM28: 33754081
B29: Total Outstanding Balance (PHP) | OH29: =SUM(OH27:OH28) -> 59169325 | OI29: =SUM(OI27:OI28) -> 57194020 | OJ29: =SUM(OJ27:OJ28) -> 55257970 | OK29: =SUM(OK27:OK28) -> 57935865 | OL29: =SUM(OL27:OL28) -> 59026176 | OM29: =SUM(OM27:OM28) -> 60154909 | ON29: =SUM(ON27:ON28) -> 60262282 | OO29: =SUM(OO27:OO28) -> 61478675 | ... RS29: =SUM(RS27:RS28) -> 92395050 | RZ29: =SUM(RZ27:RZ28) -> 1.1127306e+08 | SA29: =SUM(SA27:SA28) -> 1.1013809e+08 | SB29: =SUM(SB27:SB28) -> 1.1205459e+08 | SC29: =SUM(SC27:SC28) -> 1.1281925e+08 | SD29: =SUM(SD27:SD28) -> 1.1364602e+08 | SE29: =SUM(SE27:SE28) -> 1.1632919e+08 | SF29: =SUM(SF27:SF28) -> 1.1678031e+08 | SG29: =SUM(SG27:SG28) -> 1.1637418e+08 | ... WH29: =SUM(WH27:WH28) -> 1.8356953e+08 | WI29: 1.5655878e+08 | WJ29: =SUM(WJ27:WJ28) -> 1.8492438e+08 | WK29: =SUM(WK27:WK28) -> 1.8283137e+08 | WL29: =SUM(WL27:WL28) -> 1.8519504e+08 | WM29: =SUM(WM27:WM28) -> 1.8942319e+08 | WN29: =SUM(WN27:WN28) -> 1.8583144e+08 | WO29: =SUM(WO27:WO28) -> 1.8194462e+08 | WP29: 183491049 | WQ29: =SUM(WQ27:WQ28) -> 1.8332285e+08 | WR29: =SUM(WR27:WR28) -> 1.8441426e+08 | WS29: =SUM(WS27:WS28) -> 1.9005862e+08 | WT29: =SUM(WT27:WT28) -> 1.9539447e+08 | WU29: =SUM(WU27:WU28) -> 1.9880396e+08 | WV29: =SUM(WV27:WV28) -> 2.025823e+08 | WW29: =SUM(WW27:WW28) -> 2.0420103e+08 | WX29: =SUM(WX27:WX28) -> 2.0431929e+08 | ... YB29: =SUM(YB27:YB28) -> 2.4658519e+08 | YC29: 251248366 | YD29: =SUM(YD27:YD28) -> 2.5252898e+08 | YE29: =SUM(YE27:YE28) -> 2.5190306e+08 | YF29: =SUM(YF27:YF28) -> 2.5036085e+08 | YG29: =SUM(YG27:YG28) -> 2.4362697e+08 | YH29: =SUM(YH27:YH28) -> 2.4322067e+08 | YI29: =SUM(YI27:YI28) -> 2.3523547e+08 | YJ29: =SUM(YJ27:YJ28) -> 2.3708945e+08 | YK29: =SUM(YK27:YK28) -> 2.4353558e+08 | ... YM29: =SUM(YM27:YM28) -> 2.4722709e+08
B30: Total Outstanding Balance (USD) | SJ30: =SJ27/SJ3 -> 1527860.8 | SK30: =SK27/SK3 -> 1478154.8 | SL30: =SL27/SL3 -> 1497313.1 | SM30: =SM27/SM3 -> 1524013.5 | SN30: =SN27/SN3 -> 1545070.2 | SO30: =SO27/SO3 -> 1552882.8 | SP30: =SP27/SP3 -> 1552730.4 | SQ30: =SQ27/SQ3 -> 1586379.4 | ... SW30: =SW27/SW3 -> 1652936.6 | SX30: =SX29/SX3 -> 2033942 | SY30: =SY29/SY3 -> 2206927.4 | SZ30: =SZ29/SZ3 -> 2088630.2 | TA30: =TA29/TA3 -> 2115161.3 | TB30: =TB29/TB3 -> 2167981.3 | TC30: =TC29/TC3 -> 2184855 | TD30: =TD29/TD3 -> 2244917.1 | TE30: =TE29/TE3 -> 2291580.8 | ... WH30: =WH29/WH3 -> 3289776.4 | WI30: 2805712.9 | WJ30: =WJ29/WJ3 -> 3314056.9 | WK30: =WK29/WK3 -> 3276547.9 | WL30: =WL29/WL3 -> 3318907.5 | WM30: =WM29/WM3 -> 3394680.8 | WN30: =WN29/WN3 -> 3330312.5 | WO30: =WO29/WO3 -> 3260656.2 | WP30: 3288370.1 | WQ30: =WQ29/WQ3 -> 3285355.7 | WR30: =WR29/WR3 -> 3304915 | WS30: =WS29/WS3 -> 3406068.5 | WT30: =WT29/WT3 -> 3501693.1 | WU30: =WU29/WU3 -> 3562795 | WV30: =WV29/WV3 -> 3630507.2 | WW30: =WW29/WW3 -> 3659516.7 | WX30: =WX29/WX3 -> 3661636.1 | ... YM30: =YM29/YM3 -> 4430592.9
B33: Zed_Card_NNB - Zed Card - Zed Philippines NN (Installment Conversion)
B34: Transaction Amount | OT34: 1068311.2 | OU34: 457759.97 | OV34: 339322.13 | OW34: 213326.29 | OX34: 335975.56 | OY34: 269388.8 | OZ34: 367339.62 | PA34: 266494.5 | PB34: 338282.62 | PC34: 147724.89 | PD34: 403294.96 | PE34: 281981.55 | PF34: 394547.06 | PG34: 156755.9 | PH34: 637458.22 | PI34: 258335.5 | PJ34: 152024.53 | PK34: 170037.94 | PL34: 221288.28 | PM34: 577505.11 | PN34: 321025.19 | PO34: 302276.84 | PP34: 19059 | PQ34: 225418.61 | PR34: 222040.2 | PS34: 254192.4 | PT34: 327932.93 | PU34: 425872.6 | PV34: 534035.42 | PW34: 151498.83 | PX34: 82565.79 | PY34: 210652.08 | PZ34: 140721.78 | QA34: 361329.58 | QB34: 228391.34 | QC34: 396651.95 | QD34: 64995.65 | QE34: 252718.95 | QF34: 247552.48 | QG34: 244191.98 | QH34: 336743.38 | QI34: 510567.02 | QJ34: 446316.3 | QK34: 425020.65 | QL34: 198354.84 | QM34: 409427.27 | QN34: 543179.64 | QO34: 563275.02 | QP34: 149519.96 | QQ34: 146397.18 | QR34: 129807.43 | QS34: 318157.57 | QT34: 315122.84 | QU34: 347369.39 | QV34: 402624.42 | QW34: 404753.83 | QX34: 392592.43 | QY34: 320679.76 | QZ34: 172808.35 | RA34: 311472.73 | RB34: 261618.93 | RC34: 372146.1 | RD34: 250474.56 | RE34: 286004.56 | RF34: 262663.98 | RG34: 466377.24 | RH34: 181222.8 | RI34: 239738.78 | RJ34: 451024.11 | RK34: 384774.12 | RL34: 373236.59 | RM34: 398672.9 | RN34: 218570.04 | RO34: 232537.5 | RP34: 410680.06 | RQ34: 939267.33 | RR34: 227967.94 | RS34: 483017.77 | RT34: 152620.91 | RU34: 323175.25 | RV34: 187116.48 | RW34: 291324.58 | RX34: 304844 | RY34: 212340.31 | RZ34: 234906.58 | SA34: 423390.56 | SB34: 144176.51 | SC34: 244661.21 | SD34: 199848.87 | SE34: 488395.52 | SF34: 343157.12 | SG34: 387134.68 | SH34: 185531.59 | SI34: 192861.18 | SJ34: 275567.35 | SK34: 417554.03 | SL34: 330660.39 | SM34: 243643.18 | SN34: 306838.03 | SO34: 226200.01 | SP34: 262106.06 | SQ34: 276881.84 | SR34: 380265.9 | SS34: 477623.14 | ST34: 430274.77 | SU34: 619123.66 | SV34: 903267.63 | SW34: 411154.67 | SX34: 479297.03 | SY34: 199943.32 | SZ34: 247159.04 | TA34: 428254.36 | TB34: 254459.35 | TC34: 284870.52 | TD34: 237843.24 | TE34: 175654.4 | TF34: 584277.72 | TG34: 368415.27 | TH34: 659572.78 | TI34: 425384.98 | TJ34: 448205.25 | TK34: 323263.04 | TL34: 438876.08 | TM34: 221242.08 | TN34: 184680.63 | TO34: 367653.18 | TP34: 325373.67 | TQ34: 228816.44 | TR34: 261589.84 | TS34: 308997.08 | TT34: 327839 | TU34: 347535.75 | TV34: 297835.99 | TW34: 600823.8 | TX34: 413275.75 | TY34: 225506.69 | TZ34: 622298.33 | UA34: 254825.15 | UB34: 759960.48 | UC34: 164358.82 | UD34: 428274.41 | UE34: 201436.87 | UF34: 196977.69 | UG34: 170007.47 | UH34: 291863.5 | UI34: 341907.42 | UJ34: 278338.41 | UK34: 375486.37 | UL34: 267055.64 | UM34: 347620.4 | UN34: 426453.75 | UO34: 330798.14 | UP34: 328320.98 | UQ34: 139072.93 | UR34: 149407.39 | US34: 129089.7 | UT34: 312351.83 | UU34: 140471.18 | UV34: 175487.6 | UW34: 227834.21 | UX34: 321911.13 | UY34: 240587.45 | UZ34: 261928.88 | VA34: 257896.42 | VB34: 345325.08 | VC34: 234024.81 | VD34: 396171.82 | VE34: 603202.93 | VF34: 603202.93 | VG34: 560868.18 | VH34: 429003.96 | VI34: 172395.04 | VJ34: 384809.77 | VK34: 178356 | VL34: 174293.47 | VM34: 238884.36 | VN34: 154795.37 | VO34: 264944.49 | VP34: 119958.37 | VQ34: 349622.92 | VR34: 303816.94 | VS34: 376056.84 | VT34: 549440.46 | VU34: 249722.39 | VV34: 456573.25 | VW34: 160374.41 | VX34: 257516.43 | VY34: 165347.24 | VZ34: 363636.98 | WA34: 194973.86 | WB34: 422176.05 | WC34: 162929.24 | WD34: 138987.45 | WE34: 241066.79 | WF34: 442540.51 | WG34: 426252.13 | WH34: 533935.99 | WI34: 354161.01 | WJ34: 601420.2 | WK34: 607743.14 | WL34: 536752.75 | WM34: 984710.06 | WN34: 256956.44 | WO34: 261991.35 | WP34: 383828.92 | WQ34: 215443.41 | WR34: 433803.79 | WS34: 248031.75 | WT34: 426080.85 | WU34: 467194.51 | WV34: 328887.16 | WW34: 462143.57 | WX34: 529195.65 | WY34: 386524.47 | WZ34: 455909.19 | XA34: 487747.5 | XB34: 369144.38 | XC34: 341706.62 | XD34: 567730.45 | XE34: 338786.13 | XF34: 134774.79 | XG34: 207830.56 | XH34: 294738.36 | XI34: 482312.42 | XJ34: 421903.21 | XK34: 631523.46 | XL34: 493076.81 | XM34: 393845.5 | XN34: 307673.27 | XO34: 832589.15 | XP34: 861931.67 | XQ34: 1081610.4 | XR34: 187419.07 | XS34: 382661.91 | XT34: 248561.47 | XU34: 347883.19 | XV34: 457562.76 | XW34: 732418.07 | XX34: 411477.58 | XY34: 400113.65 | XZ34: 415562.43 | YA34: 254557.07 | YB34: 560287.84 | YC34: 953608 | YD34: 659844.86 | YE34: 821526.17 | YF34: 306077.01 | YG34: 282789.19 | YH34: 228801.98 | YI34: 544810.02 | YJ34: 514253.89 | YK34: 510173.74 | YL34: 350220.87 | YM34: 390536.62
B35: Transaction Count | OT35: 89 | OU35: 39 | OV35: 26 | OW35: 18 | OX35: 23 | OY35: 24 | OZ35: 31 | PA35: =COUNT(OO35:OQ58) -> 39 | PB35: 30 | PC35: 12 | PD35: 26 | PE35: 22 | PF35: 40 | PG35: 17 | PH35: 60 | PI35: 23 | PJ35: 17 | PK35: 16 | PL35: 20 | PM35: 43 | PN35: 23 | PO35: 26 | PP35: 3 | PQ35: 22 | PR35: 22 | PS35: 20 | PT35: 31 | PU35: 34 | PV35: 41 | PW35: 19 | PX35: 10 | PY35: 17 | PZ35: 15 | QA35: 33 | QB35: 25 | QC35: 21 | QD35: 5 | QE35: 25 | QF35: 20 | QG35: 22 | QH35: 29 | QI35: 31 | QJ35: 35 | QK35: 41 | QL35: 19 | QM35: 39 | QN35: 51 | QO35: 48 | QP35: 17 | QQ35: 15 | QR35: 6 | QS35: 20 | QT35: 32 | QU35: 27 | QV35: 38 | QW35: 33 | QX35: 28 | QY35: 29 | QZ35: 16 | RA35: 34 | RB35: 21 | RC35: 36 | RD35: 24 | RE35: 22 | RF35: 24 | RG35: 33 | RH35: 16 | RI35: 21 | RJ35: 47 | RK35: 34 | RL35: 30 | RM35: 37 | RN35: 22 | RO35: 24 | RP35: 37 | RQ35: 67 | RR35: 21 | RS35: 42 | RT35: 15 | RU35: 18 | RV35: 14 | RW35: 20 | RX35: 31 | RY35: 27 | RZ35: 17 | SA35: 27 | SB35: 12 | SC35: 20 | SD35: 19 | SE35: 41 | SF35: 39 | SG35: 41 | SH35: 17 | SI35: 16 | SJ35: 26 | SK35: 30 | SL35: 24 | SM35: 28 | SN35: 30 | SO35: 19 | SP35: 22 | SQ35: 22 | SR35: 27 | SS35: 40 | ST35: 35 | SU35: 37 | SV35: 79 | SW35: 37 | SX35: 41 | SY35: 20 | SZ35: 25 | TA35: 37 | TB35: 22 | TC35: 20 | TD35: 18 | TE35: 19 | TF35: 34 | TG35: 40 | TH35: 38 | TI35: 36 | TJ35: 44 | TK35: 28 | TL35: 41 | TM35: 20 | TN35: 18 | TO35: 25 | TP35: 24 | TQ35: 21 | TR35: 16 | TS35: 15 | TT35: 28 | TU35: 33 | TV35: 23 | TW35: 51 | TX35: 30 | TY35: 22 | TZ35: 51 | UA35: 28 | UB35: 57 | UC35: 16 | UD35: 27 | UE35: 11 | UF35: 19 | UG35: 13 | UH35: 28 | UI35: 23 | UJ35: 24 | UK35: 29 | UL35: 19 | UM35: 23 | UN35: 32 | UO35: 24 | UP35: 31 | UQ35: 11 | UR35: 17 | US35: 12 | UT35: 19 | UU35: 11 | UV35: 14 | UW35: 23 | UX35: 32 | UY35: 20 | UZ35: 15 | VA35: 20 | VB35: 30 | VC35: 22 | VD35: 33 | VE35: 38 | VF35: 38 | VG35: 47 | VH35: 40 | VI35: 16 | VJ35: 28 | VK35: 12 | VL35: 15 | VM35: 24 | VN35: 14 | VO35: 14 | VP35: 12 | VQ35: 22 | VR35: 25 | VS35: 40 | VT35: 43 | VU35: 24 | VV35: 39 | VW35: 13 | VX35: 14 | VY35: 14 | VZ35: 25 | WA35: 15 | WB35: 35 | WC35: 13 | WD35: 14 | WE35: 22 | WF35: 33 | WG35: 31 | WH35: 40 | WI35: 38 | WJ35: 44 | WK35: 44 | WL35: 41 | WM35: 74 | WN35: 23 | WO35: 21 | WP35: 28 | WQ35: 19 | WR35: 30 | WS35: 19 | WT35: 33 | WU35: 38 | WV35: 24 | WW35: 28 | WX35: 50 | WY35: 34 | WZ35: 36 | XA35: 45 | XB35: 29 | XC35: 27 | XD35: 39 | XE35: 40 | XF35: 13 | XG35: 21 | XH35: 25 | XI35: 39 | XJ35: 37 | XK35: 50 | XL35: 37 | XM35: 32 | XN35: 29 | XO35: 67 | XP35: 68 | XQ35: 68 | XR35: 21 | XS35: 31 | XT35: 23 | XU35: 24 | XV35: 44 | XW35: 59 | XX35: 33 | XY35: 29 | XZ35: 33 | YA35: 28 | YB35: 44 | YC35: 84 | YD35: 58 | YE35: 66 | YF35: 32 | YG35: 23 | YH35: 17 | YI35: 47 | YJ35: 45 | YK35: 32 | YL35: 32 | YM35: 34
B37: Revenues | UU37: x
B38: Interchange Fee Revenue | C38: 0 | D38: 28611.69 | E38: 10666.766 | F38: 0 | G38: 0 | H38: 16747.754 | I38: 5052.1026 | J38: 3356.5184 | K38: 9474.4782 | L38: 5116.9263 | M38: 0 | N38: 0 | O38: 14553.94 | P38: 7479.8753 | Q38: 4793.2852 | R38: 11605.044 | S38: 15504.995 | T38: 0 | U38: 0 | V38: 13694.8 | W38: 23145.043 | X38: 5034.3321 | Y38: 7880.8807 | Z38: 3711.1813 | AA38: 0 | AB38: 0 | AC38: 17934.675 | AD38: 6203.1458 | AE38: 2428.2503 | AF38: 8795.8369 | AG38: 8482.502 | AH38: 0 | AI38: 0 | AJ38: 27224.558 | AK38: 10816.751 | AL38: 4818.7825 | AM38: 9819.0412 | AN38: 6633.0697 | AO38: 0 | AP38: 0 | AQ38: 15719.574 | AR38: 6778.4934 | AS38: 6109.9784 | AT38: 16037.47 | AU38: 6294.5814 | AV38: 0 | AW38: 0 | AX38: 16492.48 | AY38: 31941.719 | AZ38: 5726.796 | BA38: 8616.9564 | BB38: 9804.2011 | BC38: 0 | BD38: 0 | BE38: 18359.523 | BF38: 7226.6229 | BG38: 4457.1149 | BH38: 8063.4795 | BI38: 9844.3141 | BJ38: 0 | BK38: 0 | BL38: 38574.721 | BM38: 13323.939 | BN38: 7253.8555 | BO38: 6400.1943 | BP38: 10344.895 | BQ38: 0 | BR38: 0 | BS38: 19777.459 | BT38: 11273.31 | BU38: 5698.0418 | BV38: 4526.6868 | BW38: 7988.1251 | BX38: 0 | BY38: 0 | BZ38: 26773.589 | CA38: 12551.133 | CB38: 2756.9038 | CC38: 10110.226 | CD38: 7642.193 | CE38: 0 | CF38: 0 | CG38: 21964.113 | CH38: 12009.496 | CI38: 8992.3745 | CJ38: 7815.689 | CK38: 9401.9851 | CL38: 0 | CM38: 0 | CN38: 18200.126 | CO38: 2499.2165 | CP38: 23640.721 | CQ38: 12937.04 | CR38: 9227.783 | CS38: 0 | CT38: 0 | CU38: 24611.795 | CV38: 12746.602 | CW38: 7777.5398 | CX38: 14211.87 | CY38: 8426.3078 | CZ38: 0 | DA38: 0 | DB38: 34723.812 | DC38: 8790.4614 | DD38: 15177.956 | DE38: 5557.2495 | DF38: 4552.3986 | DG38: 0 | DH38: 0 | DI38: 36929.341 | DJ38: 14215.478 | DK38: 8323.0033 | DL38: 10236.89 | DM38: 10387.515 | DN38: 0 | DO38: 0 | DP38: 28939.05 | DQ38: 11601.871 | DR38: 6163.6986 | DS38: 4421.5028 | DT38: 30004.993 | DU38: 0 | DV38: 0 | DW38: 33149.493 | DX38: 16774.375 | DY38: 10566.179 | DZ38: 9348.1534 | EA38: 10722.425 | EB38: -8.56 | EC38: 0 | ED38: 10163.604 | EE38: 32453.557 | EF38: 7853.9943 | EG38: 3834.2031 | EH38: 10140.986 | EI38: 0 | EJ38: 0 | EK38: 41700.032 | EL38: 10329.389 | EM38: 16722.594 | EN38: 10899.566 | EO38: 12970.276 | EP38: 0 | EQ38: 0 | ER38: 17451.36 | ES38: 29118.752 | ET38: 11681.557 | EU38: 10089.825 | EV38: 9960.3463 | EW38: 0 | EX38: 0 | EY38: 47584.876 | EZ38: 23878.028 | FA38: 15880.711 | FB38: 15114.281 | FC38: 6962.3192 | FD38: 0 | FE38: 0 | FF38: 46369.463 | FG38: 19977.203 | FH38: 9931.5753 | FI38: 5191.2146 | FJ38: 16107.966 | FK38: 0 | FL38: 0 | FM38: 46518.99 | FN38: 21086.457 | FO38: 12325.415 | FP38: 9420.18 | FQ38: 17771.987 | FR38: 0 | FS38: 0 | FT38: 33712.494 | FU38: 22094.437 | FV38: 15653.12 | FW38: 20836.046 | FX38: 23081.786 | FY38: 0 | FZ38: 0 | GA38: 39571.689 | GB38: 22810.128 | GC38: 27343.869 | GD38: 19344.326 | GE38: 12082.64 | GF38: -46.6 | GG38: 0 | GH38: 47787.812 | GI38: 26529.211 | GJ38: 19840.362 | GK38: 12315.704 | GL38: 14878.869 | GM38: 0 | GN38: 0 | GO38: 34590.77 | GP38: 23421.807 | GQ38: 21274.17 | GR38: 22653.438 | GS38: 13874.947 | GT38: 0 | GU38: 0 | GV38: 53542.455 | GW38: 24209.642 | GX38: 31268.482 | GY38: 31452.953 | GZ38: 14052.609 | HA38: 0 | HB38: 0 | HC38: 46769.038 | HD38: 23904.719 | HE38: 14795.341 | HF38: 17917.379 | HG38: 20354.863 | HH38: -12.15 | HI38: 0 | HJ38: 67976.093 | HK38: 25393.746 | HL38: 16013.508 | HM38: 16905.521 | HN38: 15594.069 | HO38: 0 | HP38: 0 | HQ38: 59565.684 | HR38: 26817.5 | HS38: 22307.62 | HT38: 12666.416 | HU38: 20306.261 | HV38: 0 | HW38: 0 | HX38: 58411.93 | HY38: 33972.885 | HZ38: 30710.338 | IA38: 7085.1923 | IB38: 21435.357 | IC38: 0 | ID38: -5.98 | IE38: 21747.472 | IF38: 62853.601 | IG38: 15772.14 | IH38: 30645.62 | II38: 23983.047 | IJ38: 0 | IK38: 0 | IL38: 41717.61 | IM38: 89277.471 | IN38: 35684.791 | IO38: 25438.84 | IP38: 21534.851 | IQ38: 0 | IR38: 0 | IS38: 64816.593 | IT38: 31230.873 | IU38: 22307.431 | IV38: 22412.296 | IW38: 21646.683 | IX38: -9.1 | IY38: 0 | IZ38: 79112.344 | JA38: 46318.459 | JB38: 31341.555 | JC38: 13364.978 | JD38: 44668.367 | JE38: 0 | JF38: 0 | JG38: 68678.786 | JH38: 39471.591 | JI38: 20578.304 | JJ38: 24500.114 | JK38: 29695.083 | JL38: -43.24782 | JM38: 0 | JN38: 66407.019 | JO38: 38220.749 | JP38: 28668.89 | JQ38: 54978.718 | JR38: 34411.924 | JS38: 0 | JT38: 0 | JU38: 90612.701 | JV38: 39519.7 | JW38: 28501.371 | JX38: 27822.847 | JY38: 29791.138 | JZ38: -85.78 | KA38: 0 | KB38: 43097.83 | KC38: 66521.771 | KD38: 29295.183 | KE38: 44380.84 | KF38: 42111.247 | KG38: -309.24 | KH38: 0 | KI38: 76629.368 | KJ38: 44437.472 | KK38: 25859.733 | KL38: 27763.51 | KM38: 17825.409 | KN38: 0 | KO38: 0 | KP38: 58392.01 | KQ38: 34301.878 | KR38: 21503.847 | KS38: 27409.921 | KT38: 13655.337 | KU38: 0 | KV38: 0 | KW38: 112095.39 | KX38: 62241.641 | KY38: 31155.521 | KZ38: 29772.264 | LA38: 29621.059 | LB38: 0 | LC38: 0 | LD38: 93402.937 | LE38: 27030.17 | LF38: 39339.3 | LG38: 28645.974 | LH38: 26921.495 | LI38: 0 | LJ38: 0 | LK38: 85657.888 | LL38: 38330.971 | LM38: 29265.249 | LN38: 31558.223 | LO38: 23347.468 | LP38: -40.199495 | LQ38: 0 | LR38: 74412.131 | LS38: 42048.512 | LT38: 24587.537 | LU38: 13922.59 | LV38: 47910.393 | LW38: 0 | LX38: 0 | LY38: 89776.572 | LZ38: 60180.613 | MA38: 42850.63 | MB38: 27349.41 | MC38: 31467.724 | MD38: -88.77 | ME38: 0 | MF38: 49199.434 | MG38: 93600.722 | MH38: 32784.659 | MI38: 25375.36 | MJ38: 24078.585 | MK38: 0 | ML38: 0 | MM38: 76079.623 | MN38: 51455.216 | MO38: 31165.696 | MP38: 25702.205 | MQ38: 27522.951 | MR38: 0 | MS38: 0 | MT38: 81992.666 | MU38: 45353.272 | MV38: 15760.591 | MW38: 0 | MX38: 77209.609 | MY38: 0 | MZ38: 0 | NA38: 64647.642 | NB38: 17634.326 | NC38: 19577.592 | ND38: 0 | NE38: 107778.36 | NF38: 0 | NG38: 0 | NH38: 86358.09 | NI38: 37985.606 | NJ38: 24271.074 | NK38: 16041.49 | NL38: 20637.842 | NM38: 0 | NN38: 0 | NO38: 68681.022 | NP38: 34028.79 | NQ38: 27097.297 | NR38: 27579.987 | NS38: 27546.998 | NT38: 0 | NU38: 0 | NV38: 33601.59 | NW38: 68057.299 | NX38: 34429.307 | NY38: 22401.795 | NZ38: 27873.482 | OA38: 0 | OB38: 0 | OC38: 70796.052 | OD38: 37681.222 | OE38: 26929.619 | OF38: 24793.719 | OG38: 21055.593 | OH38: 0 | OI38: 0 | OJ38: 86371.671 | OK38: 50868.353 | OL38: 29638.117 | OM38: 35705.413 | ON38: 20093.582 | OO38: -980 | OP38: 0 | OQ38: 73367.238 | OR38: 31044.14 | OS38: 27213.023 | OT38: 20801.081 | OU38: 22847.492 | OV38: 0 | OW38: 0 | OX38: 45463.93 | OY38: 63486.642 | OZ38: 71628.372 | PA38: 39229.487 | PB38: 26323.695 | PC38: -11.642867 | PD38: 0 | PE38: 81592.607 | PF38: 47414.174 | PG38: 37813.58 | PH38: 14667.65 | PI38: 34677.863 | PJ38: 0 | PK38: 0 | PL38: 106040.96 | PM38: 79257.459 | PN38: 52887.858 | PO38: 42735.064 | PP38: 33711.046 | PQ38: 0 | PR38: 0 | PS38: 90241.657 | PT38: 56705.759 | PU38: 39137.854 | PV38: 24064.927 | PW38: 27194.495 | PX38: 0 | PY38: 0 | PZ38: 117407.34 | QA38: 61439.68 | QB38: 46477.285 | QC38: 57219.263 | QD38: 21870.823 | QE38: 0 | QF38: 0 | QG38: 140619.92 | QH38: 60322.036 | QI38: 38023.414 | QJ38: 39219.231 | QK38: 48668.531 | QL38: 0 | QM38: 0 | QN38: 119144.03 | QO38: 62144.8 | QP38: 51831.269 | QQ38: 42601.58 | QR38: 34902.821 | QS38: 0 | QT38: 0 | QU38: 207480.09 | QV38: 74757.881 | QW38: 45924.733 | QX38: 26103.218 | QY38: 75626.755 | QZ38: 0 | RA38: 0 | RB38: 117994.55 | RC38: 65976.2 | RD38: 49355.643 | RE38: 55943.491 | RF38: 72391.214 | RG38: -138.02454 | RH38: 0 | RI38: 137341.12 | RJ38: 68451.005 | RK38: 47325.705 | RL38: 42866.173 | RM38: 40801.303 | RN38: 0 | RO38: 0 | RP38: 121846.11 | RQ38: 62660.71 | RR38: 33024.087 | RS38: 46532.812 | RT38: 17220.225 | RU38: 0 | RV38: 0 | RW38: 195468.34 | RX38: 81319.472 | RY38: 54782.882 | RZ38: 51906.551 | SA38: 43383.549 | SB38: 0 | SC38: 0 | SD38: 123954.05 | SE38: 65488.295 | SF38: 42025.99 | SG38: 44616.111 | SH38: 50680.523 | SI38: 0 | SJ38: 0 | SK38: 151770.73 | SL38: 78668.429 | SM38: 63733.151 | SN38: 54355.492 | SO38: 52822.259 | SP38: 0 | SQ38: 0 | SR38: 63461.3 | SS38: 146432.28 | ST38: 31616.131 | SU38: 77664.862 | SV38: 54525.919 | SW38: -217.24 | SX38: 0 | SY38: 151248.44 | SZ38: 97698.072 | TA38: 74830.735 | TB38: 82382.816 | TC38: 59163.095 | TD38: 0 | TE38: 0 | TF38: 196521.29 | TG38: 87609.563 | TH38: 65776.879 | TI38: 50341.285 | TJ38: 30885.472 | TK38: 0 | TL38: 0 | TM38: 164800.67 | TN38: 82188.644 | TO38: 73249.914 | TP38: 60131.678 | TQ38: 20556.42 | TR38: 0 | TS38: 0 | TT38: 207227.08 | TU38: 75304.822 | TV38: 58447.275 | TW38: 53580.694 | TX38: 58545.338 | TY38: 0 | TZ38: 0 | UA38: 141453.48 | UB38: 71297.128 | UC38: 52062.304 | UD38: 81979.16 | UE38: 63053.62 | UF38: 0 | UG38: 0 | UH38: 161002.18 | UI38: 102228.43 | UJ38: 68007.907 | UK38: 65376.226 | UL38: 57269.598 | UM38: 0 | UN38: 0 | UO38: 139287.32 | UP38: 80946.81 | UQ38: 56232.667 | UR38: 59708.836 | US38: 76148.517 | UT38: 0 | UU38: 0 | UV38: 162525.53 | UW38: 76826.887 | UX38: 52759.726 | UY38: 53852.24 | UZ38: 53009.515 | VA38: 0 | VB38: 0 | VC38: 140464.7 | VD38: 74402.52 | VE38: 48861.934 | VF38: 48861.934 | VG38: 41150.24 | VH38: 44314.01 | VI38: 0 | VJ38: 0 | VK38: 208904.56 | VL38: 88895.54 | VM38: 64780.38 | VN38: 50335.21 | VO38: 65938.33 | VP38: 0 | VQ38: 0 | VR38: 154254.56 | VS38: 75510.73 | VT38: 51445.57 | VU38: 48149.12 | VV38: 55861.21 | VW38: 0 | VX38: 0 | VY38: 167518.79 | VZ38: 83513.07 | WA38: 67411.75 | WB38: 56992.87 | WC38: 38803.03 | WD38: 0 | WE38: 0 | WF38: 210928.66 | WG38: 95017.73 | WH38: 66250.88 | WI38: 77676.67 | WJ38: 63288.13 | WM38: 103895.43 | WN38: 174151.03 | WO38: 85903.58 | WP38: 83096.92 | WQ38: 77396.77 | WR38: 0 | WS38: 0 | WT38: 103446.98 | WU38: 230315.4 | WV38: 95522.63 | WW38: 80468.92 | WX38: 78004.62 | WY38: 0 | WZ38: 0 | XA38: 229600.99 | XB38: 121010.99 | XC38: 67173.86 | XD38: 94234.5 | XE38: 81889.66 | XF38: 0 | XG38: 0 | XH38: 236188.89 | XI38: 119394.54 | XJ38: 75153.23 | XK38: 81673.03 | XL38: 90830.52 | XM38: 0 | XN38: 0 | XO38: 218636.87 | XP38: 135691.6 | XQ38: 71078.01 | XR38: 86993.76 | XS38: 117779.33 | XT38: 0 | XU38: 0 | XV38: 274244.49 | XW38: 130004.88 | XX38: 90604.31 | XY38: 95235.73 | XZ38: 91645.48 | YA38: 0 | YB38: 0 | YC38: 127910 | YD38: 274825.02 | YE38: 90524.24 | YF38: 94619.72 | YG38: 97057.34 | YH38: 0 | YI38: 0 | YJ38: 282938.06 | YK38: 130396.74 | YL38: 88055.09 | YM38: 81433.58
B39: Growth | C39: =IFERROR(C38/296-1,"") -> -1 | D39: =IFERROR(D38/C38-1,"") | E39: =IFERROR(E38/D38-1,"") -> -0.62718855 | F39: =IFERROR(F38/E38-1,"") -> -1 | G39: =IFERROR(G38/F38-1,"") | H39: =IFERROR(H38/G38-1,"") | I39: =IFERROR(I38/H38-1,"") -> -0.69834149 | J39: =IFERROR(J38/I38-1,"") -> -0.33561951 | K39: =IFERROR(K38/J38-1,"") -> 1.82271 | ... AF39: =IFERROR(AF38/AE38-1,"") -> 2.6222942 | WZ39: =SUM(WN38:WZ38) -> 1008306.8
B41: Delinquencies
B42: Total Delinquent (DPD30>) | JO42: =SUM(JO50:JO55) -> 2709078.8 | JP42: =SUM(JP50:JP55) -> 2709078.8 | JQ42: =SUM(JQ50:JQ55) -> 2707078.8 | JR42: =SUM(JR50:JR55) -> 3189819.5 | JS42: =SUM(JS50:JS55) -> 3189819.5 | JT42: =SUM(JT50:JT55) -> 3189819.5 | JU42: =SUM(JU50:JU55) -> 3189819.5 | JV42: =SUM(JV50:JV55) -> 3189819.5 | ... WH42: =SUM(WH50:WH55) -> 20311629 | WI42: 20311479 | WJ42: =SUM(WJ50:WJ55) -> 20241674 | WK42: =SUM(WK50:WK55) -> 20236524 | WL42: =SUM(WL50:WL55) -> 20223242 | WM42: =SUM(WM50:WM55) -> 20216918 | WN42: =SUM(WN49:WN55) -> 20552292 | WO42: =SUM(WO49:WO55) -> 21288657 | WP42: 21134824 | WQ42: =SUM(WQ49:WQ55) -> 21083870 | WR42: =SUM(WR49:WR55) -> 21048904 | WS42: =SUM(WS49:WS55) -> 21045142 | WT42: =SUM(WT49:WT55) -> 21038396 | WU42: =SUM(WU49:WU55) -> 20988827 | WV42: =SUM(WV49:WV55) -> 20937886 | WW42: =SUM(WW49:WW55) -> 20931451 | WX42: =SUM(WX50:WX55) -> 20515848 | WY42: =SUM(WY50:WY55) -> 20515698 | WZ42: =SUM(WZ50:WZ55) -> 20515048 | XA42: =SUM(XA50:XA55) -> 20514898 | XB42: =SUM(XB50:XB55) -> 20509181 | XC42: =SUM(XC50:XC55) -> 20507657 | XD42: =SUM(XD50:XD55) -> 20504507 | XE42: =SUM(XE50:XE55) -> 21178293 | ... YB42: =SUM(YB50:YB55) -> 21720414 | YC42: 21720414 | YD42: =SUM(YD50:YD55) -> 21710414 | YE42: =SUM(YE50:YE55) -> 21704362 | YF42: =SUM(YF50:YF55) -> 21686672 | YG42: =SUM(YG50:YG55) -> 21686672 | YH42: =SUM(YH50:YH55) -> 21686672 | YI42: =SUM(YI50:YI55) -> 21686672 | YJ42: =SUM(YJ50:YJ55) -> 22674176 | YK42: =SUM(YK50:YK55) -> 22674176 | ... YM42: =SUM(YM50:YM55) -> 22674176
B43: Delinquency Rate | JO43: =JO42/JO27 -> 0.05925969 | JP43: =JP42/JP27 -> 0.061381392 | JQ43: =JQ42/JQ27 -> 0.062756831 | JR43: =JR42/JR27 -> 0.073182593 | JS43: =JS42/JS27 -> 0.072420732 | JT43: =JT42/JT27 -> 0.072005825 | JU43: =JU42/JU27 -> 0.069760547 | JV43: =JV42/JV27 -> 0.070086553 | ... WH43: =WH42/WH27 -> 0.12976923 | WI43: 0.12973708 | WJ43: =WJ42/WJ27 -> 0.12899911 | WK43: =WK42/WK27 -> 0.13121903 | WL43: =WL42/WL27 -> 0.12951968 | WM43: =WM42/WM27 -> 0.12676636 | WN43: =WN42/WN27 -> 0.12796821 | WO43: =WO42/WO27 -> 0.13603929 | WP43: 0.13401778 | WQ43: =WQ42/WQ27 -> 0.1340616 | WR43: =WR42/WR27 -> 0.13327912 | WS43: =WS42/WS27 -> 0.12884677 | WT43: =WT42/WT27 -> 0.1250444 | WU43: =WU42/WU27 -> 0.12259502 | WV43: =WV42/WV27 -> 0.11972082 | WW43: =WW42/WW27 -> 0.11888696 | WX43: =WX42/WX27 -> 0.11680403 | ... YB43: =YB42/YB27 -> 0.10145461 | YC43: 0.1 | YD43: =YD42/YD27 -> 0.099387711 | YE43: =YE42/YE27 -> 0.10002689 | YF43: =YF42/YF27 -> 0.098838277 | YG43: =YG42/YG27 -> 0.1021063 | YH43: =YH42/YH27 -> 0.10240742 | YI43: =YI42/YI27 -> 0.10670713 | YJ43: =YJ42/YJ27 -> 0.11081659 | YK43: =YK42/YK27 -> 0.10770034 | ... YM43: =YM42/YM27 -> 0.10621566
B45: Number of Accounts Delinquent | LX45: =210-53 -> 157 | LY45: =211-54 -> 157 | LZ45: =209-52 -> 157 | MA45: =250-79 -> 171 | MB45: =245-74 -> 171 | MC45: =239-68 -> 171 | MD45: =234-63 -> 171 | ME45: =232-62 -> 170 | MF45: =268-90 -> 178 | MG45: =258-80 -> 178 | MH45: =250-72 -> 178 | MI45: =247-69 -> 178 | MJ45: =242-64 -> 178 | MK45: =241-63 -> 178 | ML45: =241-63 -> 178 | MM45: =241-63 -> 178 | MN45: =241-63 -> 178 | MO45: =238-60 -> 178 | MP45: =238-60 -> 178 | MQ45: =291-115 -> 176 | MR45: =278-82 -> 196 | MS45: =276-80 -> 196 | MT45: =271-75 -> 196 | MU45: =277-81 -> 196 | MV45: =275-75 -> 200 | MW45: =274-74 -> 200 | MX45: =274-74 -> 200 | MY45: =272-72 -> 200 | MZ45: =271-72 -> 199 | NA45: =269-70 -> 199 | NB45: =268-69 -> 199 | NC45: =268-69 -> 199 | ND45: =269-70 -> 199 | NE45: =268-69 -> 199 | NF45: =318-106 -> 212 | NG45: =313-101 -> 212 | NH45: =305-94 -> 211 | NI45: =299-88 -> 211 | NJ45: =296-85 -> 211 | NK45: =329-107 -> 222 | NL45: =326-104 -> 222 | NM45: =320-98 -> 222 | NN45: =318-96 -> 222 | NO45: =316-94 -> 222 | NP45: =311-89 -> 222 | NQ45: =308-86 -> 222 | NR45: =306-84 -> 222 | NS45: =301-80 -> 221 | NT45: =299-78 -> 221 | NU45: =299-78 -> 221 | NV45: =364-111 -> 253 | NW45: =354-102 -> 252 | NX45: =350-98 -> 252 | NY45: =348-93 -> 255 | NZ45: =342-87 -> 255 | OA45: =340-85 -> 255 | OB45: =337-82 -> 255 | OC45: =336-81 -> 255 | OD45: =333-79 -> 254 | OE45: =332-78 -> 254 | OF45: =331-77 -> 254 | OG45: =324-71 -> 253 | OH45: =320-68 -> 252 | OI45: =320-68 -> 252 | OJ45: =319-67 -> 252 | OK45: =390-119 -> 271 | OL45: =384-114 -> 270 | OM45: =380-110 -> 270 | ON45: =377-107 -> 270 | OO45: =374-105 -> 269 | OP45: =373-87 -> 286 | OQ45: =371-85 -> 286 | OR45: =366-80 -> 286 | OS45: =364-78 -> 286 | OT45: =362-76 -> 286 | OU45: =355-71 -> 284 | OV45: =354-70 -> 284 | OW45: =354-70 -> 284 | OX45: =351-67 -> 284 | OY45: =351-67 -> 284 | OZ45: =349-66 -> 283 | PA45: =426-116 -> 310 | PB45: =401-91 -> 310 | PC45: =401-91 -> 310 | PD45: =398-88 -> 310 | PE45: =391-83 -> 308 | PF45: =386-78 -> 308 | PG45: =383-76 -> 307 | PH45: =379-73 -> 306 | PI45: =376-71 -> 305 | PJ45: =372-68 -> 304 | PK45: =372-68 -> 304 | PL45: =368-66 -> 302 | PM45: =418-116 -> 302 | PN45: =403-101 -> 302 | PO45: =394-93 -> 301 | PP45: =394-61 -> 333 | PQ45: =393-61 -> 332 | PR45: =392-60 -> 332 | PS45: =391-59 -> 332 | PT45: =389-57 -> 332 | PU45: =386-56 -> 330 | PV45: =382-53 -> 329 | PW45: =377-49 -> 328 | PX45: =376-49 -> 327 | PY45: =374-48 -> 326 | PZ45: =372-47 -> 325 | QA45: =371-46 -> 325 | QB45: =369-44 -> 325 | QC45: =430-105 -> 325 | QD45: =410-85 -> 325 | QE45: =398-73 -> 325 | QF45: =397-47 -> 350 | QG45: =397-47 -> 350 | QH45: =396-46 -> 350 | QI45: =393-45 -> 348 | QJ45: =393-45 -> 348 | QK45: =383-38 -> 345 | QL45: =382-37 -> 345 | QM45: =381-37 -> 344 | QN45: =379-36 -> 343 | QO45: =374-33 -> 341 | QP45: =373-32 -> 341 | QQ45: =370-30 -> 340 | QR45: =422-66 -> 356 | QS45: =413-57 -> 356 | QT45: =411-55 -> 356 | QU45: =405-52 -> 353 | QV45: =402-50 -> 352 | QW45: =399-48 -> 351 | QX45: =395-44 -> 351 | QY45: =392-43 -> 349 | QZ45: =392-43 -> 349 | RA45: =391-42 -> 349 | RB45: =389-42 -> 347 | RC45: =387-40 -> 347 | RD45: =384-40 -> 344 | RE45: =383-39 -> 344 | RF45: =382-38 -> 344 | RG45: =381-37 -> 344 | RH45: =494-140 -> 354 | RI45: =462-110 -> 352 | RJ45: =452-101 -> 351 | RK45: =448-97 -> 351 | RL45: =442-91 -> 351 | RM45: =435-85 -> 350 | RN45: =431-81 -> 350 | RO45: =429-79 -> 350 | RP45: =428-78 -> 350 | RQ45: =425-75 -> 350 | RR45: =423-73 -> 350 | RS45: =420-71 -> 349 | RT45: =419-70 -> 349 | RU45: =412-63 -> 349 | RV45: =481-132 -> 349 | RW45: =461-94 -> 367 | RX45: =452-86 -> 366 | RY45: =449-83 -> 366 | RZ45: =445-80 -> 365 | SA45: =441-77 -> 364 | SB45: =441-77 -> 364 | SC45: =440-76 -> 364 | SD45: =439-75 -> 364 | SE45: =434-73 -> 361 | SF45: =433-72 -> 361 | SG45: =432-71 -> 361 | SH45: =428-69 -> 359 | SI45: =428-69 -> 359 | SJ45: 358 | SK45: 358 | SL45: 358 | SM45: 390 | SN45: 390 | SO45: 386 | SP45: 386 | SQ45: 386 | SR45: 385 | SS45: 384 | ST45: 382 | SU45: 381 | SV45: 380 | SW45: 378 | SX45: 378 | SY45: 377 | SZ45: 376 | TA45: 402 | TB45: 402 | TC45: 401 | TD45: 401 | TE45: 400 | TF45: 400 | TG45: 400 | TH45: 399 | TI45: 398 | TJ45: 396 | TK45: 395 | TL45: 395 | TM45: 392 | TN45: 391 | TO45: 391 | TP45: 391 | TQ45: 419 | TR45: 419 | TS45: 419 | TT45: 419 | TU45: 417 | TV45: 417 | TW45: 416 | TX45: 416 | TY45: 416 | TZ45: 416 | UA45: 416 | UB45: 413 | UC45: 412 | UD45: 412 | UE45: 409 | UF45: 432 | UG45: 432 | UH45: 430 | UI45: 429 | UJ45: 428 | UK45: 428 | UL45: 427 | UM45: 427 | UN45: 426 | UO45: 424 | UP45: 424 | UQ45: 424 | UR45: 424 | US45: 423 | UT45: 422 | UU45: 422 | UV45: 434 | UW45: 434 | UX45: 433 | UY45: 433 | UZ45: 433 | VA45: 433 | VB45: 433 | VC45: 433 | VD45: 433 | VE45: 433 | VF45: 433 | VG45: 432 | VH45: 431 | VI45: 432 | VJ45: 433 | VK45: 448 | VL45: 448 | VM45: 448 | VN45: 447 | VO45: 447 | VP45: 447 | VQ45: 447 | VR45: 447 | VS45: 446 | VT45: 446 | VU45: 445 | VV45: 445 | VW45: 445 | VX45: 444 | VY45: 443 | VZ45: 464 | WA45: 464 | WB45: 461 | WC45: 460 | WD45: 460 | WE45: 460 | WF45: 460 | WG45: 460 | WH45: 460 | WI45: 460 | WJ45: 459 | WK45: 458 | WL45: 458 | WM45: 457 | WN45: 457 | WO45: 462 | WP45: 462 | WQ45: 462 | WR45: 461 | WS45: 461 | WT45: 461 | WU45: 461 | WV45: 460 | WW45: 460 | WX45: 459 | WY45: 459 | WZ45: 459 | XA45: 459 | XB45: 459 | XC45: 459 | XD45: 459 | XE45: 489 | XF45: 487 | XG45: 487 | XH45: 487 | XI45: 486 | XJ45: 486 | XK45: 486 | XL45: 486 | XM45: 486 | XN45: 486 | XO45: 486 | XP45: 485 | XQ45: 486 | XR45: 486 | XS45: 486 | XT45: 501 | XU45: 501 | XV45: 501 | XW45: 501 | XX45: 501 | XY45: 501 | XZ45: 501 | YA45: 501 | YB45: 501 | YC45: 501 | YD45: 501 | YE45: 500 | YF45: 500 | YG45: 500 | YH45: 500 | YI45: 500 | YJ45: 531 | YK45: 531 | YL45: 531 | YM45: 531
B46: % of Users | LX46: =LX45/LX8 -> 0.045284107 | LY46: =LY45/LY8 -> 0.045284107 | LZ46: =LZ45/LZ8 -> 0.045284107 | MA46: =MA45/MA8 -> 0.049536501 | MB46: =MB45/MB8 -> 0.049536501 | MC46: =MC45/MC8 -> 0.046128945 | MD46: =MD45/MD8 -> 0.046128945 | ME46: =ME45/ME8 -> 0.045859185 | ... WH46: =WH45/WH8 -> 0.035197796 | WI46: 0.035168196 | WJ46: =WJ45/WJ8 -> 0.034780632 | WK46: =WK45/WK8 -> 0.034704857 | WL46: =WL45/WL8 -> 0.034704857 | WM46: =WM45/WM8 -> 0.034629082 | WN46: =WN45/WN8 -> 0.032570736 | WO46: =WO45/WO8 -> 0.032380151 | WP46: 0.032289628 | WQ46: =WQ45/WQ8 -> 0.032289628 | WR46: =WR45/WR8 -> 0.030956218 | WS46: =WS45/WS8 -> 0.030811389 | WT46: =WT45/WT8 -> 0.030406965 | WU46: =WU45/WU8 -> 0.030408971 | WV46: =WV45/WV8 -> 0.030343008 | WW46: =WW45/WW8 -> 0.029971332 | WX46: =WX45/WX8 -> 0.029820686 | ... YB46: =YB45/YB8 -> 0.030732425 | YC46: 0.03 | YD46: =YD45/YD8 -> 0.030732425 | YE46: =YE45/YE8 -> 0.030671083 | YF46: =YF45/YF8 -> 0.030671083 | YG46: =YG45/YG8 -> 0.030671083 | YH46: =YH45/YH8 -> 0.030671083 | YI46: =YI45/YI8 -> 0.030671083 | YJ46: =YJ45/YJ8 -> 0.032574689 | YK46: =YK45/YK8 -> 0.032574689 | ... YM46: =YM45/YM8 -> 0.032574689
B48: Aging
B49: 1-30 days | JO49: 1103872.5 | JP49: 1551413.5 | JQ49: 1075572.3 | JR49: 1174344.1 | JS49: 1114614.8 | JT49: 1086691 | JU49: 985758.69 | JV49: 945820.42 | JW49: 1969799.7 | JX49: 1862485.2 | JY49: 1687667 | JZ49: 1677642.5 | KA49: 1672642.5 | KB49: 1570483.2 | KC49: 1535355.7 | KD49: 1488508.3 | KE49: 1488508.3 | KF49: 1488508.3 | KG49: 1488508.3 | KH49: 2867275.1 | KI49: 2310616.7 | KK49: 2053738.8 | KL49: 2080882.9 | KM49: 2059735.6 | KN49: 1937867.6 | KO49: 1908426.9 | KP49: 1899311 | KQ49: 1826454.6 | KR49: 1826454.6 | KS49: 1774002.5 | KT49: 1767002.5 | KU49: 1767002.5 | KV49: 1584690.8 | KW49: 2866050.8 | KX49: 2741611.2 | KY49: 2709164.3 | KZ49: 2588452.7 | LA49: 2052828.5 | LB49: 2704362.6 | LC49: 2642888 | LD49: 2517185.1 | LE49: 2486585.8 | LF49: 2429271.7 | LG49: 2404530.7 | LH49: 2216761.7 | LI49: 2199561.7 | LJ49: 2199561.7 | LK49: 2171296.2 | LL49: 1271279.7 | LM49: 2927893.5 | LN49: 2614303.8 | LO49: 2545480.1 | LP49: 2464809.1 | LQ49: 2599537.3 | LR49: 2564222.1 | LS49: 2551316.3 | LT49: 2542196.6 | LU49: 2497704.9 | LV49: 2470335.9 | LW49: 2364895.4 | LX49: 2349152.4 | LY49: 2365299.5 | LZ49: 2327856.6 | MA49: 3056816.8 | MB49: 2988202.7 | MC49: 2830171.1 | MD49: 2768557.4 | ME49: 2751557.5 | MF49: 3630701.9 | MG49: 3586201.6 | MH49: 3442754.2 | MI49: 3341464.8 | MJ49: 3245276.8 | MK49: 3170396.3 | ML49: 3166167.8 | MM49: 3146708.9 | MN49: 3049098.4 | MO49: 2898960.7 | MP49: 2898960.7 | MQ49: 6051510.1 | MR49: 4485987.9 | MS49: 4473489.9 | MT49: 4396589.1 | MU49: 4634312.6 | MV49: 3828871.7 | MW49: 3794226 | MX49: 3793776 | MY49: 3758477 | MZ49: 3756477 | NA49: 3741226.1 | NB49: 3703006.5 | NC49: 3615006.5 | ND49: 3627899.1 | NE49: 3627815.7 | NF49: 3778052.9 | NG49: 3299719.2 | NH49: 3177664 | NI49: 3083510.9 | NJ49: 3074181.1 | NK49: 3092625.7 | NL49: 3030553.9 | NM49: 2989949.9 | NN49: 2941831.4 | NO49: 2924002.2 | NP49: 2870458.4 | NQ49: 2807926.7 | NR49: 2727076.6 | NS49: 2681942 | NT49: 2620882.6 | NU49: 2620782.6 | NV49: 3566803.8 | NW49: 3498839.6 | NX49: 3400694.3 | NY49: 3222872.8 | NZ49: 2647287.5 | OA49: 2615890.3 | OB49: 2578611 | OC49: 2570151 | OD49: 2435215.7 | OE49: 2421391.1 | OF49: 2355541.2 | OG49: 2195445 | OH49: 2148853.1 | OI49: 2148853.1 | OJ49: 2139089.4 | OK49: 3442834.8 | OL49: 3375679.5 | OM49: 3320799.4 | ON49: 3295171.5 | OO49: 3283298.8 | OP49: 2928191.4 | OQ49: 2886856.5 | OR49: 2811636.6 | OS49: 2768475.3 | OT49: 2726743.8 | OU49: 2630000.1 | OV49: 2609395.7 | OW49: 2604395.7 | OX49: 2482802.6 | OY49: 2482802.6 | OZ49: 2473009.5 | PA49: 3953572.7 | PB49: 3548281 | PC49: 3533689.9 | PD49: 3468845.8 | PE49: 3331881.6 | PF49: 2847208.2 | PG49: 2776442.2 | PH49: 2731968.9 | PI49: 2704117.5 | PJ49: 2666196.1 | PK49: 2616196.1 | PL49: 2555670.3 | PM49: 4436624 | PN49: 4283575.3 | PO49: 3279836.9 | PP49: 1843772 | PQ49: 1839572 | PR49: 1831731.3 | PS49: 1822415.8 | PT49: 1796539.9 | PU49: 1772216.9 | PV49: 1705639.9 | PW49: 1663047.4 | PX49: 1677387.8 | PY49: 1662527.3 | PZ49: 1648170.6 | QA49: 1599741.7 | QB49: 1577773.8 | QC49: 3368717.3 | QD49: 2951449.6 | QE49: 2359969.1 | QF49: 1022030.1 | QG49: 1022030.1 | QH49: 1015817.7 | QI49: 957242.19 | QJ49: 957242.19 | QK49: 844753.65 | QL49: 829704.67 | QM49: 829704.67 | QN49: 782951.75 | QO49: 731936.44 | QP49: 707066.44 | QQ49: 659721.06 | QR49: 1637569.4 | QS49: 1449446.6 | QT49: 1416622.5 | QU49: 1380470.9 | QV49: 1353619.1 | QW49: 1312032.9 | QX49: 1236356.9 | QY49: 1235602.8 | QZ49: 1235602.8 | RA49: 1230738.8 | RB49: 1227738.8 | RC49: 1204661.6 | RD49: 1196296 | RE49: 1173443.8 | RF49: 1166701.4 | RG49: 1138701.4 | RH49: 4023392.8 | RI49: 3532511.3 | RJ49: 3350080.8 | RK49: 3274111.4 | RL49: 3209532 | RM49: 3118377 | RN49: 3071812.4 | RO49: 3062361.8 | RP49: 3020361.8 | RQ49: 2981446 | RR49: 2946432.4 | RS49: 2919677.1 | RT49: 2812517.2 | RU49: 2501083.1 | RV49: 5486177.7 | RW49: 3322632.9 | RX49: 3189582.9 | RY49: 3121202.9 | RZ49: 3032601.2 | SA49: 2287538.5 | SB49: 2287538.5 | SC49: 2275913.8 | SD49: 2273845.8 | SE49: 2240680.3 | SF49: 2226720.5 | SG49: 2180454.7 | SH49: 2139889.2 | SI49: 2130165.3 | SJ49: 2126625.9 | SK49: 2016134.4 | SL49: 5059914.6 | SM49: 3465422 | SN49: 2950104.9 | SO49: 2723017.3 | SP49: 2635045.8 | SQ49: 2616095.5 | SR49: 2557130.8 | SS49: 2489073.4 | ST49: 2412622.1 | SU49: 2392452.7 | SV49: 2315171.9 | SW49: 2315171.9 | SX49: 2280707.9 | SY49: 2275725.5 | SZ49: 2255764.4 | TA49: 3917863.7 | TB49: 2911930.2 | TC49: 2623238.2 | TD49: 2568771.6 | TE49: 2559927.2 | TF49: 2459055.2 | TG49: 2415883 | TH49: 2350526.4 | TI49: 2257739.6 | TJ49: 2243071.4 | TK49: 2233752.2 | TL49: 2207884.8 | TM49: 2202884.8 | TN49: 2191534.8 | TO49: 2191534.8 | TP49: 2183905.1 | TQ49: 1407827.3 | TR49: 1357329.8 | TS49: 1347346.6 | TT49: 1312168.7 | TU49: 1285011.4 | TV49: 1284002.7 | TW49: 1268250.6 | TX49: 1258518.4 | TY49: 1258518.4 | TZ49: 1258518.4 | UA49: 1254891.4 | UB49: 1227233.9 | UC49: 1216846.7 | UD49: 1215005.9 | UE49: 1502522.6 | UF49: 662014.46 | UG49: 641320.6 | UH49: 640320.6 | UI49: 637173.14 | UJ49: 603420.03 | UK49: 582273.76 | UL49: 581273.76 | UM49: 569096.32 | UN49: 569096.32 | UO49: 559776.32 | UP49: 558776.32 | UQ49: 549476.76 | UR49: 549476.76 | US49: 546476.76 | UT49: 540366.62 | UU49: 1026496.8 | UV49: 837599.92 | UW49: 792893.46 | UX49: 781957.82 | UY49: 722247.29 | UZ49: 616039.84 | VA49: 612774.47 | VB49: 610269.54 | VC49: 598812.36 | VD49: 593962.23 | VE49: 593962.23 | VF49: 593962.23 | VG49: 536332.45 | VH49: 529446.71 | VI49: 520772.63 | VJ49: 381679.58 | VK49: 577871.51 | VL49: 518313.49 | VM49: 444668.73 | VN49: 408876.73 | VO49: 393637.83 | VP49: 376183.45 | VQ49: 369594.38 | VR49: 353403.76 | VS49: 339018.63 | VT49: 330919.83 | VU49: 321599.83 | VV49: 312172.63 | VW49: 299083.65 | VX49: 299083.65 | VY49: 297983.65 | VZ49: 885659.32 | WA49: 719632.53 | WB49: 622325.68 | WC49: 522183.4 | WD49: 446372.15 | WE49: 443805.37 | WF49: 408621.75 | WG49: 388700.96 | WH49: 365949.18 | WI49: 361330.73 | WJ49: 356387.71 | WK49: 347844.44 | WL49: 346317.42 | WM49: 343952.44 | WN49: 343952.44 | WO49: 744818.97 | WP49: 590986.48 | WQ49: 540032.41 | WR49: 521264.14 | WS49: 517502.34 | WT49: 510905.9 | WU49: 461336.61 | WV49: 412044.79 | WW49: 408410.34 | WX49: 408410.34 | WY49: 408410.34 | WZ49: 408410.34 | XA49: 403162.22 | XB49: 390858.69 | XC49: 381538.69 | XD49: 380254.11 | XE49: 1142117.9 | XF49: 1024539.2 | XG49: 920225 | XH49: 836338.78 | XI49: 770967.05 | XJ49: 700565.59 | XK49: 617700.99 | XL49: 577298.59 | XM49: 560598.25 | XN49: 558598.25 | XO49: 558598.25 | XP49: 534152.62 | XQ49: 467395.94 | XR49: 451998.56 | XS49: 1105455.9 | XT49: 801419.92 | XU49: 687026.25 | XV49: 611583.24 | XW49: 572129.63 | XX49: 558998.6 | XY49: 546899.42 | XZ49: 518712.38 | YA49: 498723.42 | YB49: 492056.75 | YC49: 481779 | YD49: 481778.64 | YE49: 468364.88 | YF49: 441341.41 | YG49: 441341.41 | YH49: 441341.41 | YI49: 441341.41 | YJ49: 952031.06 | YK49: 801134.8 | YL49: 682088.02 | YM49: 643747.71
B50: 31-60 days | JO50: 592244.36 | JP50: 592244.36 | JQ50: 498785.5 | JR50: 964026.19 | JS50: 964026.19 | JT50: 964026.19 | JU50: 964026.19 | JV50: 926516.28 | JW50: 1017368.1 | JX50: 1017368.1 | JY50: 1017368.1 | JZ50: 1017368.1 | KA50: 1017368.1 | KB50: 1017368.1 | KC50: 1016051.4 | KD50: 991426.26 | KE50: 991426.26 | KF50: 991426.26 | KG50: 700816.26 | KH50: 1400919.2 | KI50: 1400919.2 | KK50: 1249629.4 | KL50: 1297256.7 | KM50: 1297256.7 | KN50: 1297256.7 | KO50: 1297256.7 | KP50: 1297256.7 | KQ50: 1297256.7 | KR50: 1297256.7 | KS50: 1282996.4 | KT50: 1282996.4 | KU50: 1282996.4 | KV50: 1016279 | KW50: 1039924.3 | KX50: 1039924.3 | KY50: 1037493.4 | KZ50: 1007493.4 | LA50: 1436299.1 | LB50: 1515271.6 | LC50: 1515271.6 | LD50: 1515271.6 | LE50: 1510271.6 | LF50: 1510271.6 | LG50: 1500772.2 | LH50: 1474084.7 | LI50: 1474084.7 | LJ50: 1463174.1 | LK50: 1463174.1 | LL50: 1677420.6 | LM50: 1943856.6 | LN50: 1943856.6 | LO50: 1943856.6 | LP50: 1947478.5 | LQ50: 1951263.2 | LR50: 1949070.4 | LS50: 1949070.4 | LT50: 1949070.4 | LU50: 1913189.3 | LV50: 1886114.9 | LW50: 1883624.9 | LX50: 1879959.8 | LY50: 1877974.8 | LZ50: 1681502.6 | MA50: 2602929 | MB50: 2602929 | MC50: 2602929 | MD50: 2602929 | ME50: 2061319 | MF50: 2496003.3 | MG50: 2496003.3 | MH50: 2494003.3 | MI50: 2494003.3 | MJ50: 2492003.3 | MK50: 2492003.3 | ML50: 2492003.3 | MM50: 2492003.3 | MN50: 2492003.3 | MO50: 2492003.3 | MP50: 1435819.2 | MQ50: 1435819.2 | MR50: 2743816.7 | MS50: 2743816.7 | MT50: 2680423.7 | MU50: 2710207 | MV50: 2809564 | MW50: 2809564 | MX50: 2809564 | MY50: 2804564 | MZ50: 2872500.4 | NA50: 2857662.4 | NB50: 2815060.7 | NC50: 2815060.7 | ND50: 2815060.7 | NE50: 2810276.7 | NF50: 3190675.3 | NG50: 3190675.3 | NH50: 3182010.2 | NI50: 3177010.2 | NJ50: 3177010.2 | NK50: 3304265.2 | NL50: 3288475.7 | NM50: 3387309.7 | NN50: 3387309.7 | NO50: 3387309.7 | NP50: 3387309.7 | NQ50: 3373671.5 | NR50: 3369342.3 | NS50: 3356742.3 | NT50: 3356342.3 | NU50: 3356342.3 | NV50: 3487380.9 | NW50: 3471642.8 | NX50: 3471642.8 | NY50: 3460533.5 | NZ50: 3460533.5 | OA50: 3460533.5 | OB50: 3460133.5 | OC50: 3460133.5 | OD50: 3460133.5 | OE50: 3457529.2 | OF50: 3457529.2 | OG50: 3433202.9 | OH50: 3407674.3 | OI50: 3407674.3 | OJ50: 2221835.2 | OK50: 3097064 | OL50: 3097064 | OM50: 3097064 | ON50: 3097064 | OO50: 2453795.3 | OP50: 2739108.1 | OQ50: 2739108.1 | OR50: 2739108.1 | OS50: 2739008.1 | OT50: 2739008.1 | OU50: 2618559.2 | OV50: 2617246 | OW50: 2577376.7 | OX50: 2577376.7 | OY50: 2577376.7 | OZ50: 1138760.6 | PA50: 2520766.3 | PB50: 2520766.3 | PC50: 2516766.3 | PD50: 2368831.8 | PE50: 2350876.2 | PF50: 2350876.2 | PG50: 2342390.2 | PH50: 2329021.7 | PI50: 2302955.3 | PJ50: 2215107.6 | PK50: 2211607.6 | PL50: 2199307.4 | PM50: 2196822.7 | PN50: 2196822.7 | PO50: 1503706.3 | PP50: 2889771.2 | PQ50: 2836197.5 | PR50: 2836197.5 | PS50: 2836197.5 | PT50: 2417543.3 | PU50: 2417543.3 | PV50: 2417543.3 | PW50: 2368563.3 | PX50: 2347989.8 | PY50: 2329815.1 | PZ50: 2325890.9 | QA50: 2323890.9 | QB50: 2323890.9 | QC50: 2340169.7 | QD50: 2340169.7 | QE50: 1279315.6 | QF50: 2612440.5 | QG50: 2612440.5 | QH50: 2612440.5 | QI50: 2612440.5 | QJ50: 2612440.5 | QK50: 2609440.5 | QL50: 2600793 | QM50: 2592293 | QN50: 2478456.9 | QO50: 2478456.9 | QP50: 2476456.9 | QQ50: 2476456.9 | QR50: 3009986.5 | QS50: 3009986.5 | QT50: 1854055.6 | QU50: 1802752.9 | QV50: 1802752.9 | QW50: 1802752.9 | QX50: 1772752.9 | QY50: 1772752.9 | QZ50: 1772752.9 | RA50: 1772752.9 | RB50: 1621838.8 | RC50: 1621838.8 | RD50: 1597418.7 | RE50: 1597418.7 | RF50: 1597418.7 | RG50: 1597418.7 | RH50: 1901005 | RI50: 1780953.6 | RJ50: 731268.71 | RK50: 731268.71 | RL50: 731268.71 | RM50: 731268.71 | RN50: 731268.71 | RO50: 731268.71 | RP50: 731268.71 | RQ50: 731268.71 | RR50: 731268.71 | RS50: 709621.31 | RT50: 706121.31 | RU50: 706121.31 | RV50: 240619.53 | RW50: 900221.86 | RX50: 897221.86 | RY50: 897221.86 | RZ50: 871237.42 | SA50: 845372.93 | SB50: 826499.93 | SC50: 826499.93 | SD50: 826499.93 | SE50: 807742.14 | SF50: 807742.14 | SG50: 787742.14 | SH50: 755649.39 | SI50: 749652.75 | SJ50: 749652.75 | SK50: 749652.75 | SL50: 560114.41 | SM50: 1917913.3 | SN50: 1917913.3 | SO50: 1821393.9 | SP50: 1821393.9 | SQ50: 1821393.9 | SR50: 1816444.6 | SS50: 1816429.6 | ST50: 1786430.2 | SU50: 1786430.2 | SV50: 1777186.5 | SW50: 1777186.5 | SX50: 1772861.5 | SY50: 1766861.5 | SZ50: 1766861.5 | TA50: 2279967.5 | TB50: 2279967.5 | TC50: 2263920.3 | TD50: 2263920.3 | TE50: 2213208.2 | TF50: 2213208.2 | TG50: 2213208.2 | TH50: 2213208.2 | TI50: 2176118.3 | TJ50: 2176118.3 | TK50: 2176118.3 | TL50: 2176118.3 | TM50: 2202884.8 | TN50: 2174347.8 | TO50: 2173947.8 | TP50: 2172147.8 | TQ50: 2055012.5 | TR50: 2055012.5 | TS50: 2055012.5 | TT50: 2055012.5 | TU50: 2055012.5 | TV50: 2055012.5 | TW50: 2044532.6 | TX50: 2044532.6 | TY50: 2039490.7 | TZ50: 2039490.7 | UA50: 2039490.7 | UB50: 1996865.4 | UC50: 1981843.1 | UD50: 1981843.1 | UE50: 1132307.1 | UF50: 1922507.7 | UG50: 1922507.7 | UH50: 1887627.7 | UI50: 1825519.5 | UJ50: 1825519.5 | UK50: 582273.76 | UL50: 1786712.4 | UM50: 1786712.4 | UN50: 1786712.4 | UO50: 1750062.5 | UP50: 1739089.5 | UQ50: 1712991.2 | UR50: 1712991.2 | US50: 1710091.2 | UT50: 1710091.2 | UU50: 838745.16 | UV50: 914431.46 | UW50: 914431.46 | UX50: 914431.46 | UY50: 914431.46 | UZ50: 914431.46 | VA50: 914431.46 | VB50: 914431.46 | VC50: 914431.46 | VD50: 888493.88 | VE50: 888493.88 | VF50: 888493.88 | VG50: 876699.89 | VH50: 876699.89 | VI50: 883759.2 | VJ50: 1022852.2 | VK50: 574012.91 | VL50: 574012.91 | VM50: 574012.91 | VN50: 568804.89 | VO50: 568804.89 | VP50: 568804.89 | VQ50: 568804.89 | VR50: 568804.89 | VS50: 568804.89 | VT50: 568804.89 | VU50: 568804.89 | VV50: 561490.53 | VW50: 523798.31 | VX50: 521102.56 | VY50: 517257.55 | VZ50: 549148.27 | WA50: 503332.85 | WB50: 503332.85 | WC50: 499474.94 | WD50: 499474.94 | WE50: 499474.94 | WF50: 499474.94 | WG50: 499474.94 | WH50: 499474.94 | WI50: 499474.94 | WJ50: 499474.94 | WK50: 494474.94 | WL50: 481878.69 | WM50: 333636.5 | WN50: 182664.41 | WO50: 230245.79 | WP50: 230245.79 | WQ50: 230245.79 | WR50: 230245.79 | WS50: 230245.79 | WT50: 230245.79 | WU50: 230245.79 | WV50: 229217.39 | WW50: 229217.39 | WX50: 229217.39 | WY50: 229217.39 | WZ50: 229217.39 | XA50: 229217.39 | XB50: 229217.39 | XC50: 229217.39 | XD50: 113994.24 | XE50: 321498.83 | XF50: 301498.84 | XG50: 301498.84 | XH50: 301498.84 | XI50: 290959.78 | XJ50: 290959.78 | XK50: 290959.78 | XL50: 290959.78 | XM50: 290959.78 | XN50: 277984.78 | XO50: 277984.78 | XP50: 270554.01 | XQ50: 334949.09 | XR50: 334949.09 | XS50: 295709.65 | XT50: 499585.5 | XU50: 499585.5 | XV50: 499585.5 | XW50: 499585.5 | XX50: 499585.5 | XY50: 499585.5 | XZ50: 499585.5 | YA50: 499585.5 | YB50: 499585.5 | YC50: 499586 | YD50: 489585.5 | YE50: 488533.8 | YF50: 485434.75 | YG50: 485434.75 | YH50: 485434.75 | YI50: 301204.89 | YJ50: 711902.87 | YK50: 711902.87 | YL50: 711902.87 | YM50: 711902.87
B51: 61-89 days | JO51: 658035.01 | JP51: 658035.01 | JQ51: 749493.87 | JR51: 752993.87 | JS51: 752993.87 | JT51: 560258.56 | JU51: 560258.56 | JV51: 597768.47 | JW51: 600768.47 | JX51: 600768.47 | JY51: 600768.47 | JZ51: 600768.47 | KA51: 596645.47 | KB51: 596645.47 | KC51: 596645.47 | KD51: 596645.47 | KE51: 198053.89 | KF51: 198053.89 | KG51: 488663.89 | KH51: 499663.89 | KI51: 432955.77 | KK51: 584245.61 | KL51: 588245.61 | KM51: 588245.61 | KN51: 588245.61 | KO51: 588245.61 | KP51: 588245.61 | KQ51: 588245.61 | KR51: 586391.24 | KS51: 580137.24 | KT51: 489301.38 | KU51: 489301.38 | KV51: 938330.55 | KW51: 942330.55 | KX51: 942330.55 | KY51: 896237.64 | KZ51: 896237.64 | LA51: 957089.5 | LB51: 959089.5 | LC51: 959089.5 | LD51: 959089.5 | LE51: 959089.5 | LF51: 959089.5 | LG51: 929784.27 | LH51: 929784.27 | LI51: 918899.81 | LJ51: 634065.56 | LK51: 634065.56 | LL51: 1293237.9 | LM51: 1305237.9 | LN51: 1158056.4 | LO51: 1158056.4 | LP51: 1205683.8 | LQ51: 1205683.8 | LR51: 1205683.8 | LS51: 1205683.8 | LT51: 1205683.8 | LU51: 1196520.8 | LV51: 1196520.8 | LW51: 1196520.8 | LX51: 1184214.9 | LY51: 769828.06 | LZ51: 966300.27 | MA51: 970300.27 | MB51: 970300.27 | MC51: 970300.27 | MD51: 907448.41 | ME51: 1449058.4 | MF51: 1456058.4 | MG51: 1451058.4 | MH51: 1451058.4 | MI51: 1446058.4 | MJ51: 1439256.4 | MK51: 1439256.4 | ML51: 1439256.4 | MM51: 1439256.4 | MN51: 1427808.6 | MO51: 757473.8 | MP51: 1796657.9 | MQ51: 1804172 | MR51: 1804172 | MS51: 1762530.6 | MT51: 1817564.5 | MU51: 1786588.4 | MV51: 1786588.4 | MW51: 1786588.4 | MX51: 1786588.4 | MY51: 1786588.4 | MZ51: 1694263.4 | NA51: 1691154 | NB51: 1683823.8 | NC51: 1500280.1 | ND51: 1494280.1 | NE51: 1494280.1 | NF51: 2341146.5 | NG51: 2341146.5 | NH51: 1861429.1 | NI51: 1858766.7 | NJ51: 1846066.7 | NK51: 2380461.6 | NL51: 2380461.6 | NM51: 2263627.6 | NN51: 2263627.6 | NO51: 2269032.6 | NP51: 2259132.6 | NQ51: 2259132.6 | NR51: 2259132.6 | NS51: 1399284.2 | NT51: 1399284.2 | NU51: 1399284.2 | NV51: 2842773.9 | NW51: 2773380.9 | NX51: 2773380.9 | NY51: 2863176.2 | NZ51: 2867561.9 | OA51: 2867561.9 | OB51: 2867561.9 | OC51: 2867561.9 | OD51: 2849096.8 | OE51: 2868690.7 | OF51: 2860425.7 | OG51: 2824665 | OH51: 2824665 | OI51: 2014883.1 | OJ51: 3199722.1 | OK51: 3207722.1 | OL51: 3207722.1 | OM51: 3207722.1 | ON51: 2685492.3 | OO51: 3324086.5 | OP51: 3324086.5 | OQ51: 3314038.2 | OR51: 3314038.2 | OS51: 3337830.1 | OT51: 3337330.1 | OU51: 3323330.1 | OV51: 3302535.1 | OW51: 3300535.1 | OX51: 3300535.1 | OY51: 1889115.6 | OZ51: 3321583.7 | PA51: 3346583.7 | PB51: 3346583.7 | PC51: 3264350 | PD51: 3412284.5 | PE51: 3412284.5 | PF51: 3412284.5 | PG51: 3412284.5 | PH51: 3404839.5 | PI51: 3400087.3 | PJ51: 3401447.3 | PK51: 3401447.3 | PL51: 2235005.5 | PM51: 2226505.5 | PN51: 2226505.5 | PO51: 2919621.9 | PP51: 2919621.9 | PQ51: 2919621.9 | PR51: 2276513.9 | PS51: 2276513.9 | PT51: 2623642.4 | PU51: 2623642.4 | PV51: 2623642.4 | PW51: 2610450 | PX51: 2610450 | PY51: 2582793.2 | PZ51: 2579672.3 | QA51: 2579672.3 | QB51: 2579672.3 | QC51: 1164522.5 | QD51: 1164522.5 | QE51: 2221376.6 | QF51: 2221376.6 | QG51: 2073442.1 | QH51: 2073442.1 | QI51: 2070893 | QJ51: 2067393 | QK51: 2067393 | QL51: 2067393 | QM51: 2056290.2 | QN51: 2022932.4 | QO51: 2012679.6 | QP51: 2012679.6 | QQ51: 1986216.7 | QR51: 1333827.8 | QS51: 1333827.8 | QT51: 2489758.7 | QU51: 2489758.7 | QV51: 2489758.7 | QW51: 2187566.9 | QX51: 2187566.9 | QY51: 2153851 | QZ51: 2153851 | RA51: 2087325.2 | RB51: 2087325.2 | RC51: 2109293.2 | RD51: 2064923.9 | RE51: 2064923.9 | RF51: 2064923.9 | RG51: 2064923.9 | RH51: 1094335.1 | RI51: 1074335.1 | RJ51: 2117179.1 | RK51: 2117179.1 | RL51: 2117179.1 | RM51: 2117179.1 | RN51: 2106563.3 | RO51: 2106563.3 | RP51: 2106563.3 | RQ51: 2106563.3 | RR51: 2106563.3 | RS51: 2085741.7 | RT51: 2072457.9 | RU51: 2072457.9 | RV51: 2580959.7 | RW51: 1431401.9 | RX51: 1431401.9 | RY51: 1431401.9 | RZ51: 1431401.9 | SA51: 1431401.9 | SB51: 1431401.9 | SC51: 1431401.9 | SD51: 1431401.9 | SE51: 1384808.1 | SF51: 1384808.1 | SG51: 1384808.1 | SH51: 1388319.8 | SI51: 1388319.8 | SJ51: 1388319.8 | SK51: 1393553.5 | SL51: 1622297.1 | SM51: 662531.82 | SN51: 662531.82 | SO51: 662531.82 | SP51: 662531.82 | SQ51: 662531.82 | SR51: 662531.82 | SS51: 662531.82 | ST51: 662531.82 | SU51: 662531.82 | SV51: 662531.82 | SW51: 662531.82 | SX51: 662531.82 | SY51: 314951.03 | SZ51: 304669.21 | TA51: 814122.61 | TB51: 814122.61 | TC51: 814122.61 | TD51: 814122.61 | TE51: 814122.61 | TF51: 814122.61 | TG51: 814122.61 | TH51: 814122.61 | TI51: 814122.61 | TJ51: 814122.61 | TK51: 814122.61 | TL51: 814122.61 | TM51: 780736.23 | TN51: 780736.23 | TO51: 605731.51 | TP51: 605731.51 | TQ51: 1724075.4 | TR51: 1724075.4 | TS51: 1724075.4 | TT51: 1724075.4 | TU51: 1724075.4 | TV51: 1724075.4 | TW51: 1724075.4 | TX51: 1724075.4 | TY51: 1724075.4 | TZ51: 1724075.4 | UA51: 1724075.4 | UB51: 1707617.1 | UC51: 1724605 | UD51: 1211870.6 | UE51: 2055987.5 | UF51: 2055987.5 | UG51: 2055987.5 | UH51: 2046407.8 | UI51: 2043737.8 | UJ51: 2038737.8 | UK51: 2038737.8 | UL51: 2038737.8 | UM51: 2038737.8 | UN51: 2038737.8 | UO51: 2064663.3 | UP51: 2072636.3 | UQ51: 2098734.6 | UR51: 2098734.6 | US51: 2095957.7 | UT51: 996374.88 | UU51: 1918506.7 | UV51: 1918506.7 | UW51: 1918506.7 | UX51: 1918506.7 | UY51: 1918506.7 | UZ51: 1918506.7 | VA51: 1918506.7 | VB51: 1918506.7 | VC51: 1918506.7 | VD51: 1944444.3 | VE51: 1944444.3 | VF51: 1944444.3 | VG51: 1931162.4 | VH51: 1914170.7 | VI51: 1095942.3 | VJ51: 1095942.3 | VK51: 1752660.6 | VL51: 1752660.6 | VM51: 1752660.6 | VN51: 1752660.6 | VO51: 1752574.5 | VP51: 1752574.5 | VQ51: 1752574.5 | VR51: 1721501.3 | VS51: 1686302.4 | VT51: 1660033.1 | VU51: 1660033.1 | VV51: 1659733.1 | VW51: 1690758.7 | VX51: 779512.02 | VY51: 779512.02 | VZ51: 931001.29 | WA51: 976816.71 | WB51: 976816.71 | WC51: 976816.71 | WD51: 976816.71 | WE51: 976816.71 | WF51: 976816.71 | WG51: 949801.32 | WH51: 949801.32 | WI51: 949801.32 | WJ51: 880146.02 | WK51: 880146.02 | WL51: 879460.45 | WM51: 436983.4 | WN51: 587955.49 | WO51: 661921.01 | WP51: 661921.01 | WQ51: 661921.01 | WR51: 661921.01 | WS51: 661921.01 | WT51: 661921.01 | WU51: 661921.01 | WV51: 661921.01 | WW51: 661921.01 | WX51: 661921.01 | WY51: 661921.01 | WZ51: 629799.28 | XA51: 629799.28 | XB51: 629799.28 | XC51: 478391.01 | XD51: 547798.74 | XE51: 609131.73 | XF51: 604354.04 | XG51: 604354.04 | XH51: 604354.04 | XI51: 604354.04 | XJ51: 604354.04 | XK51: 604354.04 | XL51: 604354.04 | XM51: 604354.04 | XN51: 617329.04 | XO51: 599483.92 | XP51: 446438.78 | XQ51: 219942.45 | XR51: 219942.45 | XS51: 289021.22 | XT51: 289021.22 | XU51: 274793.1 | XV51: 274793.1 | XW51: 274793.1 | XX51: 274793.1 | XY51: 274793.1 | XZ51: 274793.1 | YA51: 274793.1 | YB51: 274793.1 | YC51: 274793 | YD51: 274793.1 | YE51: 274793.1 | YF51: 274793.1 | YG51: 108336.42 | YH51: 108336.42 | YI51: 292566.28 | YJ51: 384230.4 | YK51: 384230.4 | YL51: 384230.4 | YM51: 384230.4
B52: 90-120 days | JO52: 595623.85 | JP52: 384377.57 | JQ52: 384377.57 | JR52: 398377.57 | JS52: 398377.57 | JT52: 591112.88 | JU52: 526233.3 | JV52: 526233.3 | JW52: 529233.3 | JX52: 529233.3 | JY52: 529233.3 | JZ52: 529233.3 | KA52: 529233.3 | KB52: 529233.3 | KC52: 526733.3 | KD52: 523900.79 | KE52: 921492.37 | KF52: 667120.12 | KG52: 667120.12 | KH52: 673120.12 | KI52: 739828.24 | KK52: 739828.24 | KL52: 750828.24 | KM52: 750828.24 | KN52: 750828.24 | KO52: 750828.24 | KP52: 750828.24 | KQ52: 750828.24 | KR52: 750828.24 | KS52: 738266.35 | KT52: 687235.16 | KU52: 687235.16 | KV52: 687235.16 | KW52: 691235.16 | KX52: 691235.16 | KY52: 605083.58 | KZ52: 605083.58 | LA52: 605083.58 | LB52: 608083.58 | LC52: 608083.58 | LD52: 608083.58 | LE52: 608083.58 | LF52: 608083.58 | LG52: 608083.58 | LH52: 608083.58 | LI52: 602467.58 | LJ52: 495272.14 | LK52: 495272.14 | LL52: 495272.14 | LM52: 505272.14 | LN52: 574745.49 | LO52: 574745.49 | LP52: 574745.49 | LQ52: 575745.49 | LR52: 575745.49 | LS52: 557750.26 | LT52: 557750.26 | LU52: 557750.26 | LV52: 547596.26 | LW52: 547596.26 | LX52: 545741.89 | LY52: 888904.1 | LZ52: 888904.1 | MA52: 892904.1 | MB52: 892904.1 | MC52: 892904.1 | MD52: 912246.05 | ME52: 887331.23 | MF52: 889331.23 | MG52: 889331.23 | MH52: 889331.23 | MI52: 889331.23 | MJ52: 886694.23 | MK52: 886694.23 | ML52: 886694.23 | MM52: 886694.23 | MN52: 886694.23 | MO52: 1285109.6 | MP52: 1278890.6 | MQ52: 1276780.6 | MR52: 1276780.6 | MS52: 1179248.9 | MT52: 1179248.9 | MU52: 1182248.9 | MV52: 1182248.9 | MW52: 1175029.9 | MX52: 1175029.9 | MY52: 1175029.9 | MZ52: 1175029.9 | NA52: 1175029.9 | NB52: 1165384.5 | NC52: 1348928.2 | ND52: 953273.17 | NE52: 953273.17 | NF52: 956273.17 | NG52: 956273.17 | NH52: 1435990.5 | NI52: 1435990.5 | NJ52: 1371138.6 | NK52: 1371228.9 | NL52: 1371228.9 | NM52: 1371228.9 | NN52: 1371228.9 | NO52: 1364021.9 | NP52: 1364021.9 | NQ52: 1364021.9 | NR52: 1360409.5 | NS52: 2173382.9 | NT52: 1509821.4 | NU52: 1509821.4 | NV52: 1525821.4 | NW52: 1585214.4 | NX52: 1540573.1 | NY52: 1540573.1 | NZ52: 1533994.6 | OA52: 1533994.6 | OB52: 1533994.6 | OC52: 1533994.6 | OD52: 1522094.2 | OE52: 1494140.3 | OF52: 1494140.3 | OG52: 1454031 | OH52: 1283885.1 | OI52: 2093667.1 | OJ52: 2093667.1 | OK52: 2105348.8 | OL52: 2098717.4 | OM52: 1648244.8 | ON52: 2170474.6 | OO52: 2170474.6 | OP52: 2170474.6 | OQ52: 2170474.6 | OR52: 2170474.6 | OS52: 2118368.6 | OT52: 2118368.6 | OU52: 2116566.6 | OV52: 2116566.6 | OW52: 2116566.6 | OX52: 1371878.5 | OY52: 2765821.6 | OZ52: 2765821.6 | PA52: 2784821.6 | PB52: 2712428.6 | PC52: 2794662.3 | PD52: 2794662.3 | PE52: 2794662.3 | PF52: 2794662.3 | PG52: 2788662.3 | PH52: 2786469.5 | PI52: 2774331.6 | PJ52: 2732397.2 | PK52: 2713932.1 | PL52: 3880373.9 | PM52: 3881373.9 | PN52: 3066905.1 | PO52: 3066905.1 | PP52: 3066905.1 | PQ52: 3066905.1 | PR52: 3710013.1 | PS52: 3220189.2 | PT52: 3216935.8 | PU52: 3216935.8 | PV52: 3216935.8 | PW52: 3214102.7 | PX52: 3214102.7 | PY52: 3185418.6 | PZ52: 3159859.5 | QA52: 3157200.3 | QB52: 3157200.3 | QC52: 4574850.1 | QD52: 3238531.5 | QE52: 3238531.5 | QF52: 3238531.5 | QG52: 3385466 | QH52: 3312794 | QI52: 3312794 | QJ52: 3312794 | QK52: 3300807 | QL52: 3300607 | QM52: 3300607 | QN52: 3293859.8 | QO52: 3281034.8 | QP52: 3281034.8 | QQ52: 3278430.5 | QR52: 2798675 | QS52: 2798675 | QT52: 2798675 | QU52: 2798675 | QV52: 2798675 | QW52: 2511105.9 | QX52: 2511105.9 | QY52: 2531202.5 | QZ52: 2531202.5 | RA52: 2531202.5 | RB52: 2531202.5 | RC52: 2480452.7 | RD52: 2444570.5 | RE52: 2444570.5 | RF52: 2444570.5 | RG52: 2444570.5 | RH52: 2075813.6 | RI52: 2075813.6 | RJ52: 2075813.6 | RK52: 2075813.6 | RL52: 1923879.1 | RM52: 1921220 | RN52: 1921220 | RO52: 1921220 | RP52: 1921220 | RQ52: 1912734 | RR52: 1910117.1 | RS52: 1885064.3 | RT52: 1885064.3 | RU52: 1885064.3 | RV52: 1904064.3 | RW52: 2337112.3 | RX52: 2337112.3 | RY52: 2336112.3 | RZ52: 2336112.3 | SA52: 2336112.3 | SB52: 2048875.9 | SC52: 2048875.9 | SD52: 2048875.9 | SE52: 2042977.1 | SF52: 2042977.1 | SG52: 2036977.1 | SH52: 2009348.5 | SI52: 2009348.5 | SJ52: 2009348.5 | SK52: 2001497.9 | SL52: 2015497.9 | SM52: 2011618.7 | SN52: 2011618.7 | SO52: 2005001.5 | SP52: 2005001.5 | SQ52: 2005001.5 | SR52: 1994385.6 | SS52: 1927859.8 | ST52: 1926859.8 | SU52: 1926859.8 | SV52: 1926409.8 | SW52: 1907725.2 | SX52: 1907725.2 | SY52: 2238366.8 | SZ52: 2238366.8 | TA52: 2270366.8 | TB52: 1378343.2 | TC52: 1378343.2 | TD52: 1378343.2 | TE52: 1378343.2 | TF52: 1378343.2 | TG52: 1378343.2 | TH52: 1377814.2 | TI52: 1377814.2 | TJ52: 1349079.1 | TK52: 1349079.1 | TL52: 1349079.1 | TM52: 1345764.1 | TN52: 1326620 | TO52: 1501624.7 | TP52: 1499007.8 | TQ52: 1501307.8 | TR52: 624733.39 | TS52: 624733.39 | TT52: 624733.39 | TU52: 615498.99 | TV52: 615498.99 | TW52: 615498.99 | TX52: 604883.11 | TY52: 604883.11 | TZ52: 602068.92 | UA52: 592091.95 | UB52: 589635.04 | UC52: 564647.19 | UD52: 735739.97 | UE52: 743111.58 | UF52: 743111.58 | UG52: 743111.58 | UH52: 844592.05 | UI52: 844592.05 | UJ52: 844592.05 | UK52: 844592.05 | UL52: 844592.05 | UM52: 844592.05 | UN52: 844592.05 | UO52: 837114.59 | UP52: 837114.59 | UQ52: 823951.36 | UR52: 823951.36 | US52: 823951.36 | UT52: 1641249 | UU52: 1667487.6 | UV52: 1667487.6 | UW52: 1667487.6 | UX52: 1667487.6 | UY52: 1667487.6 | UZ52: 1667487.6 | VA52: 1667487.6 | VB52: 1667487.6 | VC52: 1656871.7 | VD52: 1656871.7 | VE52: 1656871.7 | VF52: 1656871.7 | VG52: 1656871.7 | VH52: 1656871.7 | VI52: 2473100.1 | VJ52: 1947365.7 | VK52: 1969821 | VL52: 1969821 | VM52: 1969821 | VN52: 1959205.1 | VO52: 1959205.1 | VP52: 1959205.1 | VQ52: 1959205.1 | VR52: 1990278.3 | VS52: 2019272 | VT52: 2045541.4 | VU52: 2045541.4 | VV52: 2045541.4 | VW52: 2045541.4 | VX52: 2956788 | VY52: 1836266.6 | VZ52: 1892036.3 | WA52: 1892036.3 | WB52: 1838834.4 | WC52: 1838834.4 | WD52: 1838834.4 | WE52: 1838834.4 | WF52: 1838834.4 | WG52: 1865849.8 | WH52: 1865849.8 | WI52: 1865849.8 | WJ52: 1865849.8 | WK52: 1865849.8 | WL52: 1865849.8 | WM52: 1611561.4 | WN52: 1611561.4 | WO52: 1645797.1 | WP52: 1645797.1 | WQ52: 1645797.1 | WR52: 1645797.1 | WS52: 1645797.1 | WT52: 1645797.1 | WU52: 1645797.1 | WV52: 1645797.1 | WW52: 1613544.1 | WX52: 1582430 | WY52: 1582430 | WZ52: 1614551.7 | XA52: 1614551.7 | XB52: 1614551.7 | XC52: 828496.63 | XD52: 874312.05 | XE52: 924266.31 | XF52: 924266.31 | XG52: 924266.31 | XH52: 924266.31 | XI52: 924266.31 | XJ52: 924266.31 | XK52: 924266.31 | XL52: 896094.97 | XM52: 896094.97 | XN52: 896094.97 | XO52: 913940.09 | XP52: 1060885.2 | XQ52: 1280199.7 | XR52: 663404.45 | XS52: 734281.42 | XT52: 734281.42 | XU52: 748509.54 | XV52: 748509.54 | XW52: 748509.54 | XX52: 748509.54 | XY52: 748509.54 | XZ52: 748509.54 | YA52: 748509.54 | YB52: 748509.54 | YC52: 748510 | YD52: 748509.54 | YE52: 715198.99 | YF52: 715198.99 | YG52: 881655.67 | YH52: 683254.25 | YI52: 634477.72 | YJ52: 692445.52 | YK52: 692445.52 | YL52: 692445.52 | YM52: 692445.52
B53: 121-150 days | JO53: 196375.63 | JP53: 407621.91 | JQ53: 407621.91 | JR53: 407621.91 | JS53: 407621.91 | JT53: 382622.64 | JU53: 447502.22 | JV53: 447502.22 | JW53: 447502.22 | JX53: 447502.22 | JY53: 447502.22 | JZ53: 447502.22 | KA53: 447502.22 | KB53: 447502.22 | KC53: 447502.22 | KD53: 447502.22 | KE53: 378958.07 | KF53: 565256.5 | KG53: 565256.5 | KH53: 565256.5 | KI53: 462424.29 | KK53: 462424.29 | KL53: 462424.29 | KM53: 462424.29 | KN53: 462424.29 | KO53: 462424.29 | KP53: 462424.29 | KQ53: 462424.29 | KR53: 461174.29 | KS53: 451507.99 | KT53: 391795.06 | KU53: 391795.06 | KV53: 391795.06 | KW53: 396795.06 | KX53: 396795.06 | KY53: 458576.97 | KZ53: 458576.97 | LA53: 458576.97 | LB53: 461576.97 | LC53: 461576.97 | LD53: 461576.97 | LE53: 461576.97 | LF53: 461576.97 | LG53: 456576.97 | LH53: 452733.97 | LI53: 414041.1 | LJ53: 658382.72 | LK53: 658382.72 | LL53: 656382.72 | LM53: 664382.72 | LN53: 742090.84 | LO53: 742090.84 | LP53: 742090.84 | LQ53: 743090.84 | LR53: 743090.84 | LS53: 743090.84 | LT53: 743090.84 | LU53: 743090.84 | LV53: 743090.84 | LW53: 743090.84 | LX53: 600056.3 | LY53: 671280.93 | LZ53: 671280.93 | MA53: 674280.93 | MB53: 674280.93 | MC53: 552962.44 | MD53: 596472.35 | ME53: 596472.35 | MF53: 596472.35 | MG53: 596472.35 | MH53: 596472.35 | MI53: 596472.35 | MJ53: 596472.35 | MK53: 596472.35 | ML53: 590856.35 | MM53: 590856.35 | MN53: 590856.35 | MO53: 457746.09 | MP53: 457746.09 | MQ53: 466746.09 | MR53: 388037.97 | MS53: 525957.07 | MT53: 525957.07 | MU53: 530957.07 | MV53: 530957.07 | MW53: 530957.07 | MX53: 530957.07 | MY53: 530957.07 | MZ53: 530957.07 | NA53: 530957.07 | NB53: 529102.07 | NC53: 460493.44 | ND53: 856148.44 | NE53: 856148.44 | NF53: 861148.44 | NG53: 861148.44 | NH53: 817638.53 | NI53: 817638.53 | NJ53: 882490.39 | NK53: 884490.39 | NL53: 884490.39 | NM53: 884490.39 | NN53: 884490.39 | NO53: 884490.39 | NP53: 881853.39 | NQ53: 881853.39 | NR53: 876218.3 | NS53: 604617.2 | NT53: 1261353.5 | NU53: 1261353.5 | NV53: 1273353.5 | NW53: 1132289.4 | NX53: 1176930.8 | NY53: 1176930.8 | NZ53: 1176930.8 | OA53: 1176930.8 | OB53: 1176930.8 | OC53: 1176930.8 | OD53: 1176930.8 | OE53: 1176930.8 | OF53: 1176930.8 | OG53: 1177435.2 | OH53: 950879.85 | OI53: 950879.85 | OJ53: 950879.85 | OK53: 953267.48 | OL53: 946330.48 | OM53: 1329951.2 | ON53: 1329951.2 | OO53: 1329951.2 | OP53: 1329951.2 | OQ53: 1329951.2 | OR53: 1329951.2 | OS53: 1329951.2 | OT53: 1327951.2 | OU53: 1327951.2 | OV53: 1327951.2 | OW53: 1302727.3 | OX53: 1384291.1 | OY53: 1384291.1 | OZ53: 1384291.1 | PA53: 1374836.2 | PB53: 1397083.4 | PC53: 1397083.4 | PD53: 1397083.4 | PE53: 1392328.4 | PF53: 1392328.4 | PG53: 1392328.4 | PH53: 1392328.4 | PI53: 1392328.4 | PJ53: 1389219.1 | PK53: 1389219.1 | PL53: 1223298 | PM53: 1223298 | PN53: 2035104.4 | PO53: 2035104.4 | PP53: 2035104.4 | PQ53: 1608677.8 | PR53: 1608677.8 | PS53: 2098501.7 | PT53: 2089441.8 | PU53: 2072074.4 | PV53: 2065192.8 | PW53: 2065192.8 | PX53: 2065192.8 | PY53: 2065192.8 | PZ53: 2065192.8 | QA53: 2065192.8 | QB53: 2065192.8 | QC53: 1360744.2 | QD53: 2689617.8 | QE53: 2689617.8 | QF53: 2689617.8 | QG53: 2617224.8 | QH53: 2689896.8 | QI53: 2689896.8 | QJ53: 2689896.8 | QK53: 2687704 | QL53: 2687704 | QM53: 2643974 | QN53: 2634412.3 | QO53: 2623254 | QP53: 2623254 | QQ53: 2623254 | QR53: 2967022.5 | QS53: 2967022.5 | QT53: 2967022.5 | QU53: 2967022.5 | QV53: 2959746.6 | QW53: 3073677.8 | QX53: 3073677.8 | QY53: 3043532.9 | QZ53: 3043532.9 | RA53: 3043532.9 | RB53: 3043532.9 | RC53: 3042532.9 | RD53: 3019115.9 | RE53: 3009215.9 | RF53: 3009215.9 | RG53: 3009215.9 | RH53: 3165576.3 | RI53: 3165576.3 | RJ53: 3164576.3 | RK53: 3164576.3 | RL53: 3256411.3 | RM53: 3248966.3 | RN53: 3248966.3 | RO53: 3248966.3 | RP53: 3248966.3 | RQ53: 3248966.3 | RR53: 3254890 | RS53: 3244057.8 | RT53: 3239210.3 | RU53: 3239210.3 | RV53: 2129197.7 | RW53: 2768707.5 | RX53: 2768707.5 | RY53: 2768707.5 | RZ53: 2768707.5 | SA53: 2199921.2 | SB53: 2487157.6 | SC53: 2477109.3 | SD53: 2477109.3 | SE53: 2472109.3 | SF53: 2472109.3 | SG53: 2462109.3 | SH53: 2430695.3 | SI53: 2430695.3 | SJ53: 2418835.1 | SK53: 2416415.1 | SL53: 1047474.3 | SM53: 2011118.8 | SN53: 2002632.8 | SO53: 1994147.1 | SP53: 1838212.6 | SQ53: 1838212.6 | SR53: 1838212.6 | SS53: 1838212.6 | ST53: 1820219.6 | SU53: 1820251.8 | SV53: 1820251.8 | SW53: 1809377 | SX53: 1809377 | SY53: 1814224.5 | SZ53: 1814224.5 | TA53: 1204730.2 | TB53: 2096753.9 | TC53: 2096753.9 | TD53: 2096753.9 | TE53: 2096753.9 | TF53: 1872352.3 | TG53: 1872352.3 | TH53: 1862304 | TI53: 1862304 | TJ53: 1862304 | TK53: 1852304 | TL53: 1852304 | TM53: 1836591.4 | TN53: 1836591.4 | TO53: 1836591.4 | TP53: 1836591.4 | TQ53: 1042612.9 | TR53: 1919187.3 | TS53: 1919187.3 | TT53: 1919187.3 | TU53: 1919187.3 | TV53: 1918187.3 | TW53: 1918187.3 | TX53: 1918187.3 | TY53: 1917987.3 | TZ53: 1917987.3 | UA53: 1927964.3 | UB53: 1913116.8 | UC53: 1913116.8 | UD53: 2254758.4 | UE53: 2287758.4 | UF53: 1394734.7 | UG53: 1394734.7 | UH53: 1233254.2 | UI53: 1233254.2 | UJ53: 1233254.2 | UK53: 1233254.2 | UL53: 1233254.2 | UM53: 1233254.2 | UN53: 1233254.2 | UO53: 1233254.2 | UP53: 1133331.4 | UQ53: 1132570.4 | UR53: 1132570.4 | US53: 1132570.4 | UT53: 1409555.6 | UU53: 1438883.8 | UV53: 613268.24 | UW53: 613268.24 | UX53: 600210.63 | UY53: 600210.63 | UZ53: 600210.63 | VA53: 600210.63 | VB53: 600210.63 | VC53: 600210.63 | VD53: 600210.63 | VE53: 590233.66 | VF53: 590233.66 | VG53: 590233.66 | VH53: 590233.66 | VI53: 237592.04 | VJ53: 763326.44 | VK53: 777903.65 | VL53: 777903.65 | VM53: 777903.65 | VN53: 777903.65 | VO53: 777903.65 | VP53: 777903.65 | VQ53: 777903.65 | VR53: 777903.65 | VS53: 777903.65 | VT53: 777903.65 | VU53: 763700.93 | VV53: 753700.93 | VW53: 749776.71 | VX53: 568281.98 | VY53: 1688803.4 | VZ53: 1718141.8 | WA53: 1718141.8 | WB53: 1718141.8 | WC53: 1718141.8 | WD53: 1718141.8 | WE53: 1718141.8 | WF53: 1718141.8 | WG53: 1718141.8 | WH53: 1718141.8 | WI53: 1718141.8 | WJ53: 1718141.8 | WK53: 1718141.8 | WL53: 1718141.8 | WM53: 2016513.9 | WN53: 2016513.9 | WO53: 2041392 | WP53: 2041392 | WQ53: 2041392 | WR53: 2025194.3 | WS53: 2025194.3 | WT53: 2025194.3 | WU53: 2025194.3 | WV53: 2025194.3 | WW53: 2061466.2 | WX53: 2092580.4 | WY53: 2092580.4 | WZ53: 2092080.4 | XA53: 2092080.4 | XB53: 2092080.4 | XC53: 1880183.9 | XD53: 1880183.9 | XE53: 1934270.3 | XF53: 1934270.3 | XG53: 1934270.3 | XH53: 1934270.3 | XI53: 1934270.3 | XJ53: 1934270.3 | XK53: 1934270.3 | XL53: 1962441.6 | XM53: 1962441.6 | XN53: 1962441.6 | XO53: 1955598.5 | XP53: 1955598.5 | XQ53: 1092036.7 | XR53: 1708832 | XS53: 1744068.6 | XT53: 1744068.6 | XU53: 1744068.6 | XV53: 1744068.6 | XW53: 1744068.6 | XX53: 1744068.6 | XY53: 1744068.6 | XZ53: 1744068.6 | YA53: 1710498.8 | YB53: 1677176.4 | YC53: 1677176 | YD53: 1677176.4 | YE53: 1710486.9 | YF53: 1710486.9 | YG53: 724209 | YH53: 922610.42 | YI53: 971386.95 | YJ53: 1019470.2 | YK53: 1019470.2 | YL53: 1019470.2 | YM53: 1019470.2
B54: 151-180 days | JO54: 231773.37 | JP54: 231773.37 | JQ54: 231773.37 | JR54: 231773.37 | JS54: 231773.37 | JT54: 256772.64 | JU54: 256772.64 | JV54: 256772.64 | JW54: 256772.64 | JX54: 256772.64 | JY54: 256772.64 | JZ54: 256772.64 | KA54: 256772.64 | KB54: 256772.64 | KC54: 256772.64 | KD54: 245243.37 | KE54: 289023.76 | KF54: 274023.76 | KG54: 274023.76 | KH54: 274023.76 | KI54: 301878.54 | KK54: 301878.54 | KL54: 301878.54 | KM54: 301878.54 | KN54: 301878.54 | KO54: 301878.54 | KP54: 301878.54 | KQ54: 301878.54 | KR54: 301878.54 | KS54: 196375.63 | KT54: 397955.61 | KU54: 397955.61 | KV54: 397955.61 | KW54: 400955.61 | KX54: 375956.34 | KY54: 440835.92 | KZ54: 440835.92 | LA54: 440835.92 | LB54: 441835.92 | LC54: 441835.92 | LD54: 441835.92 | LE54: 441835.92 | LF54: 441835.92 | LG54: 441835.92 | LH54: 441835.92 | LI54: 373291.77 | LJ54: 520979.84 | LK54: 520979.84 | LL54: 520979.84 | LM54: 438732.81 | LN54: 438732.81 | LO54: 438482.81 | LP54: 438482.81 | LQ54: 438482.81 | LR54: 438482.81 | LS54: 438482.81 | LT54: 438482.81 | LU54: 438482.81 | LV54: 437232.81 | LW54: 432066.53 | LX54: 375687.37 | LY54: 375687.37 | LZ54: 375687.37 | MA54: 379687.37 | MB54: 379687.37 | MC54: 435126.28 | MD54: 435126.28 | ME54: 435126.28 | MF54: 439126.28 | MG54: 439126.28 | MH54: 437626.28 | MI54: 437626.28 | MJ54: 436126.28 | MK54: 436126.28 | ML54: 435526.28 | MM54: 435526.28 | MN54: 435526.28 | MO54: 672382.72 | MP54: 672382.72 | MQ54: 682282.72 | MR54: 760990.84 | MS54: 760990.84 | MT54: 760990.84 | MU54: 771990.84 | MV54: 771990.84 | MW54: 771990.84 | MX54: 771990.84 | MY54: 771990.84 | MZ54: 769090.84 | NA54: 769080.84 | NB54: 622046.3 | NC54: 690654.93 | ND54: 690654.93 | NE54: 690654.93 | NF54: 693654.93 | NG54: 568336.44 | NH54: 611846.35 | NI54: 611846.35 | NJ54: 611846.35 | NK54: 614846.35 | NL54: 614846.35 | NM54: 614846.35 | NN54: 614846.35 | NO54: 609230.35 | NP54: 609230.35 | NQ54: 609230.35 | NR54: 210708.17 | NS54: 482309.27 | NT54: 482309.27 | NU54: 482309.27 | NV54: 398282.82 | NW54: 539346.92 | NX54: 539346.92 | NY54: 539346.92 | NZ54: 539346.92 | OA54: 539346.92 | OB54: 539346.92 | OC54: 539346.92 | OD54: 539346.92 | OE54: 539346.92 | OF54: 539346.92 | OG54: 460098.3 | OH54: 854944.54 | OI54: 854944.54 | OJ54: 849124.71 | OK54: 855808.54 | OL54: 809298.63 | OM54: 876150.49 | ON54: 876150.49 | OO54: 876150.49 | OP54: 876150.49 | OQ54: 876150.49 | OR54: 876150.49 | OS54: 876150.49 | OT54: 876150.49 | OU54: 873514.14 | OV54: 873514.14 | OW54: 600520.83 | OX54: 1259320.1 | OY54: 1259320.1 | OZ54: 1259320.1 | PA54: 1136868.5 | PB54: 1187014.4 | PC54: 1187014.4 | PD54: 1187014.4 | PE54: 1187014.4 | PF54: 1187014.4 | PG54: 1187014.4 | PH54: 1187014.4 | PI54: 1179940.5 | PJ54: 1177306.8 | PK54: 1175976.5 | PL54: 954132.85 | PM54: 954132.85 | PN54: 954132.85 | PO54: 954132.85 | PP54: 954132.85 | PQ54: 1311707.5 | PR54: 1311707.5 | PS54: 1311707.5 | PT54: 1311707.5 | PU54: 1311707.5 | PV54: 1311707.5 | PW54: 1309095.2 | PX54: 1309095.2 | PY54: 1303460.1 | PZ54: 1297460.1 | QA54: 1297460.1 | QB54: 1297460.1 | QC54: 1337440.7 | QD54: 1337440.7 | QE54: 1337440.7 | QF54: 1337440.7 | QG54: 1360941.8 | QH54: 1360941.8 | QI54: 1357832.5 | QJ54: 1357832.5 | QK54: 1349876.3 | QL54: 1349876.3 | QM54: 1349876.3 | QN54: 1349876.3 | QO54: 1348876.3 | QP54: 1348876.3 | QQ54: 1186567.5 | QR54: 2012843.5 | QS54: 2012843.5 | QT54: 2012843.5 | QU54: 2010181.1 | QV54: 1592499 | QW54: 2066381.3 | QX54: 2066381.3 | QY54: 2066381.3 | QZ54: 2066381.3 | RA54: 2066381.3 | RB54: 2053911.8 | RC54: 2053911.8 | RD54: 2053911.8 | RE54: 2053911.8 | RF54: 2053911.8 | RG54: 1352125.6 | RH54: 2671110.9 | RI54: 2671110.9 | RJ54: 2671110.9 | RK54: 2617143.6 | RL54: 2674978.1 | RM54: 2674978.1 | RN54: 2674978.1 | RO54: 2674978.1 | RP54: 2674978.1 | RQ54: 2674978.1 | RR54: 2663130.7 | RS54: 2592092 | RT54: 2574933.7 | RU54: 2574933.7 | RV54: 2888871.3 | RW54: 2888871.3 | RX54: 2888871.3 | RY54: 2888871.3 | RZ54: 2888871.3 | SA54: 2971775.3 | SB54: 2971775.3 | SC54: 2971775.3 | SD54: 2971775.3 | SE54: 2970775.3 | SF54: 2970775.3 | SG54: 2970775.3 | SH54: 2953182.3 | SI54: 2908182.3 | SJ54: 2908182.3 | SK54: 2908182.3 | SL54: 3091133.8 | SM54: 3086604 | SN54: 3085604 | SO54: 3085604 | SP54: 3193551.4 | SQ54: 3193551.4 | SR54: 3185051.4 | SS54: 3185051.4 | ST54: 3185051.4 | SU54: 3166055.2 | SV54: 3158611.2 | SW54: 3156884.1 | SX54: 3156884.1 | SY54: 3158341.5 | SZ54: 2122082.4 | TA54: 2746576.7 | TB54: 2746576.7 | TC54: 2746576.7 | TD54: 2746576.7 | TE54: 2288582.6 | TF54: 2512984.2 | TG54: 2512984.2 | TH54: 2512984.2 | TI54: 2512984.2 | TJ54: 2512984.2 | TK54: 2477097.2 | TL54: 2477097.2 | TM54: 2399408.6 | TN54: 2399408.6 | TO54: 2399408.6 | TP54: 1134673.2 | TQ54: 1931351.8 | TR54: 1931351.8 | TS54: 1931351.8 | TT54: 1771417.2 | TU54: 1771417.2 | TV54: 1771417.2 | TW54: 1771417.2 | TX54: 1771417.2 | TY54: 1771417.2 | TZ54: 1771417.2 | UA54: 1771417.2 | UB54: 1771417.2 | UC54: 1771417.2 | UD54: 1771417.2 | UE54: 1150922.9 | UF54: 2043946.6 | UG54: 2043946.6 | UH54: 2043946.6 | UI54: 2035211.2 | UJ54: 1809909.6 | UK54: 1809909.6 | UL54: 1809909.6 | UM54: 1809909.6 | UN54: 1801411.3 | UO54: 1801411.3 | UP54: 1901334.1 | UQ54: 1894141.7 | UR54: 1894141.7 | US54: 1894141.7 | UT54: 1894141.7 | UU54: 1099762.9 | UV54: 1835378.5 | UW54: 1835378.5 | UX54: 1835378.5 | UY54: 1835378.5 | UZ54: 1834841.3 | VA54: 1834841.3 | VB54: 1834841.3 | VC54: 1834841.3 | VD54: 1833641.3 | VE54: 1843618.2 | VF54: 1843618.2 | VG54: 1843618.2 | VH54: 1843618.2 | VI54: 2196259.9 | VJ54: 2196259.9 | VK54: 1357892.7 | VL54: 1357892.7 | VM54: 1357892.7 | VN54: 1357892.7 | VO54: 1357892.7 | VP54: 1357892.7 | VQ54: 1357892.7 | VR54: 1357892.7 | VS54: 1277913.2 | VT54: 1165538.2 | VU54: 1178740.9 | VV54: 1171548.5 | VW54: 1170847.5 | VX54: 1352342.2 | VY54: 1352342.2 | VZ54: 633545.85 | WA54: 633545.85 | WB54: 633545.85 | WC54: 633545.85 | WD54: 633545.85 | WE54: 633545.85 | WF54: 633545.85 | WG54: 633545.85 | WH54: 633545.85 | WI54: 622538.95 | WJ54: 622538.95 | WK54: 622538.95 | WL54: 257839.41 | WM54: 798151.02 | WN54: 789572.69 | WO54: 805843.44 | WP54: 805843.44 | WQ54: 805843.44 | WR54: 805843.44 | WS54: 805843.44 | WT54: 805843.44 | WU54: 805843.44 | WV54: 805843.44 | WW54: 800024.45 | WX54: 792832.09 | WY54: 777548.7 | WZ54: 777548.7 | XA54: 777548.7 | XB54: 589572.7 | XC54: 1738932.5 | XD54: 1735932.5 | XE54: 1768234.2 | XF54: 1768234.2 | XG54: 1768234.2 | XH54: 1768234.2 | XI54: 1768234.2 | XJ54: 1768234.2 | XK54: 1768234.2 | XL54: 1768234.2 | XM54: 1768234.2 | XN54: 1768234.2 | XO54: 1768234.2 | XP54: 1768234.2 | XQ54: 2075346 | XR54: 2075346 | XS54: 2102668.5 | XT54: 2102668.5 | XU54: 2102668.5 | XV54: 2102668.5 | XW54: 2102668.5 | XX54: 2102668.5 | XY54: 2102668.5 | XZ54: 2102668.5 | YA54: 2136188.3 | YB54: 2169510.7 | YC54: 2169511 | YD54: 2169510.7 | YE54: 2169510.7 | YF54: 2169510.7 | YG54: 1977127.1 | YH54: 1977127.1 | YI54: 1977127.1 | YJ54: 2031674.4 | YK54: 2031674.4 | YL54: 2031674.4 | YM54: 2031674.4
B55: 181 days and over | JO55: 435026.54 | JP55: 435026.54 | JQ55: 435026.54 | JR55: 435026.54 | JS55: 435026.54 | JT55: 435026.54 | JU55: 435026.54 | JV55: 435026.54 | JW55: 430865.5 | JX55: 430865.5 | JY55: 430865.5 | JZ55: 430865.5 | KA55: 430865.5 | KB55: 430865.5 | KC55: 430865.5 | KD55: 430865.5 | KE55: 455629.26 | KF55: 470629.26 | KG55: 470629.26 | KH55: 471629.26 | KI55: 546606.69 | KK55: 546606.69 | KL55: 546606.69 | KM55: 546606.69 | KN55: 546606.69 | KO55: 546606.69 | KP55: 546606.69 | KQ55: 546606.69 | KR55: 546606.69 | KS55: 652109.6 | KT55: 652109.6 | KU55: 652109.6 | KV55: 652109.6 | KW55: 640657.6 | KX55: 665656.87 | KY55: 665656.87 | KZ55: 654127.61 | LA55: 654127.61 | LB55: 653127.61 | LC55: 653127.61 | LD55: 653127.61 | LE55: 653127.61 | LF55: 642574.98 | LG55: 642574.98 | LH55: 642574.98 | LI55: 706958.09 | LJ55: 706958.09 | LK55: 706958.09 | LL55: 706958.09 | LM55: 812790.3 | LN55: 812790.3 | LO55: 812790.3 | LP55: 812790.3 | LQ55: 812790.3 | LR55: 812790.3 | LS55: 812790.3 | LT55: 812790.3 | LU55: 792459.3 | LV55: 792459.3 | LW55: 792459.3 | LX55: 973071 | LY55: 962629.48 | LZ55: 962629.48 | MA55: 967629.48 | MB55: 967629.48 | MC55: 1033509.1 | MD55: 1033509.1 | ME55: 1033509.1 | MF55: 1036509.1 | MG55: 1036509.1 | MH55: 1036509.1 | MI55: 1036509.1 | MJ55: 1036509.1 | MK55: 1036509.1 | ML55: 1034731.3 | MM55: 1034731.3 | MN55: 1034731.3 | MO55: 1197904.5 | MP55: 1197904.5 | MQ55: 1201004.5 | MR55: 1201004.5 | MS55: 1201004.5 | MT55: 1201004.5 | MU55: 1207004.5 | MV55: 1207004.5 | MW55: 1207004.5 | MX55: 1207004.5 | MY55: 1207004.5 | MZ55: 1207004.5 | NA55: 1207004.5 | NB55: 1354039.1 | NC55: 1354039.1 | ND55: 1354039.1 | NE55: 1354039.1 | NF55: 1366039.1 | NG55: 1491357.6 | NH55: 1491357.6 | NI55: 1491357.6 | NJ55: 1491357.6 | NK55: 1499357.6 | NL55: 1499357.6 | NM55: 1499357.6 | NN55: 1499357.6 | NO55: 1499357.6 | NP55: 1499357.6 | NQ55: 1499357.6 | NR55: 1893269.4 | NS55: 1893269.4 | NT55: 1893269.4 | NU55: 1893269.4 | NV55: 1994816.5 | NW55: 1994816.5 | NX55: 1994816.5 | NY55: 1994816.5 | NZ55: 1990655.5 | OA55: 1990655.5 | OB55: 1990655.5 | OC55: 1990655.5 | OD55: 1980214 | OE55: 1980214 | OF55: 1980214 | OG55: 2050539.1 | OH55: 2050539.1 | OI55: 2050539.1 | OJ55: 2050539.1 | OK55: 2072707.6 | OL55: 2119217.5 | OM55: 2119217.5 | ON55: 2119217.5 | OO55: 2119217.5 | OP55: 2119217.5 | OQ55: 2119217.5 | OR55: 2119217.5 | OS55: 2119217.5 | OT55: 2117439.5 | OU55: 2117439.5 | OV55: 2113278.5 | OW55: 2374903.6 | OX55: 2374893.6 | OY55: 2374893.6 | OZ55: 2374893.6 | PA55: 2553344.2 | PB55: 2553344.2 | PC55: 2553344.2 | PD55: 2553344.2 | PE55: 2553344.2 | PF55: 2553344.2 | PG55: 2541531.7 | PH55: 2541531.7 | PI55: 2531090.1 | PJ55: 2529235.1 | PK55: 2529235.1 | PL55: 2916147.4 | PM55: 2918147.4 | PN55: 2918147.4 | PO55: 2913986.4 | PP55: 2913986.4 | PQ55: 2982838.2 | PR55: 2982838.2 | PS55: 2982838.2 | PT55: 2982838.2 | PU55: 2978638.2 | PV55: 2976860.2 | PW55: 2976860.2 | PX55: 2976860.2 | PY55: 2976860.2 | PZ55: 2975541.7 | QA55: 2975541.7 | QB55: 2975541.7 | QC55: 3640009.7 | QD55: 3639989.7 | QE55: 3639989.7 | QF55: 3639989.7 | QG55: 3688881.6 | QH55: 3688881.6 | QI55: 3688881.6 | QJ55: 3688881.6 | QK55: 3688881.6 | QL55: 3688861.6 | QM55: 3688861.6 | QN55: 3677531.3 | QO55: 3675280.9 | QP55: 3675280.9 | QQ55: 3837569.6 | QR55: 3876569.6 | QS55: 3875127.8 | QT55: 3875127.8 | QU55: 3875107.8 | QV55: 4292789.9 | QW55: 4292789.9 | QX55: 4292789.9 | QY55: 4123345.2 | QZ55: 4123345.2 | RA55: 4123345.2 | RB55: 4123345.2 | RC55: 4121820.4 | RD55: 4110618.3 | RE55: 4110618.3 | RF55: 4110618.3 | RG55: 4812404.5 | RH55: 4962962.6 | RI55: 4962962.6 | RJ55: 4962962.6 | RK55: 5016929.9 | RL55: 5016929.9 | RM55: 5016929.9 | RN55: 5016929.9 | RO55: 5016929.9 | RP55: 5016929.9 | RQ55: 5015151.9 | RR55: 5015151.9 | RS55: 5013821.6 | RT55: 5013821.6 | RU55: 5013821.6 | RV55: 5943896.7 | RW55: 5943896.7 | RX55: 5912918.6 | RY55: 5912918.6 | RZ55: 5911476.8 | SA55: 6397359.1 | SB55: 6397359.1 | SC55: 6397359.1 | SD55: 6397359.1 | SE55: 6397359.1 | SF55: 6397359.1 | SG55: 6392614.5 | SH55: 6376379.4 | SI55: 6376379.4 | SJ55: 6376379.4 | SK55: 6376379.4 | SL55: 7687358.7 | SM55: 7687358.7 | SN55: 7687358.7 | SO55: 7687358.7 | SP55: 7735345.8 | SQ55: 7735345.8 | SR55: 7735345.8 | SS55: 7735345.8 | ST55: 7735345.8 | SU55: 7735345.8 | SV55: 7735345.8 | SW55: 7735345.8 | SX55: 7734015.5 | SY55: 7711704.8 | SZ55: 8745561.8 | TA55: 8781561.8 | TB55: 8781561.8 | TC55: 8781561.8 | TD55: 8781561.8 | TE55: 9239556 | TF55: 9239556 | TG55: 9239556 | TH55: 9238114 | TI55: 9232114 | TJ55: 9232114 | TK55: 9232114 | TL55: 9230336.2 | TM55: 9217609.3 | TN55: 9217609.3 | TO55: 9217609.3 | TP55: 10473845 | TQ55: 10484203 | TR55: 10484203 | TS55: 10484203 | TT55: 10644138 | TU55: 10644138 | TV55: 10644138 | TW55: 10638138 | TX55: 10638138 | TY55: 10638138 | TZ55: 10638138 | UA55: 10638138 | UB55: 10636807 | UC55: 10636807 | UD55: 10636807 | UE55: 11338971 | UF55: 11338971 | UG55: 11338971 | UH55: 11338971 | UI55: 11347707 | UJ55: 11573008 | UK55: 11573008 | UL55: 11572008 | UM55: 11572008 | UN55: 11572008 | UO55: 11572008 | UP55: 11564664 | UQ55: 11563139 | UR55: 11563139 | US55: 11563139 | UT55: 11563139 | UU55: 12549665 | UV55: 12549665 | UW55: 12549665 | UX55: 12549665 | UY55: 12549665 | UZ55: 12548665 | VA55: 12548665 | VB55: 12548665 | VC55: 12548665 | VD55: 12548665 | VE55: 12548665 | VF55: 12548665 | VG55: 12548665 | VH55: 12548665 | VI55: 12548665 | VJ55: 12548665 | VK55: 13512912 | VL55: 13512912 | VM55: 13511912 | VN55: 13511912 | VO55: 13511912 | VP55: 13511912 | VQ55: 13511912 | VR55: 13511912 | VS55: 13591892 | VT55: 13704267 | VU55: 13702490 | VV55: 13699360 | VW55: 13692268 | VX55: 13692268 | VY55: 13692268 | VZ55: 14657652 | WA55: 14657652 | WB55: 14645465 | WC55: 14645465 | WD55: 14645365 | WE55: 14645265 | WF55: 14645115 | WG55: 14644965 | WH55: 14644815 | WI55: 14655672 | WJ55: 14655522 | WK55: 14655372 | WL55: 15020072 | WM55: 15020072 | WN55: 15020072 | WO55: 15158639 | WP55: 15158639 | WQ55: 15158639 | WR55: 15158639 | WS55: 15158639 | WT55: 15158489 | WU55: 15158489 | WV55: 15157868 | WW55: 15156868 | WX55: 15156868 | WY55: 15172001 | WZ55: 15171851 | XA55: 15171701 | XB55: 15353960 | XC55: 15352435 | XD55: 15352285 | XE55: 15620892 | XF55: 15620892 | XG55: 15620592 | XH55: 15620592 | XI55: 15620442 | XJ55: 15620442 | XK55: 15620442 | XL55: 15618318 | XM55: 15618318 | XN55: 15618318 | XO55: 15617818 | XP55: 15617818 | XQ55: 16174268 | XR55: 16165101 | XS55: 16350839 | XT55: 16350839 | XU55: 16350839 | XV55: 16350839 | XW55: 16350839 | XX55: 16350839 | XY55: 16350839 | XZ55: 16350839 | YA55: 16350839 | YB55: 16350839 | YC55: 16350839 | YD55: 16350839 | YE55: 16345839 | YF55: 16331247 | YG55: 17509909 | YH55: 17509909 | YI55: 17509909 | YJ55: 17834452 | YK55: 17834452 | YL55: 17834452 | YM55: 17834452
B56: Charge off amount | JO56: 0 | JP56: 0 | JQ56: 0 | JR56: 0 | JS56: 0 | JT56: 0 | JU56: 0 | JV56: 0 | JW56: 0 | JX56: 0 | JY56: 0 | JZ56: 0 | KA56: 0 | KB56: 0 | KC56: 0 | KD56: 0 | KE56: 0 | KF56: 0 | KG56: 0 | KH56: 0 | KI56: 0 | KJ56: 0 | KK56: 0 | KL56: 0 | KM56: 0 | KN56: 0 | KO56: 0 | KP56: 0 | KQ56: 0 | KR56: 0 | KS56: 0 | KT56: 0 | KU56: 0 | KV56: 0 | KW56: 0 | KX56: 0 | KY56: 0 | KZ56: 0 | LA56: 0 | LB56: 0 | LC56: 0 | LD56: 0 | LE56: 0 | LF56: 0 | LG56: 0 | LH56: 0 | LI56: 0 | LJ56: 0 | LK56: 0 | LL56: 0 | LM56: 0 | LN56: 0 | LO56: 0 | LP56: 0 | LQ56: 0 | LR56: 0 | LS56: 0 | LT56: 0 | LU56: 0 | LV56: 0 | LW56: 0 | LX56: 0 | LY56: 0 | LZ56: 0 | MA56: 0 | MB56: 0 | MC56: 0 | MD56: 0 | ME56: 0 | MF56: 0 | MG56: 0 | MH56: 0 | MI56: 0 | MJ56: 0 | MK56: 0 | ML56: 0 | MM56: 0 | MN56: 0 | MO56: 0 | MP56: 0 | MQ56: 0 | MR56: 0 | MS56: 0 | MT56: 0 | MU56: 0 | MV56: 0 | MW56: 0 | MX56: 0 | MY56: 0 | MZ56: 0 | NA56: 0 | NB56: 0 | NC56: 0 | ND56: 0 | NE56: 0 | NF56: 0 | NG56: 0 | NH56: 0 | NI56: 0 | NJ56: 0 | NK56: 0 | NL56: 0 | NM56: 0 | NN56: 0 | NO56: 0 | NP56: 0 | NQ56: 0 | NR56: 0 | NS56: 0 | NT56: 0 | NU56: 0 | NV56: 0 | NW56: 0 | NX56: 0 | NY56: 0 | NZ56: 0 | OA56: 0 | OB56: 0 | OC56: 0 | OD56: 0 | OE56: 0 | OF56: 0 | OG56: 0 | OH56: 0 | OI56: 0 | OJ56: 0 | OK56: 0 | OL56: 0 | OM56: 0 | ON56: 0 | OO56: 0 | OP56: 0 | OQ56: 0 | OR56: 0 | OS56: 0 | OT56: 0 | OU56: 0 | OV56: 0 | OW56: 0 | OX56: 0 | OY56: 0 | OZ56: 0 | PA56: 0 | PB56: 0 | PC56: 0 | PD56: 0 | PE56: 0 | PF56: 0 | PG56: 0 | PH56: 0 | PI56: 0 | PJ56: 0 | PK56: 0 | PL56: 0 | PM56: 0 | PN56: 0 | PO56: 0 | PP56: 0 | PQ56: 0 | PR56: 0 | PS56: 0 | PT56: 0 | PU56: 0 | PV56: 0 | PW56: 0 | PX56: 0 | PY56: 0 | PZ56: 0 | QA56: 0 | QB56: 0 | QC56: 0 | QD56: 0 | QE56: 0 | QF56: 0 | QG56: 0 | QH56: 0 | QI56: 0 | QJ56: 0 | QK56: 0 | QL56: 0 | QM56: 0 | QN56: 0 | QO56: 0 | QP56: 0 | QQ56: 0 | QR56: 0 | QS56: 0 | QT56: 0 | QU56: 0 | QV56: 0 | QW56: 0 | QX56: 0 | QY56: 0 | QZ56: 0 | RA56: 0 | RB56: 0 | RC56: 0 | RD56: 0 | RE56: 0
B59: Credit Limit | ND59: 244870000 | NE59: 244870000 | NF59: 244870000 | NG59: 244870000 | NH59: 244805000 | NI59: 244805000 | NJ59: 245635000 | NK59: 245635000 | NL59: 245635000 | NM59: 245635000 | NN59: 245635000 | NO59: 246440000 | NP59: 246540000 | NQ59: 246540000 | NR59: 246540000 | NS59: 246540000 | NT59: 246540000 | NU59: 246540000 | NV59: 247630000 | NW59: 247630000 | NX59: 247630000 | NY59: 247630000 | NZ59: 247630000 | OA59: 247630000 | OB59: 247630000 | OC59: 247630000 | OD59: 249490000 | OE59: 252655000 | OF59: 254475000 | OG59: 256875000 | OH59: 256875000 | OI59: 256875000 | OJ59: 257680000 | OK59: 258625000 | OL59: 258625000 | OM59: 259080000 | ON59: 259700000 | OO59: 259700000 | OP59: 259700000 | OQ59: 259650000 | OR59: 262020000 | OS59: 266335000 | OT59: 267975000 | OU59: 269635000 | OV59: 269635000 | OW59: 273610000 | OX59: 275425000 | OY59: 277220000 | OZ59: 282330000 | PA59: 288205000 | PB59: 288700000 | PC59: 293000000 | PD59: 293000000 | PE59: 293720000 | PF59: 296205000 | PG59: 301760000 | PH59: 313200000 | PI59: 313200000 | PJ59: 313200000 | PK59: 313200000 | PL59: 314745000 | PM59: 316535000 | PN59: 316590000 | PO59: 316590000 | PP59: 317425000 | PQ59: 317425000 | PR59: 317425000 | PS59: 317425000 | PT59: 320715000 | PU59: 320715000 | PV59: 325120000 | PW59: 370240000 | PX59: 370240000 | PY59: 370240000 | PZ59: 371745000 | QA59: 371745000 | QB59: 374590000 | QC59: 377720000 | QD59: 381225000 | QE59: 381225000 | QF59: 382780000 | QG59: 382780000 | QH59: 382780000 | QI59: 379635000 | QJ59: 391965000 | QK59: 397010000 | QL59: 397010000 | QM59: 397010000 | QN59: 399230000 | QO59: 431830000 | QP59: 431605000 | QQ59: 431605000 | QR59: 454755000 | QS59: 454755000 | QT59: 454755000 | QU59: 454755000 | QV59: 466710000 | QW59: 468985000 | QX59: 468985000 | QY59: 468985000 | QZ59: 468985000 | RA59: 468985000 | RB59: 468720000 | RC59: 475355000 | RD59: 475355000 | RE59: 478915000 | RF59: 478915000 | RG59: 478915000 | RH59: 478915000 | RI59: 482970000 | RJ59: 486175000 | RK59: 486175000 | RL59: 486275000 | RM59: 496650000 | RN59: 496650000 | RO59: 496650000 | RP59: 501270000 | RQ59: 501270000 | RR59: 501270000 | RS59: 501270000 | RT59: 501270000 | RU59: 501270000 | RV59: 501270000 | RW59: 501270000 | RX59: 512765000 | RY59: 522545000 | RZ59: 526075000 | SA59: 526075000 | SB59: 526075000 | SC59: 526075000 | SD59: 534940000 | SE59: 534940000 | SF59: 536825000 | SG59: 542315000 | SH59: 542315000 | SI59: 542415000 | SJ59: 542415000 | SK59: 549985000 | SL59: 565030000 | SM59: 565030000 | SN59: 565030000 | SO59: 569410000 | SP59: 569410000 | SQ59: 569410000 | SR59: 569410000 | SS59: 579035000 | ST59: 587560000 | SU59: 592360000 | SV59: 594900000 | SW59: 594900000 | SX59: 594900000 | SY59: 594855000 | SZ59: 658915000 | TA59: 663470000 | TB59: 663455000 | TC59: 674555000 | TD59: 674555000 | TE59: 674555000 | TF59: 685520000 | TG59: 690650000 | TH59: 699840000 | TI59: 699805000 | TJ59: 699805000 | TK59: 699805000 | TL59: 699805000 | TM59: 711270000 | TN59: 722290000 | TO59: 731750000 | TP59: 734285000 | TQ59: 734285000 | TR59: 734285000 | TS59: 734285000 | TT59: 734285000 | TU59: 753090000 | TV59: 754675000 | TW59: 755980000 | TX59: 763120000 | TY59: 763120000 | TZ59: 763120000 | UA59: 763395000 | UB59: 778710000 | UC59: 779750000 | UD59: 779750000 | UE59: 779750000 | UF59: 779750000 | UG59: 779680000 | UH59: 779680000 | UI59: 779610000 | UJ59: 788625000 | UK59: 789040000 | UL59: 789040000 | UM59: 789040000 | UN59: 789040000 | UO59: 790695000 | UP59: 790685000 | UQ59: 794115000 | UR59: 794760000 | US59: 795490000 | UT59: 795490000 | UU59: 795490000 | UV59: 795490000 | UW59: 812805000 | UX59: 814115000 | UY59: 820055000 | UZ59: 820055000 | VA59: 820055000 | VB59: 820055000 | VC59: 820875000 | VD59: 821010000 | VE59: 826050000 | VF59: 826050000 | VG59: 836340000 | VH59: 840940000 | VI59: 840965000 | VJ59: 840965000 | VK59: 840950000 | VL59: 840950000 | VM59: 846765000 | VN59: 846765000 | VO59: 855075000 | VP59: 855075000 | VQ59: 855075000 | VR59: 857355000 | VS59: 867495000 | VT59: 867495000 | VU59: 867495000 | VV59: 869955000 | VW59: 869955000 | VX59: 869955000 | VY59: 869955000 | VZ59: 869955000 | WA59: 937180000 | WB59: 937180000 | WC59: 937180000 | WD59: 937180000 | WE59: 937180000 | WF59: 937180000 | WG59: 966510000 | WH59: 966510000 | WI59: 967190000 | WJ59: 974395000 | WK59: 974395000 | WL59: 974395000 | WM59: 974395000 | WN59: 1003735000 | WO59: 1011960000 | WP59: 1013415000 | WQ59: 1013415000 | WR59: 1034045000 | WS59: 1036460000 | WT59: 1047445000 | WU59: 1047305000 | WV59: 1047205000 | WW59: 1056645000 | WX59: 1059150000 | WY59: 1059150000 | WZ59: 1059150000 | XA59: 1059135000 | XB59: 1068015000 | XC59: 1072470000 | XD59: 1073300000 | XE59: 1076265000 | XF59: 1076265000 | XG59: 1076265000 | XH59: 1102405000 | XI59: 1105155000 | XJ59: 1108505000 | XK59: 1112565000 | XL59: 1116070000 | XM59: 1116070000 | XN59: 1116070000 | XO59: 1116070000 | XP59: 1130960000 | XQ59: 1130910000 | XR59: 1130910000 | XS59: 1130910000 | XT59: 1130910000 | XU59: 1130910000 | XV59: 1130910000 | XW59: 1135675000 | XX59: 1135675000 | XY59: 1135675000 | XZ59: 1135450000 | YA59: 1135450000 | YB59: 1135450000 | YC59: 1135450000 | YD59: 1135450000 | YE59: 1149900000 | YF59: 1149900000 | YG59: 1149900000 | YH59: 1149900000 | YI59: 1149900000 | YJ59: 1149885000 | YK59: 1149885000 | YL59: 1149885000 | YM59: 1149885000
B60: Average Credit Limit | ND60: =ND59/ND8 -> 63918.037 | NE60: =NE59/NE8 -> 63918.037 | NF60: =NF59/NF8 -> 63918.037 | NG60: =NG59/NG8 -> 63918.037 | NH60: =NH59/NH8 -> 63951.149 | NI60: =NI59/NI8 -> 64034.789 | NJ60: =NJ59/NJ8 -> 63984.11 | NK60: =NK59/NK8 -> 63984.11 | ... WH60: =WH59/WH8 -> 73954.396 | WI60: 73944.19 | WJ60: =WJ59/WJ8 -> 73834.584 | WK60: =WK59/WK8 -> 73834.584 | WL60: =WL59/WL8 -> 73834.584 | WM60: =WM59/WM8 -> 73834.584 | WN60: =WN59/WN8 -> 71536.954 | WO60: =WO59/WO8 -> 70925.147 | WP60: 70828.557 | WQ60: =WQ59/WQ8 -> 70828.557 | WR60: =WR59/WR8 -> 69436.275 | WS60: =WS59/WS8 -> 69272.824 | WT60: =WT59/WT8 -> 69088.121 | WU60: =WU59/WU8 -> 69083.443 | WV60: =WV59/WV8 -> 69076.847 | WW60: =WW59/WW8 -> 68845.778 | WX60: =WX59/WX8 -> 68811.72 | ... YB60: =YB59/YB8 -> 69650.963 | YC60: 69651 | YD60: =YD59/YD8 -> 69650.963 | YE60: =YE59/YE8 -> 70537.357 | YF60: =YF59/YF8 -> 70537.357 | YG60: =YG59/YG8 -> 70537.357 | YH60: =YH59/YH8 -> 70537.357 | YI60: =YI59/YI8 -> 70537.357 | YJ60: =YJ59/YJ8 -> 70540.764 | YK60: =YK59/YK8 -> 70540.764 | ... YM60: =YM59/YM8 -> 70540.764
PZ67: =PZ19/55.8 -> 130994.95 | QF67: =QF19*31 -> 1.0598753e+08 | QN67: =SUM($PK$19:QN19) -> 1.0051763e+08 | QO67: =SUM($PK$19:QO19) -> 1.0427639e+08
PZ68: =PZ67*31 -> 4060843.6 | QF68: =QF67/55.8 -> 1899418 | QN68: =QN67/55.8 -> 1801391.2 | QO68: =QO67/55.8 -> 1868752.5 | WT68: =WT42-WT55 -> 5879907.5
WT69: =WT29-WT55 -> 1.8023598e+08
WT70: =WT68/WT69 -> 0.032623383
QN71: =SUM($PK$38:QN38) -> 1302388.6 | QO71: =SUM($PK$38:QO38) -> 1364533.4
QN72: =QN71/55.8 -> 23340.298 | QO72: =QO71/55.8 -> 24454.004
QN73: =QN72*12 -> 280083.57 | QO73: =QO72*12 -> 293448.05
QO75: =AVERAGE(PK8:QO8) -> 5514.8065
QO76: 4000
QO77: =QO76/QO75 -> 0.72532011
QO80: =SUM(PK22:QO22) -> 74398
QO81: 3997
QO82: =QO80/QO81 -> 18.61346

Sheet Monthly Cohorts
C2: Monthly Active Rate
C3: Months after First Transaction | D3: 45200 | E3: 45231 | F3: 45261 | G3: 45292 | H3: 45323 | I3: 45352 | J3: 45383 | K3: 45413 | L3: 45444 | M3: 45474 | N3: 45505 | O3: 45536 | P3: 45566 | Q3: 45597 | R3: 45627 | S3: 45658 | T3: 45689 | U3: 45717 | V3: 45748 | W3: 45778 | X3: 45809 | Y3: 45863 | Z3: 45894 | AA3: 45925 | AB3: 45931 | AC3: 45962 | AD3: 46022 | AE3: 46053 | AF3: 46081 | AG3: 46112 | AH3: 46142 | AI3: 46173 | AJ3: 46203 | AK3: 46234 | AL3: 46265 | AM3: 46295
B4: # of CH | C4: Cohort | D4: 0 | E4: =D4+1 -> 1 | F4: =E4+1 -> 2 | G4: =F4+1 -> 3 | H4: =G4+1 -> 4 | I4: =H4+1 -> 5 | J4: =I4+1 -> 6 | K4: =J4+1 -> 7 | L4: =K4+1 -> 8 | ... V4: =U4+1 -> 18 | W4: 19 | X4: 20 | Y4: 21 | Z4: 22 | AA4: 23 | AB4: 24 | AC4: 25 | AD4: 26 | AE4: 27 | AF4: 28 | AG4: 29 | AH4: 30 | AI4: 31 | AJ4: 32 | AK4: 33 | AL4: 34 | AM4: 35
B5: 4 | C5: 45200 | D5: 1 | E5: 1 | F5: 1 | G5: 1 | H5: 1 | I5: 1 | J5: 1 | K5: 0.75 | L5: 1 | M5: 1 | N5: 1 | O5: 1 | P5: 1 | Q5: 1 | R5: 1 | S5: 1 | T5: 1 | U5: 1 | V5: 1 | W5: 1 | X5: 1 | Y5: 1 | Z5: 1 | AA5: 1 | AB5: 1 | AC5: 1 | AD5: 1 | AE5: 1 | AF5: 1 | AG5: 1 | AH5: 1 | AI5: 1 | AJ5: 1 | AK5: 1 | AL5: 1 | AM5: 1
B6: 5 | C6: 45261 | D6: 1 | E6: 1 | F6: 0.8 | G6: 0.8 | H6: 1 | I6: 1 | J6: 0.8 | K6: 0.8 | L6: 0.8 | M6: 0.8 | N6: 1 | O6: 1 | P6: 1 | Q6: 1 | R6: 1 | S6: 1 | T6: 1 | U6: 1 | V6: 1 | W6: 1 | X6: 1 | Y6: 1 | Z6: 1 | AA6: 1 | AB6: 1 | AC6: 1 | AD6: 1 | AE6: 1 | AF6: 1 | AG6: 1 | AH6: 1 | AI6: 1 | AJ6: 1 | AK6: 1
B7: 6 | C7: 45292 | D7: 1 | E7: 0.5 | F7: 0.66666667 | G7: 0.66666667 | H7: 1 | I7: 0.83333333 | J7: 0.83333333 | K7: 0.83333333 | L7: 0.83333333 | M7: 0.83333333 | N7: 0.83333333 | O7: 0.83333333 | P7: 1 | Q7: 1 | R7: 1 | S7: 0.83333333 | T7: 1 | U7: 1 | V7: 1 | W7: 1 | X7: 1 | Y7: 1 | Z7: 1 | AA7: 1 | AB7: 1 | AC7: 1 | AD7: 1 | AE7: 1 | AF7: 1 | AG7: 1 | AH7: 1 | AI7: 0.83333333 | AJ7: 1
B8: 1 | C8: 45323 | D8: 1 | E8: 1 | F8: 1 | G8: 1 | H8: 1 | I8: 1 | J8: 1 | K8: 1 | L8: 1 | M8: 1 | N8: 1 | O8: 1 | P8: 1 | Q8: 1 | R8: 1 | S8: 1 | T8: 1 | U8: 1 | V8: 1 | W8: 1 | X8: 1 | Y8: 1 | Z8: 1 | AA8: 1 | AB8: 1 | AC8: 1 | AD8: 1 | AE8: 1 | AF8: 1 | AG8: 1 | AH8: 1 | AI8: 1
B9: 20 | C9: 45352 | D9: 1 | E9: 1 | F9: 1 | G9: 1 | H9: 0.95 | I9: 0.9 | J9: 0.95 | K9: 0.9 | L9: 0.9 | M9: 0.85 | N9: 0.9 | O9: 0.95 | P9: 0.95 | Q9: 0.95 | R9: 0.95 | S9: 0.9 | T9: 0.95 | U9: 0.95 | V9: 0.95 | W9: 1 | X9: 0.9 | Y9: 0.95 | Z9: 0.95 | AA9: 0.95 | AB9: 0.95 | AC9: 0.9 | AD9: 0.95 | AE9: 0.9 | AF9: 0.9 | AG9: 0.9 | AH9: 0.95
B10: 12 | C10: 45383 | D10: 1 | E10: 0.75 | F10: 0.66666667 | G10: 0.75 | H10: 0.66666667 | I10: 0.66666667 | J10: 0.66666667 | K10: 0.75 | L10: 0.66666667 | M10: 0.66666667 | N10: 0.75 | O10: 0.83333333 | P10: 0.66666667 | Q10: 0.5 | R10: 0.5 | S10: 0.5 | T10: 0.5 | U10: 0.58333333 | V10: 0.58 | W10: 0.66666667 | X10: 0.66666667 | Y10: 0.75 | Z10: 0.58333333 | AA10: 0.66666667 | AB10: 0.66666667 | AC10: 0.83333333 | AD10: 0.66666667 | AE10: 0.75 | AF10: 0.66666667 | AG10: 0.75
B11: 13 | C11: 45413 | D11: 1 | E11: 0.84615385 | F11: 0.92307692 | G11: 0.84615385 | H11: 0.92307692 | I11: 0.84615385 | J11: 0.84615385 | K11: 0.84615385 | L11: 0.76923077 | M11: 0.76923077 | N11: 0.76923077 | O11: 0.84615385 | P11: 0.84615385 | Q11: 0.77 | R11: 0.76923077 | S11: 0.69230769 | T11: 0.84615385 | U11: 0.85 | V11: 0.76923077 | W11: 0.84615385 | X11: 0.85 | Y11: 0.84615385 | Z11: 0.84615385 | AA11: 0.76923077 | AB11: 0.84615385 | AC11: 0.84615385 | AD11: 0.76923077 | AE11: 0.76923077 | AF11: 0.69230769
B12: 46 | C12: 45444 | D12: 1 | E12: 0.95833333 | F12: 0.875 | G12: 0.89583333 | H12: 0.89583333 | I12: 0.85416667 | J12: 0.83333333 | K12: 0.79166667 | L12: 0.72916667 | M12: 0.72916667 | N12: 0.77083333 | O12: 0.72916667 | P12: 0.73 | Q12: 0.66666667 | R12: 0.66666667 | S12: 0.75 | T12: 0.77 | U12: 0.75 | V12: 0.77083333 | W12: 0.75 | X12: 0.72916667 | Y12: 0.72916667 | Z12: 0.7826087 | AA12: 0.76086957 | AB12: 0.86956522 | AC12: 0.7826087 | AD12: 0.80434783 | AE12: 0.80434783
B13: 43 | C13: 45474 | D13: 1 | E13: 0.8 | F13: 0.77777778 | G13: 0.73333333 | H13: 0.68888889 | I13: 0.75555556 | J13: 0.71111111 | K13: 0.64444444 | L13: 0.62222222 | M13: 0.62222222 | N13: 0.64444444 | O13: 0.64 | P13: 0.62222222 | Q13: 0.6 | R13: 0.62222222 | S13: 0.56 | T13: 0.66666667 | U13: 0.64444444 | V13: 0.62 | W13: 0.62222222 | X13: 0.57777778 | Y13: 0.6744186 | Z13: 0.72093023 | AA13: 0.53488372 | AB13: 0.53488372 | AC13: 0.58139535 | AD13: 0.55813953
